Workbook

Sheet 20260228波箱油&刹车油售价&订单
AD1: 订货周期（OC） | AK1: 排序 | AL1: 产品名称 | AM1: BCS HO | BI1: 历史销量 | BJ1: 库存状态 | BN1: 调拨需求 | BT1: BCS 01-KLG | CE1: BCS 02-PIK 2 | CP1: BCS HO ST0CK-(Franchise store requirements)
A2: 序号 | B2: 零件号 | C2: 品牌 | D2: 零件类别 | E2: 产品类型 | F2: 产品类型 | J2: 产品名称 | K2: 产品名称 | L2: Quantity | M2: Unit | N2: Cost Price | O2: Fixed Markup Rate | P2: Floating Markup Rate | Q2: Total Markup Rate | S2: BQUICK 参考价 | T2: shopee官网 | U2: tokopedia官网 | V2: 平均 参考价 | W2: 初始销售价 --02 | X2: 初始销售价 --03 | Y2: 修正销售价 | Z2: 工时费 | AA2: 含工时费 销售价 | AB2: 毛利 | AC2: 毛利率 | AD2: 订货周期（OC） | AF2: 到货周期（LT） | AH2: 安全库存 行业系数经验值 | AI2: 安全库存周期（SS） | AM2: Total | AN2: Average 6 | AO2: Average 11 | AP2: 销售趋向系数 | AQ2: 5~9月 进店量 | AR2: 配件 更换率 | AS2: 月度 理论销量 | AT2: 最小库存量 （安全库存量） | AU2: 标准库存量（SSQ） | AV2: 现有库存量 （O/H） | AW2: 在途库存量 （O/O） | AX2: 追加订单量 （B/O） | AY2: 建议订单量 （SOQ） | AZ2: 修正订单 | BA2: 修正订单/箱 | BB2: 包装 | BC2: 桶/箱 | BD2: 对应送货动作 | BF2: 备货策略 | BG2: 质量等级 | BH2: 产品名称 | BJ2: BCS 01-KLG | BK2: BCS 02-PIK 2 | BL2: BCS HO | BM2: TOTAL | BN2: BCS 01-KLG | BO2: BCS 02-PIK 2 | BP2: TOTAL | BQ2: KLG | BR2: PIK2 | BS2: 产品名称 | BT2: Average 6 | BU2: Avergae 11 | BV2: 销售趋向系数 | BW2: 修正 最小库存量 | BX2: 最小库存量 （安全库存量） | BY2: 标准库存量（SSQ） | BZ2: 现有库存量 （O/H） | CA2: 在途库存量 （O/O） | CB2: 追加订单量 （B/O） | CC2: 建议订单量 （SOQ） | CD2: 修正订单 | CE2: Average 6 | CF2: Average 6 | CG2: 销售趋向系数 | CH2: 修正 最小库存量 | CI2: 最小库存量 （安全库存量） | CJ2: 标准库存量（SSQ） | CK2: 现有库存量 （O/H） | CL2: 在途库存量 （O/O） | CM2: 追加订单量 （B/O） | CN2: 建议订单量 （SOQ） | CO2: 修正订单 | CP2: Average 6 | CQ2: Average 6 | CR2: 销售趋向系数 | CS2: 修正 最小库存量 | CT2: 最小库存量 （安全库存量） | CU2: 标准库存量（SSQ） | CV2: 现有库存量 （O/H） | CW2: 在途库存量 （O/O） | CX2: 追加订单量 （B/O） | CY2: 建议订单量 （SOQ） | CZ2: 修正订单/桶 | DA2: 产品名称
A3: NO | B3: Part Number | C3: Brand | D3: Part Category | E3: Product Type | F3: Product Type | G3: 容量/桶 | H3: 包装 | I3: 桶/箱 | J3: Product Name | K3: Product Name | L3: 数量 | M3: 单位 | N3: 成本价 | O3: 固定加价率 | P3: 浮动加价率 | Q3: 合计加价率 | R3: 初始销售价01 | BD3: BCS 01-KLG | BE3: BCS 02-PIK 2 | BH3: Product Name | BJ3: 库存 | BK3: 库存 | BL3: 库存 | BM3: 总计 | BN3: 需求 | BO3: 需求 | BP3: 需求 | BS3: Product Name | DA3: Product Name
A4: 2 | B4: 101771 | C4: MOBIL | D4: Transmission Oil | E4: Dexron-VI | F4: ATF | G4: 1L | H4: 12*1L | I4: 12 | J4: =C4&" "&D4&" "&E4&" "&F4&" "&G4 -> MOBIL Transmission Oil Dexron-VI ATF 1L | K4: MOBIL Transmission Oil Dexron-VI ATF 1L | L4: 1 | M4: 桶 | N4: 65100 | O4: 0.4 | P4: 0.2 | Q4: =O4+P4 -> 0.6 | R4: =N4*(1+Q4) -> 104160 | S4: 0 | T4: 0 | U4: 0 | V4: =IF((S4+T4+U4)=0,R4,IF(AND(S4>0,T4=0,U4=0),S4,IF(AND(S4=0,T4>0,U4=0),T4,IF(AND(S4=0,T4=0,U4>0),U4,IF(AND(S4>0,T4>0,U4=0),(S4+T4)/2,IF(AND(S4>0,T4=0,U4>0),(S4+U4)/2,IF(AND(S4=0,T4>0,U4>0),(T4+U4)/2,IF(AND(S4>0,T4>0,U4>0),(S4+T4+U4)/3,)))))))) -> 104160 | W4: =IF(R4=V4,V4,IF(R4/V4<70%,R4*1.18,IF(AND(R4/V4>=70%,R4/V4<75%),R4*1.15,IF(AND(R4/V4>=75%,R4/V4<80%),R4*1.12,IF(AND(R4/V4>=80%,R4/V4<85%),R4*1.09,IF(AND(R4/V4>=85%,R4/V4<90%),R4*1.06,IF(AND(R4/V4>=90%,R4/V4<95%),R4*1.03,IF(AND(R4/V4>=95%,R4/V4<105%),V4,IF(AND(R4/V4>=105%,R4/V4<110%),R4*0.97,IF(AND(R4/V4>=110%,R4/V4<115%),R4*0.94,IF(AND(R4/V4>=115%,R4/V4<120%),R4*0.91,IF(AND(R4/V4>=120%,R4/V4<125%),R4*0.88,IF(AND(R4/V4>=125%,R4/V4<130%),R4*0.85,IF(AND(R4/V4>=130%,R4/V4<135%),R4*0.82,IF(R4/V4>=135%,R4*0.8,))))))))))))))) -> 104160 | X4: =IF(N4=0,1,IF(N4<10000,N4*2.8,IF(AND(N4>=10000,N4<20000),N4*2.2,IF(AND(N4>=20000,N4<30000),N4*1.8,IF(AND(N4>=30000,N4<40000),N4*1.78,IF(AND(N4>=40000,N4<50000),N4*1.76,IF(AND(N4>=50000,N4<60000),N4*1.74,IF(AND(N4>=60000,N4<70000),N4*1.72,IF(AND(N4>=70000,N4<80000),N4*1.7,IF(AND(N4>=80000,N4<90000),N4*1.68,IF(AND(N4>=90000,N4<100000),N4*1.66,IF(AND(N4>=100000,N4<110000),N4*1.65,IF(AND(N4>=110000,N4<120000),N4*1.64,IF(AND(N4>=120000,N4<130000),N4*1.63,IF(AND(N4>=130000,N4<140000),N4*1.62,IF(AND(N4>=140000,N4<150000),N4*1.61,IF(AND(N4>=150000,N4<160000),N4*1.6,IF(AND(N4>=160000,N4<170000),N4*1.59,IF(AND(N4>=170000,N4<180000),N4*1.58,IF(AND(N4>=180000,N4<190000),N4*1.57,IF(AND(N4>=190000,N4<200000),N4*1.56,IF(AND(N4>=200000,N4<300000),N4*1.54,IF(AND(N4>=300000,N4<400000),N4*1.52,IF(AND(N4>=400000,N4<500000),N4*1.5,IF(AND(N4>=500000,N4<600000),N4*1.48,IF(AND(N4>=600000,N4<700000),N4*1.46,IF(AND(N4>=700000,N4<800000),N4*1.44,IF(AND(N4>=800000,N4<900000),N4*1.42,IF(AND(N4>=900000,N4<1000000),N4*1.4,IF(AND(N4>=1000000,N4<2000000),N4*1.39,IF(AND(N4>=2000000,N4<3000000),N4*1.38,IF(AND(N4>=3000000,N4<4000000),N4*1.37,IF(AND(N4>=4000000,N4<5000000),N4*1.36,IF(AND(N4>=5000000,N4<6000000),N4*1.35,IF(AND(N4>=6000000,N4<7000000),N4*1.34,IF(AND(N4>=7000000,N4<8000000),N4*1.33,IF(AND(N4>=8000000,N4<9000000),N4*1.32,IF(AND(N4>=9000000,N4<10000000),N4*1.31,IF(N4>=10000000,N4*1.3,""))))))))))))))))))))))))))))))))))))))) -> 111972 | Y4: =CEILING((R4+W4+X4)/3,1000) -> 107000 | Z4: 0 | AA4: =CEILING((Y4+Z4),1000) -> 107000 | AB4: =AA4-N4 -> 41900 | AC4: =AB4/AA4 -> 0.39158879 | AD4: 30 | AE4: =AD4/30 -> 1 | AF4: 10 | AG4: =AF4/30 -> 0.33333333 | AH4: 0.7 | AI4: =(AE4+AG4)*AH4 -> 0.93333333 | AJ4: =AI4*30 -> 28 | AK4: - | AL4: =K4 -> MOBIL Transmission Oil Dexron-VI ATF 1L | AM4: =_xlfn.XLOOKUP(AL4,ITEM!B:B,ITEM!AY:AY,0) -> 764 | AN4: =_xlfn.XLOOKUP(AL4,ITEM!B:B,ITEM!AZ:AZ,0) -> 103.5 | AO4: =_xlfn.XLOOKUP(AL4,ITEM!B:B,ITEM!BA:BA,0) -> 68.454545 | AP4: =AN4/AO4 -> 1.5119522 | AQ4: 0 | AR4: 0 | AS4: 0 | AT4: =AN4*$AI4 -> 96.6 | AU4: =AN4*(AE4+AG4+AI4) -> 234.6 | AV4: =_xlfn.XLOOKUP(AL4,ITEM!B:B,ITEM!BN:BN,0) -> 180 | AW4: 0 | AX4: 0 | AY4: =AU4-AV4-AW4+AX4 -> 54.6 | AZ4: 120 | BA4: =AZ4/BC4 -> 10 | BB4: =H4 -> 12*1L | BC4: 12 | BD4: - | BE4: - | BF4: ★★★ | BG4: - | BH4: =K4 -> MOBIL Transmission Oil Dexron-VI ATF 1L | BI4: =AM4 -> 764 | BJ4: =BZ4 -> 8 | BK4: =CK4 -> 112 | BL4: =CV4 -> 60 | BM4: =BJ4+BK4+BL4 -> 180 | BN4: =CC4 -> 76.244444 | BO4: =CN4 -> 38.355556 | BP4: =AY4 -> 54.6 | BQ4: 24 | BS4: =K4 -> MOBIL Transmission Oil Dexron-VI ATF 1L | BT4: =_xlfn.XLOOKUP(BS4,ITEM!B:B,ITEM!BB:BB,0) -> 37.166667 | BU4: =_xlfn.XLOOKUP(BS4,ITEM!B:B,ITEM!BC:BC,0) -> 32.272727 | BV4: =BT4/BU4 -> 1.1516432 | BW4: 0 | BX4: =BT4*$AI4 -> 34.688889 | BY4: =BT4*($AE4+$AG4+$AI4) -> 84.244444 | BZ4: =_xlfn.XLOOKUP(BS4,ITEM!B:B,ITEM!BK:BK,0) -> 8 | CA4: 0 | CB4: 0 | CC4: =BY4-BZ4-CA4+CB4 -> 76.244444 | CD4: 0 | CE4: =_xlfn.XLOOKUP(BS4,ITEM!B:B,ITEM!BE:BE,0) -> 66.333333 | CF4: =_xlfn.XLOOKUP(BS4,ITEM!B:B,ITEM!BF:BF,0) -> 66.333333 | CG4: =CE4/CF4 -> 1 | CH4: 0 | CI4: =CE4*$AI4 -> 61.911111 | CJ4: =CE4*($AE4+$AG4+$AI4) -> 150.35556 | CK4: =_xlfn.XLOOKUP(BS4,ITEM!B:B,ITEM!BL:BL,0) -> 112 | CL4: 0 | CM4: 0 | CN4: =CJ4-CK4-CL4+CM4 -> 38.355556 | CO4: 0 | CP4: =_xlfn.XLOOKUP(BS4,ITEM!B:B,ITEM!BH:BH,0) -> 0 | CQ4: =_xlfn.XLOOKUP(BS4,ITEM!B:B,ITEM!BI:BI,0) -> 0 | CR4: =CP4/CQ4 -> #DIV/0! | CS4: 0 | CT4: =CP4*$AI4 -> 0 | CU4: =CP4*($AE4+$AG4+$AI4) -> 0 | CV4: =_xlfn.XLOOKUP(BS4,ITEM!B:B,ITEM!BM:BM,0) -> 60 | CW4: 0 | CX4: 0 | CY4: =CU4-CV4-CW4+CX4 -> -60 | CZ4: 0 | DA4: =K4 -> MOBIL Transmission Oil Dexron-VI ATF 1L
A5: 12 | B5: 101753 | C5: CASTROL | D5: Brake Fluid | E5: DOT 3 | F5: - | G5: 500ml | H5: 0 | I5: 0 | J5: =C5&" "&D5&" "&E5&" "&F5&" "&G5 -> CASTROL Brake Fluid DOT 3 - 500ml | K5: CASTROL Brake Fluid DOT 3 - 500ml | L5: 1 | M5: 桶 | N5: 77900 | O5: 0.4 | P5: 0.2 | Q5: =O5+P5 -> 0.6 | R5: =N5*(1+Q5) -> 124640 | S5: 0 | T5: 0 | U5: 0 | V5: =IF((S5+T5+U5)=0,R5,IF(AND(S5>0,T5=0,U5=0),S5,IF(AND(S5=0,T5>0,U5=0),T5,IF(AND(S5=0,T5=0,U5>0),U5,IF(AND(S5>0,T5>0,U5=0),(S5+T5)/2,IF(AND(S5>0,T5=0,U5>0),(S5+U5)/2,IF(AND(S5=0,T5>0,U5>0),(T5+U5)/2,IF(AND(S5>0,T5>0,U5>0),(S5+T5+U5)/3,)))))))) -> 124640 | W5: =IF(R5=V5,V5,IF(R5/V5<70%,R5*1.18,IF(AND(R5/V5>=70%,R5/V5<75%),R5*1.15,IF(AND(R5/V5>=75%,R5/V5<80%),R5*1.12,IF(AND(R5/V5>=80%,R5/V5<85%),R5*1.09,IF(AND(R5/V5>=85%,R5/V5<90%),R5*1.06,IF(AND(R5/V5>=90%,R5/V5<95%),R5*1.03,IF(AND(R5/V5>=95%,R5/V5<105%),V5,IF(AND(R5/V5>=105%,R5/V5<110%),R5*0.97,IF(AND(R5/V5>=110%,R5/V5<115%),R5*0.94,IF(AND(R5/V5>=115%,R5/V5<120%),R5*0.91,IF(AND(R5/V5>=120%,R5/V5<125%),R5*0.88,IF(AND(R5/V5>=125%,R5/V5<130%),R5*0.85,IF(AND(R5/V5>=130%,R5/V5<135%),R5*0.82,IF(R5/V5>=135%,R5*0.8,))))))))))))))) -> 124640 | X5: =IF(N5=0,1,IF(N5<10000,N5*2.8,IF(AND(N5>=10000,N5<20000),N5*2.2,IF(AND(N5>=20000,N5<30000),N5*1.8,IF(AND(N5>=30000,N5<40000),N5*1.78,IF(AND(N5>=40000,N5<50000),N5*1.76,IF(AND(N5>=50000,N5<60000),N5*1.74,IF(AND(N5>=60000,N5<70000),N5*1.72,IF(AND(N5>=70000,N5<80000),N5*1.7,IF(AND(N5>=80000,N5<90000),N5*1.68,IF(AND(N5>=90000,N5<100000),N5*1.66,IF(AND(N5>=100000,N5<110000),N5*1.65,IF(AND(N5>=110000,N5<120000),N5*1.64,IF(AND(N5>=120000,N5<130000),N5*1.63,IF(AND(N5>=130000,N5<140000),N5*1.62,IF(AND(N5>=140000,N5<150000),N5*1.61,IF(AND(N5>=150000,N5<160000),N5*1.6,IF(AND(N5>=160000,N5<170000),N5*1.59,IF(AND(N5>=170000,N5<180000),N5*1.58,IF(AND(N5>=180000,N5<190000),N5*1.57,IF(AND(N5>=190000,N5<200000),N5*1.56,IF(AND(N5>=200000,N5<300000),N5*1.54,IF(AND(N5>=300000,N5<400000),N5*1.52,IF(AND(N5>=400000,N5<500000),N5*1.5,IF(AND(N5>=500000,N5<600000),N5*1.48,IF(AND(N5>=600000,N5<700000),N5*1.46,IF(AND(N5>=700000,N5<800000),N5*1.44,IF(AND(N5>=800000,N5<900000),N5*1.42,IF(AND(N5>=900000,N5<1000000),N5*1.4,IF(AND(N5>=1000000,N5<2000000),N5*1.39,IF(AND(N5>=2000000,N5<3000000),N5*1.38,IF(AND(N5>=3000000,N5<4000000),N5*1.37,IF(AND(N5>=4000000,N5<5000000),N5*1.36,IF(AND(N5>=5000000,N5<6000000),N5*1.35,IF(AND(N5>=6000000,N5<7000000),N5*1.34,IF(AND(N5>=7000000,N5<8000000),N5*1.33,IF(AND(N5>=8000000,N5<9000000),N5*1.32,IF(AND(N5>=9000000,N5<10000000),N5*1.31,IF(N5>=10000000,N5*1.3,""))))))))))))))))))))))))))))))))))))))) -> 132430 | Y5: =CEILING((R5+W5+X5)/3,1000) -> 128000 | Z5: 0 | AA5: =CEILING((Y5+Z5),1000) -> 128000 | AB5: =AA5-N5 -> 50100 | AC5: =AB5/AA5 -> 0.39140625 | AD5: 30 | AE5: =AD5/30 -> 1 | AF5: 10 | AG5: =AF5/30 -> 0.33333333 | AH5: 0.7 | AI5: =(AE5+AG5)*AH5 -> 0.93333333 | AJ5: =AI5*30 -> 28 | AK5: - | AL5: =K5 -> CASTROL Brake Fluid DOT 3 - 500ml | AM5: =_xlfn.XLOOKUP(AL5,ITEM!B:B,ITEM!AY:AY,0) -> 646 | AN5: =_xlfn.XLOOKUP(AL5,ITEM!B:B,ITEM!AZ:AZ,0) -> 66.833333 | AO5: =_xlfn.XLOOKUP(AL5,ITEM!B:B,ITEM!BA:BA,0) -> 58.363636 | AP5: =AN5/AO5 -> 1.1451194 | AQ5: 0 | AR5: 0 | AS5: 0 | AT5: =AN5*$AI5 -> 62.377778 | AU5: =AN5*(AE5+AG5+AI5) -> 151.48889 | AV5: =_xlfn.XLOOKUP(AL5,ITEM!B:B,ITEM!BN:BN,0) -> 1 | AW5: 0 | AX5: 0 | AY5: =AU5-AV5-AW5+AX5 -> 150.48889 | AZ5: 0 | BA5: =AZ5/BC5 -> #DIV/0! | BB5: =H5 -> 0 | BC5: 0 | BD5: - | BE5: - | BF5: ★★ | BG5: ★ | BH5: =K5 -> CASTROL Brake Fluid DOT 3 - 500ml | BI5: =AM5 -> 646 | BJ5: =BZ5 -> 0 | BK5: =CK5 -> 1 | BL5: =CV5 -> 0 | BM5: =BJ5+BK5+BL5 -> 1 | BN5: =CC5 -> 55.533333 | BO5: =CN5 -> 94.955556 | BP5: =AY5 -> 150.48889 | BQ5: - | BS5: =K5 -> CASTROL Brake Fluid DOT 3 - 500ml | BT5: =_xlfn.XLOOKUP(BS5,ITEM!B:B,ITEM!BB:BB,0) -> 24.5 | BU5: =_xlfn.XLOOKUP(BS5,ITEM!B:B,ITEM!BC:BC,0) -> 35.272727 | BV5: =BT5/BU5 -> 0.69458763 | BW5: 0 | BX5: =BT5*$AI5 -> 22.866667 | BY5: =BT5*($AE5+$AG5+$AI5) -> 55.533333 | BZ5: =_xlfn.XLOOKUP(BS5,ITEM!B:B,ITEM!BK:BK,0) -> 0 | CA5: 0 | CB5: 0 | CC5: =BY5-BZ5-CA5+CB5 -> 55.533333 | CD5: 0 | CE5: =_xlfn.XLOOKUP(BS5,ITEM!B:B,ITEM!BE:BE,0) -> 42.333333 | CF5: =_xlfn.XLOOKUP(BS5,ITEM!B:B,ITEM!BF:BF,0) -> 42.333333 | CG5: =CE5/CF5 -> 1 | CH5: 0 | CI5: =CE5*$AI5 -> 39.511111 | CJ5: =CE5*($AE5+$AG5+$AI5) -> 95.955556 | CK5: =_xlfn.XLOOKUP(BS5,ITEM!B:B,ITEM!BL:BL,0) -> 1 | CL5: 0 | CM5: 0 | CN5: =CJ5-CK5-CL5+CM5 -> 94.955556 | CO5: 0 | CP5: =_xlfn.XLOOKUP(BS5,ITEM!B:B,ITEM!BH:BH,0) -> 0 | CQ5: =_xlfn.XLOOKUP(BS5,ITEM!B:B,ITEM!BI:BI,0) -> 0 | CR5: =CP5/CQ5 -> #DIV/0! | CS5: 0 | CT5: =CP5*$AI5 -> 0 | CU5: =CP5*($AE5+$AG5+$AI5) -> 0 | CV5: =_xlfn.XLOOKUP(BS5,ITEM!B:B,ITEM!BM:BM,0) -> 0 | CW5: 0 | CX5: 0 | CY5: =CU5-CV5-CW5+CX5 -> 0 | CZ5: 0 | DA5: =K5 -> CASTROL Brake Fluid DOT 3 - 500ml
A6: 8 | B6: 108112 | C6: SHELL | D6: Transmission Oil | E6: Spirax | F6: ATF 6 | G6: 1L | H6: 12*1L | I6: 12 | J6: =C6&" "&D6&" "&E6&" "&F6&" "&G6 -> SHELL Transmission Oil Spirax ATF 6 1L | K6: SHELL Transmission Oil Spirax ATF 6 1L | L6: 1 | M6: 桶 | N6: 65229 | O6: 0.4 | P6: 0.2 | Q6: =O6+P6 -> 0.6 | R6: =N6*(1+Q6) -> 104366.4 | S6: 0 | T6: 0 | U6: 0 | V6: =IF((S6+T6+U6)=0,R6,IF(AND(S6>0,T6=0,U6=0),S6,IF(AND(S6=0,T6>0,U6=0),T6,IF(AND(S6=0,T6=0,U6>0),U6,IF(AND(S6>0,T6>0,U6=0),(S6+T6)/2,IF(AND(S6>0,T6=0,U6>0),(S6+U6)/2,IF(AND(S6=0,T6>0,U6>0),(T6+U6)/2,IF(AND(S6>0,T6>0,U6>0),(S6+T6+U6)/3,)))))))) -> 104366.4 | W6: =IF(R6=V6,V6,IF(R6/V6<70%,R6*1.18,IF(AND(R6/V6>=70%,R6/V6<75%),R6*1.15,IF(AND(R6/V6>=75%,R6/V6<80%),R6*1.12,IF(AND(R6/V6>=80%,R6/V6<85%),R6*1.09,IF(AND(R6/V6>=85%,R6/V6<90%),R6*1.06,IF(AND(R6/V6>=90%,R6/V6<95%),R6*1.03,IF(AND(R6/V6>=95%,R6/V6<105%),V6,IF(AND(R6/V6>=105%,R6/V6<110%),R6*0.97,IF(AND(R6/V6>=110%,R6/V6<115%),R6*0.94,IF(AND(R6/V6>=115%,R6/V6<120%),R6*0.91,IF(AND(R6/V6>=120%,R6/V6<125%),R6*0.88,IF(AND(R6/V6>=125%,R6/V6<130%),R6*0.85,IF(AND(R6/V6>=130%,R6/V6<135%),R6*0.82,IF(R6/V6>=135%,R6*0.8,))))))))))))))) -> 104366.4 | X6: =IF(N6=0,1,IF(N6<10000,N6*2.8,IF(AND(N6>=10000,N6<20000),N6*2.2,IF(AND(N6>=20000,N6<30000),N6*1.8,IF(AND(N6>=30000,N6<40000),N6*1.78,IF(AND(N6>=40000,N6<50000),N6*1.76,IF(AND(N6>=50000,N6<60000),N6*1.74,IF(AND(N6>=60000,N6<70000),N6*1.72,IF(AND(N6>=70000,N6<80000),N6*1.7,IF(AND(N6>=80000,N6<90000),N6*1.68,IF(AND(N6>=90000,N6<100000),N6*1.66,IF(AND(N6>=100000,N6<110000),N6*1.65,IF(AND(N6>=110000,N6<120000),N6*1.64,IF(AND(N6>=120000,N6<130000),N6*1.63,IF(AND(N6>=130000,N6<140000),N6*1.62,IF(AND(N6>=140000,N6<150000),N6*1.61,IF(AND(N6>=150000,N6<160000),N6*1.6,IF(AND(N6>=160000,N6<170000),N6*1.59,IF(AND(N6>=170000,N6<180000),N6*1.58,IF(AND(N6>=180000,N6<190000),N6*1.57,IF(AND(N6>=190000,N6<200000),N6*1.56,IF(AND(N6>=200000,N6<300000),N6*1.54,IF(AND(N6>=300000,N6<400000),N6*1.52,IF(AND(N6>=400000,N6<500000),N6*1.5,IF(AND(N6>=500000,N6<600000),N6*1.48,IF(AND(N6>=600000,N6<700000),N6*1.46,IF(AND(N6>=700000,N6<800000),N6*1.44,IF(AND(N6>=800000,N6<900000),N6*1.42,IF(AND(N6>=900000,N6<1000000),N6*1.4,IF(AND(N6>=1000000,N6<2000000),N6*1.39,IF(AND(N6>=2000000,N6<3000000),N6*1.38,IF(AND(N6>=3000000,N6<4000000),N6*1.37,IF(AND(N6>=4000000,N6<5000000),N6*1.36,IF(AND(N6>=5000000,N6<6000000),N6*1.35,IF(AND(N6>=6000000,N6<7000000),N6*1.34,IF(AND(N6>=7000000,N6<8000000),N6*1.33,IF(AND(N6>=8000000,N6<9000000),N6*1.32,IF(AND(N6>=9000000,N6<10000000),N6*1.31,IF(N6>=10000000,N6*1.3,""))))))))))))))))))))))))))))))))))))))) -> 112193.88 | Y6: =CEILING((R6+W6+X6)/3,1000) -> 107000 | Z6: 0 | AA6: =CEILING((Y6+Z6),1000) -> 107000 | AB6: =AA6-N6 -> 41771 | AC6: =AB6/AA6 -> 0.39038318 | AD6: 30 | AE6: =AD6/30 -> 1 | AF6: 10 | AG6: =AF6/30 -> 0.33333333 | AH6: 0.7 | AI6: =(AE6+AG6)*AH6 -> 0.93333333 | AJ6: =AI6*30 -> 28 | AK6: - | AL6: =K6 -> SHELL Transmission Oil Spirax ATF 6 1L | AM6: =_xlfn.XLOOKUP(AL6,ITEM!B:B,ITEM!AY:AY,0) -> 347 | AN6: =_xlfn.XLOOKUP(AL6,ITEM!B:B,ITEM!AZ:AZ,0) -> 52.333333 | AO6: =_xlfn.XLOOKUP(AL6,ITEM!B:B,ITEM!BA:BA,0) -> 31.545455 | AP6: =AN6/AO6 -> 1.6589817 | AQ6: 0 | AR6: 0 | AS6: 0 | AT6: =AN6*$AI6 -> 48.844444 | AU6: =AN6*(AE6+AG6+AI6) -> 118.62222 | AV6: =_xlfn.XLOOKUP(AL6,ITEM!B:B,ITEM!BN:BN,0) -> 110 | AW6: 0 | AX6: 0 | AY6: =AU6-AV6-AW6+AX6 -> 8.6222222 | AZ6: 60 | BA6: =AZ6/BC6 -> 5 | BB6: =H6 -> 12*1L | BC6: 12 | BD6: - | BE6: - | BF6: ★★★ | BG6: - | BH6: =K6 -> SHELL Transmission Oil Spirax ATF 6 1L | BI6: =AM6 -> 347 | BJ6: =BZ6 -> 3 | BK6: =CK6 -> 59 | BL6: =CV6 -> 48 | BM6: =BJ6+BK6+BL6 -> 110 | BN6: =CC6 -> 77.466667 | BO6: =CN6 -> -20.844444 | BP6: =AY6 -> 8.6222222 | BQ6: 24 | BS6: =K6 -> SHELL Transmission Oil Spirax ATF 6 1L | BT6: =_xlfn.XLOOKUP(BS6,ITEM!B:B,ITEM!BB:BB,0) -> 35.5 | BU6: =_xlfn.XLOOKUP(BS6,ITEM!B:B,ITEM!BC:BC,0) -> 22.363636 | BV6: =BT6/BU6 -> 1.5873984 | BW6: 0 | BX6: =BT6*$AI6 -> 33.133333 | BY6: =BT6*($AE6+$AG6+$AI6) -> 80.466667 | BZ6: =_xlfn.XLOOKUP(BS6,ITEM!B:B,ITEM!BK:BK,0) -> 3 | CA6: 0 | CB6: 0 | CC6: =BY6-BZ6-CA6+CB6 -> 77.466667 | CD6: 0 | CE6: =_xlfn.XLOOKUP(BS6,ITEM!B:B,ITEM!BE:BE,0) -> 16.833333 | CF6: =_xlfn.XLOOKUP(BS6,ITEM!B:B,ITEM!BF:BF,0) -> 16.833333 | CG6: =CE6/CF6 -> 1 | CH6: 0 | CI6: =CE6*$AI6 -> 15.711111 | CJ6: =CE6*($AE6+$AG6+$AI6) -> 38.155556 | CK6: =_xlfn.XLOOKUP(BS6,ITEM!B:B,ITEM!BL:BL,0) -> 59 | CL6: 0 | CM6: 0 | CN6: =CJ6-CK6-CL6+CM6 -> -20.844444 | CO6: 0 | CP6: =_xlfn.XLOOKUP(BS6,ITEM!B:B,ITEM!BH:BH,0) -> 0 | CQ6: =_xlfn.XLOOKUP(BS6,ITEM!B:B,ITEM!BI:BI,0) -> 0 | CR6: =CP6/CQ6 -> #DIV/0! | CS6: 0 | CT6: =CP6*$AI6 -> 0 | CU6: =CP6*($AE6+$AG6+$AI6) -> 0 | CV6: =_xlfn.XLOOKUP(BS6,ITEM!B:B,ITEM!BM:BM,0) -> 48 | CW6: 0 | CX6: 0 | CY6: =CU6-CV6-CW6+CX6 -> -48 | CZ6: 0 | DA6: =K6 -> SHELL Transmission Oil Spirax ATF 6 1L
A7: 3 | B7: 101760 | C7: MOBIL | D7: Gear Oil | E7: Mobilube-HD | F7: 80W-90 | G7: 1L | H7: 12*1L | I7: 12 | J7: =C7&" "&D7&" "&E7&" "&F7&" "&G7 -> MOBIL Gear Oil Mobilube-HD 80W-90 1L | K7: MOBIL Gear Oil Mobilube-HD 80W-90 1L | L7: 1 | M7: 桶 | N7: 51729 | O7: 0.4 | P7: 0.2 | Q7: =O7+P7 -> 0.6 | R7: =N7*(1+Q7) -> 82766.4 | S7: 0 | T7: 0 | U7: 0 | V7: =IF((S7+T7+U7)=0,R7,IF(AND(S7>0,T7=0,U7=0),S7,IF(AND(S7=0,T7>0,U7=0),T7,IF(AND(S7=0,T7=0,U7>0),U7,IF(AND(S7>0,T7>0,U7=0),(S7+T7)/2,IF(AND(S7>0,T7=0,U7>0),(S7+U7)/2,IF(AND(S7=0,T7>0,U7>0),(T7+U7)/2,IF(AND(S7>0,T7>0,U7>0),(S7+T7+U7)/3,)))))))) -> 82766.4 | W7: =IF(R7=V7,V7,IF(R7/V7<70%,R7*1.18,IF(AND(R7/V7>=70%,R7/V7<75%),R7*1.15,IF(AND(R7/V7>=75%,R7/V7<80%),R7*1.12,IF(AND(R7/V7>=80%,R7/V7<85%),R7*1.09,IF(AND(R7/V7>=85%,R7/V7<90%),R7*1.06,IF(AND(R7/V7>=90%,R7/V7<95%),R7*1.03,IF(AND(R7/V7>=95%,R7/V7<105%),V7,IF(AND(R7/V7>=105%,R7/V7<110%),R7*0.97,IF(AND(R7/V7>=110%,R7/V7<115%),R7*0.94,IF(AND(R7/V7>=115%,R7/V7<120%),R7*0.91,IF(AND(R7/V7>=120%,R7/V7<125%),R7*0.88,IF(AND(R7/V7>=125%,R7/V7<130%),R7*0.85,IF(AND(R7/V7>=130%,R7/V7<135%),R7*0.82,IF(R7/V7>=135%,R7*0.8,))))))))))))))) -> 82766.4 | X7: =IF(N7=0,1,IF(N7<10000,N7*2.8,IF(AND(N7>=10000,N7<20000),N7*2.2,IF(AND(N7>=20000,N7<30000),N7*1.8,IF(AND(N7>=30000,N7<40000),N7*1.78,IF(AND(N7>=40000,N7<50000),N7*1.76,IF(AND(N7>=50000,N7<60000),N7*1.74,IF(AND(N7>=60000,N7<70000),N7*1.72,IF(AND(N7>=70000,N7<80000),N7*1.7,IF(AND(N7>=80000,N7<90000),N7*1.68,IF(AND(N7>=90000,N7<100000),N7*1.66,IF(AND(N7>=100000,N7<110000),N7*1.65,IF(AND(N7>=110000,N7<120000),N7*1.64,IF(AND(N7>=120000,N7<130000),N7*1.63,IF(AND(N7>=130000,N7<140000),N7*1.62,IF(AND(N7>=140000,N7<150000),N7*1.61,IF(AND(N7>=150000,N7<160000),N7*1.6,IF(AND(N7>=160000,N7<170000),N7*1.59,IF(AND(N7>=170000,N7<180000),N7*1.58,IF(AND(N7>=180000,N7<190000),N7*1.57,IF(AND(N7>=190000,N7<200000),N7*1.56,IF(AND(N7>=200000,N7<300000),N7*1.54,IF(AND(N7>=300000,N7<400000),N7*1.52,IF(AND(N7>=400000,N7<500000),N7*1.5,IF(AND(N7>=500000,N7<600000),N7*1.48,IF(AND(N7>=600000,N7<700000),N7*1.46,IF(AND(N7>=700000,N7<800000),N7*1.44,IF(AND(N7>=800000,N7<900000),N7*1.42,IF(AND(N7>=900000,N7<1000000),N7*1.4,IF(AND(N7>=1000000,N7<2000000),N7*1.39,IF(AND(N7>=2000000,N7<3000000),N7*1.38,IF(AND(N7>=3000000,N7<4000000),N7*1.37,IF(AND(N7>=4000000,N7<5000000),N7*1.36,IF(AND(N7>=5000000,N7<6000000),N7*1.35,IF(AND(N7>=6000000,N7<7000000),N7*1.34,IF(AND(N7>=7000000,N7<8000000),N7*1.33,IF(AND(N7>=8000000,N7<9000000),N7*1.32,IF(AND(N7>=9000000,N7<10000000),N7*1.31,IF(N7>=10000000,N7*1.3,""))))))))))))))))))))))))))))))))))))))) -> 90008.46 | Y7: =CEILING((R7+W7+X7)/3,1000) -> 86000 | Z7: 0 | AA7: =CEILING((Y7+Z7),1000) -> 86000 | AB7: =AA7-N7 -> 34271 | AC7: =AB7/AA7 -> 0.3985 | AD7: 30 | AE7: =AD7/30 -> 1 | AF7: 10 | AG7: =AF7/30 -> 0.33333333 | AH7: 0.7 | AI7: =(AE7+AG7)*AH7 -> 0.93333333 | AJ7: =AI7*30 -> 28 | AK7: - | AL7: =K7 -> MOBIL Gear Oil Mobilube-HD 80W-90 1L | AM7: =_xlfn.XLOOKUP(AL7,ITEM!B:B,ITEM!AY:AY,0) -> 324 | AN7: =_xlfn.XLOOKUP(AL7,ITEM!B:B,ITEM!AZ:AZ,0) -> 18.333333 | AO7: =_xlfn.XLOOKUP(AL7,ITEM!B:B,ITEM!BA:BA,0) -> 29.181818 | AP7: =AN7/AO7 -> 0.62824507 | AQ7: 0 | AR7: 0 | AS7: 0 | AT7: =AN7*$AI7 -> 17.111111 | AU7: =AN7*(AE7+AG7+AI7) -> 41.555556 | AV7: =_xlfn.XLOOKUP(AL7,ITEM!B:B,ITEM!BN:BN,0) -> 78 | AW7: 0 | AX7: 0 | AY7: =AU7-AV7-AW7+AX7 -> -36.444444 | AZ7: 36 | BA7: =AZ7/BC7 -> 3 | BB7: =H7 -> 12*1L | BC7: 12 | BD7: - | BE7: - | BF7: ★★★ | BG7: - | BH7: =K7 -> MOBIL Gear Oil Mobilube-HD 80W-90 1L | BI7: =AM7 -> 324 | BJ7: =BZ7 -> 25 | BK7: =CK7 -> 17 | BL7: =CV7 -> 36 | BM7: =BJ7+BK7+BL7 -> 78 | BN7: =CC7 -> 9.3777778 | BO7: =CN7 -> -9.8222222 | BP7: =AY7 -> -36.444444 | BQ7: - | BS7: =K7 -> MOBIL Gear Oil Mobilube-HD 80W-90 1L | BT7: =_xlfn.XLOOKUP(BS7,ITEM!B:B,ITEM!BB:BB,0) -> 15.166667 | BU7: =_xlfn.XLOOKUP(BS7,ITEM!B:B,ITEM!BC:BC,0) -> 27.454545 | BV7: =BT7/BU7 -> 0.55242826 | BW7: 0 | BX7: =BT7*$AI7 -> 14.155556 | BY7: =BT7*($AE7+$AG7+$AI7) -> 34.377778 | BZ7: =_xlfn.XLOOKUP(BS7,ITEM!B:B,ITEM!BK:BK,0) -> 25 | CA7: 0 | CB7: 0 | CC7: =BY7-BZ7-CA7+CB7 -> 9.3777778 | CD7: 0 | CE7: =_xlfn.XLOOKUP(BS7,ITEM!B:B,ITEM!BE:BE,0) -> 3.1666667 | CF7: =_xlfn.XLOOKUP(BS7,ITEM!B:B,ITEM!BF:BF,0) -> 3.1666667 | CG7: =CE7/CF7 -> 1 | CH7: 0 | CI7: =CE7*$AI7 -> 2.9555556 | CJ7: =CE7*($AE7+$AG7+$AI7) -> 7.1777778 | CK7: =_xlfn.XLOOKUP(BS7,ITEM!B:B,ITEM!BL:BL,0) -> 17 | CL7: 0 | CM7: 0 | CN7: =CJ7-CK7-CL7+CM7 -> -9.8222222 | CO7: 0 | CP7: =_xlfn.XLOOKUP(BS7,ITEM!B:B,ITEM!BH:BH,0) -> 0 | CQ7: =_xlfn.XLOOKUP(BS7,ITEM!B:B,ITEM!BI:BI,0) -> 0 | CR7: =CP7/CQ7 -> #DIV/0! | CS7: 0 | CT7: =CP7*$AI7 -> 0 | CU7: =CP7*($AE7+$AG7+$AI7) -> 0 | CV7: =_xlfn.XLOOKUP(BS7,ITEM!B:B,ITEM!BM:BM,0) -> 36 | CW7: 0 | CX7: 0 | CY7: =CU7-CV7-CW7+CX7 -> -36 | CZ7: 0 | DA7: =K7 -> MOBIL Gear Oil Mobilube-HD 80W-90 1L
A8: 1 | B8: 108296 | C8: MOBIL | D8: Transmission Oil | E8: CVTF | F8: Multi-Vehicle | G8: 1L | H8: 12*1L | I8: 12 | J8: =C8&" "&D8&" "&E8&" "&F8&" "&G8 -> MOBIL Transmission Oil CVTF Multi-Vehicle 1L | K8: MOBIL Transmission Oil CVTF Multi-Vehicle 1L | L8: 1 | M8: 桶 | N8: 77900 | O8: 0.4 | P8: 0.2 | Q8: =O8+P8 -> 0.6 | R8: =N8*(1+Q8) -> 124640 | S8: 0 | T8: 0 | U8: 0 | V8: =IF((S8+T8+U8)=0,R8,IF(AND(S8>0,T8=0,U8=0),S8,IF(AND(S8=0,T8>0,U8=0),T8,IF(AND(S8=0,T8=0,U8>0),U8,IF(AND(S8>0,T8>0,U8=0),(S8+T8)/2,IF(AND(S8>0,T8=0,U8>0),(S8+U8)/2,IF(AND(S8=0,T8>0,U8>0),(T8+U8)/2,IF(AND(S8>0,T8>0,U8>0),(S8+T8+U8)/3,)))))))) -> 124640 | W8: =IF(R8=V8,V8,IF(R8/V8<70%,R8*1.18,IF(AND(R8/V8>=70%,R8/V8<75%),R8*1.15,IF(AND(R8/V8>=75%,R8/V8<80%),R8*1.12,IF(AND(R8/V8>=80%,R8/V8<85%),R8*1.09,IF(AND(R8/V8>=85%,R8/V8<90%),R8*1.06,IF(AND(R8/V8>=90%,R8/V8<95%),R8*1.03,IF(AND(R8/V8>=95%,R8/V8<105%),V8,IF(AND(R8/V8>=105%,R8/V8<110%),R8*0.97,IF(AND(R8/V8>=110%,R8/V8<115%),R8*0.94,IF(AND(R8/V8>=115%,R8/V8<120%),R8*0.91,IF(AND(R8/V8>=120%,R8/V8<125%),R8*0.88,IF(AND(R8/V8>=125%,R8/V8<130%),R8*0.85,IF(AND(R8/V8>=130%,R8/V8<135%),R8*0.82,IF(R8/V8>=135%,R8*0.8,))))))))))))))) -> 124640 | X8: =IF(N8=0,1,IF(N8<10000,N8*2.8,IF(AND(N8>=10000,N8<20000),N8*2.2,IF(AND(N8>=20000,N8<30000),N8*1.8,IF(AND(N8>=30000,N8<40000),N8*1.78,IF(AND(N8>=40000,N8<50000),N8*1.76,IF(AND(N8>=50000,N8<60000),N8*1.74,IF(AND(N8>=60000,N8<70000),N8*1.72,IF(AND(N8>=70000,N8<80000),N8*1.7,IF(AND(N8>=80000,N8<90000),N8*1.68,IF(AND(N8>=90000,N8<100000),N8*1.66,IF(AND(N8>=100000,N8<110000),N8*1.65,IF(AND(N8>=110000,N8<120000),N8*1.64,IF(AND(N8>=120000,N8<130000),N8*1.63,IF(AND(N8>=130000,N8<140000),N8*1.62,IF(AND(N8>=140000,N8<150000),N8*1.61,IF(AND(N8>=150000,N8<160000),N8*1.6,IF(AND(N8>=160000,N8<170000),N8*1.59,IF(AND(N8>=170000,N8<180000),N8*1.58,IF(AND(N8>=180000,N8<190000),N8*1.57,IF(AND(N8>=190000,N8<200000),N8*1.56,IF(AND(N8>=200000,N8<300000),N8*1.54,IF(AND(N8>=300000,N8<400000),N8*1.52,IF(AND(N8>=400000,N8<500000),N8*1.5,IF(AND(N8>=500000,N8<600000),N8*1.48,IF(AND(N8>=600000,N8<700000),N8*1.46,IF(AND(N8>=700000,N8<800000),N8*1.44,IF(AND(N8>=800000,N8<900000),N8*1.42,IF(AND(N8>=900000,N8<1000000),N8*1.4,IF(AND(N8>=1000000,N8<2000000),N8*1.39,IF(AND(N8>=2000000,N8<3000000),N8*1.38,IF(AND(N8>=3000000,N8<4000000),N8*1.37,IF(AND(N8>=4000000,N8<5000000),N8*1.36,IF(AND(N8>=5000000,N8<6000000),N8*1.35,IF(AND(N8>=6000000,N8<7000000),N8*1.34,IF(AND(N8>=7000000,N8<8000000),N8*1.33,IF(AND(N8>=8000000,N8<9000000),N8*1.32,IF(AND(N8>=9000000,N8<10000000),N8*1.31,IF(N8>=10000000,N8*1.3,""))))))))))))))))))))))))))))))))))))))) -> 132430 | Y8: =CEILING((R8+W8+X8)/3,1000) -> 128000 | Z8: 0 | AA8: =CEILING((Y8+Z8),1000) -> 128000 | AB8: =AA8-N8 -> 50100 | AC8: =AB8/AA8 -> 0.39140625 | AD8: 30 | AE8: =AD8/30 -> 1 | AF8: 10 | AG8: =AF8/30 -> 0.33333333 | AH8: 0.7 | AI8: =(AE8+AG8)*AH8 -> 0.93333333 | AJ8: =AI8*30 -> 28 | AK8: - | AL8: =K8 -> MOBIL Transmission Oil CVTF Multi-Vehicle 1L | AM8: =_xlfn.XLOOKUP(AL8,ITEM!B:B,ITEM!AY:AY,0) -> 288 | AN8: =_xlfn.XLOOKUP(AL8,ITEM!B:B,ITEM!AZ:AZ,0) -> 48 | AO8: =_xlfn.XLOOKUP(AL8,ITEM!B:B,ITEM!BA:BA,0) -> 26.181818 | AP8: =AN8/AO8 -> 1.8333333 | AQ8: 0 | AR8: 0 | AS8: 0 | AT8: =AN8*$AI8 -> 44.8 | AU8: =AN8*(AE8+AG8+AI8) -> 108.8 | AV8: =_xlfn.XLOOKUP(AL8,ITEM!B:B,ITEM!BN:BN,0) -> 66 | AW8: 0 | AX8: 0 | AY8: =AU8-AV8-AW8+AX8 -> 42.8 | AZ8: 120 | BA8: =AZ8/BC8 -> 10 | BB8: =H8 -> 12*1L | BC8: 12 | BD8: - | BE8: - | BF8: ★★★ | BG8: - | BH8: =K8 -> MOBIL Transmission Oil CVTF Multi-Vehicle 1L | BI8: =AM8 -> 288 | BJ8: =BZ8 -> 4 | BK8: =CK8 -> 14 | BL8: =CV8 -> 48 | BM8: =BJ8+BK8+BL8 -> 66 | BN8: =CC8 -> 41.333333 | BO8: =CN8 -> 48.333333 | BP8: =AY8 -> 42.8 | BQ8: 24 | BR8: 24 | BS8: =K8 -> MOBIL Transmission Oil CVTF Multi-Vehicle 1L | BT8: =_xlfn.XLOOKUP(BS8,ITEM!B:B,ITEM!BB:BB,0) -> 20 | BU8: =_xlfn.XLOOKUP(BS8,ITEM!B:B,ITEM!BC:BC,0) -> 10.909091 | BV8: =BT8/BU8 -> 1.8333333 | BW8: 0 | BX8: =BT8*$AI8 -> 18.666667 | BY8: =BT8*($AE8+$AG8+$AI8) -> 45.333333 | BZ8: =_xlfn.XLOOKUP(BS8,ITEM!B:B,ITEM!BK:BK,0) -> 4 | CA8: 0 | CB8: 0 | CC8: =BY8-BZ8-CA8+CB8 -> 41.333333 | CD8: 0 | CE8: =_xlfn.XLOOKUP(BS8,ITEM!B:B,ITEM!BE:BE,0) -> 27.5 | CF8: =_xlfn.XLOOKUP(BS8,ITEM!B:B,ITEM!BF:BF,0) -> 27.5 | CG8: =CE8/CF8 -> 1 | CH8: 0 | CI8: =CE8*$AI8 -> 25.666667 | CJ8: =CE8*($AE8+$AG8+$AI8) -> 62.333333 | CK8: =_xlfn.XLOOKUP(BS8,ITEM!B:B,ITEM!BL:BL,0) -> 14 | CL8: 0 | CM8: 0 | CN8: =CJ8-CK8-CL8+CM8 -> 48.333333 | CO8: 0 | CP8: =_xlfn.XLOOKUP(BS8,ITEM!B:B,ITEM!BH:BH,0) -> 0.5 | CQ8: =_xlfn.XLOOKUP(BS8,ITEM!B:B,ITEM!BI:BI,0) -> 0.5 | CR8: =CP8/CQ8 -> 1 | CS8: 0 | CT8: =CP8*$AI8 -> 0.46666667 | CU8: =CP8*($AE8+$AG8+$AI8) -> 1.1333333 | CV8: =_xlfn.XLOOKUP(BS8,ITEM!B:B,ITEM!BM:BM,0) -> 48 | CW8: 0 | CX8: 0 | CY8: =CU8-CV8-CW8+CX8 -> -46.866667 | CZ8: 0 | DA8: =K8 -> MOBIL Transmission Oil CVTF Multi-Vehicle 1L
A9: 16 | B9: 102253 | C9: PRESTONE | D9: Brake Fluid | E9: DOT 3 | F9: - | G9: 1000ml | H9: 0 | I9: 0 | J9: =C9&" "&D9&" "&E9&" "&F9&" "&G9 -> PRESTONE Brake Fluid DOT 3 - 1000ml | K9: PRESTONE Brake Fluid DOT 3 - 1000ml | L9: 1 | M9: 桶 | N9: 171570 | O9: 0.4 | P9: 0.2 | Q9: =O9+P9 -> 0.6 | R9: =N9*(1+Q9) -> 274512 | S9: 0 | T9: 0 | U9: 0 | V9: =IF((S9+T9+U9)=0,R9,IF(AND(S9>0,T9=0,U9=0),S9,IF(AND(S9=0,T9>0,U9=0),T9,IF(AND(S9=0,T9=0,U9>0),U9,IF(AND(S9>0,T9>0,U9=0),(S9+T9)/2,IF(AND(S9>0,T9=0,U9>0),(S9+U9)/2,IF(AND(S9=0,T9>0,U9>0),(T9+U9)/2,IF(AND(S9>0,T9>0,U9>0),(S9+T9+U9)/3,)))))))) -> 274512 | W9: =IF(R9=V9,V9,IF(R9/V9<70%,R9*1.18,IF(AND(R9/V9>=70%,R9/V9<75%),R9*1.15,IF(AND(R9/V9>=75%,R9/V9<80%),R9*1.12,IF(AND(R9/V9>=80%,R9/V9<85%),R9*1.09,IF(AND(R9/V9>=85%,R9/V9<90%),R9*1.06,IF(AND(R9/V9>=90%,R9/V9<95%),R9*1.03,IF(AND(R9/V9>=95%,R9/V9<105%),V9,IF(AND(R9/V9>=105%,R9/V9<110%),R9*0.97,IF(AND(R9/V9>=110%,R9/V9<115%),R9*0.94,IF(AND(R9/V9>=115%,R9/V9<120%),R9*0.91,IF(AND(R9/V9>=120%,R9/V9<125%),R9*0.88,IF(AND(R9/V9>=125%,R9/V9<130%),R9*0.85,IF(AND(R9/V9>=130%,R9/V9<135%),R9*0.82,IF(R9/V9>=135%,R9*0.8,))))))))))))))) -> 274512 | X9: =IF(N9=0,1,IF(N9<10000,N9*2.8,IF(AND(N9>=10000,N9<20000),N9*2.2,IF(AND(N9>=20000,N9<30000),N9*1.8,IF(AND(N9>=30000,N9<40000),N9*1.78,IF(AND(N9>=40000,N9<50000),N9*1.76,IF(AND(N9>=50000,N9<60000),N9*1.74,IF(AND(N9>=60000,N9<70000),N9*1.72,IF(AND(N9>=70000,N9<80000),N9*1.7,IF(AND(N9>=80000,N9<90000),N9*1.68,IF(AND(N9>=90000,N9<100000),N9*1.66,IF(AND(N9>=100000,N9<110000),N9*1.65,IF(AND(N9>=110000,N9<120000),N9*1.64,IF(AND(N9>=120000,N9<130000),N9*1.63,IF(AND(N9>=130000,N9<140000),N9*1.62,IF(AND(N9>=140000,N9<150000),N9*1.61,IF(AND(N9>=150000,N9<160000),N9*1.6,IF(AND(N9>=160000,N9<170000),N9*1.59,IF(AND(N9>=170000,N9<180000),N9*1.58,IF(AND(N9>=180000,N9<190000),N9*1.57,IF(AND(N9>=190000,N9<200000),N9*1.56,IF(AND(N9>=200000,N9<300000),N9*1.54,IF(AND(N9>=300000,N9<400000),N9*1.52,IF(AND(N9>=400000,N9<500000),N9*1.5,IF(AND(N9>=500000,N9<600000),N9*1.48,IF(AND(N9>=600000,N9<700000),N9*1.46,IF(AND(N9>=700000,N9<800000),N9*1.44,IF(AND(N9>=800000,N9<900000),N9*1.42,IF(AND(N9>=900000,N9<1000000),N9*1.4,IF(AND(N9>=1000000,N9<2000000),N9*1.39,IF(AND(N9>=2000000,N9<3000000),N9*1.38,IF(AND(N9>=3000000,N9<4000000),N9*1.37,IF(AND(N9>=4000000,N9<5000000),N9*1.36,IF(AND(N9>=5000000,N9<6000000),N9*1.35,IF(AND(N9>=6000000,N9<7000000),N9*1.34,IF(AND(N9>=7000000,N9<8000000),N9*1.33,IF(AND(N9>=8000000,N9<9000000),N9*1.32,IF(AND(N9>=9000000,N9<10000000),N9*1.31,IF(N9>=10000000,N9*1.3,""))))))))))))))))))))))))))))))))))))))) -> 271080.6 | Y9: =CEILING((R9+W9+X9)/3,1000) -> 274000 | Z9: 0 | AA9: =CEILING((Y9+Z9),1000) -> 274000 | AB9: =AA9-N9 -> 102430 | AC9: =AB9/AA9 -> 0.37383212 | AD9: 30 | AE9: =AD9/30 -> 1 | AF9: 10 | AG9: =AF9/30 -> 0.33333333 | AH9: 0.7 | AI9: =(AE9+AG9)*AH9 -> 0.93333333 | AJ9: =AI9*30 -> 28 | AK9: - | AL9: =K9 -> PRESTONE Brake Fluid DOT 3 - 1000ml | AM9: =_xlfn.XLOOKUP(AL9,ITEM!B:B,ITEM!AY:AY,0) -> 277 | AN9: =_xlfn.XLOOKUP(AL9,ITEM!B:B,ITEM!AZ:AZ,0) -> 35.833333 | AO9: =_xlfn.XLOOKUP(AL9,ITEM!B:B,ITEM!BA:BA,0) -> 25.181818 | AP9: =AN9/AO9 -> 1.4229844 | AQ9: 0 | AR9: 0 | AS9: 0 | AT9: =AN9*$AI9 -> 33.444444 | AU9: =AN9*(AE9+AG9+AI9) -> 81.222222 | AV9: =_xlfn.XLOOKUP(AL9,ITEM!B:B,ITEM!BN:BN,0) -> 0 | AW9: 0 | AX9: 0 | AY9: =AU9-AV9-AW9+AX9 -> 81.222222 | AZ9: 0 | BA9: =AZ9/BC9 -> #DIV/0! | BB9: =H9 -> 0 | BC9: 0 | BD9: - | BE9: - | BF9: ★ | BG9: ★ | BH9: =K9 -> PRESTONE Brake Fluid DOT 3 - 1000ml | BI9: =AM9 -> 277 | BJ9: =BZ9 -> 0 | BK9: =CK9 -> 0 | BL9: =CV9 -> 0 | BM9: =BJ9+BK9+BL9 -> 0 | BN9: =CC9 -> 60.444444 | BO9: =CN9 -> 20.777778 | BP9: =AY9 -> 81.222222 | BQ9: - | BS9: =K9 -> PRESTONE Brake Fluid DOT 3 - 1000ml | BT9: =_xlfn.XLOOKUP(BS9,ITEM!B:B,ITEM!BB:BB,0) -> 26.666667 | BU9: =_xlfn.XLOOKUP(BS9,ITEM!B:B,ITEM!BC:BC,0) -> 20.181818 | BV9: =BT9/BU9 -> 1.3213213 | BW9: 0 | BX9: =BT9*$AI9 -> 24.888889 | BY9: =BT9*($AE9+$AG9+$AI9) -> 60.444444 | BZ9: =_xlfn.XLOOKUP(BS9,ITEM!B:B,ITEM!BK:BK,0) -> 0 | CA9: 0 | CB9: 0 | CC9: =BY9-BZ9-CA9+CB9 -> 60.444444 | CD9: 0 | CE9: =_xlfn.XLOOKUP(BS9,ITEM!B:B,ITEM!BE:BE,0) -> 9.1666667 | CF9: =_xlfn.XLOOKUP(BS9,ITEM!B:B,ITEM!BF:BF,0) -> 9.1666667 | CG9: =CE9/CF9 -> 1 | CH9: 0 | CI9: =CE9*$AI9 -> 8.5555556 | CJ9: =CE9*($AE9+$AG9+$AI9) -> 20.777778 | CK9: =_xlfn.XLOOKUP(BS9,ITEM!B:B,ITEM!BL:BL,0) -> 0 | CL9: 0 | CM9: 0 | CN9: =CJ9-CK9-CL9+CM9 -> 20.777778 | CO9: 0 | CP9: =_xlfn.XLOOKUP(BS9,ITEM!B:B,ITEM!BH:BH,0) -> 0 | CQ9: =_xlfn.XLOOKUP(BS9,ITEM!B:B,ITEM!BI:BI,0) -> 0 | CR9: =CP9/CQ9 -> #DIV/0! | CS9: 0 | CT9: =CP9*$AI9 -> 0 | CU9: =CP9*($AE9+$AG9+$AI9) -> 0 | CV9: =_xlfn.XLOOKUP(BS9,ITEM!B:B,ITEM!BM:BM,0) -> 0 | CW9: 0 | CX9: 0 | CY9: =CU9-CV9-CW9+CX9 -> 0 | CZ9: 0 | DA9: =K9 -> PRESTONE Brake Fluid DOT 3 - 1000ml
A10: 10 | B10: 108237 | C10: SHELL | D10: Axle Oil | E10: Spirax | F10: S2 A 80W-90 | G10: 1L | H10: 12*1L | I10: 12 | J10: =C10&" "&D10&" "&E10&" "&F10&" "&G10 -> SHELL Axle Oil Spirax S2 A 80W-90 1L | K10: SHELL Axle Oil Spirax S2 A 80W-90 1L | L10: 1 | M10: 桶 | N10: 51524 | O10: 0.4 | P10: 0.2 | Q10: =O10+P10 -> 0.6 | R10: =N10*(1+Q10) -> 82438.4 | S10: 0 | T10: 0 | U10: 0 | V10: =IF((S10+T10+U10)=0,R10,IF(AND(S10>0,T10=0,U10=0),S10,IF(AND(S10=0,T10>0,U10=0),T10,IF(AND(S10=0,T10=0,U10>0),U10,IF(AND(S10>0,T10>0,U10=0),(S10+T10)/2,IF(AND(S10>0,T10=0,U10>0),(S10+U10)/2,IF(AND(S10=0,T10>0,U10>0),(T10+U10)/2,IF(AND(S10>0,T10>0,U10>0),(S10+T10+U10)/3,)))))))) -> 82438.4 | W10: =IF(R10=V10,V10,IF(R10/V10<70%,R10*1.18,IF(AND(R10/V10>=70%,R10/V10<75%),R10*1.15,IF(AND(R10/V10>=75%,R10/V10<80%),R10*1.12,IF(AND(R10/V10>=80%,R10/V10<85%),R10*1.09,IF(AND(R10/V10>=85%,R10/V10<90%),R10*1.06,IF(AND(R10/V10>=90%,R10/V10<95%),R10*1.03,IF(AND(R10/V10>=95%,R10/V10<105%),V10,IF(AND(R10/V10>=105%,R10/V10<110%),R10*0.97,IF(AND(R10/V10>=110%,R10/V10<115%),R10*0.94,IF(AND(R10/V10>=115%,R10/V10<120%),R10*0.91,IF(AND(R10/V10>=120%,R10/V10<125%),R10*0.88,IF(AND(R10/V10>=125%,R10/V10<130%),R10*0.85,IF(AND(R10/V10>=130%,R10/V10<135%),R10*0.82,IF(R10/V10>=135%,R10*0.8,))))))))))))))) -> 82438.4 | X10: =IF(N10=0,1,IF(N10<10000,N10*2.8,IF(AND(N10>=10000,N10<20000),N10*2.2,IF(AND(N10>=20000,N10<30000),N10*1.8,IF(AND(N10>=30000,N10<40000),N10*1.78,IF(AND(N10>=40000,N10<50000),N10*1.76,IF(AND(N10>=50000,N10<60000),N10*1.74,IF(AND(N10>=60000,N10<70000),N10*1.72,IF(AND(N10>=70000,N10<80000),N10*1.7,IF(AND(N10>=80000,N10<90000),N10*1.68,IF(AND(N10>=90000,N10<100000),N10*1.66,IF(AND(N10>=100000,N10<110000),N10*1.65,IF(AND(N10>=110000,N10<120000),N10*1.64,IF(AND(N10>=120000,N10<130000),N10*1.63,IF(AND(N10>=130000,N10<140000),N10*1.62,IF(AND(N10>=140000,N10<150000),N10*1.61,IF(AND(N10>=150000,N10<160000),N10*1.6,IF(AND(N10>=160000,N10<170000),N10*1.59,IF(AND(N10>=170000,N10<180000),N10*1.58,IF(AND(N10>=180000,N10<190000),N10*1.57,IF(AND(N10>=190000,N10<200000),N10*1.56,IF(AND(N10>=200000,N10<300000),N10*1.54,IF(AND(N10>=300000,N10<400000),N10*1.52,IF(AND(N10>=400000,N10<500000),N10*1.5,IF(AND(N10>=500000,N10<600000),N10*1.48,IF(AND(N10>=600000,N10<700000),N10*1.46,IF(AND(N10>=700000,N10<800000),N10*1.44,IF(AND(N10>=800000,N10<900000),N10*1.42,IF(AND(N10>=900000,N10<1000000),N10*1.4,IF(AND(N10>=1000000,N10<2000000),N10*1.39,IF(AND(N10>=2000000,N10<3000000),N10*1.38,IF(AND(N10>=3000000,N10<4000000),N10*1.37,IF(AND(N10>=4000000,N10<5000000),N10*1.36,IF(AND(N10>=5000000,N10<6000000),N10*1.35,IF(AND(N10>=6000000,N10<7000000),N10*1.34,IF(AND(N10>=7000000,N10<8000000),N10*1.33,IF(AND(N10>=8000000,N10<9000000),N10*1.32,IF(AND(N10>=9000000,N10<10000000),N10*1.31,IF(N10>=10000000,N10*1.3,""))))))))))))))))))))))))))))))))))))))) -> 89651.76 | Y10: =CEILING((R10+W10+X10)/3,1000) -> 85000 | Z10: 0 | AA10: =CEILING((Y10+Z10),1000) -> 85000 | AB10: =AA10-N10 -> 33476 | AC10: =AB10/AA10 -> 0.39383529 | AD10: 30 | AE10: =AD10/30 -> 1 | AF10: 10 | AG10: =AF10/30 -> 0.33333333 | AH10: 0.7 | AI10: =(AE10+AG10)*AH10 -> 0.93333333 | AJ10: =AI10*30 -> 28 | AK10: - | AL10: =K10 -> SHELL Axle Oil Spirax S2 A 80W-90 1L | AM10: =_xlfn.XLOOKUP(AL10,ITEM!B:B,ITEM!AY:AY,0) -> 276 | AN10: =_xlfn.XLOOKUP(AL10,ITEM!B:B,ITEM!AZ:AZ,0) -> 46 | AO10: =_xlfn.XLOOKUP(AL10,ITEM!B:B,ITEM!BA:BA,0) -> 25.090909 | AP10: =AN10/AO10 -> 1.8333333 | AQ10: 0 | AR10: 0 | AS10: 0 | AT10: =AN10*$AI10 -> 42.933333 | AU10: =AN10*(AE10+AG10+AI10) -> 104.26667 | AV10: =_xlfn.XLOOKUP(AL10,ITEM!B:B,ITEM!BN:BN,0) -> 109 | AW10: 0 | AX10: 0 | AY10: =AU10-AV10-AW10+AX10 -> -4.7333333 | AZ10: 24 | BA10: =AZ10/BC10 -> 2 | BB10: =H10 -> 12*1L | BC10: 12 | BD10: - | BE10: - | BF10: ★★★ | BG10: - | BH10: =K10 -> SHELL Axle Oil Spirax S2 A 80W-90 1L | BI10: =AM10 -> 276 | BJ10: =BZ10 -> 13 | BK10: =CK10 -> 48 | BL10: =CV10 -> 48 | BM10: =BJ10+BK10+BL10 -> 109 | BN10: =CC10 -> 44.422222 | BO10: =CN10 -> -1.1555556 | BP10: =AY10 -> -4.7333333 | BQ10: 24 | BS10: =K10 -> SHELL Axle Oil Spirax S2 A 80W-90 1L | BT10: =_xlfn.XLOOKUP(BS10,ITEM!B:B,ITEM!BB:BB,0) -> 25.333333 | BU10: =_xlfn.XLOOKUP(BS10,ITEM!B:B,ITEM!BC:BC,0) -> 13.818182 | BV10: =BT10/BU10 -> 1.8333333 | BW10: 0 | BX10: =BT10*$AI10 -> 23.644444 | BY10: =BT10*($AE10+$AG10+$AI10) -> 57.422222 | BZ10: =_xlfn.XLOOKUP(BS10,ITEM!B:B,ITEM!BK:BK,0) -> 13 | CA10: 0 | CB10: 0 | CC10: =BY10-BZ10-CA10+CB10 -> 44.422222 | CD10: 0 | CE10: =_xlfn.XLOOKUP(BS10,ITEM!B:B,ITEM!BE:BE,0) -> 20.666667 | CF10: =_xlfn.XLOOKUP(BS10,ITEM!B:B,ITEM!BF:BF,0) -> 20.666667 | CG10: =CE10/CF10 -> 1 | CH10: 0 | CI10: =CE10*$AI10 -> 19.288889 | CJ10: =CE10*($AE10+$AG10+$AI10) -> 46.844444 | CK10: =_xlfn.XLOOKUP(BS10,ITEM!B:B,ITEM!BL:BL,0) -> 48 | CL10: 0 | CM10: 0 | CN10: =CJ10-CK10-CL10+CM10 -> -1.1555556 | CO10: 0 | CP10: =_xlfn.XLOOKUP(BS10,ITEM!B:B,ITEM!BH:BH,0) -> 0 | CQ10: =_xlfn.XLOOKUP(BS10,ITEM!B:B,ITEM!BI:BI,0) -> 0 | CR10: =CP10/CQ10 -> #DIV/0! | CS10: 0 | CT10: =CP10*$AI10 -> 0 | CU10: =CP10*($AE10+$AG10+$AI10) -> 0 | CV10: =_xlfn.XLOOKUP(BS10,ITEM!B:B,ITEM!BM:BM,0) -> 48 | CW10: 0 | CX10: 0 | CY10: =CU10-CV10-CW10+CX10 -> -48 | CZ10: 0 | DA10: =K10 -> SHELL Axle Oil Spirax S2 A 80W-90 1L
A11: 13 | B11: 101754 | C11: CASTROL | D11: Brake Fluid | E11: DOT 4 | F11: - | G11: 500ml | H11: 0 | I11: 0 | J11: =C11&" "&D11&" "&E11&" "&F11&" "&G11 -> CASTROL Brake Fluid DOT 4 - 500ml | K11: CASTROL Brake Fluid DOT 4 - 500ml | L11: 1 | M11: 桶 | N11: 65100 | O11: 0.4 | P11: 0.2 | Q11: =O11+P11 -> 0.6 | R11: =N11*(1+Q11) -> 104160 | S11: 0 | T11: 0 | U11: 0 | V11: =IF((S11+T11+U11)=0,R11,IF(AND(S11>0,T11=0,U11=0),S11,IF(AND(S11=0,T11>0,U11=0),T11,IF(AND(S11=0,T11=0,U11>0),U11,IF(AND(S11>0,T11>0,U11=0),(S11+T11)/2,IF(AND(S11>0,T11=0,U11>0),(S11+U11)/2,IF(AND(S11=0,T11>0,U11>0),(T11+U11)/2,IF(AND(S11>0,T11>0,U11>0),(S11+T11+U11)/3,)))))))) -> 104160 | W11: =IF(R11=V11,V11,IF(R11/V11<70%,R11*1.18,IF(AND(R11/V11>=70%,R11/V11<75%),R11*1.15,IF(AND(R11/V11>=75%,R11/V11<80%),R11*1.12,IF(AND(R11/V11>=80%,R11/V11<85%),R11*1.09,IF(AND(R11/V11>=85%,R11/V11<90%),R11*1.06,IF(AND(R11/V11>=90%,R11/V11<95%),R11*1.03,IF(AND(R11/V11>=95%,R11/V11<105%),V11,IF(AND(R11/V11>=105%,R11/V11<110%),R11*0.97,IF(AND(R11/V11>=110%,R11/V11<115%),R11*0.94,IF(AND(R11/V11>=115%,R11/V11<120%),R11*0.91,IF(AND(R11/V11>=120%,R11/V11<125%),R11*0.88,IF(AND(R11/V11>=125%,R11/V11<130%),R11*0.85,IF(AND(R11/V11>=130%,R11/V11<135%),R11*0.82,IF(R11/V11>=135%,R11*0.8,))))))))))))))) -> 104160 | X11: =IF(N11=0,1,IF(N11<10000,N11*2.8,IF(AND(N11>=10000,N11<20000),N11*2.2,IF(AND(N11>=20000,N11<30000),N11*1.8,IF(AND(N11>=30000,N11<40000),N11*1.78,IF(AND(N11>=40000,N11<50000),N11*1.76,IF(AND(N11>=50000,N11<60000),N11*1.74,IF(AND(N11>=60000,N11<70000),N11*1.72,IF(AND(N11>=70000,N11<80000),N11*1.7,IF(AND(N11>=80000,N11<90000),N11*1.68,IF(AND(N11>=90000,N11<100000),N11*1.66,IF(AND(N11>=100000,N11<110000),N11*1.65,IF(AND(N11>=110000,N11<120000),N11*1.64,IF(AND(N11>=120000,N11<130000),N11*1.63,IF(AND(N11>=130000,N11<140000),N11*1.62,IF(AND(N11>=140000,N11<150000),N11*1.61,IF(AND(N11>=150000,N11<160000),N11*1.6,IF(AND(N11>=160000,N11<170000),N11*1.59,IF(AND(N11>=170000,N11<180000),N11*1.58,IF(AND(N11>=180000,N11<190000),N11*1.57,IF(AND(N11>=190000,N11<200000),N11*1.56,IF(AND(N11>=200000,N11<300000),N11*1.54,IF(AND(N11>=300000,N11<400000),N11*1.52,IF(AND(N11>=400000,N11<500000),N11*1.5,IF(AND(N11>=500000,N11<600000),N11*1.48,IF(AND(N11>=600000,N11<700000),N11*1.46,IF(AND(N11>=700000,N11<800000),N11*1.44,IF(AND(N11>=800000,N11<900000),N11*1.42,IF(AND(N11>=900000,N11<1000000),N11*1.4,IF(AND(N11>=1000000,N11<2000000),N11*1.39,IF(AND(N11>=2000000,N11<3000000),N11*1.38,IF(AND(N11>=3000000,N11<4000000),N11*1.37,IF(AND(N11>=4000000,N11<5000000),N11*1.36,IF(AND(N11>=5000000,N11<6000000),N11*1.35,IF(AND(N11>=6000000,N11<7000000),N11*1.34,IF(AND(N11>=7000000,N11<8000000),N11*1.33,IF(AND(N11>=8000000,N11<9000000),N11*1.32,IF(AND(N11>=9000000,N11<10000000),N11*1.31,IF(N11>=10000000,N11*1.3,""))))))))))))))))))))))))))))))))))))))) -> 111972 | Y11: =CEILING((R11+W11+X11)/3,1000) -> 107000 | Z11: 0 | AA11: =CEILING((Y11+Z11),1000) -> 107000 | AB11: =AA11-N11 -> 41900 | AC11: =AB11/AA11 -> 0.39158879 | AD11: 30 | AE11: =AD11/30 -> 1 | AF11: 10 | AG11: =AF11/30 -> 0.33333333 | AH11: 0.7 | AI11: =(AE11+AG11)*AH11 -> 0.93333333 | AJ11: =AI11*30 -> 28 | AK11: - | AL11: =K11 -> CASTROL Brake Fluid DOT 4 - 500ml | AM11: =_xlfn.XLOOKUP(AL11,ITEM!B:B,ITEM!AY:AY,0) -> 267 | AN11: =_xlfn.XLOOKUP(AL11,ITEM!B:B,ITEM!AZ:AZ,0) -> 32.833333 | AO11: =_xlfn.XLOOKUP(AL11,ITEM!B:B,ITEM!BA:BA,0) -> 24.272727 | AP11: =AN11/AO11 -> 1.3526841 | AQ11: 0 | AR11: 0 | AS11: 0 | AT11: =AN11*$AI11 -> 30.644444 | AU11: =AN11*(AE11+AG11+AI11) -> 74.422222 | AV11: =_xlfn.XLOOKUP(AL11,ITEM!B:B,ITEM!BN:BN,0) -> 53 | AW11: 0 | AX11: 0 | AY11: =AU11-AV11-AW11+AX11 -> 21.422222 | AZ11: 0 | BA11: =AZ11/BC11 -> #DIV/0! | BB11: =H11 -> 0 | BC11: 0 | BD11: - | BE11: - | BF11: ★★ | BG11: ★★ | BH11: =K11 -> CASTROL Brake Fluid DOT 4 - 500ml | BI11: =AM11 -> 267 | BJ11: =BZ11 -> 19 | BK11: =CK11 -> 22 | BL11: =CV11 -> 12 | BM11: =BJ11+BK11+BL11 -> 53 | BN11: =CC11 -> 5.5555556 | BO11: =CN11 -> 27.866667 | BP11: =AY11 -> 21.422222 | BQ11: - | BS11: =K11 -> CASTROL Brake Fluid DOT 4 - 500ml | BT11: =_xlfn.XLOOKUP(BS11,ITEM!B:B,ITEM!BB:BB,0) -> 10.833333 | BU11: =_xlfn.XLOOKUP(BS11,ITEM!B:B,ITEM!BC:BC,0) -> 12.272727 | BV11: =BT11/BU11 -> 0.88271605 | BW11: 0 | BX11: =BT11*$AI11 -> 10.111111 | BY11: =BT11*($AE11+$AG11+$AI11) -> 24.555556 | BZ11: =_xlfn.XLOOKUP(BS11,ITEM!B:B,ITEM!BK:BK,0) -> 19 | CA11: 0 | CB11: 0 | CC11: =BY11-BZ11-CA11+CB11 -> 5.5555556 | CD11: 0 | CE11: =_xlfn.XLOOKUP(BS11,ITEM!B:B,ITEM!BE:BE,0) -> 22 | CF11: =_xlfn.XLOOKUP(BS11,ITEM!B:B,ITEM!BF:BF,0) -> 22 | CG11: =CE11/CF11 -> 1 | CH11: 0 | CI11: =CE11*$AI11 -> 20.533333 | CJ11: =CE11*($AE11+$AG11+$AI11) -> 49.866667 | CK11: =_xlfn.XLOOKUP(BS11,ITEM!B:B,ITEM!BL:BL,0) -> 22 | CL11: 0 | CM11: 0 | CN11: =CJ11-CK11-CL11+CM11 -> 27.866667 | CO11: 0 | CP11: =_xlfn.XLOOKUP(BS11,ITEM!B:B,ITEM!BH:BH,0) -> 0 | CQ11: =_xlfn.XLOOKUP(BS11,ITEM!B:B,ITEM!BI:BI,0) -> 0 | CR11: =CP11/CQ11 -> #DIV/0! | CS11: 0 | CT11: =CP11*$AI11 -> 0 | CU11: =CP11*($AE11+$AG11+$AI11) -> 0 | CV11: =_xlfn.XLOOKUP(BS11,ITEM!B:B,ITEM!BM:BM,0) -> 12 | CW11: 0 | CX11: 0 | CY11: =CU11-CV11-CW11+CX11 -> -12 | CZ11: 0 | DA11: =K11 -> CASTROL Brake Fluid DOT 4 - 500ml
A12: 11 | B12: 108238 | C12: SHELL | D12: Gear Oil | E12: Spirax | F12: S2 G 80W-90 | G12: 1L | H12: 12*1L | I12: 12 | J12: =C12&" "&D12&" "&E12&" "&F12&" "&G12 -> SHELL Gear Oil Spirax S2 G 80W-90 1L | K12: SHELL Gear Oil Spirax S2 G 80W-90 1L | L12: 1 | M12: 桶 | N12: 51414 | O12: 0.4 | P12: 0.2 | Q12: =O12+P12 -> 0.6 | R12: =N12*(1+Q12) -> 82262.4 | S12: 0 | T12: 0 | U12: 0 | V12: =IF((S12+T12+U12)=0,R12,IF(AND(S12>0,T12=0,U12=0),S12,IF(AND(S12=0,T12>0,U12=0),T12,IF(AND(S12=0,T12=0,U12>0),U12,IF(AND(S12>0,T12>0,U12=0),(S12+T12)/2,IF(AND(S12>0,T12=0,U12>0),(S12+U12)/2,IF(AND(S12=0,T12>0,U12>0),(T12+U12)/2,IF(AND(S12>0,T12>0,U12>0),(S12+T12+U12)/3,)))))))) -> 82262.4 | W12: =IF(R12=V12,V12,IF(R12/V12<70%,R12*1.18,IF(AND(R12/V12>=70%,R12/V12<75%),R12*1.15,IF(AND(R12/V12>=75%,R12/V12<80%),R12*1.12,IF(AND(R12/V12>=80%,R12/V12<85%),R12*1.09,IF(AND(R12/V12>=85%,R12/V12<90%),R12*1.06,IF(AND(R12/V12>=90%,R12/V12<95%),R12*1.03,IF(AND(R12/V12>=95%,R12/V12<105%),V12,IF(AND(R12/V12>=105%,R12/V12<110%),R12*0.97,IF(AND(R12/V12>=110%,R12/V12<115%),R12*0.94,IF(AND(R12/V12>=115%,R12/V12<120%),R12*0.91,IF(AND(R12/V12>=120%,R12/V12<125%),R12*0.88,IF(AND(R12/V12>=125%,R12/V12<130%),R12*0.85,IF(AND(R12/V12>=130%,R12/V12<135%),R12*0.82,IF(R12/V12>=135%,R12*0.8,))))))))))))))) -> 82262.4 | X12: =IF(N12=0,1,IF(N12<10000,N12*2.8,IF(AND(N12>=10000,N12<20000),N12*2.2,IF(AND(N12>=20000,N12<30000),N12*1.8,IF(AND(N12>=30000,N12<40000),N12*1.78,IF(AND(N12>=40000,N12<50000),N12*1.76,IF(AND(N12>=50000,N12<60000),N12*1.74,IF(AND(N12>=60000,N12<70000),N12*1.72,IF(AND(N12>=70000,N12<80000),N12*1.7,IF(AND(N12>=80000,N12<90000),N12*1.68,IF(AND(N12>=90000,N12<100000),N12*1.66,IF(AND(N12>=100000,N12<110000),N12*1.65,IF(AND(N12>=110000,N12<120000),N12*1.64,IF(AND(N12>=120000,N12<130000),N12*1.63,IF(AND(N12>=130000,N12<140000),N12*1.62,IF(AND(N12>=140000,N12<150000),N12*1.61,IF(AND(N12>=150000,N12<160000),N12*1.6,IF(AND(N12>=160000,N12<170000),N12*1.59,IF(AND(N12>=170000,N12<180000),N12*1.58,IF(AND(N12>=180000,N12<190000),N12*1.57,IF(AND(N12>=190000,N12<200000),N12*1.56,IF(AND(N12>=200000,N12<300000),N12*1.54,IF(AND(N12>=300000,N12<400000),N12*1.52,IF(AND(N12>=400000,N12<500000),N12*1.5,IF(AND(N12>=500000,N12<600000),N12*1.48,IF(AND(N12>=600000,N12<700000),N12*1.46,IF(AND(N12>=700000,N12<800000),N12*1.44,IF(AND(N12>=800000,N12<900000),N12*1.42,IF(AND(N12>=900000,N12<1000000),N12*1.4,IF(AND(N12>=1000000,N12<2000000),N12*1.39,IF(AND(N12>=2000000,N12<3000000),N12*1.38,IF(AND(N12>=3000000,N12<4000000),N12*1.37,IF(AND(N12>=4000000,N12<5000000),N12*1.36,IF(AND(N12>=5000000,N12<6000000),N12*1.35,IF(AND(N12>=6000000,N12<7000000),N12*1.34,IF(AND(N12>=7000000,N12<8000000),N12*1.33,IF(AND(N12>=8000000,N12<9000000),N12*1.32,IF(AND(N12>=9000000,N12<10000000),N12*1.31,IF(N12>=10000000,N12*1.3,""))))))))))))))))))))))))))))))))))))))) -> 89460.36 | Y12: =CEILING((R12+W12+X12)/3,1000) -> 85000 | Z12: 0 | AA12: =CEILING((Y12+Z12),1000) -> 85000 | AB12: =AA12-N12 -> 33586 | AC12: =AB12/AA12 -> 0.39512941 | AD12: 30 | AE12: =AD12/30 -> 1 | AF12: 10 | AG12: =AF12/30 -> 0.33333333 | AH12: 0.7 | AI12: =(AE12+AG12)*AH12 -> 0.93333333 | AJ12: =AI12*30 -> 28 | AK12: - | AL12: =K12 -> SHELL Gear Oil Spirax S2 G 80W-90 1L | AM12: =_xlfn.XLOOKUP(AL12,ITEM!B:B,ITEM!AY:AY,0) -> 242 | AN12: =_xlfn.XLOOKUP(AL12,ITEM!B:B,ITEM!AZ:AZ,0) -> 40.333333 | AO12: =_xlfn.XLOOKUP(AL12,ITEM!B:B,ITEM!BA:BA,0) -> 22 | AP12: =AN12/AO12 -> 1.8333333 | AQ12: 0 | AR12: 0 | AS12: 0 | AT12: =AN12*$AI12 -> 37.644444 | AU12: =AN12*(AE12+AG12+AI12) -> 91.422222 | AV12: =_xlfn.XLOOKUP(AL12,ITEM!B:B,ITEM!BN:BN,0) -> 73 | AW12: 0 | AX12: 0 | AY12: =AU12-AV12-AW12+AX12 -> 18.422222 | AZ12: 60 | BA12: =AZ12/BC12 -> 5 | BB12: =H12 -> 12*1L | BC12: 12 | BD12: - | BE12: - | BF12: ★★★ | BG12: - | BH12: =K12 -> SHELL Gear Oil Spirax S2 G 80W-90 1L | BI12: =AM12 -> 242 | BJ12: =BZ12 -> 16 | BK12: =CK12 -> 32 | BL12: =CV12 -> 25 | BM12: =BJ12+BK12+BL12 -> 73 | BN12: =CC12 -> 37.266667 | BO12: =CN12 -> 6.1555556 | BP12: =AY12 -> 18.422222 | BQ12: - | BS12: =K12 -> SHELL Gear Oil Spirax S2 G 80W-90 1L | BT12: =_xlfn.XLOOKUP(BS12,ITEM!B:B,ITEM!BB:BB,0) -> 23.5 | BU12: =_xlfn.XLOOKUP(BS12,ITEM!B:B,ITEM!BC:BC,0) -> 12.818182 | BV12: =BT12/BU12 -> 1.8333333 | BW12: 0 | BX12: =BT12*$AI12 -> 21.933333 | BY12: =BT12*($AE12+$AG12+$AI12) -> 53.266667 | BZ12: =_xlfn.XLOOKUP(BS12,ITEM!B:B,ITEM!BK:BK,0) -> 16 | CA12: 0 | CB12: 0 | CC12: =BY12-BZ12-CA12+CB12 -> 37.266667 | CD12: 0 | CE12: =_xlfn.XLOOKUP(BS12,ITEM!B:B,ITEM!BE:BE,0) -> 16.833333 | CF12: =_xlfn.XLOOKUP(BS12,ITEM!B:B,ITEM!BF:BF,0) -> 16.833333 | CG12: =CE12/CF12 -> 1 | CH12: 0 | CI12: =CE12*$AI12 -> 15.711111 | CJ12: =CE12*($AE12+$AG12+$AI12) -> 38.155556 | CK12: =_xlfn.XLOOKUP(BS12,ITEM!B:B,ITEM!BL:BL,0) -> 32 | CL12: 0 | CM12: 0 | CN12: =CJ12-CK12-CL12+CM12 -> 6.1555556 | CO12: 0 | CP12: =_xlfn.XLOOKUP(BS12,ITEM!B:B,ITEM!BH:BH,0) -> 0 | CQ12: =_xlfn.XLOOKUP(BS12,ITEM!B:B,ITEM!BI:BI,0) -> 0 | CR12: =CP12/CQ12 -> #DIV/0! | CS12: 0 | CT12: =CP12*$AI12 -> 0 | CU12: =CP12*($AE12+$AG12+$AI12) -> 0 | CV12: =_xlfn.XLOOKUP(BS12,ITEM!B:B,ITEM!BM:BM,0) -> 25 | CW12: 0 | CX12: 0 | CY12: =CU12-CV12-CW12+CX12 -> -25 | CZ12: 0 | DA12: =K12 -> SHELL Gear Oil Spirax S2 G 80W-90 1L
A13: 9 | B13: 108111 | C13: SHELL | D13: Transmission Oil | E13: Spirax | F13: S5 CVTX | G13: 1L | H13: 12*1L | I13: 12 | J13: =C13&" "&D13&" "&E13&" "&F13&" "&G13 -> SHELL Transmission Oil Spirax S5 CVTX 1L | K13: SHELL Transmission Oil Spirax S5 CVTX 1L | L13: 1 | M13: 桶 | N13: 77510 | O13: 0.4 | P13: 0.2 | Q13: =O13+P13 -> 0.6 | R13: =N13*(1+Q13) -> 124016 | S13: 0 | T13: 0 | U13: 0 | V13: =IF((S13+T13+U13)=0,R13,IF(AND(S13>0,T13=0,U13=0),S13,IF(AND(S13=0,T13>0,U13=0),T13,IF(AND(S13=0,T13=0,U13>0),U13,IF(AND(S13>0,T13>0,U13=0),(S13+T13)/2,IF(AND(S13>0,T13=0,U13>0),(S13+U13)/2,IF(AND(S13=0,T13>0,U13>0),(T13+U13)/2,IF(AND(S13>0,T13>0,U13>0),(S13+T13+U13)/3,)))))))) -> 124016 | W13: =IF(R13=V13,V13,IF(R13/V13<70%,R13*1.18,IF(AND(R13/V13>=70%,R13/V13<75%),R13*1.15,IF(AND(R13/V13>=75%,R13/V13<80%),R13*1.12,IF(AND(R13/V13>=80%,R13/V13<85%),R13*1.09,IF(AND(R13/V13>=85%,R13/V13<90%),R13*1.06,IF(AND(R13/V13>=90%,R13/V13<95%),R13*1.03,IF(AND(R13/V13>=95%,R13/V13<105%),V13,IF(AND(R13/V13>=105%,R13/V13<110%),R13*0.97,IF(AND(R13/V13>=110%,R13/V13<115%),R13*0.94,IF(AND(R13/V13>=115%,R13/V13<120%),R13*0.91,IF(AND(R13/V13>=120%,R13/V13<125%),R13*0.88,IF(AND(R13/V13>=125%,R13/V13<130%),R13*0.85,IF(AND(R13/V13>=130%,R13/V13<135%),R13*0.82,IF(R13/V13>=135%,R13*0.8,))))))))))))))) -> 124016 | X13: =IF(N13=0,1,IF(N13<10000,N13*2.8,IF(AND(N13>=10000,N13<20000),N13*2.2,IF(AND(N13>=20000,N13<30000),N13*1.8,IF(AND(N13>=30000,N13<40000),N13*1.78,IF(AND(N13>=40000,N13<50000),N13*1.76,IF(AND(N13>=50000,N13<60000),N13*1.74,IF(AND(N13>=60000,N13<70000),N13*1.72,IF(AND(N13>=70000,N13<80000),N13*1.7,IF(AND(N13>=80000,N13<90000),N13*1.68,IF(AND(N13>=90000,N13<100000),N13*1.66,IF(AND(N13>=100000,N13<110000),N13*1.65,IF(AND(N13>=110000,N13<120000),N13*1.64,IF(AND(N13>=120000,N13<130000),N13*1.63,IF(AND(N13>=130000,N13<140000),N13*1.62,IF(AND(N13>=140000,N13<150000),N13*1.61,IF(AND(N13>=150000,N13<160000),N13*1.6,IF(AND(N13>=160000,N13<170000),N13*1.59,IF(AND(N13>=170000,N13<180000),N13*1.58,IF(AND(N13>=180000,N13<190000),N13*1.57,IF(AND(N13>=190000,N13<200000),N13*1.56,IF(AND(N13>=200000,N13<300000),N13*1.54,IF(AND(N13>=300000,N13<400000),N13*1.52,IF(AND(N13>=400000,N13<500000),N13*1.5,IF(AND(N13>=500000,N13<600000),N13*1.48,IF(AND(N13>=600000,N13<700000),N13*1.46,IF(AND(N13>=700000,N13<800000),N13*1.44,IF(AND(N13>=800000,N13<900000),N13*1.42,IF(AND(N13>=900000,N13<1000000),N13*1.4,IF(AND(N13>=1000000,N13<2000000),N13*1.39,IF(AND(N13>=2000000,N13<3000000),N13*1.38,IF(AND(N13>=3000000,N13<4000000),N13*1.37,IF(AND(N13>=4000000,N13<5000000),N13*1.36,IF(AND(N13>=5000000,N13<6000000),N13*1.35,IF(AND(N13>=6000000,N13<7000000),N13*1.34,IF(AND(N13>=7000000,N13<8000000),N13*1.33,IF(AND(N13>=8000000,N13<9000000),N13*1.32,IF(AND(N13>=9000000,N13<10000000),N13*1.31,IF(N13>=10000000,N13*1.3,""))))))))))))))))))))))))))))))))))))))) -> 131767 | Y13: =CEILING((R13+W13+X13)/3,1000) -> 127000 | Z13: 0 | AA13: =CEILING((Y13+Z13),1000) -> 127000 | AB13: =AA13-N13 -> 49490 | AC13: =AB13/AA13 -> 0.38968504 | AD13: 30 | AE13: =AD13/30 -> 1 | AF13: 10 | AG13: =AF13/30 -> 0.33333333 | AH13: 0.7 | AI13: =(AE13+AG13)*AH13 -> 0.93333333 | AJ13: =AI13*30 -> 28 | AK13: - | AL13: =K13 -> SHELL Transmission Oil Spirax S5 CVTX 1L | AM13: =_xlfn.XLOOKUP(AL13,ITEM!B:B,ITEM!AY:AY,0) -> 220 | AN13: =_xlfn.XLOOKUP(AL13,ITEM!B:B,ITEM!AZ:AZ,0) -> 31.333333 | AO13: =_xlfn.XLOOKUP(AL13,ITEM!B:B,ITEM!BA:BA,0) -> 20 | AP13: =AN13/AO13 -> 1.5666667 | AQ13: 0 | AR13: 0 | AS13: 0 | AT13: =AN13*$AI13 -> 29.244444 | AU13: =AN13*(AE13+AG13+AI13) -> 71.022222 | AV13: =_xlfn.XLOOKUP(AL13,ITEM!B:B,ITEM!BN:BN,0) -> 41 | AW13: 0 | AX13: 0 | AY13: =AU13-AV13-AW13+AX13 -> 30.022222 | AZ13: 120 | BA13: =AZ13/BC13 -> 10 | BB13: =H13 -> 12*1L | BC13: 12 | BD13: - | BE13: - | BF13: ★★★ | BG13: - | BH13: =K13 -> SHELL Transmission Oil Spirax S5 CVTX 1L | BI13: =AM13 -> 220 | BJ13: =BZ13 -> 5 | BK13: =CK13 -> 36 | BL13: =CV13 -> 0 | BM13: =BJ13+BK13+BL13 -> 41 | BN13: =CC13 -> 58.466667 | BO13: =CN13 -> -28.444444 | BP13: =AY13 -> 30.022222 | BQ13: 12 | BS13: =K13 -> SHELL Transmission Oil Spirax S5 CVTX 1L | BT13: =_xlfn.XLOOKUP(BS13,ITEM!B:B,ITEM!BB:BB,0) -> 28 | BU13: =_xlfn.XLOOKUP(BS13,ITEM!B:B,ITEM!BC:BC,0) -> 18.181818 | BV13: =BT13/BU13 -> 1.54 | BW13: 0 | BX13: =BT13*$AI13 -> 26.133333 | BY13: =BT13*($AE13+$AG13+$AI13) -> 63.466667 | BZ13: =_xlfn.XLOOKUP(BS13,ITEM!B:B,ITEM!BK:BK,0) -> 5 | CA13: 0 | CB13: 0 | CC13: =BY13-BZ13-CA13+CB13 -> 58.466667 | CD13: 0 | CE13: =_xlfn.XLOOKUP(BS13,ITEM!B:B,ITEM!BE:BE,0) -> 3.3333333 | CF13: =_xlfn.XLOOKUP(BS13,ITEM!B:B,ITEM!BF:BF,0) -> 3.3333333 | CG13: =CE13/CF13 -> 1 | CH13: 0 | CI13: =CE13*$AI13 -> 3.1111111 | CJ13: =CE13*($AE13+$AG13+$AI13) -> 7.5555556 | CK13: =_xlfn.XLOOKUP(BS13,ITEM!B:B,ITEM!BL:BL,0) -> 36 | CL13: 0 | CM13: 0 | CN13: =CJ13-CK13-CL13+CM13 -> -28.444444 | CO13: 0 | CP13: =_xlfn.XLOOKUP(BS13,ITEM!B:B,ITEM!BH:BH,0) -> 0 | CQ13: =_xlfn.XLOOKUP(BS13,ITEM!B:B,ITEM!BI:BI,0) -> 0 | CR13: =CP13/CQ13 -> #DIV/0! | CS13: 0 | CT13: =CP13*$AI13 -> 0 | CU13: =CP13*($AE13+$AG13+$AI13) -> 0 | CV13: =_xlfn.XLOOKUP(BS13,ITEM!B:B,ITEM!BM:BM,0) -> 0 | CW13: 0 | CX13: 0 | CY13: =CU13-CV13-CW13+CX13 -> 0 | CZ13: 0 | DA13: =K13 -> SHELL Transmission Oil Spirax S5 CVTX 1L
A14: 5 | B14: 101844 | C14: MOTUL | D14: Transmission Oil | E14: Multi | F14: CVTF | G14: 1L | H14: 12*1L | I14: 12 | J14: =C14&" "&D14&" "&E14&" "&F14&" "&G14 -> MOTUL Transmission Oil Multi CVTF 1L | K14: MOTUL Transmission Oil Multi CVTF 1L | L14: 1 | M14: 桶 | N14: 171570 | O14: 0.4 | P14: 0.2 | Q14: =O14+P14 -> 0.6 | R14: =N14*(1+Q14) -> 274512 | S14: 0 | T14: 0 | U14: 0 | V14: =IF((S14+T14+U14)=0,R14,IF(AND(S14>0,T14=0,U14=0),S14,IF(AND(S14=0,T14>0,U14=0),T14,IF(AND(S14=0,T14=0,U14>0),U14,IF(AND(S14>0,T14>0,U14=0),(S14+T14)/2,IF(AND(S14>0,T14=0,U14>0),(S14+U14)/2,IF(AND(S14=0,T14>0,U14>0),(T14+U14)/2,IF(AND(S14>0,T14>0,U14>0),(S14+T14+U14)/3,)))))))) -> 274512 | W14: =IF(R14=V14,V14,IF(R14/V14<70%,R14*1.18,IF(AND(R14/V14>=70%,R14/V14<75%),R14*1.15,IF(AND(R14/V14>=75%,R14/V14<80%),R14*1.12,IF(AND(R14/V14>=80%,R14/V14<85%),R14*1.09,IF(AND(R14/V14>=85%,R14/V14<90%),R14*1.06,IF(AND(R14/V14>=90%,R14/V14<95%),R14*1.03,IF(AND(R14/V14>=95%,R14/V14<105%),V14,IF(AND(R14/V14>=105%,R14/V14<110%),R14*0.97,IF(AND(R14/V14>=110%,R14/V14<115%),R14*0.94,IF(AND(R14/V14>=115%,R14/V14<120%),R14*0.91,IF(AND(R14/V14>=120%,R14/V14<125%),R14*0.88,IF(AND(R14/V14>=125%,R14/V14<130%),R14*0.85,IF(AND(R14/V14>=130%,R14/V14<135%),R14*0.82,IF(R14/V14>=135%,R14*0.8,))))))))))))))) -> 274512 | X14: =IF(N14=0,1,IF(N14<10000,N14*2.8,IF(AND(N14>=10000,N14<20000),N14*2.2,IF(AND(N14>=20000,N14<30000),N14*1.8,IF(AND(N14>=30000,N14<40000),N14*1.78,IF(AND(N14>=40000,N14<50000),N14*1.76,IF(AND(N14>=50000,N14<60000),N14*1.74,IF(AND(N14>=60000,N14<70000),N14*1.72,IF(AND(N14>=70000,N14<80000),N14*1.7,IF(AND(N14>=80000,N14<90000),N14*1.68,IF(AND(N14>=90000,N14<100000),N14*1.66,IF(AND(N14>=100000,N14<110000),N14*1.65,IF(AND(N14>=110000,N14<120000),N14*1.64,IF(AND(N14>=120000,N14<130000),N14*1.63,IF(AND(N14>=130000,N14<140000),N14*1.62,IF(AND(N14>=140000,N14<150000),N14*1.61,IF(AND(N14>=150000,N14<160000),N14*1.6,IF(AND(N14>=160000,N14<170000),N14*1.59,IF(AND(N14>=170000,N14<180000),N14*1.58,IF(AND(N14>=180000,N14<190000),N14*1.57,IF(AND(N14>=190000,N14<200000),N14*1.56,IF(AND(N14>=200000,N14<300000),N14*1.54,IF(AND(N14>=300000,N14<400000),N14*1.52,IF(AND(N14>=400000,N14<500000),N14*1.5,IF(AND(N14>=500000,N14<600000),N14*1.48,IF(AND(N14>=600000,N14<700000),N14*1.46,IF(AND(N14>=700000,N14<800000),N14*1.44,IF(AND(N14>=800000,N14<900000),N14*1.42,IF(AND(N14>=900000,N14<1000000),N14*1.4,IF(AND(N14>=1000000,N14<2000000),N14*1.39,IF(AND(N14>=2000000,N14<3000000),N14*1.38,IF(AND(N14>=3000000,N14<4000000),N14*1.37,IF(AND(N14>=4000000,N14<5000000),N14*1.36,IF(AND(N14>=5000000,N14<6000000),N14*1.35,IF(AND(N14>=6000000,N14<7000000),N14*1.34,IF(AND(N14>=7000000,N14<8000000),N14*1.33,IF(AND(N14>=8000000,N14<9000000),N14*1.32,IF(AND(N14>=9000000,N14<10000000),N14*1.31,IF(N14>=10000000,N14*1.3,""))))))))))))))))))))))))))))))))))))))) -> 271080.6 | Y14: =CEILING((R14+W14+X14)/3,1000) -> 274000 | Z14: 0 | AA14: =CEILING((Y14+Z14),1000) -> 274000 | AB14: =AA14-N14 -> 102430 | AC14: =AB14/AA14 -> 0.37383212 | AD14: 30 | AE14: =AD14/30 -> 1 | AF14: 10 | AG14: =AF14/30 -> 0.33333333 | AH14: 0.7 | AI14: =(AE14+AG14)*AH14 -> 0.93333333 | AJ14: =AI14*30 -> 28 | AK14: - | AL14: =K14 -> MOTUL Transmission Oil Multi CVTF 1L | AM14: =_xlfn.XLOOKUP(AL14,ITEM!B:B,ITEM!AY:AY,0) -> 200 | AN14: =_xlfn.XLOOKUP(AL14,ITEM!B:B,ITEM!AZ:AZ,0) -> 6.6666667 | AO14: =_xlfn.XLOOKUP(AL14,ITEM!B:B,ITEM!BA:BA,0) -> 17.818182 | AP14: =AN14/AO14 -> 0.37414966 | AQ14: 0 | AR14: 0 | AS14: 0 | AT14: =AN14*$AI14 -> 6.2222222 | AU14: =AN14*(AE14+AG14+AI14) -> 15.111111 | AV14: =_xlfn.XLOOKUP(AL14,ITEM!B:B,ITEM!BN:BN,0) -> 73 | AW14: 0 | AX14: 0 | AY14: =AU14-AV14-AW14+AX14 -> -57.888889 | AZ14: 0 | BA14: =AZ14/BC14 -> 0 | BB14: =H14 -> 12*1L | BC14: 12 | BD14: - | BE14: - | BF14: ★ | BG14: - | BH14: =K14 -> MOTUL Transmission Oil Multi CVTF 1L | BI14: =AM14 -> 200 | BJ14: =BZ14 -> 28 | BK14: =CK14 -> 20 | BL14: =CV14 -> 25 | BM14: =BJ14+BK14+BL14 -> 73 | BN14: =CC14 -> -21.955556 | BO14: =CN14 -> -10.933333 | BP14: =AY14 -> -57.888889 | BQ14: - | BS14: =K14 -> MOTUL Transmission Oil Multi CVTF 1L | BT14: =_xlfn.XLOOKUP(BS14,ITEM!B:B,ITEM!BB:BB,0) -> 2.6666667 | BU14: =_xlfn.XLOOKUP(BS14,ITEM!B:B,ITEM!BC:BC,0) -> 15.636364 | BV14: =BT14/BU14 -> 0.17054264 | BW14: 0 | BX14: =BT14*$AI14 -> 2.4888889 | BY14: =BT14*($AE14+$AG14+$AI14) -> 6.0444444 | BZ14: =_xlfn.XLOOKUP(BS14,ITEM!B:B,ITEM!BK:BK,0) -> 28 | CA14: 0 | CB14: 0 | CC14: =BY14-BZ14-CA14+CB14 -> -21.955556 | CD14: 0 | CE14: =_xlfn.XLOOKUP(BS14,ITEM!B:B,ITEM!BE:BE,0) -> 4 | CF14: =_xlfn.XLOOKUP(BS14,ITEM!B:B,ITEM!BF:BF,0) -> 4 | CG14: =CE14/CF14 -> 1 | CH14: 0 | CI14: =CE14*$AI14 -> 3.7333333 | CJ14: =CE14*($AE14+$AG14+$AI14) -> 9.0666667 | CK14: =_xlfn.XLOOKUP(BS14,ITEM!B:B,ITEM!BL:BL,0) -> 20 | CL14: 0 | CM14: 0 | CN14: =CJ14-CK14-CL14+CM14 -> -10.933333 | CO14: 0 | CP14: =_xlfn.XLOOKUP(BS14,ITEM!B:B,ITEM!BH:BH,0) -> 0 | CQ14: =_xlfn.XLOOKUP(BS14,ITEM!B:B,ITEM!BI:BI,0) -> 0 | CR14: =CP14/CQ14 -> #DIV/0! | CS14: 0 | CT14: =CP14*$AI14 -> 0 | CU14: =CP14*($AE14+$AG14+$AI14) -> 0 | CV14: =_xlfn.XLOOKUP(BS14,ITEM!B:B,ITEM!BM:BM,0) -> 25 | CW14: 0 | CX14: 0 | CY14: =CU14-CV14-CW14+CX14 -> -25 | CZ14: 0 | DA14: =K14 -> MOTUL Transmission Oil Multi CVTF 1L
A15: 4 | B15: 101840 | C15: MOTUL | D15: Transmission Oil | E15: ATF | F15: VI | G15: 1L | H15: 12*1L | I15: 12 | J15: =C15&" "&D15&" "&E15&" "&F15&" "&G15 -> MOTUL Transmission Oil ATF VI 1L | K15: MOTUL Transmission Oil ATF VI 1L | L15: 1 | M15: 桶 | N15: 142252 | O15: 0.4 | P15: 0.2 | Q15: =O15+P15 -> 0.6 | R15: =N15*(1+Q15) -> 227603.2 | S15: 0 | T15: 0 | U15: 0 | V15: =IF((S15+T15+U15)=0,R15,IF(AND(S15>0,T15=0,U15=0),S15,IF(AND(S15=0,T15>0,U15=0),T15,IF(AND(S15=0,T15=0,U15>0),U15,IF(AND(S15>0,T15>0,U15=0),(S15+T15)/2,IF(AND(S15>0,T15=0,U15>0),(S15+U15)/2,IF(AND(S15=0,T15>0,U15>0),(T15+U15)/2,IF(AND(S15>0,T15>0,U15>0),(S15+T15+U15)/3,)))))))) -> 227603.2 | W15: =IF(R15=V15,V15,IF(R15/V15<70%,R15*1.18,IF(AND(R15/V15>=70%,R15/V15<75%),R15*1.15,IF(AND(R15/V15>=75%,R15/V15<80%),R15*1.12,IF(AND(R15/V15>=80%,R15/V15<85%),R15*1.09,IF(AND(R15/V15>=85%,R15/V15<90%),R15*1.06,IF(AND(R15/V15>=90%,R15/V15<95%),R15*1.03,IF(AND(R15/V15>=95%,R15/V15<105%),V15,IF(AND(R15/V15>=105%,R15/V15<110%),R15*0.97,IF(AND(R15/V15>=110%,R15/V15<115%),R15*0.94,IF(AND(R15/V15>=115%,R15/V15<120%),R15*0.91,IF(AND(R15/V15>=120%,R15/V15<125%),R15*0.88,IF(AND(R15/V15>=125%,R15/V15<130%),R15*0.85,IF(AND(R15/V15>=130%,R15/V15<135%),R15*0.82,IF(R15/V15>=135%,R15*0.8,))))))))))))))) -> 227603.2 | X15: =IF(N15=0,1,IF(N15<10000,N15*2.8,IF(AND(N15>=10000,N15<20000),N15*2.2,IF(AND(N15>=20000,N15<30000),N15*1.8,IF(AND(N15>=30000,N15<40000),N15*1.78,IF(AND(N15>=40000,N15<50000),N15*1.76,IF(AND(N15>=50000,N15<60000),N15*1.74,IF(AND(N15>=60000,N15<70000),N15*1.72,IF(AND(N15>=70000,N15<80000),N15*1.7,IF(AND(N15>=80000,N15<90000),N15*1.68,IF(AND(N15>=90000,N15<100000),N15*1.66,IF(AND(N15>=100000,N15<110000),N15*1.65,IF(AND(N15>=110000,N15<120000),N15*1.64,IF(AND(N15>=120000,N15<130000),N15*1.63,IF(AND(N15>=130000,N15<140000),N15*1.62,IF(AND(N15>=140000,N15<150000),N15*1.61,IF(AND(N15>=150000,N15<160000),N15*1.6,IF(AND(N15>=160000,N15<170000),N15*1.59,IF(AND(N15>=170000,N15<180000),N15*1.58,IF(AND(N15>=180000,N15<190000),N15*1.57,IF(AND(N15>=190000,N15<200000),N15*1.56,IF(AND(N15>=200000,N15<300000),N15*1.54,IF(AND(N15>=300000,N15<400000),N15*1.52,IF(AND(N15>=400000,N15<500000),N15*1.5,IF(AND(N15>=500000,N15<600000),N15*1.48,IF(AND(N15>=600000,N15<700000),N15*1.46,IF(AND(N15>=700000,N15<800000),N15*1.44,IF(AND(N15>=800000,N15<900000),N15*1.42,IF(AND(N15>=900000,N15<1000000),N15*1.4,IF(AND(N15>=1000000,N15<2000000),N15*1.39,IF(AND(N15>=2000000,N15<3000000),N15*1.38,IF(AND(N15>=3000000,N15<4000000),N15*1.37,IF(AND(N15>=4000000,N15<5000000),N15*1.36,IF(AND(N15>=5000000,N15<6000000),N15*1.35,IF(AND(N15>=6000000,N15<7000000),N15*1.34,IF(AND(N15>=7000000,N15<8000000),N15*1.33,IF(AND(N15>=8000000,N15<9000000),N15*1.32,IF(AND(N15>=9000000,N15<10000000),N15*1.31,IF(N15>=10000000,N15*1.3,""))))))))))))))))))))))))))))))))))))))) -> 229025.72 | Y15: =CEILING((R15+W15+X15)/3,1000) -> 229000 | Z15: 0 | AA15: =CEILING((Y15+Z15),1000) -> 229000 | AB15: =AA15-N15 -> 86748 | AC15: =AB15/AA15 -> 0.37881223 | AD15: 30 | AE15: =AD15/30 -> 1 | AF15: 10 | AG15: =AF15/30 -> 0.33333333 | AH15: 0.7 | AI15: =(AE15+AG15)*AH15 -> 0.93333333 | AJ15: =AI15*30 -> 28 | AK15: - | AL15: =K15 -> MOTUL Transmission Oil ATF VI 1L | AM15: =_xlfn.XLOOKUP(AL15,ITEM!B:B,ITEM!AY:AY,0) -> 74 | AN15: =_xlfn.XLOOKUP(AL15,ITEM!B:B,ITEM!AZ:AZ,0) -> 4.8333333 | AO15: =_xlfn.XLOOKUP(AL15,ITEM!B:B,ITEM!BA:BA,0) -> 6.7272727 | AP15: =AN15/AO15 -> 0.71846847 | AQ15: 0 | AR15: 0 | AS15: 0 | AT15: =AN15*$AI15 -> 4.5111111 | AU15: =AN15*(AE15+AG15+AI15) -> 10.955556 | AV15: =_xlfn.XLOOKUP(AL15,ITEM!B:B,ITEM!BN:BN,0) -> 57 | AW15: 0 | AX15: 0 | AY15: =AU15-AV15-AW15+AX15 -> -46.044444 | AZ15: 0 | BA15: =AZ15/BC15 -> 0 | BB15: =H15 -> 12*1L | BC15: 12 | BD15: - | BE15: - | BF15: ★ | BG15: - | BH15: =K15 -> MOTUL Transmission Oil ATF VI 1L | BI15: =AM15 -> 74 | BJ15: =BZ15 -> 20 | BK15: =CK15 -> 36 | BL15: =CV15 -> 1 | BM15: =BJ15+BK15+BL15 -> 57 | BN15: =CC15 -> -18.111111 | BO15: =CN15 -> -26.933333 | BP15: =AY15 -> -46.044444 | BQ15: - | BS15: =K15 -> MOTUL Transmission Oil ATF VI 1L | BT15: =_xlfn.XLOOKUP(BS15,ITEM!B:B,ITEM!BB:BB,0) -> 0.83333333 | BU15: =_xlfn.XLOOKUP(BS15,ITEM!B:B,ITEM!BC:BC,0) -> 4.5454545 | BV15: =BT15/BU15 -> 0.18333333 | BW15: 0 | BX15: =BT15*$AI15 -> 0.77777778 | BY15: =BT15*($AE15+$AG15+$AI15) -> 1.8888889 | BZ15: =_xlfn.XLOOKUP(BS15,ITEM!B:B,ITEM!BK:BK,0) -> 20 | CA15: 0 | CB15: 0 | CC15: =BY15-BZ15-CA15+CB15 -> -18.111111 | CD15: 0 | CE15: =_xlfn.XLOOKUP(BS15,ITEM!B:B,ITEM!BE:BE,0) -> 4 | CF15: =_xlfn.XLOOKUP(BS15,ITEM!B:B,ITEM!BF:BF,0) -> 4 | CG15: =CE15/CF15 -> 1 | CH15: 0 | CI15: =CE15*$AI15 -> 3.7333333 | CJ15: =CE15*($AE15+$AG15+$AI15) -> 9.0666667 | CK15: =_xlfn.XLOOKUP(BS15,ITEM!B:B,ITEM!BL:BL,0) -> 36 | CL15: 0 | CM15: 0 | CN15: =CJ15-CK15-CL15+CM15 -> -26.933333 | CO15: 0 | CP15: =_xlfn.XLOOKUP(BS15,ITEM!B:B,ITEM!BH:BH,0) -> 0 | CQ15: =_xlfn.XLOOKUP(BS15,ITEM!B:B,ITEM!BI:BI,0) -> 0 | CR15: =CP15/CQ15 -> #DIV/0! | CS15: 0 | CT15: =CP15*$AI15 -> 0 | CU15: =CP15*($AE15+$AG15+$AI15) -> 0 | CV15: =_xlfn.XLOOKUP(BS15,ITEM!B:B,ITEM!BM:BM,0) -> 1 | CW15: 0 | CX15: 0 | CY15: =CU15-CV15-CW15+CX15 -> -1 | CZ15: 0 | DA15: =K15 -> MOTUL Transmission Oil ATF VI 1L
A16: 6 | B16: 101855 | C16: MOTUL | D16: Transmission Oil | E16: Multi | F16: ATF | G16: 1L | H16: 12*1L | I16: 12 | J16: =C16&" "&D16&" "&E16&" "&F16&" "&G16 -> MOTUL Transmission Oil Multi ATF 1L | K16: MOTUL Transmission Oil Multi ATF 1L | L16: 1 | M16: 桶 | N16: 181837 | O16: 0.4 | P16: 0.2 | Q16: =O16+P16 -> 0.6 | R16: =N16*(1+Q16) -> 290939.2 | S16: 0 | T16: 0 | U16: 0 | V16: =IF((S16+T16+U16)=0,R16,IF(AND(S16>0,T16=0,U16=0),S16,IF(AND(S16=0,T16>0,U16=0),T16,IF(AND(S16=0,T16=0,U16>0),U16,IF(AND(S16>0,T16>0,U16=0),(S16+T16)/2,IF(AND(S16>0,T16=0,U16>0),(S16+U16)/2,IF(AND(S16=0,T16>0,U16>0),(T16+U16)/2,IF(AND(S16>0,T16>0,U16>0),(S16+T16+U16)/3,)))))))) -> 290939.2 | W16: =IF(R16=V16,V16,IF(R16/V16<70%,R16*1.18,IF(AND(R16/V16>=70%,R16/V16<75%),R16*1.15,IF(AND(R16/V16>=75%,R16/V16<80%),R16*1.12,IF(AND(R16/V16>=80%,R16/V16<85%),R16*1.09,IF(AND(R16/V16>=85%,R16/V16<90%),R16*1.06,IF(AND(R16/V16>=90%,R16/V16<95%),R16*1.03,IF(AND(R16/V16>=95%,R16/V16<105%),V16,IF(AND(R16/V16>=105%,R16/V16<110%),R16*0.97,IF(AND(R16/V16>=110%,R16/V16<115%),R16*0.94,IF(AND(R16/V16>=115%,R16/V16<120%),R16*0.91,IF(AND(R16/V16>=120%,R16/V16<125%),R16*0.88,IF(AND(R16/V16>=125%,R16/V16<130%),R16*0.85,IF(AND(R16/V16>=130%,R16/V16<135%),R16*0.82,IF(R16/V16>=135%,R16*0.8,))))))))))))))) -> 290939.2 | X16: =IF(N16=0,1,IF(N16<10000,N16*2.8,IF(AND(N16>=10000,N16<20000),N16*2.2,IF(AND(N16>=20000,N16<30000),N16*1.8,IF(AND(N16>=30000,N16<40000),N16*1.78,IF(AND(N16>=40000,N16<50000),N16*1.76,IF(AND(N16>=50000,N16<60000),N16*1.74,IF(AND(N16>=60000,N16<70000),N16*1.72,IF(AND(N16>=70000,N16<80000),N16*1.7,IF(AND(N16>=80000,N16<90000),N16*1.68,IF(AND(N16>=90000,N16<100000),N16*1.66,IF(AND(N16>=100000,N16<110000),N16*1.65,IF(AND(N16>=110000,N16<120000),N16*1.64,IF(AND(N16>=120000,N16<130000),N16*1.63,IF(AND(N16>=130000,N16<140000),N16*1.62,IF(AND(N16>=140000,N16<150000),N16*1.61,IF(AND(N16>=150000,N16<160000),N16*1.6,IF(AND(N16>=160000,N16<170000),N16*1.59,IF(AND(N16>=170000,N16<180000),N16*1.58,IF(AND(N16>=180000,N16<190000),N16*1.57,IF(AND(N16>=190000,N16<200000),N16*1.56,IF(AND(N16>=200000,N16<300000),N16*1.54,IF(AND(N16>=300000,N16<400000),N16*1.52,IF(AND(N16>=400000,N16<500000),N16*1.5,IF(AND(N16>=500000,N16<600000),N16*1.48,IF(AND(N16>=600000,N16<700000),N16*1.46,IF(AND(N16>=700000,N16<800000),N16*1.44,IF(AND(N16>=800000,N16<900000),N16*1.42,IF(AND(N16>=900000,N16<1000000),N16*1.4,IF(AND(N16>=1000000,N16<2000000),N16*1.39,IF(AND(N16>=2000000,N16<3000000),N16*1.38,IF(AND(N16>=3000000,N16<4000000),N16*1.37,IF(AND(N16>=4000000,N16<5000000),N16*1.36,IF(AND(N16>=5000000,N16<6000000),N16*1.35,IF(AND(N16>=6000000,N16<7000000),N16*1.34,IF(AND(N16>=7000000,N16<8000000),N16*1.33,IF(AND(N16>=8000000,N16<9000000),N16*1.32,IF(AND(N16>=9000000,N16<10000000),N16*1.31,IF(N16>=10000000,N16*1.3,""))))))))))))))))))))))))))))))))))))))) -> 285484.09 | Y16: =CEILING((R16+W16+X16)/3,1000) -> 290000 | Z16: 0 | AA16: =CEILING((Y16+Z16),1000) -> 290000 | AB16: =AA16-N16 -> 108163 | AC16: =AB16/AA16 -> 0.37297586 | AD16: 30 | AE16: =AD16/30 -> 1 | AF16: 10 | AG16: =AF16/30 -> 0.33333333 | AH16: 0.7 | AI16: =(AE16+AG16)*AH16 -> 0.93333333 | AJ16: =AI16*30 -> 28 | AK16: - | AL16: =K16 -> MOTUL Transmission Oil Multi ATF 1L | AM16: =_xlfn.XLOOKUP(AL16,ITEM!B:B,ITEM!AY:AY,0) -> 55 | AN16: =_xlfn.XLOOKUP(AL16,ITEM!B:B,ITEM!AZ:AZ,0) -> 1.3333333 | AO16: =_xlfn.XLOOKUP(AL16,ITEM!B:B,ITEM!BA:BA,0) -> 4.7272727 | AP16: =AN16/AO16 -> 0.28205128 | AQ16: 0 | AR16: 0 | AS16: 0 | AT16: =AN16*$AI16 -> 1.2444444 | AU16: =AN16*(AE16+AG16+AI16) -> 3.0222222 | AV16: =_xlfn.XLOOKUP(AL16,ITEM!B:B,ITEM!BN:BN,0) -> 51 | AW16: 0 | AX16: 0 | AY16: =AU16-AV16-AW16+AX16 -> -47.977778 | AZ16: 0 | BA16: =AZ16/BC16 -> 0 | BB16: =H16 -> 12*1L | BC16: 12 | BD16: - | BE16: - | BF16: ★ | BG16: - | BH16: =K16 -> MOTUL Transmission Oil Multi ATF 1L | BI16: =AM16 -> 55 | BJ16: =BZ16 -> 51 | BK16: =CK16 -> 0 | BL16: =CV16 -> 0 | BM16: =BJ16+BK16+BL16 -> 51 | BN16: =CC16 -> -47.977778 | BO16: =CN16 -> 0 | BP16: =AY16 -> -47.977778 | BQ16: - | BS16: =K16 -> MOTUL Transmission Oil Multi ATF 1L | BT16: =_xlfn.XLOOKUP(BS16,ITEM!B:B,ITEM!BB:BB,0) -> 1.3333333 | BU16: =_xlfn.XLOOKUP(BS16,ITEM!B:B,ITEM!BC:BC,0) -> 4.7272727 | BV16: =BT16/BU16 -> 0.28205128 | BW16: 0 | BX16: =BT16*$AI16 -> 1.2444444 | BY16: =BT16*($AE16+$AG16+$AI16) -> 3.0222222 | BZ16: =_xlfn.XLOOKUP(BS16,ITEM!B:B,ITEM!BK:BK,0) -> 51 | CA16: 0 | CB16: 0 | CC16: =BY16-BZ16-CA16+CB16 -> -47.977778 | CD16: 0 | CE16: =_xlfn.XLOOKUP(BS16,ITEM!B:B,ITEM!BE:BE,0) -> 0 | CF16: =_xlfn.XLOOKUP(BS16,ITEM!B:B,ITEM!BF:BF,0) -> 0 | CG16: =CE16/CF16 -> #DIV/0! | CH16: 0 | CI16: =CE16*$AI16 -> 0 | CJ16: =CE16*($AE16+$AG16+$AI16) -> 0 | CK16: =_xlfn.XLOOKUP(BS16,ITEM!B:B,ITEM!BL:BL,0) -> 0 | CL16: 0 | CM16: 0 | CN16: =CJ16-CK16-CL16+CM16 -> 0 | CO16: 0 | CP16: =_xlfn.XLOOKUP(BS16,ITEM!B:B,ITEM!BH:BH,0) -> 0 | CQ16: =_xlfn.XLOOKUP(BS16,ITEM!B:B,ITEM!BI:BI,0) -> 0 | CR16: =CP16/CQ16 -> #DIV/0! | CS16: 0 | CT16: =CP16*$AI16 -> 0 | CU16: =CP16*($AE16+$AG16+$AI16) -> 0 | CV16: =_xlfn.XLOOKUP(BS16,ITEM!B:B,ITEM!BM:BM,0) -> 0 | CW16: 0 | CX16: 0 | CY16: =CU16-CV16-CW16+CX16 -> 0 | CZ16: 0 | DA16: =K16 -> MOTUL Transmission Oil Multi ATF 1L
A17: 7 | B17: 101813 | C17: MOTUL | D17: Gear Oil | E17: HDX | F17: 80W-90 | G17: 1L | H17: 12*1L | I17: 12 | J17: =C17&" "&D17&" "&E17&" "&F17&" "&G17 -> MOTUL Gear Oil HDX 80W-90 1L | K17: MOTUL Gear Oil HDX 80W-90 1L | L17: 1 | M17: 桶 | N17: 118889 | O17: 0.4 | P17: 0.2 | Q17: =O17+P17 -> 0.6 | R17: =N17*(1+Q17) -> 190222.4 | S17: 0 | T17: 0 | U17: 0 | V17: =IF((S17+T17+U17)=0,R17,IF(AND(S17>0,T17=0,U17=0),S17,IF(AND(S17=0,T17>0,U17=0),T17,IF(AND(S17=0,T17=0,U17>0),U17,IF(AND(S17>0,T17>0,U17=0),(S17+T17)/2,IF(AND(S17>0,T17=0,U17>0),(S17+U17)/2,IF(AND(S17=0,T17>0,U17>0),(T17+U17)/2,IF(AND(S17>0,T17>0,U17>0),(S17+T17+U17)/3,)))))))) -> 190222.4 | W17: =IF(R17=V17,V17,IF(R17/V17<70%,R17*1.18,IF(AND(R17/V17>=70%,R17/V17<75%),R17*1.15,IF(AND(R17/V17>=75%,R17/V17<80%),R17*1.12,IF(AND(R17/V17>=80%,R17/V17<85%),R17*1.09,IF(AND(R17/V17>=85%,R17/V17<90%),R17*1.06,IF(AND(R17/V17>=90%,R17/V17<95%),R17*1.03,IF(AND(R17/V17>=95%,R17/V17<105%),V17,IF(AND(R17/V17>=105%,R17/V17<110%),R17*0.97,IF(AND(R17/V17>=110%,R17/V17<115%),R17*0.94,IF(AND(R17/V17>=115%,R17/V17<120%),R17*0.91,IF(AND(R17/V17>=120%,R17/V17<125%),R17*0.88,IF(AND(R17/V17>=125%,R17/V17<130%),R17*0.85,IF(AND(R17/V17>=130%,R17/V17<135%),R17*0.82,IF(R17/V17>=135%,R17*0.8,))))))))))))))) -> 190222.4 | X17: =IF(N17=0,1,IF(N17<10000,N17*2.8,IF(AND(N17>=10000,N17<20000),N17*2.2,IF(AND(N17>=20000,N17<30000),N17*1.8,IF(AND(N17>=30000,N17<40000),N17*1.78,IF(AND(N17>=40000,N17<50000),N17*1.76,IF(AND(N17>=50000,N17<60000),N17*1.74,IF(AND(N17>=60000,N17<70000),N17*1.72,IF(AND(N17>=70000,N17<80000),N17*1.7,IF(AND(N17>=80000,N17<90000),N17*1.68,IF(AND(N17>=90000,N17<100000),N17*1.66,IF(AND(N17>=100000,N17<110000),N17*1.65,IF(AND(N17>=110000,N17<120000),N17*1.64,IF(AND(N17>=120000,N17<130000),N17*1.63,IF(AND(N17>=130000,N17<140000),N17*1.62,IF(AND(N17>=140000,N17<150000),N17*1.61,IF(AND(N17>=150000,N17<160000),N17*1.6,IF(AND(N17>=160000,N17<170000),N17*1.59,IF(AND(N17>=170000,N17<180000),N17*1.58,IF(AND(N17>=180000,N17<190000),N17*1.57,IF(AND(N17>=190000,N17<200000),N17*1.56,IF(AND(N17>=200000,N17<300000),N17*1.54,IF(AND(N17>=300000,N17<400000),N17*1.52,IF(AND(N17>=400000,N17<500000),N17*1.5,IF(AND(N17>=500000,N17<600000),N17*1.48,IF(AND(N17>=600000,N17<700000),N17*1.46,IF(AND(N17>=700000,N17<800000),N17*1.44,IF(AND(N17>=800000,N17<900000),N17*1.42,IF(AND(N17>=900000,N17<1000000),N17*1.4,IF(AND(N17>=1000000,N17<2000000),N17*1.39,IF(AND(N17>=2000000,N17<3000000),N17*1.38,IF(AND(N17>=3000000,N17<4000000),N17*1.37,IF(AND(N17>=4000000,N17<5000000),N17*1.36,IF(AND(N17>=5000000,N17<6000000),N17*1.35,IF(AND(N17>=6000000,N17<7000000),N17*1.34,IF(AND(N17>=7000000,N17<8000000),N17*1.33,IF(AND(N17>=8000000,N17<9000000),N17*1.32,IF(AND(N17>=9000000,N17<10000000),N17*1.31,IF(N17>=10000000,N17*1.3,""))))))))))))))))))))))))))))))))))))))) -> 194977.96 | Y17: =CEILING((R17+W17+X17)/3,1000) -> 192000 | Z17: 0 | AA17: =CEILING((Y17+Z17),1000) -> 192000 | AB17: =AA17-N17 -> 73111 | AC17: =AB17/AA17 -> 0.38078646 | AD17: 30 | AE17: =AD17/30 -> 1 | AF17: 10 | AG17: =AF17/30 -> 0.33333333 | AH17: 0.7 | AI17: =(AE17+AG17)*AH17 -> 0.93333333 | AJ17: =AI17*30 -> 28 | AK17: - | AL17: =K17 -> MOTUL Gear Oil HDX 80W-90 1L | AM17: =_xlfn.XLOOKUP(AL17,ITEM!B:B,ITEM!AY:AY,0) -> 12 | AN17: =_xlfn.XLOOKUP(AL17,ITEM!B:B,ITEM!AZ:AZ,0) -> 0 | AO17: =_xlfn.XLOOKUP(AL17,ITEM!B:B,ITEM!BA:BA,0) -> 1.0909091 | AP17: =AN17/AO17 -> 0 | AQ17: 0 | AR17: 0 | AS17: 0 | AT17: =AN17*$AI17 -> 0 | AU17: =AN17*(AE17+AG17+AI17) -> 0 | AV17: =_xlfn.XLOOKUP(AL17,ITEM!B:B,ITEM!BN:BN,0) -> 12 | AW17: 0 | AX17: 0 | AY17: =AU17-AV17-AW17+AX17 -> -12 | AZ17: 0 | BA17: =AZ17/BC17 -> 0 | BB17: =H17 -> 12*1L | BC17: 12 | BD17: - | BE17: - | BF17: ★ | BG17: - | BH17: =K17 -> MOTUL Gear Oil HDX 80W-90 1L | BI17: =AM17 -> 12 | BJ17: =BZ17 -> 0 | BK17: =CK17 -> 0 | BL17: =CV17 -> 12 | BM17: =BJ17+BK17+BL17 -> 12 | BN17: =CC17 -> 0 | BO17: =CN17 -> 0 | BP17: =AY17 -> -12 | BQ17: - | BS17: =K17 -> MOTUL Gear Oil HDX 80W-90 1L | BT17: =_xlfn.XLOOKUP(BS17,ITEM!B:B,ITEM!BB:BB,0) -> 0 | BU17: =_xlfn.XLOOKUP(BS17,ITEM!B:B,ITEM!BC:BC,0) -> 1.0909091 | BV17: =BT17/BU17 -> 0 | BW17: 0 | BX17: =BT17*$AI17 -> 0 | BY17: =BT17*($AE17+$AG17+$AI17) -> 0 | BZ17: =_xlfn.XLOOKUP(BS17,ITEM!B:B,ITEM!BK:BK,0) -> 0 | CA17: 0 | CB17: 0 | CC17: =BY17-BZ17-CA17+CB17 -> 0 | CD17: 0 | CE17: =_xlfn.XLOOKUP(BS17,ITEM!B:B,ITEM!BE:BE,0) -> 0 | CF17: =_xlfn.XLOOKUP(BS17,ITEM!B:B,ITEM!BF:BF,0) -> 0 | CG17: =CE17/CF17 -> #DIV/0! | CH17: 0 | CI17: =CE17*$AI17 -> 0 | CJ17: =CE17*($AE17+$AG17+$AI17) -> 0 | CK17: =_xlfn.XLOOKUP(BS17,ITEM!B:B,ITEM!BL:BL,0) -> 0 | CL17: 0 | CM17: 0 | CN17: =CJ17-CK17-CL17+CM17 -> 0 | CO17: 0 | CP17: =_xlfn.XLOOKUP(BS17,ITEM!B:B,ITEM!BH:BH,0) -> 0 | CQ17: =_xlfn.XLOOKUP(BS17,ITEM!B:B,ITEM!BI:BI,0) -> 0 | CR17: =CP17/CQ17 -> #DIV/0! | CS17: 0 | CT17: =CP17*$AI17 -> 0 | CU17: =CP17*($AE17+$AG17+$AI17) -> 0 | CV17: =_xlfn.XLOOKUP(BS17,ITEM!B:B,ITEM!BM:BM,0) -> 12 | CW17: 0 | CX17: 0 | CY17: =CU17-CV17-CW17+CX17 -> -12 | CZ17: 0 | DA17: =K17 -> MOTUL Gear Oil HDX 80W-90 1L
A18: 14 | B18: 101806 | C18: MOTUL | D18: Brake Fluid | E18: DOT 4 | F18: - | G18: 500ml | H18: 0 | I18: 0 | J18: =C18&" "&D18&" "&E18&" "&F18&" "&G18 -> MOTUL Brake Fluid DOT 4 - 500ml | K18: MOTUL Brake Fluid DOT 4 - 500ml | L18: 1 | M18: 桶 | N18: 51729 | O18: 0.4 | P18: 0.2 | Q18: =O18+P18 -> 0.6 | R18: =N18*(1+Q18) -> 82766.4 | S18: 0 | T18: 0 | U18: 0 | V18: =IF((S18+T18+U18)=0,R18,IF(AND(S18>0,T18=0,U18=0),S18,IF(AND(S18=0,T18>0,U18=0),T18,IF(AND(S18=0,T18=0,U18>0),U18,IF(AND(S18>0,T18>0,U18=0),(S18+T18)/2,IF(AND(S18>0,T18=0,U18>0),(S18+U18)/2,IF(AND(S18=0,T18>0,U18>0),(T18+U18)/2,IF(AND(S18>0,T18>0,U18>0),(S18+T18+U18)/3,)))))))) -> 82766.4 | W18: =IF(R18=V18,V18,IF(R18/V18<70%,R18*1.18,IF(AND(R18/V18>=70%,R18/V18<75%),R18*1.15,IF(AND(R18/V18>=75%,R18/V18<80%),R18*1.12,IF(AND(R18/V18>=80%,R18/V18<85%),R18*1.09,IF(AND(R18/V18>=85%,R18/V18<90%),R18*1.06,IF(AND(R18/V18>=90%,R18/V18<95%),R18*1.03,IF(AND(R18/V18>=95%,R18/V18<105%),V18,IF(AND(R18/V18>=105%,R18/V18<110%),R18*0.97,IF(AND(R18/V18>=110%,R18/V18<115%),R18*0.94,IF(AND(R18/V18>=115%,R18/V18<120%),R18*0.91,IF(AND(R18/V18>=120%,R18/V18<125%),R18*0.88,IF(AND(R18/V18>=125%,R18/V18<130%),R18*0.85,IF(AND(R18/V18>=130%,R18/V18<135%),R18*0.82,IF(R18/V18>=135%,R18*0.8,))))))))))))))) -> 82766.4 | X18: =IF(N18=0,1,IF(N18<10000,N18*2.8,IF(AND(N18>=10000,N18<20000),N18*2.2,IF(AND(N18>=20000,N18<30000),N18*1.8,IF(AND(N18>=30000,N18<40000),N18*1.78,IF(AND(N18>=40000,N18<50000),N18*1.76,IF(AND(N18>=50000,N18<60000),N18*1.74,IF(AND(N18>=60000,N18<70000),N18*1.72,IF(AND(N18>=70000,N18<80000),N18*1.7,IF(AND(N18>=80000,N18<90000),N18*1.68,IF(AND(N18>=90000,N18<100000),N18*1.66,IF(AND(N18>=100000,N18<110000),N18*1.65,IF(AND(N18>=110000,N18<120000),N18*1.64,IF(AND(N18>=120000,N18<130000),N18*1.63,IF(AND(N18>=130000,N18<140000),N18*1.62,IF(AND(N18>=140000,N18<150000),N18*1.61,IF(AND(N18>=150000,N18<160000),N18*1.6,IF(AND(N18>=160000,N18<170000),N18*1.59,IF(AND(N18>=170000,N18<180000),N18*1.58,IF(AND(N18>=180000,N18<190000),N18*1.57,IF(AND(N18>=190000,N18<200000),N18*1.56,IF(AND(N18>=200000,N18<300000),N18*1.54,IF(AND(N18>=300000,N18<400000),N18*1.52,IF(AND(N18>=400000,N18<500000),N18*1.5,IF(AND(N18>=500000,N18<600000),N18*1.48,IF(AND(N18>=600000,N18<700000),N18*1.46,IF(AND(N18>=700000,N18<800000),N18*1.44,IF(AND(N18>=800000,N18<900000),N18*1.42,IF(AND(N18>=900000,N18<1000000),N18*1.4,IF(AND(N18>=1000000,N18<2000000),N18*1.39,IF(AND(N18>=2000000,N18<3000000),N18*1.38,IF(AND(N18>=3000000,N18<4000000),N18*1.37,IF(AND(N18>=4000000,N18<5000000),N18*1.36,IF(AND(N18>=5000000,N18<6000000),N18*1.35,IF(AND(N18>=6000000,N18<7000000),N18*1.34,IF(AND(N18>=7000000,N18<8000000),N18*1.33,IF(AND(N18>=8000000,N18<9000000),N18*1.32,IF(AND(N18>=9000000,N18<10000000),N18*1.31,IF(N18>=10000000,N18*1.3,""))))))))))))))))))))))))))))))))))))))) -> 90008.46 | Y18: =CEILING((R18+W18+X18)/3,1000) -> 86000 | Z18: 0 | AA18: =CEILING((Y18+Z18),1000) -> 86000 | AB18: =AA18-N18 -> 34271 | AC18: =AB18/AA18 -> 0.3985 | AD18: 30 | AE18: =AD18/30 -> 1 | AF18: 10 | AG18: =AF18/30 -> 0.33333333 | AH18: 0.7 | AI18: =(AE18+AG18)*AH18 -> 0.93333333 | AJ18: =AI18*30 -> 28 | AK18: - | AL18: =K18 -> MOTUL Brake Fluid DOT 4 - 500ml | AM18: =_xlfn.XLOOKUP(AL18,ITEM!B:B,ITEM!AY:AY,0) -> 7 | AN18: =_xlfn.XLOOKUP(AL18,ITEM!B:B,ITEM!AZ:AZ,0) -> 0 | AO18: =_xlfn.XLOOKUP(AL18,ITEM!B:B,ITEM!BA:BA,0) -> 0.54545455 | AP18: =AN18/AO18 -> 0 | AQ18: 0 | AR18: 0 | AS18: 0 | AT18: =AN18*$AI18 -> 0 | AU18: =AN18*(AE18+AG18+AI18) -> 0 | AV18: =_xlfn.XLOOKUP(AL18,ITEM!B:B,ITEM!BN:BN,0) -> 25 | AW18: 0 | AX18: 0 | AY18: =AU18-AV18-AW18+AX18 -> -25 | AZ18: 0 | BA18: =AZ18/BC18 -> #DIV/0! | BB18: =H18 -> 0 | BC18: 0 | BD18: - | BE18: - | BF18: ★ | BG18: ★★ | BH18: =K18 -> MOTUL Brake Fluid DOT 4 - 500ml | BI18: =AM18 -> 7 | BJ18: =BZ18 -> 0 | BK18: =CK18 -> 25 | BL18: =CV18 -> 0 | BM18: =BJ18+BK18+BL18 -> 25 | BN18: =CC18 -> 0 | BO18: =CN18 -> -25 | BP18: =AY18 -> -25 | BQ18: - | BS18: =K18 -> MOTUL Brake Fluid DOT 4 - 500ml | BT18: =_xlfn.XLOOKUP(BS18,ITEM!B:B,ITEM!BB:BB,0) -> 0 | BU18: =_xlfn.XLOOKUP(BS18,ITEM!B:B,ITEM!BC:BC,0) -> 0.54545455 | BV18: =BT18/BU18 -> 0 | BW18: 0 | BX18: =BT18*$AI18 -> 0 | BY18: =BT18*($AE18+$AG18+$AI18) -> 0 | BZ18: =_xlfn.XLOOKUP(BS18,ITEM!B:B,ITEM!BK:BK,0) -> 0 | CA18: 0 | CB18: 0 | CC18: =BY18-BZ18-CA18+CB18 -> 0 | CD18: 0 | CE18: =_xlfn.XLOOKUP(BS18,ITEM!B:B,ITEM!BE:BE,0) -> 0 | CF18: =_xlfn.XLOOKUP(BS18,ITEM!B:B,ITEM!BF:BF,0) -> 0 | CG18: =CE18/CF18 -> #DIV/0! | CH18: 0 | CI18: =CE18*$AI18 -> 0 | CJ18: =CE18*($AE18+$AG18+$AI18) -> 0 | CK18: =_xlfn.XLOOKUP(BS18,ITEM!B:B,ITEM!BL:BL,0) -> 25 | CL18: 0 | CM18: 0 | CN18: =CJ18-CK18-CL18+CM18 -> -25 | CO18: 0 | CP18: =_xlfn.XLOOKUP(BS18,ITEM!B:B,ITEM!BH:BH,0) -> 0 | CQ18: =_xlfn.XLOOKUP(BS18,ITEM!B:B,ITEM!BI:BI,0) -> 0 | CR18: =CP18/CQ18 -> #DIV/0! | CS18: 0 | CT18: =CP18*$AI18 -> 0 | CU18: =CP18*($AE18+$AG18+$AI18) -> 0 | CV18: =_xlfn.XLOOKUP(BS18,ITEM!B:B,ITEM!BM:BM,0) -> 0 | CW18: 0 | CX18: 0 | CY18: =CU18-CV18-CW18+CX18 -> 0 | CZ18: 0 | DA18: =K18 -> MOTUL Brake Fluid DOT 4 - 500ml
A19: 15 | B19: 101823 | C19: MOTUL | D19: Brake Fluid | E19: DOT 5.1 | F19: - | G19: 500ml | H19: 0 | I19: 0 | J19: =C19&" "&D19&" "&E19&" "&F19&" "&G19 -> MOTUL Brake Fluid DOT 5.1 - 500ml | K19: MOTUL Brake Fluid DOT 5.1 - 500ml | L19: 1 | M19: 桶 | N19: 142252 | O19: 0.4 | P19: 0.2 | Q19: =O19+P19 -> 0.6 | R19: =N19*(1+Q19) -> 227603.2 | S19: 0 | T19: 0 | U19: 0 | V19: =IF((S19+T19+U19)=0,R19,IF(AND(S19>0,T19=0,U19=0),S19,IF(AND(S19=0,T19>0,U19=0),T19,IF(AND(S19=0,T19=0,U19>0),U19,IF(AND(S19>0,T19>0,U19=0),(S19+T19)/2,IF(AND(S19>0,T19=0,U19>0),(S19+U19)/2,IF(AND(S19=0,T19>0,U19>0),(T19+U19)/2,IF(AND(S19>0,T19>0,U19>0),(S19+T19+U19)/3,)))))))) -> 227603.2 | W19: =IF(R19=V19,V19,IF(R19/V19<70%,R19*1.18,IF(AND(R19/V19>=70%,R19/V19<75%),R19*1.15,IF(AND(R19/V19>=75%,R19/V19<80%),R19*1.12,IF(AND(R19/V19>=80%,R19/V19<85%),R19*1.09,IF(AND(R19/V19>=85%,R19/V19<90%),R19*1.06,IF(AND(R19/V19>=90%,R19/V19<95%),R19*1.03,IF(AND(R19/V19>=95%,R19/V19<105%),V19,IF(AND(R19/V19>=105%,R19/V19<110%),R19*0.97,IF(AND(R19/V19>=110%,R19/V19<115%),R19*0.94,IF(AND(R19/V19>=115%,R19/V19<120%),R19*0.91,IF(AND(R19/V19>=120%,R19/V19<125%),R19*0.88,IF(AND(R19/V19>=125%,R19/V19<130%),R19*0.85,IF(AND(R19/V19>=130%,R19/V19<135%),R19*0.82,IF(R19/V19>=135%,R19*0.8,))))))))))))))) -> 227603.2 | X19: =IF(N19=0,1,IF(N19<10000,N19*2.8,IF(AND(N19>=10000,N19<20000),N19*2.2,IF(AND(N19>=20000,N19<30000),N19*1.8,IF(AND(N19>=30000,N19<40000),N19*1.78,IF(AND(N19>=40000,N19<50000),N19*1.76,IF(AND(N19>=50000,N19<60000),N19*1.74,IF(AND(N19>=60000,N19<70000),N19*1.72,IF(AND(N19>=70000,N19<80000),N19*1.7,IF(AND(N19>=80000,N19<90000),N19*1.68,IF(AND(N19>=90000,N19<100000),N19*1.66,IF(AND(N19>=100000,N19<110000),N19*1.65,IF(AND(N19>=110000,N19<120000),N19*1.64,IF(AND(N19>=120000,N19<130000),N19*1.63,IF(AND(N19>=130000,N19<140000),N19*1.62,IF(AND(N19>=140000,N19<150000),N19*1.61,IF(AND(N19>=150000,N19<160000),N19*1.6,IF(AND(N19>=160000,N19<170000),N19*1.59,IF(AND(N19>=170000,N19<180000),N19*1.58,IF(AND(N19>=180000,N19<190000),N19*1.57,IF(AND(N19>=190000,N19<200000),N19*1.56,IF(AND(N19>=200000,N19<300000),N19*1.54,IF(AND(N19>=300000,N19<400000),N19*1.52,IF(AND(N19>=400000,N19<500000),N19*1.5,IF(AND(N19>=500000,N19<600000),N19*1.48,IF(AND(N19>=600000,N19<700000),N19*1.46,IF(AND(N19>=700000,N19<800000),N19*1.44,IF(AND(N19>=800000,N19<900000),N19*1.42,IF(AND(N19>=900000,N19<1000000),N19*1.4,IF(AND(N19>=1000000,N19<2000000),N19*1.39,IF(AND(N19>=2000000,N19<3000000),N19*1.38,IF(AND(N19>=3000000,N19<4000000),N19*1.37,IF(AND(N19>=4000000,N19<5000000),N19*1.36,IF(AND(N19>=5000000,N19<6000000),N19*1.35,IF(AND(N19>=6000000,N19<7000000),N19*1.34,IF(AND(N19>=7000000,N19<8000000),N19*1.33,IF(AND(N19>=8000000,N19<9000000),N19*1.32,IF(AND(N19>=9000000,N19<10000000),N19*1.31,IF(N19>=10000000,N19*1.3,""))))))))))))))))))))))))))))))))))))))) -> 229025.72 | Y19: =CEILING((R19+W19+X19)/3,1000) -> 229000 | Z19: 0 | AA19: =CEILING((Y19+Z19),1000) -> 229000 | AB19: =AA19-N19 -> 86748 | AC19: =AB19/AA19 -> 0.37881223 | AD19: 30 | AE19: =AD19/30 -> 1 | AF19: 10 | AG19: =AF19/30 -> 0.33333333 | AH19: 0.7 | AI19: =(AE19+AG19)*AH19 -> 0.93333333 | AJ19: =AI19*30 -> 28 | AK19: - | AL19: =K19 -> MOTUL Brake Fluid DOT 5.1 - 500ml | AM19: =_xlfn.XLOOKUP(AL19,ITEM!B:B,ITEM!AY:AY,0) -> 2 | AN19: =_xlfn.XLOOKUP(AL19,ITEM!B:B,ITEM!AZ:AZ,0) -> 0.33333333 | AO19: =_xlfn.XLOOKUP(AL19,ITEM!B:B,ITEM!BA:BA,0) -> 0.18181818 | AP19: =AN19/AO19 -> 1.8333333 | AQ19: 0 | AR19: 0 | AS19: 0 | AT19: =AN19*$AI19 -> 0.31111111 | AU19: =AN19*(AE19+AG19+AI19) -> 0.75555556 | AV19: =_xlfn.XLOOKUP(AL19,ITEM!B:B,ITEM!BN:BN,0) -> 9 | AW19: 0 | AX19: 0 | AY19: =AU19-AV19-AW19+AX19 -> -8.2444444 | AZ19: 0 | BA19: =AZ19/BC19 -> #DIV/0! | BB19: =H19 -> 0 | BC19: 0 | BD19: - | BE19: - | BF19: ★ | BG19: ★★★ | BH19: =K19 -> MOTUL Brake Fluid DOT 5.1 - 500ml | BI19: =AM19 -> 2 | BJ19: =BZ19 -> 3 | BK19: =CK19 -> 5 | BL19: =CV19 -> 1 | BM19: =BJ19+BK19+BL19 -> 9 | BN19: =CC19 -> -2.2444444 | BO19: =CN19 -> -5 | BP19: =AY19 -> -8.2444444 | BQ19: - | BS19: =K19 -> MOTUL Brake Fluid DOT 5.1 - 500ml | BT19: =_xlfn.XLOOKUP(BS19,ITEM!B:B,ITEM!BB:BB,0) -> 0.33333333 | BU19: =_xlfn.XLOOKUP(BS19,ITEM!B:B,ITEM!BC:BC,0) -> 0.18181818 | BV19: =BT19/BU19 -> 1.8333333 | BW19: 0 | BX19: =BT19*$AI19 -> 0.31111111 | BY19: =BT19*($AE19+$AG19+$AI19) -> 0.75555556 | BZ19: =_xlfn.XLOOKUP(BS19,ITEM!B:B,ITEM!BK:BK,0) -> 3 | CA19: 0 | CB19: 0 | CC19: =BY19-BZ19-CA19+CB19 -> -2.2444444 | CD19: 0 | CE19: =_xlfn.XLOOKUP(BS19,ITEM!B:B,ITEM!BE:BE,0) -> 0 | CF19: =_xlfn.XLOOKUP(BS19,ITEM!B:B,ITEM!BF:BF,0) -> 0 | CG19: =CE19/CF19 -> #DIV/0! | CH19: 0 | CI19: =CE19*$AI19 -> 0 | CJ19: =CE19*($AE19+$AG19+$AI19) -> 0 | CK19: =_xlfn.XLOOKUP(BS19,ITEM!B:B,ITEM!BL:BL,0) -> 5 | CL19: 0 | CM19: 0 | CN19: =CJ19-CK19-CL19+CM19 -> -5 | CO19: 0 | CP19: =_xlfn.XLOOKUP(BS19,ITEM!B:B,ITEM!BH:BH,0) -> 0 | CQ19: =_xlfn.XLOOKUP(BS19,ITEM!B:B,ITEM!BI:BI,0) -> 0 | CR19: =CP19/CQ19 -> #DIV/0! | CS19: 0 | CT19: =CP19*$AI19 -> 0 | CU19: =CP19*($AE19+$AG19+$AI19) -> 0 | CV19: =_xlfn.XLOOKUP(BS19,ITEM!B:B,ITEM!BM:BM,0) -> 1 | CW19: 0 | CX19: 0 | CY19: =CU19-CV19-CW19+CX19 -> -1 | CZ19: 0 | DA19: =K19 -> MOTUL Brake Fluid DOT 5.1 - 500ml
A20: 17 | B20: 102339 | C20: PRESTONE | D20: Brake Fluid | E20: DOT 3 | F20: - | G20: 300ml | H20: 0 | I20: 0 | J20: =C20&" "&D20&" "&E20&" "&F20&" "&G20 -> PRESTONE Brake Fluid DOT 3 - 300ml | K20: PRESTONE Brake Fluid DOT 3 - 300ml | L20: 1 | M20: 桶 | N20: 181837 | O20: 0.4 | P20: 0.2 | Q20: =O20+P20 -> 0.6 | R20: =N20*(1+Q20) -> 290939.2 | S20: 0 | T20: 0 | U20: 0 | V20: =IF((S20+T20+U20)=0,R20,IF(AND(S20>0,T20=0,U20=0),S20,IF(AND(S20=0,T20>0,U20=0),T20,IF(AND(S20=0,T20=0,U20>0),U20,IF(AND(S20>0,T20>0,U20=0),(S20+T20)/2,IF(AND(S20>0,T20=0,U20>0),(S20+U20)/2,IF(AND(S20=0,T20>0,U20>0),(T20+U20)/2,IF(AND(S20>0,T20>0,U20>0),(S20+T20+U20)/3,)))))))) -> 290939.2 | W20: =IF(R20=V20,V20,IF(R20/V20<70%,R20*1.18,IF(AND(R20/V20>=70%,R20/V20<75%),R20*1.15,IF(AND(R20/V20>=75%,R20/V20<80%),R20*1.12,IF(AND(R20/V20>=80%,R20/V20<85%),R20*1.09,IF(AND(R20/V20>=85%,R20/V20<90%),R20*1.06,IF(AND(R20/V20>=90%,R20/V20<95%),R20*1.03,IF(AND(R20/V20>=95%,R20/V20<105%),V20,IF(AND(R20/V20>=105%,R20/V20<110%),R20*0.97,IF(AND(R20/V20>=110%,R20/V20<115%),R20*0.94,IF(AND(R20/V20>=115%,R20/V20<120%),R20*0.91,IF(AND(R20/V20>=120%,R20/V20<125%),R20*0.88,IF(AND(R20/V20>=125%,R20/V20<130%),R20*0.85,IF(AND(R20/V20>=130%,R20/V20<135%),R20*0.82,IF(R20/V20>=135%,R20*0.8,))))))))))))))) -> 290939.2 | X20: =IF(N20=0,1,IF(N20<10000,N20*2.8,IF(AND(N20>=10000,N20<20000),N20*2.2,IF(AND(N20>=20000,N20<30000),N20*1.8,IF(AND(N20>=30000,N20<40000),N20*1.78,IF(AND(N20>=40000,N20<50000),N20*1.76,IF(AND(N20>=50000,N20<60000),N20*1.74,IF(AND(N20>=60000,N20<70000),N20*1.72,IF(AND(N20>=70000,N20<80000),N20*1.7,IF(AND(N20>=80000,N20<90000),N20*1.68,IF(AND(N20>=90000,N20<100000),N20*1.66,IF(AND(N20>=100000,N20<110000),N20*1.65,IF(AND(N20>=110000,N20<120000),N20*1.64,IF(AND(N20>=120000,N20<130000),N20*1.63,IF(AND(N20>=130000,N20<140000),N20*1.62,IF(AND(N20>=140000,N20<150000),N20*1.61,IF(AND(N20>=150000,N20<160000),N20*1.6,IF(AND(N20>=160000,N20<170000),N20*1.59,IF(AND(N20>=170000,N20<180000),N20*1.58,IF(AND(N20>=180000,N20<190000),N20*1.57,IF(AND(N20>=190000,N20<200000),N20*1.56,IF(AND(N20>=200000,N20<300000),N20*1.54,IF(AND(N20>=300000,N20<400000),N20*1.52,IF(AND(N20>=400000,N20<500000),N20*1.5,IF(AND(N20>=500000,N20<600000),N20*1.48,IF(AND(N20>=600000,N20<700000),N20*1.46,IF(AND(N20>=700000,N20<800000),N20*1.44,IF(AND(N20>=800000,N20<900000),N20*1.42,IF(AND(N20>=900000,N20<1000000),N20*1.4,IF(AND(N20>=1000000,N20<2000000),N20*1.39,IF(AND(N20>=2000000,N20<3000000),N20*1.38,IF(AND(N20>=3000000,N20<4000000),N20*1.37,IF(AND(N20>=4000000,N20<5000000),N20*1.36,IF(AND(N20>=5000000,N20<6000000),N20*1.35,IF(AND(N20>=6000000,N20<7000000),N20*1.34,IF(AND(N20>=7000000,N20<8000000),N20*1.33,IF(AND(N20>=8000000,N20<9000000),N20*1.32,IF(AND(N20>=9000000,N20<10000000),N20*1.31,IF(N20>=10000000,N20*1.3,""))))))))))))))))))))))))))))))))))))))) -> 285484.09 | Y20: =CEILING((R20+W20+X20)/3,1000) -> 290000 | Z20: 0 | AA20: =CEILING((Y20+Z20),1000) -> 290000 | AB20: =AA20-N20 -> 108163 | AC20: =AB20/AA20 -> 0.37297586 | AD20: 30 | AE20: =AD20/30 -> 1 | AF20: 10 | AG20: =AF20/30 -> 0.33333333 | AH20: 0.7 | AI20: =(AE20+AG20)*AH20 -> 0.93333333 | AJ20: =AI20*30 -> 28 | AK20: - | AL20: =K20 -> PRESTONE Brake Fluid DOT 3 - 300ml | AM20: =_xlfn.XLOOKUP(AL20,ITEM!B:B,ITEM!AY:AY,0) -> 0 | AN20: =_xlfn.XLOOKUP(AL20,ITEM!B:B,ITEM!AZ:AZ,0) -> 0 | AO20: =_xlfn.XLOOKUP(AL20,ITEM!B:B,ITEM!BA:BA,0) -> 0 | AP20: =AN20/AO20 -> #DIV/0! | AQ20: 0 | AR20: 0 | AS20: 0 | AT20: =AN20*$AI20 -> 0 | AU20: =AN20*(AE20+AG20+AI20) -> 0 | AV20: =_xlfn.XLOOKUP(AL20,ITEM!B:B,ITEM!BN:BN,0) -> 0 | AW20: 0 | AX20: 0 | AY20: =AU20-AV20-AW20+AX20 -> 0 | AZ20: 0 | BA20: =AZ20/BC20 -> #DIV/0! | BB20: =H20 -> 0 | BC20: 0 | BD20: - | BE20: - | BF20: ★ | BG20: ★ | BH20: =K20 -> PRESTONE Brake Fluid DOT 3 - 300ml | BI20: =AM20 -> 0 | BJ20: =BZ20 -> 0 | BK20: =CK20 -> 0 | BL20: =CV20 -> 0 | BM20: =BJ20+BK20+BL20 -> 0 | BN20: =CC20 -> 0 | BO20: =CN20 -> 0 | BP20: =AY20 -> 0 | BQ20: - | BS20: =K20 -> PRESTONE Brake Fluid DOT 3 - 300ml | BT20: =_xlfn.XLOOKUP(BS20,ITEM!B:B,ITEM!BB:BB,0) -> 0 | BU20: =_xlfn.XLOOKUP(BS20,ITEM!B:B,ITEM!BC:BC,0) -> 0 | BV20: =BT20/BU20 -> #DIV/0! | BW20: 0 | BX20: =BT20*$AI20 -> 0 | BY20: =BT20*($AE20+$AG20+$AI20) -> 0 | BZ20: =_xlfn.XLOOKUP(BS20,ITEM!B:B,ITEM!BK:BK,0) -> 0 | CA20: 0 | CB20: 0 | CC20: =BY20-BZ20-CA20+CB20 -> 0 | CD20: 0 | CE20: =_xlfn.XLOOKUP(BS20,ITEM!B:B,ITEM!BE:BE,0) -> 0 | CF20: =_xlfn.XLOOKUP(BS20,ITEM!B:B,ITEM!BF:BF,0) -> 0 | CG20: =CE20/CF20 -> #DIV/0! | CH20: 0 | CI20: =CE20*$AI20 -> 0 | CJ20: =CE20*($AE20+$AG20+$AI20) -> 0 | CK20: =_xlfn.XLOOKUP(BS20,ITEM!B:B,ITEM!BL:BL,0) -> 0 | CL20: 0 | CM20: 0 | CN20: =CJ20-CK20-CL20+CM20 -> 0 | CO20: 0 | CP20: =_xlfn.XLOOKUP(BS20,ITEM!B:B,ITEM!BH:BH,0) -> 0 | CQ20: =_xlfn.XLOOKUP(BS20,ITEM!B:B,ITEM!BI:BI,0) -> 0 | CR20: =CP20/CQ20 -> #DIV/0! | CS20: 0 | CT20: =CP20*$AI20 -> 0 | CU20: =CP20*($AE20+$AG20+$AI20) -> 0 | CV20: =_xlfn.XLOOKUP(BS20,ITEM!B:B,ITEM!BM:BM,0) -> 0 | CW20: 0 | CX20: 0 | CY20: =CU20-CV20-CW20+CX20 -> 0 | CZ20: 0 | DA20: =K20 -> PRESTONE Brake Fluid DOT 3 - 300ml
A21: 18 | B21: 108297 | C21: PRESTONE | D21: Brake Fluid | E21: DOT 4 | F21: - | G21: 1000ml | H21: 0 | I21: 0 | J21: =C21&" "&D21&" "&E21&" "&F21&" "&G21 -> PRESTONE Brake Fluid DOT 4 - 1000ml | K21: PRESTONE Brake Fluid DOT 4 - 1000ml | L21: 1 | M21: 桶 | N21: 118889 | O21: 0.4 | P21: 0.2 | Q21: =O21+P21 -> 0.6 | R21: =N21*(1+Q21) -> 190222.4 | S21: 0 | T21: 0 | U21: 0 | V21: =IF((S21+T21+U21)=0,R21,IF(AND(S21>0,T21=0,U21=0),S21,IF(AND(S21=0,T21>0,U21=0),T21,IF(AND(S21=0,T21=0,U21>0),U21,IF(AND(S21>0,T21>0,U21=0),(S21+T21)/2,IF(AND(S21>0,T21=0,U21>0),(S21+U21)/2,IF(AND(S21=0,T21>0,U21>0),(T21+U21)/2,IF(AND(S21>0,T21>0,U21>0),(S21+T21+U21)/3,)))))))) -> 190222.4 | W21: =IF(R21=V21,V21,IF(R21/V21<70%,R21*1.18,IF(AND(R21/V21>=70%,R21/V21<75%),R21*1.15,IF(AND(R21/V21>=75%,R21/V21<80%),R21*1.12,IF(AND(R21/V21>=80%,R21/V21<85%),R21*1.09,IF(AND(R21/V21>=85%,R21/V21<90%),R21*1.06,IF(AND(R21/V21>=90%,R21/V21<95%),R21*1.03,IF(AND(R21/V21>=95%,R21/V21<105%),V21,IF(AND(R21/V21>=105%,R21/V21<110%),R21*0.97,IF(AND(R21/V21>=110%,R21/V21<115%),R21*0.94,IF(AND(R21/V21>=115%,R21/V21<120%),R21*0.91,IF(AND(R21/V21>=120%,R21/V21<125%),R21*0.88,IF(AND(R21/V21>=125%,R21/V21<130%),R21*0.85,IF(AND(R21/V21>=130%,R21/V21<135%),R21*0.82,IF(R21/V21>=135%,R21*0.8,))))))))))))))) -> 190222.4 | X21: =IF(N21=0,1,IF(N21<10000,N21*2.8,IF(AND(N21>=10000,N21<20000),N21*2.2,IF(AND(N21>=20000,N21<30000),N21*1.8,IF(AND(N21>=30000,N21<40000),N21*1.78,IF(AND(N21>=40000,N21<50000),N21*1.76,IF(AND(N21>=50000,N21<60000),N21*1.74,IF(AND(N21>=60000,N21<70000),N21*1.72,IF(AND(N21>=70000,N21<80000),N21*1.7,IF(AND(N21>=80000,N21<90000),N21*1.68,IF(AND(N21>=90000,N21<100000),N21*1.66,IF(AND(N21>=100000,N21<110000),N21*1.65,IF(AND(N21>=110000,N21<120000),N21*1.64,IF(AND(N21>=120000,N21<130000),N21*1.63,IF(AND(N21>=130000,N21<140000),N21*1.62,IF(AND(N21>=140000,N21<150000),N21*1.61,IF(AND(N21>=150000,N21<160000),N21*1.6,IF(AND(N21>=160000,N21<170000),N21*1.59,IF(AND(N21>=170000,N21<180000),N21*1.58,IF(AND(N21>=180000,N21<190000),N21*1.57,IF(AND(N21>=190000,N21<200000),N21*1.56,IF(AND(N21>=200000,N21<300000),N21*1.54,IF(AND(N21>=300000,N21<400000),N21*1.52,IF(AND(N21>=400000,N21<500000),N21*1.5,IF(AND(N21>=500000,N21<600000),N21*1.48,IF(AND(N21>=600000,N21<700000),N21*1.46,IF(AND(N21>=700000,N21<800000),N21*1.44,IF(AND(N21>=800000,N21<900000),N21*1.42,IF(AND(N21>=900000,N21<1000000),N21*1.4,IF(AND(N21>=1000000,N21<2000000),N21*1.39,IF(AND(N21>=2000000,N21<3000000),N21*1.38,IF(AND(N21>=3000000,N21<4000000),N21*1.37,IF(AND(N21>=4000000,N21<5000000),N21*1.36,IF(AND(N21>=5000000,N21<6000000),N21*1.35,IF(AND(N21>=6000000,N21<7000000),N21*1.34,IF(AND(N21>=7000000,N21<8000000),N21*1.33,IF(AND(N21>=8000000,N21<9000000),N21*1.32,IF(AND(N21>=9000000,N21<10000000),N21*1.31,IF(N21>=10000000,N21*1.3,""))))))))))))))))))))))))))))))))))))))) -> 194977.96 | Y21: =CEILING((R21+W21+X21)/3,1000) -> 192000 | Z21: 0 | AA21: =CEILING((Y21+Z21),1000) -> 192000 | AB21: =AA21-N21 -> 73111 | AC21: =AB21/AA21 -> 0.38078646 | AD21: 30 | AE21: =AD21/30 -> 1 | AF21: 10 | AG21: =AF21/30 -> 0.33333333 | AH21: 0.7 | AI21: =(AE21+AG21)*AH21 -> 0.93333333 | AJ21: =AI21*30 -> 28 | AK21: - | AL21: =K21 -> PRESTONE Brake Fluid DOT 4 - 1000ml | AM21: =_xlfn.XLOOKUP(AL21,ITEM!B:B,ITEM!AY:AY,0) -> 0 | AN21: =_xlfn.XLOOKUP(AL21,ITEM!B:B,ITEM!AZ:AZ,0) -> 0 | AO21: =_xlfn.XLOOKUP(AL21,ITEM!B:B,ITEM!BA:BA,0) -> 0 | AP21: =AN21/AO21 -> #DIV/0! | AQ21: 0 | AR21: 0 | AS21: 0 | AT21: =AN21*$AI21 -> 0 | AU21: =AN21*(AE21+AG21+AI21) -> 0 | AV21: =_xlfn.XLOOKUP(AL21,ITEM!B:B,ITEM!BN:BN,0) -> 0 | AW21: 0 | AX21: 0 | AY21: =AU21-AV21-AW21+AX21 -> 0 | AZ21: 0 | BA21: =AZ21/BC21 -> #DIV/0! | BB21: =H21 -> 0 | BC21: 0 | BD21: - | BE21: - | BF21: ★ | BG21: ★★ | BH21: =K21 -> PRESTONE Brake Fluid DOT 4 - 1000ml | BI21: =AM21 -> 0 | BJ21: =BZ21 -> 0 | BK21: =CK21 -> 0 | BL21: =CV21 -> 0 | BM21: =BJ21+BK21+BL21 -> 0 | BN21: =CC21 -> 0 | BO21: =CN21 -> 0 | BP21: =AY21 -> 0 | BQ21: - | BS21: =K21 -> PRESTONE Brake Fluid DOT 4 - 1000ml | BT21: =_xlfn.XLOOKUP(BS21,ITEM!B:B,ITEM!BB:BB,0) -> 0 | BU21: =_xlfn.XLOOKUP(BS21,ITEM!B:B,ITEM!BC:BC,0) -> 0 | BV21: =BT21/BU21 -> #DIV/0! | BW21: 0 | BX21: =BT21*$AI21 -> 0 | BY21: =BT21*($AE21+$AG21+$AI21) -> 0 | BZ21: =_xlfn.XLOOKUP(BS21,ITEM!B:B,ITEM!BK:BK,0) -> 0 | CA21: 0 | CB21: 0 | CC21: =BY21-BZ21-CA21+CB21 -> 0 | CD21: 0 | CE21: =_xlfn.XLOOKUP(BS21,ITEM!B:B,ITEM!BE:BE,0) -> 0 | CF21: =_xlfn.XLOOKUP(BS21,ITEM!B:B,ITEM!BF:BF,0) -> 0 | CG21: =CE21/CF21 -> #DIV/0! | CH21: 0 | CI21: =CE21*$AI21 -> 0 | CJ21: =CE21*($AE21+$AG21+$AI21) -> 0 | CK21: =_xlfn.XLOOKUP(BS21,ITEM!B:B,ITEM!BL:BL,0) -> 0 | CL21: 0 | CM21: 0 | CN21: =CJ21-CK21-CL21+CM21 -> 0 | CO21: 0 | CP21: =_xlfn.XLOOKUP(BS21,ITEM!B:B,ITEM!BH:BH,0) -> 0 | CQ21: =_xlfn.XLOOKUP(BS21,ITEM!B:B,ITEM!BI:BI,0) -> 0 | CR21: =CP21/CQ21 -> #DIV/0! | CS21: 0 | CT21: =CP21*$AI21 -> 0 | CU21: =CP21*($AE21+$AG21+$AI21) -> 0 | CV21: =_xlfn.XLOOKUP(BS21,ITEM!B:B,ITEM!BM:BM,0) -> 0 | CW21: 0 | CX21: 0 | CY21: =CU21-CV21-CW21+CX21 -> 0 | CZ21: 0 | DA21: =K21 -> PRESTONE Brake Fluid DOT 4 - 1000ml
A22: 19 | B22: 102340 | C22: PRESTONE | D22: Brake Fluid | E22: DOT 4 | F22: - | G22: 300ml | H22: 0 | I22: 0 | J22: =C22&" "&D22&" "&E22&" "&F22&" "&G22 -> PRESTONE Brake Fluid DOT 4 - 300ml | K22: PRESTONE Brake Fluid DOT 4 - 300ml | L22: 1 | M22: 桶 | N22: 118889 | O22: 0.4 | P22: 0.2 | Q22: =O22+P22 -> 0.6 | R22: =N22*(1+Q22) -> 190222.4 | S22: 0 | T22: 0 | U22: 0 | V22: =IF((S22+T22+U22)=0,R22,IF(AND(S22>0,T22=0,U22=0),S22,IF(AND(S22=0,T22>0,U22=0),T22,IF(AND(S22=0,T22=0,U22>0),U22,IF(AND(S22>0,T22>0,U22=0),(S22+T22)/2,IF(AND(S22>0,T22=0,U22>0),(S22+U22)/2,IF(AND(S22=0,T22>0,U22>0),(T22+U22)/2,IF(AND(S22>0,T22>0,U22>0),(S22+T22+U22)/3,)))))))) -> 190222.4 | W22: =IF(R22=V22,V22,IF(R22/V22<70%,R22*1.18,IF(AND(R22/V22>=70%,R22/V22<75%),R22*1.15,IF(AND(R22/V22>=75%,R22/V22<80%),R22*1.12,IF(AND(R22/V22>=80%,R22/V22<85%),R22*1.09,IF(AND(R22/V22>=85%,R22/V22<90%),R22*1.06,IF(AND(R22/V22>=90%,R22/V22<95%),R22*1.03,IF(AND(R22/V22>=95%,R22/V22<105%),V22,IF(AND(R22/V22>=105%,R22/V22<110%),R22*0.97,IF(AND(R22/V22>=110%,R22/V22<115%),R22*0.94,IF(AND(R22/V22>=115%,R22/V22<120%),R22*0.91,IF(AND(R22/V22>=120%,R22/V22<125%),R22*0.88,IF(AND(R22/V22>=125%,R22/V22<130%),R22*0.85,IF(AND(R22/V22>=130%,R22/V22<135%),R22*0.82,IF(R22/V22>=135%,R22*0.8,))))))))))))))) -> 190222.4 | X22: =IF(N22=0,1,IF(N22<10000,N22*2.8,IF(AND(N22>=10000,N22<20000),N22*2.2,IF(AND(N22>=20000,N22<30000),N22*1.8,IF(AND(N22>=30000,N22<40000),N22*1.78,IF(AND(N22>=40000,N22<50000),N22*1.76,IF(AND(N22>=50000,N22<60000),N22*1.74,IF(AND(N22>=60000,N22<70000),N22*1.72,IF(AND(N22>=70000,N22<80000),N22*1.7,IF(AND(N22>=80000,N22<90000),N22*1.68,IF(AND(N22>=90000,N22<100000),N22*1.66,IF(AND(N22>=100000,N22<110000),N22*1.65,IF(AND(N22>=110000,N22<120000),N22*1.64,IF(AND(N22>=120000,N22<130000),N22*1.63,IF(AND(N22>=130000,N22<140000),N22*1.62,IF(AND(N22>=140000,N22<150000),N22*1.61,IF(AND(N22>=150000,N22<160000),N22*1.6,IF(AND(N22>=160000,N22<170000),N22*1.59,IF(AND(N22>=170000,N22<180000),N22*1.58,IF(AND(N22>=180000,N22<190000),N22*1.57,IF(AND(N22>=190000,N22<200000),N22*1.56,IF(AND(N22>=200000,N22<300000),N22*1.54,IF(AND(N22>=300000,N22<400000),N22*1.52,IF(AND(N22>=400000,N22<500000),N22*1.5,IF(AND(N22>=500000,N22<600000),N22*1.48,IF(AND(N22>=600000,N22<700000),N22*1.46,IF(AND(N22>=700000,N22<800000),N22*1.44,IF(AND(N22>=800000,N22<900000),N22*1.42,IF(AND(N22>=900000,N22<1000000),N22*1.4,IF(AND(N22>=1000000,N22<2000000),N22*1.39,IF(AND(N22>=2000000,N22<3000000),N22*1.38,IF(AND(N22>=3000000,N22<4000000),N22*1.37,IF(AND(N22>=4000000,N22<5000000),N22*1.36,IF(AND(N22>=5000000,N22<6000000),N22*1.35,IF(AND(N22>=6000000,N22<7000000),N22*1.34,IF(AND(N22>=7000000,N22<8000000),N22*1.33,IF(AND(N22>=8000000,N22<9000000),N22*1.32,IF(AND(N22>=9000000,N22<10000000),N22*1.31,IF(N22>=10000000,N22*1.3,""))))))))))))))))))))))))))))))))))))))) -> 194977.96 | Y22: =CEILING((R22+W22+X22)/3,1000) -> 192000 | Z22: 0 | AA22: =CEILING((Y22+Z22),1000) -> 192000 | AB22: =AA22-N22 -> 73111 | AC22: =AB22/AA22 -> 0.38078646 | AD22: 30 | AE22: =AD22/30 -> 1 | AF22: 10 | AG22: =AF22/30 -> 0.33333333 | AH22: 0.7 | AI22: =(AE22+AG22)*AH22 -> 0.93333333 | AJ22: =AI22*30 -> 28 | AK22: - | AL22: =K22 -> PRESTONE Brake Fluid DOT 4 - 300ml | AM22: =_xlfn.XLOOKUP(AL22,ITEM!B:B,ITEM!AY:AY,0) -> 0 | AN22: =_xlfn.XLOOKUP(AL22,ITEM!B:B,ITEM!AZ:AZ,0) -> 0 | AO22: =_xlfn.XLOOKUP(AL22,ITEM!B:B,ITEM!BA:BA,0) -> 0 | AP22: =AN22/AO22 -> #DIV/0! | AQ22: 0 | AR22: 0 | AS22: 0 | AT22: =AN22*$AI22 -> 0 | AU22: =AN22*(AE22+AG22+AI22) -> 0 | AV22: =_xlfn.XLOOKUP(AL22,ITEM!B:B,ITEM!BN:BN,0) -> 0 | AW22: 0 | AX22: 0 | AY22: =AU22-AV22-AW22+AX22 -> 0 | AZ22: 0 | BA22: =AZ22/BC22 -> #DIV/0! | BB22: =H22 -> 0 | BC22: 0 | BD22: - | BE22: - | BF22: ★ | BG22: ★★ | BH22: =K22 -> PRESTONE Brake Fluid DOT 4 - 300ml | BI22: =AM22 -> 0 | BJ22: =BZ22 -> 0 | BK22: =CK22 -> 0 | BL22: =CV22 -> 0 | BM22: =BJ22+BK22+BL22 -> 0 | BN22: =CC22 -> 0 | BO22: =CN22 -> 0 | BP22: =AY22 -> 0 | BQ22: - | BS22: =K22 -> PRESTONE Brake Fluid DOT 4 - 300ml | BT22: =_xlfn.XLOOKUP(BS22,ITEM!B:B,ITEM!BB:BB,0) -> 0 | BU22: =_xlfn.XLOOKUP(BS22,ITEM!B:B,ITEM!BC:BC,0) -> 0 | BV22: =BT22/BU22 -> #DIV/0! | BW22: 0 | BX22: =BT22*$AI22 -> 0 | BY22: =BT22*($AE22+$AG22+$AI22) -> 0 | BZ22: =_xlfn.XLOOKUP(BS22,ITEM!B:B,ITEM!BK:BK,0) -> 0 | CA22: 0 | CB22: 0 | CC22: =BY22-BZ22-CA22+CB22 -> 0 | CD22: 0 | CE22: =_xlfn.XLOOKUP(BS22,ITEM!B:B,ITEM!BE:BE,0) -> 0 | CF22: =_xlfn.XLOOKUP(BS22,ITEM!B:B,ITEM!BF:BF,0) -> 0 | CG22: =CE22/CF22 -> #DIV/0! | CH22: 0 | CI22: =CE22*$AI22 -> 0 | CJ22: =CE22*($AE22+$AG22+$AI22) -> 0 | CK22: =_xlfn.XLOOKUP(BS22,ITEM!B:B,ITEM!BL:BL,0) -> 0 | CL22: 0 | CM22: 0 | CN22: =CJ22-CK22-CL22+CM22 -> 0 | CO22: 0 | CP22: =_xlfn.XLOOKUP(BS22,ITEM!B:B,ITEM!BH:BH,0) -> 0 | CQ22: =_xlfn.XLOOKUP(BS22,ITEM!B:B,ITEM!BI:BI,0) -> 0 | CR22: =CP22/CQ22 -> #DIV/0! | CS22: 0 | CT22: =CP22*$AI22 -> 0 | CU22: =CP22*($AE22+$AG22+$AI22) -> 0 | CV22: =_xlfn.XLOOKUP(BS22,ITEM!B:B,ITEM!BM:BM,0) -> 0 | CW22: 0 | CX22: 0 | CY22: =CU22-CV22-CW22+CX22 -> 0 | CZ22: 0 | DA22: =K22 -> PRESTONE Brake Fluid DOT 4 - 300ml

Sheet ITEM
A1: Item name | C1: Item name | D1: Item name | AY1: 汇总 | BB1: BCS-1-KLG | BE1: BCS-2 PIK 2 | BH1: BCS HO | BK1: 实际库存
A2: NO | B2: Item name | C2: March | F2: TOTAL 3 | G2: April | J2: TOTAL 4 | K2: May | N2: TOTAL 5 | O2: June | R2: TOTAL 6 | S2: July | V2: TOTAL 7 | W2: August | Z2: TOTAL 8 | AA2: September | AD2: TOTAL 9 | AE2: Oktober | AH2: TOTAL 10 | AI2: November | AL2: TOTAL 11 | AM2: December | AP2: TOTAL 12 | AQ2: 26-1 January | AT2: TOTAL 26-1 | AU2: 26-2 February | AX2: TOTAL 26-2 | AY2: Total | AZ2: Average 6 | BA2: Avergae 11 | BB2: Average 6 | BC2: Avergae 11 | BD2: stock KLG | BE2: Average 6 | BF2: Average 6 | BG2: stock PIK2 | BH2: Average 6 | BI2: Average 6 | BJ2: stock HO | BK2: stock | BN2: total stock
C3: BCS-1 KELAPA GADING--Central Warehouse | D3: BCS-2 PIK 2--Central Warehouse | E3: BCS-HEAD OFFICE--Central Warehouse | G3: BCS-1 KELAPA GADING--Central Warehouse | H3: BCS-2 PIK 2--Central Warehouse | I3: BCS-HEAD OFFICE--Central Warehouse | K3: BCS-1 KELAPA GADING--Central Warehouse | L3: BCS-2 PIK 2--Central Warehouse | M3: BCS-HEAD OFFICE--Central Warehouse | O3: BCS-1 KELAPA GADING--Central Warehouse | P3: BCS-2 PIK 2--Central Warehouse | Q3: BCS-HEAD OFFICE--Central Warehouse | S3: BCS-1 KELAPA GADING--Central Warehouse | T3: BCS-2 PIK 2--Central Warehouse | U3: BCS-HEAD OFFICE--Central Warehouse | W3: BCS-1 KELAPA GADING--Central Warehouse | X3: BCS-2 PIK 2--Central Warehouse | Y3: BCS-HEAD OFFICE--Central Warehouse | AA3: BCS-1 KELAPA GADING--Central Warehouse | AB3: BCS-2 PIK 2--Central Warehouse | AC3: BCS-HEAD OFFICE--Central Warehouse | AE3: BCS-1 KELAPA GADING--Central Warehouse | AF3: BCS-2 PIK 2--Central Warehouse | AG3: BCS-HEAD OFFICE--Central Warehouse | AI3: BCS-1 KELAPA GADING--Central Warehouse | AJ3: BCS-2 PIK 2--Central Warehouse | AK3: BCS HEAD OFFICE--Central Warehouse | AM3: BCS-1 KELAPA GADING--Central Warehouse | AN3: BCS-2 PIK 2--Central Warehouse | AO3: BCS HEAD OFFICE--Central Warehouse | AQ3: BCS-1 KELAPA GADING--Central Warehouse | AR3: BCS-2 PIK 2--Central Warehouse | AS3: BCS HEAD OFFICE--Central Warehouse | AU3: BCS-1 KELAPA GADING--Central Warehouse | AV3: BCS-2 PIK 2--Central Warehouse | AW3: BCS HEAD OFFICE--Central Warehouse | BK3: BCS-1-KLG | BL3: BCS-2 PIK 2 | BM3: BCS HO | BN3: Qty
A4: 1 | B4: MOBIL Transmission Oil CVTF Multi-Vehicle 1L | C4: {=_xlfn.XLOOKUP($B4&$C$3,'25-03'!B:B&'25-03'!C:C,'25-03'!D:D,0)} -> 0 | D4: {=_xlfn.XLOOKUP($B4&$D$3,'25-03'!B:B&'25-03'!C:C,'25-03'!D:D,0)} -> 0 | E4: {=_xlfn.XLOOKUP($B4&E$3,'25-03'!B:B&'25-03'!C:C,'25-03'!D:D,0)} -> 0 | F4: =SUM(C4:E4) -> 0 | G4: {=_xlfn.XLOOKUP($B4&G$3,'25-04'!B:B&'25-04'!C:C,'25-04'!D:D,0)} -> 0 | H4: {=_xlfn.XLOOKUP($B4&H$3,'25-04'!B:B&'25-04'!C:C,'25-04'!D:D,0)} -> 0 | I4: {=_xlfn.XLOOKUP($B4&I$3,'25-04'!B:B&'25-04'!C:C,'25-04'!D:D,0)} -> 0 | J4: =SUM(G4:I4) -> 0 | K4: {=_xlfn.XLOOKUP($B4&K$3,'25-05'!B:B&'25-05'!C:C,'25-05'!D:D,0)} -> 0 | L4: {=_xlfn.XLOOKUP($B4&L$3,'25-05'!B:B&'25-05'!C:C,'25-05'!D:D,0)} -> 0 | M4: {=_xlfn.XLOOKUP($B4&M$3,'25-05'!B:B&'25-05'!C:C,'25-05'!D:D,0)} -> 0 | N4: =SUM(K4:M4) -> 0 | O4: {=_xlfn.XLOOKUP($B4&O$3,'26-06'!B:B&'26-06'!C:C,'26-06'!D:D,0)} -> 0 | P4: {=_xlfn.XLOOKUP($B4&P$3,'26-06'!B:B&'26-06'!C:C,'26-06'!D:D,0)} -> 0 | Q4: {=_xlfn.XLOOKUP($B4&Q$3,'26-06'!B:B&'26-06'!C:C,'26-06'!D:D,0)} -> 0 | R4: =SUM(O4:Q4) -> 0 | S4: {=_xlfn.XLOOKUP($B4&S$3,'25-07'!B:B&'25-07'!C:C,'25-07'!D:D,0)} -> 0 | T4: {=_xlfn.XLOOKUP($B4&T$3,'25-07'!B:B&'25-07'!C:C,'25-07'!D:D,0)} -> 0 | U4: {=_xlfn.XLOOKUP($B4&U$3,'25-07'!B:B&'25-07'!C:C,'25-07'!D:D,0)} -> 0 | V4: =SUM(S4:U4) -> 0 | W4: {=_xlfn.XLOOKUP($B4&W$3,'25-08'!B:B&'25-08'!C:C,'25-08'!D:D,0)} -> 0 | X4: {=_xlfn.XLOOKUP($B4&X$3,'25-08'!B:B&'25-08'!C:C,'25-08'!D:D,0)} -> 0 | Y4: {=_xlfn.XLOOKUP($B4&Y$3,'25-08'!B:B&'25-08'!C:C,'25-08'!D:D,0)} -> 0 | Z4: =SUM(W4:Y4) -> 0 | AA4: {=_xlfn.XLOOKUP($B4&AA$3,'25-09'!B:B&'25-09'!C:C,'25-09'!D:D,0)} -> 13 | AB4: {=_xlfn.XLOOKUP($B4&AB$3,'25-09'!B:B&'25-09'!C:C,'25-09'!D:D,0)} -> 0 | AC4: {=_xlfn.XLOOKUP($B4&AC$3,'25-09'!B:B&'25-09'!C:C,'25-09'!D:D,0)} -> 0 | AD4: =SUM(AA4:AC4) -> 13 | AE4: {=_xlfn.XLOOKUP($B4&AE$3,'25-10'!B:B&'25-10'!C:C,'25-10'!D:D,0)} -> 20 | AF4: {=_xlfn.XLOOKUP($B4&AF$3,'25-10'!B:B&'25-10'!C:C,'25-10'!D:D,0)} -> 8 | AG4: {=_xlfn.XLOOKUP($B4&AG$3,'25-10'!B:B&'25-10'!C:C,'25-10'!D:D,0)} -> 0 | AH4: =SUM(AE4:AG4) -> 28 | AI4: {=_xlfn.XLOOKUP($B4&AI$3,'25-11'!B:B&'25-11'!C:C,'25-11'!D:D,0)} -> 28 | AJ4: {=_xlfn.XLOOKUP($B4&AJ$3,'25-11'!B:B&'25-11'!C:C,'25-11'!D:D,0)} -> 18 | AK4: {=_xlfn.XLOOKUP($B4&AK$3,'25-11'!B:B&'25-11'!C:C,'25-11'!D:D,0)} -> 0 | AL4: =SUM(AI4:AK4) -> 46 | AM4: {=_xlfn.XLOOKUP($B4&AM$3,'25-12'!B:B&'25-12'!C:C,'25-12'!D:D,0)} -> 6 | AN4: {=_xlfn.XLOOKUP($B4&AN$3,'25-12'!B:B&'25-12'!C:C,'25-12'!D:D,0)} -> 57 | AO4: {=_xlfn.XLOOKUP($B4&AO$3,'25-12'!B:B&'25-12'!C:C,'25-12'!D:D,0)} -> 0 | AP4: =SUM(AM4:AO4) -> 63 | AQ4: {=_xlfn.XLOOKUP($B4&AQ$3,'26-01'!B:B&'26-01'!C:C,'26-01'!D:D,0)} -> 6 | AR4: {=_xlfn.XLOOKUP($B4&AR$3,'26-01'!B:B&'26-01'!C:C,'26-01'!D:D,0)} -> 43 | AS4: {=_xlfn.XLOOKUP($B4&AS$3,'26-01'!B:B&'26-01'!C:C,'26-01'!D:D,0)} -> 3 | AT4: =SUM(AQ4:AS4) -> 52 | AU4: {=_xlfn.XLOOKUP($B4&AU$3,'26-02'!B:B&'26-02'!C:C,'26-02'!D:D,0)} -> 47 | AV4: {=_xlfn.XLOOKUP($B4&AV$3,'26-02'!B:B&'26-02'!C:C,'26-02'!D:D,0)} -> 39 | AW4: {=_xlfn.XLOOKUP($B4&AW$3,'26-02'!B:B&'26-02'!C:C,'26-02'!D:D,0)} -> 0 | AX4: =SUM(AU4:AW4) -> 86 | AY4: =SUM(AX4,AT4,AP4,AL4,AH4,AD4,Z4,V4,R4,N4,J4,F4) -> 288 | AZ4: =AVERAGE(AX4,AT4,AP4,AL4,AH4,AD4) -> 48 | BA4: =AVERAGE(AX4,AT4,AP4,AL4,AH4,AD4,Z4,V4,R4,N4,J4) -> 26.181818 | BB4: =AVERAGE(AU4,AQ4,AM4,AI4,AE4,AA4) -> 20 | BC4: =AVERAGE(AU4,AQ4,AM4,AI4,AE4,AA4,W4,S4,O4,K4,G4) -> 10.909091 | BD4: =BK4 -> 4 | BE4: =AVERAGE(AV4,AR4,AN4,AJ4,AF4,AB4) -> 27.5 | BF4: =AVERAGE(AV4,AR4,AN4,AJ4,AF4,AB4) -> 27.5 | BG4: =BL4 -> 14 | BH4: =AVERAGE(AW4,AS4,AO4,AK4,AG4,AC4) -> 0.5 | BI4: =AVERAGE(AW4,AS4,AO4,AK4,AG4,AC4) -> 0.5 | BJ4: =BM4 -> 48 | BK4: =_xlfn.XLOOKUP($B4,'BCS-1-KLG'!C:C,'BCS-1-KLG'!E:E,0) -> 4 | BL4: =_xlfn.XLOOKUP($B4,'BCS-2 PIK 2'!C:C,'BCS-2 PIK 2'!E:E,0) -> 14 | BM4: =_xlfn.XLOOKUP($B4,'BCS HO'!C:C,'BCS HO'!E:E,0) -> 48 | BN4: =SUM(BK4:BM4) -> 66
A5: 2 | B5: MOBIL Transmission Oil Dexron-VI ATF 1L | C5: {=_xlfn.XLOOKUP($B5&$C$3,'25-03'!B:B&'25-03'!C:C,'25-03'!D:D,0)} -> 11 | D5: {=_xlfn.XLOOKUP($B5&$D$3,'25-03'!B:B&'25-03'!C:C,'25-03'!D:D,0)} -> 0 | E5: {=_xlfn.XLOOKUP($B5&E$3,'25-03'!B:B&'25-03'!C:C,'25-03'!D:D,0)} -> 0 | F5: =SUM(C5:E5) -> 11 | G5: {=_xlfn.XLOOKUP($B5&G$3,'25-04'!B:B&'25-04'!C:C,'25-04'!D:D,0)} -> 4 | H5: {=_xlfn.XLOOKUP($B5&H$3,'25-04'!B:B&'25-04'!C:C,'25-04'!D:D,0)} -> 0 | I5: {=_xlfn.XLOOKUP($B5&I$3,'25-04'!B:B&'25-04'!C:C,'25-04'!D:D,0)} -> 0 | J5: =SUM(G5:I5) -> 4 | K5: {=_xlfn.XLOOKUP($B5&K$3,'25-05'!B:B&'25-05'!C:C,'25-05'!D:D,0)} -> 36 | L5: {=_xlfn.XLOOKUP($B5&L$3,'25-05'!B:B&'25-05'!C:C,'25-05'!D:D,0)} -> 0 | M5: {=_xlfn.XLOOKUP($B5&M$3,'25-05'!B:B&'25-05'!C:C,'25-05'!D:D,0)} -> 0 | N5: =SUM(K5:M5) -> 36 | O5: {=_xlfn.XLOOKUP($B5&O$3,'26-06'!B:B&'26-06'!C:C,'26-06'!D:D,0)} -> 13 | P5: {=_xlfn.XLOOKUP($B5&P$3,'26-06'!B:B&'26-06'!C:C,'26-06'!D:D,0)} -> 0 | Q5: {=_xlfn.XLOOKUP($B5&Q$3,'26-06'!B:B&'26-06'!C:C,'26-06'!D:D,0)} -> 0 | R5: =SUM(O5:Q5) -> 13 | S5: {=_xlfn.XLOOKUP($B5&S$3,'25-07'!B:B&'25-07'!C:C,'25-07'!D:D,0)} -> 0 | T5: {=_xlfn.XLOOKUP($B5&T$3,'25-07'!B:B&'25-07'!C:C,'25-07'!D:D,0)} -> 0 | U5: {=_xlfn.XLOOKUP($B5&U$3,'25-07'!B:B&'25-07'!C:C,'25-07'!D:D,0)} -> 0 | V5: =SUM(S5:U5) -> 0 | W5: {=_xlfn.XLOOKUP($B5&W$3,'25-08'!B:B&'25-08'!C:C,'25-08'!D:D,0)} -> 79 | X5: {=_xlfn.XLOOKUP($B5&X$3,'25-08'!B:B&'25-08'!C:C,'25-08'!D:D,0)} -> 0 | Y5: {=_xlfn.XLOOKUP($B5&Y$3,'25-08'!B:B&'25-08'!C:C,'25-08'!D:D,0)} -> 0 | Z5: =SUM(W5:Y5) -> 79 | AA5: {=_xlfn.XLOOKUP($B5&AA$3,'25-09'!B:B&'25-09'!C:C,'25-09'!D:D,0)} -> 59 | AB5: {=_xlfn.XLOOKUP($B5&AB$3,'25-09'!B:B&'25-09'!C:C,'25-09'!D:D,0)} -> 57 | AC5: {=_xlfn.XLOOKUP($B5&AC$3,'25-09'!B:B&'25-09'!C:C,'25-09'!D:D,0)} -> 0 | AD5: =SUM(AA5:AC5) -> 116 | AE5: {=_xlfn.XLOOKUP($B5&AE$3,'25-10'!B:B&'25-10'!C:C,'25-10'!D:D,0)} -> 19 | AF5: {=_xlfn.XLOOKUP($B5&AF$3,'25-10'!B:B&'25-10'!C:C,'25-10'!D:D,0)} -> 39 | AG5: {=_xlfn.XLOOKUP($B5&AG$3,'25-10'!B:B&'25-10'!C:C,'25-10'!D:D,0)} -> 0 | AH5: =SUM(AE5:AG5) -> 58 | AI5: {=_xlfn.XLOOKUP($B5&AI$3,'25-11'!B:B&'25-11'!C:C,'25-11'!D:D,0)} -> 17 | AJ5: {=_xlfn.XLOOKUP($B5&AJ$3,'25-11'!B:B&'25-11'!C:C,'25-11'!D:D,0)} -> 66 | AK5: {=_xlfn.XLOOKUP($B5&AK$3,'25-11'!B:B&'25-11'!C:C,'25-11'!D:D,0)} -> 0 | AL5: =SUM(AI5:AK5) -> 83 | AM5: {=_xlfn.XLOOKUP($B5&AM$3,'25-12'!B:B&'25-12'!C:C,'25-12'!D:D,0)} -> 39 | AN5: {=_xlfn.XLOOKUP($B5&AN$3,'25-12'!B:B&'25-12'!C:C,'25-12'!D:D,0)} -> 102 | AO5: {=_xlfn.XLOOKUP($B5&AO$3,'25-12'!B:B&'25-12'!C:C,'25-12'!D:D,0)} -> 0 | AP5: =SUM(AM5:AO5) -> 141 | AQ5: {=_xlfn.XLOOKUP($B5&AQ$3,'26-01'!B:B&'26-01'!C:C,'26-01'!D:D,0)} -> 45 | AR5: {=_xlfn.XLOOKUP($B5&AR$3,'26-01'!B:B&'26-01'!C:C,'26-01'!D:D,0)} -> 72 | AS5: {=_xlfn.XLOOKUP($B5&AS$3,'26-01'!B:B&'26-01'!C:C,'26-01'!D:D,0)} -> 0 | AT5: =SUM(AQ5:AS5) -> 117 | AU5: {=_xlfn.XLOOKUP($B5&AU$3,'26-02'!B:B&'26-02'!C:C,'26-02'!D:D,0)} -> 44 | AV5: {=_xlfn.XLOOKUP($B5&AV$3,'26-02'!B:B&'26-02'!C:C,'26-02'!D:D,0)} -> 62 | AW5: {=_xlfn.XLOOKUP($B5&AW$3,'26-02'!B:B&'26-02'!C:C,'26-02'!D:D,0)} -> 0 | AX5: =SUM(AU5:AW5) -> 106 | AY5: =SUM(AX5,AT5,AP5,AL5,AH5,AD5,Z5,V5,R5,N5,J5,F5) -> 764 | AZ5: =AVERAGE(AX5,AT5,AP5,AL5,AH5,AD5) -> 103.5 | BA5: =AVERAGE(AX5,AT5,AP5,AL5,AH5,AD5,Z5,V5,R5,N5,J5) -> 68.454545 | BB5: =AVERAGE(AU5,AQ5,AM5,AI5,AE5,AA5) -> 37.166667 | BC5: =AVERAGE(AU5,AQ5,AM5,AI5,AE5,AA5,W5,S5,O5,K5,G5) -> 32.272727 | BD5: =BK5 -> 8 | BE5: =AVERAGE(AV5,AR5,AN5,AJ5,AF5,AB5) -> 66.333333 | BF5: =AVERAGE(AV5,AR5,AN5,AJ5,AF5,AB5) -> 66.333333 | BG5: =BL5 -> 112 | BH5: =AVERAGE(AW5,AS5,AO5,AK5,AG5,AC5) -> 0 | BI5: =AVERAGE(AW5,AS5,AO5,AK5,AG5,AC5) -> 0 | BJ5: =BM5 -> 60 | BK5: =_xlfn.XLOOKUP($B5,'BCS-1-KLG'!C:C,'BCS-1-KLG'!E:E,0) -> 8 | BL5: =_xlfn.XLOOKUP($B5,'BCS-2 PIK 2'!C:C,'BCS-2 PIK 2'!E:E,0) -> 112 | BM5: =_xlfn.XLOOKUP($B5,'BCS HO'!C:C,'BCS HO'!E:E,0) -> 60 | BN5: =SUM(BK5:BM5) -> 180
A6: 3 | B6: MOBIL Gear Oil Mobilube-HD 80W-90 1L | C6: {=_xlfn.XLOOKUP($B6&$C$3,'25-03'!B:B&'25-03'!C:C,'25-03'!D:D,0)} -> 3 | D6: {=_xlfn.XLOOKUP($B6&$D$3,'25-03'!B:B&'25-03'!C:C,'25-03'!D:D,0)} -> 0 | E6: {=_xlfn.XLOOKUP($B6&E$3,'25-03'!B:B&'25-03'!C:C,'25-03'!D:D,0)} -> 0 | F6: =SUM(C6:E6) -> 3 | G6: {=_xlfn.XLOOKUP($B6&G$3,'25-04'!B:B&'25-04'!C:C,'25-04'!D:D,0)} -> 0 | H6: {=_xlfn.XLOOKUP($B6&H$3,'25-04'!B:B&'25-04'!C:C,'25-04'!D:D,0)} -> 0 | I6: {=_xlfn.XLOOKUP($B6&I$3,'25-04'!B:B&'25-04'!C:C,'25-04'!D:D,0)} -> 0 | J6: =SUM(G6:I6) -> 0 | K6: {=_xlfn.XLOOKUP($B6&K$3,'25-05'!B:B&'25-05'!C:C,'25-05'!D:D,0)} -> 24 | L6: {=_xlfn.XLOOKUP($B6&L$3,'25-05'!B:B&'25-05'!C:C,'25-05'!D:D,0)} -> 0 | M6: {=_xlfn.XLOOKUP($B6&M$3,'25-05'!B:B&'25-05'!C:C,'25-05'!D:D,0)} -> 0 | N6: =SUM(K6:M6) -> 24 | O6: {=_xlfn.XLOOKUP($B6&O$3,'26-06'!B:B&'26-06'!C:C,'26-06'!D:D,0)} -> 14 | P6: {=_xlfn.XLOOKUP($B6&P$3,'26-06'!B:B&'26-06'!C:C,'26-06'!D:D,0)} -> 0 | Q6: {=_xlfn.XLOOKUP($B6&Q$3,'26-06'!B:B&'26-06'!C:C,'26-06'!D:D,0)} -> 0 | R6: =SUM(O6:Q6) -> 14 | S6: {=_xlfn.XLOOKUP($B6&S$3,'25-07'!B:B&'25-07'!C:C,'25-07'!D:D,0)} -> 65 | T6: {=_xlfn.XLOOKUP($B6&T$3,'25-07'!B:B&'25-07'!C:C,'25-07'!D:D,0)} -> 0 | U6: {=_xlfn.XLOOKUP($B6&U$3,'25-07'!B:B&'25-07'!C:C,'25-07'!D:D,0)} -> 0 | V6: =SUM(S6:U6) -> 65 | W6: {=_xlfn.XLOOKUP($B6&W$3,'25-08'!B:B&'25-08'!C:C,'25-08'!D:D,0)} -> 108 | X6: {=_xlfn.XLOOKUP($B6&X$3,'25-08'!B:B&'25-08'!C:C,'25-08'!D:D,0)} -> 0 | Y6: {=_xlfn.XLOOKUP($B6&Y$3,'25-08'!B:B&'25-08'!C:C,'25-08'!D:D,0)} -> 0 | Z6: =SUM(W6:Y6) -> 108 | AA6: {=_xlfn.XLOOKUP($B6&AA$3,'25-09'!B:B&'25-09'!C:C,'25-09'!D:D,0)} -> 52 | AB6: {=_xlfn.XLOOKUP($B6&AB$3,'25-09'!B:B&'25-09'!C:C,'25-09'!D:D,0)} -> 0 | AC6: {=_xlfn.XLOOKUP($B6&AC$3,'25-09'!B:B&'25-09'!C:C,'25-09'!D:D,0)} -> 0 | AD6: =SUM(AA6:AC6) -> 52 | AE6: {=_xlfn.XLOOKUP($B6&AE$3,'25-10'!B:B&'25-10'!C:C,'25-10'!D:D,0)} -> 18 | AF6: {=_xlfn.XLOOKUP($B6&AF$3,'25-10'!B:B&'25-10'!C:C,'25-10'!D:D,0)} -> 0 | AG6: {=_xlfn.XLOOKUP($B6&AG$3,'25-10'!B:B&'25-10'!C:C,'25-10'!D:D,0)} -> 0 | AH6: =SUM(AE6:AG6) -> 18 | AI6: {=_xlfn.XLOOKUP($B6&AI$3,'25-11'!B:B&'25-11'!C:C,'25-11'!D:D,0)} -> 4 | AJ6: {=_xlfn.XLOOKUP($B6&AJ$3,'25-11'!B:B&'25-11'!C:C,'25-11'!D:D,0)} -> 0 | AK6: {=_xlfn.XLOOKUP($B6&AK$3,'25-11'!B:B&'25-11'!C:C,'25-11'!D:D,0)} -> 0 | AL6: =SUM(AI6:AK6) -> 4 | AM6: {=_xlfn.XLOOKUP($B6&AM$3,'25-12'!B:B&'25-12'!C:C,'25-12'!D:D,0)} -> 6 | AN6: {=_xlfn.XLOOKUP($B6&AN$3,'25-12'!B:B&'25-12'!C:C,'25-12'!D:D,0)} -> 0 | AO6: {=_xlfn.XLOOKUP($B6&AO$3,'25-12'!B:B&'25-12'!C:C,'25-12'!D:D,0)} -> 0 | AP6: =SUM(AM6:AO6) -> 6 | AQ6: {=_xlfn.XLOOKUP($B6&AQ$3,'26-01'!B:B&'26-01'!C:C,'26-01'!D:D,0)} -> 0 | AR6: {=_xlfn.XLOOKUP($B6&AR$3,'26-01'!B:B&'26-01'!C:C,'26-01'!D:D,0)} -> 8 | AS6: {=_xlfn.XLOOKUP($B6&AS$3,'26-01'!B:B&'26-01'!C:C,'26-01'!D:D,0)} -> 0 | AT6: =SUM(AQ6:AS6) -> 8 | AU6: {=_xlfn.XLOOKUP($B6&AU$3,'26-02'!B:B&'26-02'!C:C,'26-02'!D:D,0)} -> 11 | AV6: {=_xlfn.XLOOKUP($B6&AV$3,'26-02'!B:B&'26-02'!C:C,'26-02'!D:D,0)} -> 11 | AW6: {=_xlfn.XLOOKUP($B6&AW$3,'26-02'!B:B&'26-02'!C:C,'26-02'!D:D,0)} -> 0 | AX6: =SUM(AU6:AW6) -> 22 | AY6: =SUM(AX6,AT6,AP6,AL6,AH6,AD6,Z6,V6,R6,N6,J6,F6) -> 324 | AZ6: =AVERAGE(AX6,AT6,AP6,AL6,AH6,AD6) -> 18.333333 | BA6: =AVERAGE(AX6,AT6,AP6,AL6,AH6,AD6,Z6,V6,R6,N6,J6) -> 29.181818 | BB6: =AVERAGE(AU6,AQ6,AM6,AI6,AE6,AA6) -> 15.166667 | BC6: =AVERAGE(AU6,AQ6,AM6,AI6,AE6,AA6,W6,S6,O6,K6,G6) -> 27.454545 | BD6: =BK6 -> 25 | BE6: =AVERAGE(AV6,AR6,AN6,AJ6,AF6,AB6) -> 3.1666667 | BF6: =AVERAGE(AV6,AR6,AN6,AJ6,AF6,AB6) -> 3.1666667 | BG6: =BL6 -> 17 | BH6: =AVERAGE(AW6,AS6,AO6,AK6,AG6,AC6) -> 0 | BI6: =AVERAGE(AW6,AS6,AO6,AK6,AG6,AC6) -> 0 | BJ6: =BM6 -> 36 | BK6: =_xlfn.XLOOKUP($B6,'BCS-1-KLG'!C:C,'BCS-1-KLG'!E:E,0) -> 25 | BL6: =_xlfn.XLOOKUP($B6,'BCS-2 PIK 2'!C:C,'BCS-2 PIK 2'!E:E,0) -> 17 | BM6: =_xlfn.XLOOKUP($B6,'BCS HO'!C:C,'BCS HO'!E:E,0) -> 36 | BN6: =SUM(BK6:BM6) -> 78
A7: 4 | B7: MOTUL Transmission Oil ATF VI 1L | C7: {=_xlfn.XLOOKUP($B7&$C$3,'25-03'!B:B&'25-03'!C:C,'25-03'!D:D,0)} -> 0 | D7: {=_xlfn.XLOOKUP($B7&$D$3,'25-03'!B:B&'25-03'!C:C,'25-03'!D:D,0)} -> 0 | E7: {=_xlfn.XLOOKUP($B7&E$3,'25-03'!B:B&'25-03'!C:C,'25-03'!D:D,0)} -> 0 | F7: =SUM(C7:E7) -> 0 | G7: {=_xlfn.XLOOKUP($B7&G$3,'25-04'!B:B&'25-04'!C:C,'25-04'!D:D,0)} -> 0 | H7: {=_xlfn.XLOOKUP($B7&H$3,'25-04'!B:B&'25-04'!C:C,'25-04'!D:D,0)} -> 0 | I7: {=_xlfn.XLOOKUP($B7&I$3,'25-04'!B:B&'25-04'!C:C,'25-04'!D:D,0)} -> 0 | J7: =SUM(G7:I7) -> 0 | K7: {=_xlfn.XLOOKUP($B7&K$3,'25-05'!B:B&'25-05'!C:C,'25-05'!D:D,0)} -> 0 | L7: {=_xlfn.XLOOKUP($B7&L$3,'25-05'!B:B&'25-05'!C:C,'25-05'!D:D,0)} -> 0 | M7: {=_xlfn.XLOOKUP($B7&M$3,'25-05'!B:B&'25-05'!C:C,'25-05'!D:D,0)} -> 0 | N7: =SUM(K7:M7) -> 0 | O7: {=_xlfn.XLOOKUP($B7&O$3,'26-06'!B:B&'26-06'!C:C,'26-06'!D:D,0)} -> 13 | P7: {=_xlfn.XLOOKUP($B7&P$3,'26-06'!B:B&'26-06'!C:C,'26-06'!D:D,0)} -> 0 | Q7: {=_xlfn.XLOOKUP($B7&Q$3,'26-06'!B:B&'26-06'!C:C,'26-06'!D:D,0)} -> 0 | R7: =SUM(O7:Q7) -> 13 | S7: {=_xlfn.XLOOKUP($B7&S$3,'25-07'!B:B&'25-07'!C:C,'25-07'!D:D,0)} -> 24 | T7: {=_xlfn.XLOOKUP($B7&T$3,'25-07'!B:B&'25-07'!C:C,'25-07'!D:D,0)} -> 0 | U7: {=_xlfn.XLOOKUP($B7&U$3,'25-07'!B:B&'25-07'!C:C,'25-07'!D:D,0)} -> 0 | V7: =SUM(S7:U7) -> 24 | W7: {=_xlfn.XLOOKUP($B7&W$3,'25-08'!B:B&'25-08'!C:C,'25-08'!D:D,0)} -> 8 | X7: {=_xlfn.XLOOKUP($B7&X$3,'25-08'!B:B&'25-08'!C:C,'25-08'!D:D,0)} -> 0 | Y7: {=_xlfn.XLOOKUP($B7&Y$3,'25-08'!B:B&'25-08'!C:C,'25-08'!D:D,0)} -> 0 | Z7: =SUM(W7:Y7) -> 8 | AA7: {=_xlfn.XLOOKUP($B7&AA$3,'25-09'!B:B&'25-09'!C:C,'25-09'!D:D,0)} -> 4 | AB7: {=_xlfn.XLOOKUP($B7&AB$3,'25-09'!B:B&'25-09'!C:C,'25-09'!D:D,0)} -> 0 | AC7: {=_xlfn.XLOOKUP($B7&AC$3,'25-09'!B:B&'25-09'!C:C,'25-09'!D:D,0)} -> 0 | AD7: =SUM(AA7:AC7) -> 4 | AE7: {=_xlfn.XLOOKUP($B7&AE$3,'25-10'!B:B&'25-10'!C:C,'25-10'!D:D,0)} -> 1 | AF7: {=_xlfn.XLOOKUP($B7&AF$3,'25-10'!B:B&'25-10'!C:C,'25-10'!D:D,0)} -> 0 | AG7: {=_xlfn.XLOOKUP($B7&AG$3,'25-10'!B:B&'25-10'!C:C,'25-10'!D:D,0)} -> 0 | AH7: =SUM(AE7:AG7) -> 1 | AI7: {=_xlfn.XLOOKUP($B7&AI$3,'25-11'!B:B&'25-11'!C:C,'25-11'!D:D,0)} -> 0 | AJ7: {=_xlfn.XLOOKUP($B7&AJ$3,'25-11'!B:B&'25-11'!C:C,'25-11'!D:D,0)} -> 0 | AK7: {=_xlfn.XLOOKUP($B7&AK$3,'25-11'!B:B&'25-11'!C:C,'25-11'!D:D,0)} -> 0 | AL7: =SUM(AI7:AK7) -> 0 | AM7: {=_xlfn.XLOOKUP($B7&AM$3,'25-12'!B:B&'25-12'!C:C,'25-12'!D:D,0)} -> 0 | AN7: {=_xlfn.XLOOKUP($B7&AN$3,'25-12'!B:B&'25-12'!C:C,'25-12'!D:D,0)} -> 0 | AO7: {=_xlfn.XLOOKUP($B7&AO$3,'25-12'!B:B&'25-12'!C:C,'25-12'!D:D,0)} -> 0 | AP7: =SUM(AM7:AO7) -> 0 | AQ7: {=_xlfn.XLOOKUP($B7&AQ$3,'26-01'!B:B&'26-01'!C:C,'26-01'!D:D,0)} -> 0 | AR7: {=_xlfn.XLOOKUP($B7&AR$3,'26-01'!B:B&'26-01'!C:C,'26-01'!D:D,0)} -> 12 | AS7: {=_xlfn.XLOOKUP($B7&AS$3,'26-01'!B:B&'26-01'!C:C,'26-01'!D:D,0)} -> 0 | AT7: =SUM(AQ7:AS7) -> 12 | AU7: {=_xlfn.XLOOKUP($B7&AU$3,'26-02'!B:B&'26-02'!C:C,'26-02'!D:D,0)} -> 0 | AV7: {=_xlfn.XLOOKUP($B7&AV$3,'26-02'!B:B&'26-02'!C:C,'26-02'!D:D,0)} -> 12 | AW7: {=_xlfn.XLOOKUP($B7&AW$3,'26-02'!B:B&'26-02'!C:C,'26-02'!D:D,0)} -> 0 | AX7: =SUM(AU7:AW7) -> 12 | AY7: =SUM(AX7,AT7,AP7,AL7,AH7,AD7,Z7,V7,R7,N7,J7,F7) -> 74 | AZ7: =AVERAGE(AX7,AT7,AP7,AL7,AH7,AD7) -> 4.8333333 | BA7: =AVERAGE(AX7,AT7,AP7,AL7,AH7,AD7,Z7,V7,R7,N7,J7) -> 6.7272727 | BB7: =AVERAGE(AU7,AQ7,AM7,AI7,AE7,AA7) -> 0.83333333 | BC7: =AVERAGE(AU7,AQ7,AM7,AI7,AE7,AA7,W7,S7,O7,K7,G7) -> 4.5454545 | BD7: =BK7 -> 20 | BE7: =AVERAGE(AV7,AR7,AN7,AJ7,AF7,AB7) -> 4 | BF7: =AVERAGE(AV7,AR7,AN7,AJ7,AF7,AB7) -> 4 | BG7: =BL7 -> 36 | BH7: =AVERAGE(AW7,AS7,AO7,AK7,AG7,AC7) -> 0 | BI7: =AVERAGE(AW7,AS7,AO7,AK7,AG7,AC7) -> 0 | BJ7: =BM7 -> 1 | BK7: =_xlfn.XLOOKUP($B7,'BCS-1-KLG'!C:C,'BCS-1-KLG'!E:E,0) -> 20 | BL7: =_xlfn.XLOOKUP($B7,'BCS-2 PIK 2'!C:C,'BCS-2 PIK 2'!E:E,0) -> 36 | BM7: =_xlfn.XLOOKUP($B7,'BCS HO'!C:C,'BCS HO'!E:E,0) -> 1 | BN7: =SUM(BK7:BM7) -> 57
A8: 5 | B8: MOTUL Transmission Oil Multi CVTF 1L | C8: {=_xlfn.XLOOKUP($B8&$C$3,'25-03'!B:B&'25-03'!C:C,'25-03'!D:D,0)} -> 4 | D8: {=_xlfn.XLOOKUP($B8&$D$3,'25-03'!B:B&'25-03'!C:C,'25-03'!D:D,0)} -> 0 | E8: {=_xlfn.XLOOKUP($B8&E$3,'25-03'!B:B&'25-03'!C:C,'25-03'!D:D,0)} -> 0 | F8: =SUM(C8:E8) -> 4 | G8: {=_xlfn.XLOOKUP($B8&G$3,'25-04'!B:B&'25-04'!C:C,'25-04'!D:D,0)} -> 0 | H8: {=_xlfn.XLOOKUP($B8&H$3,'25-04'!B:B&'25-04'!C:C,'25-04'!D:D,0)} -> 0 | I8: {=_xlfn.XLOOKUP($B8&I$3,'25-04'!B:B&'25-04'!C:C,'25-04'!D:D,0)} -> 0 | J8: =SUM(G8:I8) -> 0 | K8: {=_xlfn.XLOOKUP($B8&K$3,'25-05'!B:B&'25-05'!C:C,'25-05'!D:D,0)} -> 32 | L8: {=_xlfn.XLOOKUP($B8&L$3,'25-05'!B:B&'25-05'!C:C,'25-05'!D:D,0)} -> 0 | M8: {=_xlfn.XLOOKUP($B8&M$3,'25-05'!B:B&'25-05'!C:C,'25-05'!D:D,0)} -> 0 | N8: =SUM(K8:M8) -> 32 | O8: {=_xlfn.XLOOKUP($B8&O$3,'26-06'!B:B&'26-06'!C:C,'26-06'!D:D,0)} -> 20 | P8: {=_xlfn.XLOOKUP($B8&P$3,'26-06'!B:B&'26-06'!C:C,'26-06'!D:D,0)} -> 0 | Q8: {=_xlfn.XLOOKUP($B8&Q$3,'26-06'!B:B&'26-06'!C:C,'26-06'!D:D,0)} -> 0 | R8: =SUM(O8:Q8) -> 20 | S8: {=_xlfn.XLOOKUP($B8&S$3,'25-07'!B:B&'25-07'!C:C,'25-07'!D:D,0)} -> 36 | T8: {=_xlfn.XLOOKUP($B8&T$3,'25-07'!B:B&'25-07'!C:C,'25-07'!D:D,0)} -> 0 | U8: {=_xlfn.XLOOKUP($B8&U$3,'25-07'!B:B&'25-07'!C:C,'25-07'!D:D,0)} -> 0 | V8: =SUM(S8:U8) -> 36 | W8: {=_xlfn.XLOOKUP($B8&W$3,'25-08'!B:B&'25-08'!C:C,'25-08'!D:D,0)} -> 68 | X8: {=_xlfn.XLOOKUP($B8&X$3,'25-08'!B:B&'25-08'!C:C,'25-08'!D:D,0)} -> 0 | Y8: {=_xlfn.XLOOKUP($B8&Y$3,'25-08'!B:B&'25-08'!C:C,'25-08'!D:D,0)} -> 0 | Z8: =SUM(W8:Y8) -> 68 | AA8: {=_xlfn.XLOOKUP($B8&AA$3,'25-09'!B:B&'25-09'!C:C,'25-09'!D:D,0)} -> 8 | AB8: {=_xlfn.XLOOKUP($B8&AB$3,'25-09'!B:B&'25-09'!C:C,'25-09'!D:D,0)} -> 12 | AC8: {=_xlfn.XLOOKUP($B8&AC$3,'25-09'!B:B&'25-09'!C:C,'25-09'!D:D,0)} -> 0 | AD8: =SUM(AA8:AC8) -> 20 | AE8: {=_xlfn.XLOOKUP($B8&AE$3,'25-10'!B:B&'25-10'!C:C,'25-10'!D:D,0)} -> 8 | AF8: {=_xlfn.XLOOKUP($B8&AF$3,'25-10'!B:B&'25-10'!C:C,'25-10'!D:D,0)} -> 0 | AG8: {=_xlfn.XLOOKUP($B8&AG$3,'25-10'!B:B&'25-10'!C:C,'25-10'!D:D,0)} -> 0 | AH8: =SUM(AE8:AG8) -> 8 | AI8: {=_xlfn.XLOOKUP($B8&AI$3,'25-11'!B:B&'25-11'!C:C,'25-11'!D:D,0)} -> 0 | AJ8: {=_xlfn.XLOOKUP($B8&AJ$3,'25-11'!B:B&'25-11'!C:C,'25-11'!D:D,0)} -> 0 | AK8: {=_xlfn.XLOOKUP($B8&AK$3,'25-11'!B:B&'25-11'!C:C,'25-11'!D:D,0)} -> 0 | AL8: =SUM(AI8:AK8) -> 0 | AM8: {=_xlfn.XLOOKUP($B8&AM$3,'25-12'!B:B&'25-12'!C:C,'25-12'!D:D,0)} -> 0 | AN8: {=_xlfn.XLOOKUP($B8&AN$3,'25-12'!B:B&'25-12'!C:C,'25-12'!D:D,0)} -> 8 | AO8: {=_xlfn.XLOOKUP($B8&AO$3,'25-12'!B:B&'25-12'!C:C,'25-12'!D:D,0)} -> 0 | AP8: =SUM(AM8:AO8) -> 8 | AQ8: {=_xlfn.XLOOKUP($B8&AQ$3,'26-01'!B:B&'26-01'!C:C,'26-01'!D:D,0)} -> 0 | AR8: {=_xlfn.XLOOKUP($B8&AR$3,'26-01'!B:B&'26-01'!C:C,'26-01'!D:D,0)} -> 4 | AS8: {=_xlfn.XLOOKUP($B8&AS$3,'26-01'!B:B&'26-01'!C:C,'26-01'!D:D,0)} -> 0 | AT8: =SUM(AQ8:AS8) -> 4 | AU8: {=_xlfn.XLOOKUP($B8&AU$3,'26-02'!B:B&'26-02'!C:C,'26-02'!D:D,0)} -> 0 | AV8: {=_xlfn.XLOOKUP($B8&AV$3,'26-02'!B:B&'26-02'!C:C,'26-02'!D:D,0)} -> 0 | AW8: {=_xlfn.XLOOKUP($B8&AW$3,'26-02'!B:B&'26-02'!C:C,'26-02'!D:D,0)} -> 0 | AX8: =SUM(AU8:AW8) -> 0 | AY8: =SUM(AX8,AT8,AP8,AL8,AH8,AD8,Z8,V8,R8,N8,J8,F8) -> 200 | AZ8: =AVERAGE(AX8,AT8,AP8,AL8,AH8,AD8) -> 6.6666667 | BA8: =AVERAGE(AX8,AT8,AP8,AL8,AH8,AD8,Z8,V8,R8,N8,J8) -> 17.818182 | BB8: =AVERAGE(AU8,AQ8,AM8,AI8,AE8,AA8) -> 2.6666667 | BC8: =AVERAGE(AU8,AQ8,AM8,AI8,AE8,AA8,W8,S8,O8,K8,G8) -> 15.636364 | BD8: =BK8 -> 28 | BE8: =AVERAGE(AV8,AR8,AN8,AJ8,AF8,AB8) -> 4 | BF8: =AVERAGE(AV8,AR8,AN8,AJ8,AF8,AB8) -> 4 | BG8: =BL8 -> 20 | BH8: =AVERAGE(AW8,AS8,AO8,AK8,AG8,AC8) -> 0 | BI8: =AVERAGE(AW8,AS8,AO8,AK8,AG8,AC8) -> 0 | BJ8: =BM8 -> 25 | BK8: =_xlfn.XLOOKUP($B8,'BCS-1-KLG'!C:C,'BCS-1-KLG'!E:E,0) -> 28 | BL8: =_xlfn.XLOOKUP($B8,'BCS-2 PIK 2'!C:C,'BCS-2 PIK 2'!E:E,0) -> 20 | BM8: =_xlfn.XLOOKUP($B8,'BCS HO'!C:C,'BCS HO'!E:E,0) -> 25 | BN8: =SUM(BK8:BM8) -> 73
A9: 6 | B9: MOTUL Transmission Oil Multi ATF 1L | C9: {=_xlfn.XLOOKUP($B9&$C$3,'25-03'!B:B&'25-03'!C:C,'25-03'!D:D,0)} -> 3 | D9: {=_xlfn.XLOOKUP($B9&$D$3,'25-03'!B:B&'25-03'!C:C,'25-03'!D:D,0)} -> 0 | E9: {=_xlfn.XLOOKUP($B9&E$3,'25-03'!B:B&'25-03'!C:C,'25-03'!D:D,0)} -> 0 | F9: =SUM(C9:E9) -> 3 | G9: {=_xlfn.XLOOKUP($B9&G$3,'25-04'!B:B&'25-04'!C:C,'25-04'!D:D,0)} -> 0 | H9: {=_xlfn.XLOOKUP($B9&H$3,'25-04'!B:B&'25-04'!C:C,'25-04'!D:D,0)} -> 0 | I9: {=_xlfn.XLOOKUP($B9&I$3,'25-04'!B:B&'25-04'!C:C,'25-04'!D:D,0)} -> 0 | J9: =SUM(G9:I9) -> 0 | K9: {=_xlfn.XLOOKUP($B9&K$3,'25-05'!B:B&'25-05'!C:C,'25-05'!D:D,0)} -> 0 | L9: {=_xlfn.XLOOKUP($B9&L$3,'25-05'!B:B&'25-05'!C:C,'25-05'!D:D,0)} -> 0 | M9: {=_xlfn.XLOOKUP($B9&M$3,'25-05'!B:B&'25-05'!C:C,'25-05'!D:D,0)} -> 0 | N9: =SUM(K9:M9) -> 0 | O9: {=_xlfn.XLOOKUP($B9&O$3,'26-06'!B:B&'26-06'!C:C,'26-06'!D:D,0)} -> 24 | P9: {=_xlfn.XLOOKUP($B9&P$3,'26-06'!B:B&'26-06'!C:C,'26-06'!D:D,0)} -> 0 | Q9: {=_xlfn.XLOOKUP($B9&Q$3,'26-06'!B:B&'26-06'!C:C,'26-06'!D:D,0)} -> 0 | R9: =SUM(O9:Q9) -> 24 | S9: {=_xlfn.XLOOKUP($B9&S$3,'25-07'!B:B&'25-07'!C:C,'25-07'!D:D,0)} -> 20 | T9: {=_xlfn.XLOOKUP($B9&T$3,'25-07'!B:B&'25-07'!C:C,'25-07'!D:D,0)} -> 0 | U9: {=_xlfn.XLOOKUP($B9&U$3,'25-07'!B:B&'25-07'!C:C,'25-07'!D:D,0)} -> 0 | V9: =SUM(S9:U9) -> 20 | W9: {=_xlfn.XLOOKUP($B9&W$3,'25-08'!B:B&'25-08'!C:C,'25-08'!D:D,0)} -> 0 | X9: {=_xlfn.XLOOKUP($B9&X$3,'25-08'!B:B&'25-08'!C:C,'25-08'!D:D,0)} -> 0 | Y9: {=_xlfn.XLOOKUP($B9&Y$3,'25-08'!B:B&'25-08'!C:C,'25-08'!D:D,0)} -> 0 | Z9: =SUM(W9:Y9) -> 0 | AA9: {=_xlfn.XLOOKUP($B9&AA$3,'25-09'!B:B&'25-09'!C:C,'25-09'!D:D,0)} -> 4 | AB9: {=_xlfn.XLOOKUP($B9&AB$3,'25-09'!B:B&'25-09'!C:C,'25-09'!D:D,0)} -> 0 | AC9: {=_xlfn.XLOOKUP($B9&AC$3,'25-09'!B:B&'25-09'!C:C,'25-09'!D:D,0)} -> 0 | AD9: =SUM(AA9:AC9) -> 4 | AE9: {=_xlfn.XLOOKUP($B9&AE$3,'25-10'!B:B&'25-10'!C:C,'25-10'!D:D,0)} -> 0 | AF9: {=_xlfn.XLOOKUP($B9&AF$3,'25-10'!B:B&'25-10'!C:C,'25-10'!D:D,0)} -> 0 | AG9: {=_xlfn.XLOOKUP($B9&AG$3,'25-10'!B:B&'25-10'!C:C,'25-10'!D:D,0)} -> 0 | AH9: =SUM(AE9:AG9) -> 0 | AI9: {=_xlfn.XLOOKUP($B9&AI$3,'25-11'!B:B&'25-11'!C:C,'25-11'!D:D,0)} -> 4 | AJ9: {=_xlfn.XLOOKUP($B9&AJ$3,'25-11'!B:B&'25-11'!C:C,'25-11'!D:D,0)} -> 0 | AK9: {=_xlfn.XLOOKUP($B9&AK$3,'25-11'!B:B&'25-11'!C:C,'25-11'!D:D,0)} -> 0 | AL9: =SUM(AI9:AK9) -> 4 | AM9: {=_xlfn.XLOOKUP($B9&AM$3,'25-12'!B:B&'25-12'!C:C,'25-12'!D:D,0)} -> 0 | AN9: {=_xlfn.XLOOKUP($B9&AN$3,'25-12'!B:B&'25-12'!C:C,'25-12'!D:D,0)} -> 0 | AO9: {=_xlfn.XLOOKUP($B9&AO$3,'25-12'!B:B&'25-12'!C:C,'25-12'!D:D,0)} -> 0 | AP9: =SUM(AM9:AO9) -> 0 | AQ9: {=_xlfn.XLOOKUP($B9&AQ$3,'26-01'!B:B&'26-01'!C:C,'26-01'!D:D,0)} -> 0 | AR9: {=_xlfn.XLOOKUP($B9&AR$3,'26-01'!B:B&'26-01'!C:C,'26-01'!D:D,0)} -> 0 | AS9: {=_xlfn.XLOOKUP($B9&AS$3,'26-01'!B:B&'26-01'!C:C,'26-01'!D:D,0)} -> 0 | AT9: =SUM(AQ9:AS9) -> 0 | AU9: {=_xlfn.XLOOKUP($B9&AU$3,'26-02'!B:B&'26-02'!C:C,'26-02'!D:D,0)} -> 0 | AV9: {=_xlfn.XLOOKUP($B9&AV$3,'26-02'!B:B&'26-02'!C:C,'26-02'!D:D,0)} -> 0 | AW9: {=_xlfn.XLOOKUP($B9&AW$3,'26-02'!B:B&'26-02'!C:C,'26-02'!D:D,0)} -> 0 | AX9: =SUM(AU9:AW9) -> 0 | AY9: =SUM(AX9,AT9,AP9,AL9,AH9,AD9,Z9,V9,R9,N9,J9,F9) -> 55 | AZ9: =AVERAGE(AX9,AT9,AP9,AL9,AH9,AD9) -> 1.3333333 | BA9: =AVERAGE(AX9,AT9,AP9,AL9,AH9,AD9,Z9,V9,R9,N9,J9) -> 4.7272727 | BB9: =AVERAGE(AU9,AQ9,AM9,AI9,AE9,AA9) -> 1.3333333 | BC9: =AVERAGE(AU9,AQ9,AM9,AI9,AE9,AA9,W9,S9,O9,K9,G9) -> 4.7272727 | BD9: =BK9 -> 51 | BE9: =AVERAGE(AV9,AR9,AN9,AJ9,AF9,AB9) -> 0 | BF9: =AVERAGE(AV9,AR9,AN9,AJ9,AF9,AB9) -> 0 | BG9: =BL9 -> 0 | BH9: =AVERAGE(AW9,AS9,AO9,AK9,AG9,AC9) -> 0 | BI9: =AVERAGE(AW9,AS9,AO9,AK9,AG9,AC9) -> 0 | BJ9: =BM9 -> 0 | BK9: =_xlfn.XLOOKUP($B9,'BCS-1-KLG'!C:C,'BCS-1-KLG'!E:E,0) -> 51 | BL9: =_xlfn.XLOOKUP($B9,'BCS-2 PIK 2'!C:C,'BCS-2 PIK 2'!E:E,0) -> 0 | BM9: =_xlfn.XLOOKUP($B9,'BCS HO'!C:C,'BCS HO'!E:E,0) -> 0 | BN9: =SUM(BK9:BM9) -> 51
A10: 7 | B10: MOTUL Gear Oil HDX 80W-90 1L | C10: {=_xlfn.XLOOKUP($B10&$C$3,'25-03'!B:B&'25-03'!C:C,'25-03'!D:D,0)} -> 0 | D10: {=_xlfn.XLOOKUP($B10&$D$3,'25-03'!B:B&'25-03'!C:C,'25-03'!D:D,0)} -> 0 | E10: {=_xlfn.XLOOKUP($B10&E$3,'25-03'!B:B&'25-03'!C:C,'25-03'!D:D,0)} -> 0 | F10: =SUM(C10:E10) -> 0 | G10: {=_xlfn.XLOOKUP($B10&G$3,'25-04'!B:B&'25-04'!C:C,'25-04'!D:D,0)} -> 0 | H10: {=_xlfn.XLOOKUP($B10&H$3,'25-04'!B:B&'25-04'!C:C,'25-04'!D:D,0)} -> 0 | I10: {=_xlfn.XLOOKUP($B10&I$3,'25-04'!B:B&'25-04'!C:C,'25-04'!D:D,0)} -> 0 | J10: =SUM(G10:I10) -> 0 | K10: {=_xlfn.XLOOKUP($B10&K$3,'25-05'!B:B&'25-05'!C:C,'25-05'!D:D,0)} -> 2 | L10: {=_xlfn.XLOOKUP($B10&L$3,'25-05'!B:B&'25-05'!C:C,'25-05'!D:D,0)} -> 0 | M10: {=_xlfn.XLOOKUP($B10&M$3,'25-05'!B:B&'25-05'!C:C,'25-05'!D:D,0)} -> 0 | N10: =SUM(K10:M10) -> 2 | O10: {=_xlfn.XLOOKUP($B10&O$3,'26-06'!B:B&'26-06'!C:C,'26-06'!D:D,0)} -> 0 | P10: {=_xlfn.XLOOKUP($B10&P$3,'26-06'!B:B&'26-06'!C:C,'26-06'!D:D,0)} -> 0 | Q10: {=_xlfn.XLOOKUP($B10&Q$3,'26-06'!B:B&'26-06'!C:C,'26-06'!D:D,0)} -> 0 | R10: =SUM(O10:Q10) -> 0 | S10: {=_xlfn.XLOOKUP($B10&S$3,'25-07'!B:B&'25-07'!C:C,'25-07'!D:D,0)} -> 8 | T10: {=_xlfn.XLOOKUP($B10&T$3,'25-07'!B:B&'25-07'!C:C,'25-07'!D:D,0)} -> 0 | U10: {=_xlfn.XLOOKUP($B10&U$3,'25-07'!B:B&'25-07'!C:C,'25-07'!D:D,0)} -> 0 | V10: =SUM(S10:U10) -> 8 | W10: {=_xlfn.XLOOKUP($B10&W$3,'25-08'!B:B&'25-08'!C:C,'25-08'!D:D,0)} -> 2 | X10: {=_xlfn.XLOOKUP($B10&X$3,'25-08'!B:B&'25-08'!C:C,'25-08'!D:D,0)} -> 0 | Y10: {=_xlfn.XLOOKUP($B10&Y$3,'25-08'!B:B&'25-08'!C:C,'25-08'!D:D,0)} -> 0 | Z10: =SUM(W10:Y10) -> 2 | AA10: {=_xlfn.XLOOKUP($B10&AA$3,'25-09'!B:B&'25-09'!C:C,'25-09'!D:D,0)} -> 0 | AB10: {=_xlfn.XLOOKUP($B10&AB$3,'25-09'!B:B&'25-09'!C:C,'25-09'!D:D,0)} -> 0 | AC10: {=_xlfn.XLOOKUP($B10&AC$3,'25-09'!B:B&'25-09'!C:C,'25-09'!D:D,0)} -> 0 | AD10: =SUM(AA10:AC10) -> 0 | AE10: {=_xlfn.XLOOKUP($B10&AE$3,'25-10'!B:B&'25-10'!C:C,'25-10'!D:D,0)} -> 0 | AF10: {=_xlfn.XLOOKUP($B10&AF$3,'25-10'!B:B&'25-10'!C:C,'25-10'!D:D,0)} -> 0 | AG10: {=_xlfn.XLOOKUP($B10&AG$3,'25-10'!B:B&'25-10'!C:C,'25-10'!D:D,0)} -> 0 | AH10: =SUM(AE10:AG10) -> 0 | AI10: {=_xlfn.XLOOKUP($B10&AI$3,'25-11'!B:B&'25-11'!C:C,'25-11'!D:D,0)} -> 0 | AJ10: {=_xlfn.XLOOKUP($B10&AJ$3,'25-11'!B:B&'25-11'!C:C,'25-11'!D:D,0)} -> 0 | AK10: {=_xlfn.XLOOKUP($B10&AK$3,'25-11'!B:B&'25-11'!C:C,'25-11'!D:D,0)} -> 0 | AL10: =SUM(AI10:AK10) -> 0 | AM10: {=_xlfn.XLOOKUP($B10&AM$3,'25-12'!B:B&'25-12'!C:C,'25-12'!D:D,0)} -> 0 | AN10: {=_xlfn.XLOOKUP($B10&AN$3,'25-12'!B:B&'25-12'!C:C,'25-12'!D:D,0)} -> 0 | AO10: {=_xlfn.XLOOKUP($B10&AO$3,'25-12'!B:B&'25-12'!C:C,'25-12'!D:D,0)} -> 0 | AP10: =SUM(AM10:AO10) -> 0 | AQ10: {=_xlfn.XLOOKUP($B10&AQ$3,'26-01'!B:B&'26-01'!C:C,'26-01'!D:D,0)} -> 0 | AR10: {=_xlfn.XLOOKUP($B10&AR$3,'26-01'!B:B&'26-01'!C:C,'26-01'!D:D,0)} -> 0 | AS10: {=_xlfn.XLOOKUP($B10&AS$3,'26-01'!B:B&'26-01'!C:C,'26-01'!D:D,0)} -> 0 | AT10: =SUM(AQ10:AS10) -> 0 | AU10: {=_xlfn.XLOOKUP($B10&AU$3,'26-02'!B:B&'26-02'!C:C,'26-02'!D:D,0)} -> 0 | AV10: {=_xlfn.XLOOKUP($B10&AV$3,'26-02'!B:B&'26-02'!C:C,'26-02'!D:D,0)} -> 0 | AW10: {=_xlfn.XLOOKUP($B10&AW$3,'26-02'!B:B&'26-02'!C:C,'26-02'!D:D,0)} -> 0 | AX10: =SUM(AU10:AW10) -> 0 | AY10: =SUM(AX10,AT10,AP10,AL10,AH10,AD10,Z10,V10,R10,N10,J10,F10) -> 12 | AZ10: =AVERAGE(AX10,AT10,AP10,AL10,AH10,AD10) -> 0 | BA10: =AVERAGE(AX10,AT10,AP10,AL10,AH10,AD10,Z10,V10,R10,N10,J10) -> 1.0909091 | BB10: =AVERAGE(AU10,AQ10,AM10,AI10,AE10,AA10) -> 0 | BC10: =AVERAGE(AU10,AQ10,AM10,AI10,AE10,AA10,W10,S10,O10,K10,G10) -> 1.0909091 | BD10: =BK10 -> 0 | BE10: =AVERAGE(AV10,AR10,AN10,AJ10,AF10,AB10) -> 0 | BF10: =AVERAGE(AV10,AR10,AN10,AJ10,AF10,AB10) -> 0 | BG10: =BL10 -> 0 | BH10: =AVERAGE(AW10,AS10,AO10,AK10,AG10,AC10) -> 0 | BI10: =AVERAGE(AW10,AS10,AO10,AK10,AG10,AC10) -> 0 | BJ10: =BM10 -> 12 | BK10: =_xlfn.XLOOKUP($B10,'BCS-1-KLG'!C:C,'BCS-1-KLG'!E:E,0) -> 0 | BL10: =_xlfn.XLOOKUP($B10,'BCS-2 PIK 2'!C:C,'BCS-2 PIK 2'!E:E,0) -> 0 | BM10: =_xlfn.XLOOKUP($B10,'BCS HO'!C:C,'BCS HO'!E:E,0) -> 12 | BN10: =SUM(BK10:BM10) -> 12
A11: 8 | B11: SHELL Transmission Oil Spirax ATF 6 1L | C11: {=_xlfn.XLOOKUP($B11&$C$3,'25-03'!B:B&'25-03'!C:C,'25-03'!D:D,0)} -> 0 | D11: {=_xlfn.XLOOKUP($B11&$D$3,'25-03'!B:B&'25-03'!C:C,'25-03'!D:D,0)} -> 0 | E11: {=_xlfn.XLOOKUP($B11&E$3,'25-03'!B:B&'25-03'!C:C,'25-03'!D:D,0)} -> 0 | F11: =SUM(C11:E11) -> 0 | G11: {=_xlfn.XLOOKUP($B11&G$3,'25-04'!B:B&'25-04'!C:C,'25-04'!D:D,0)} -> 0 | H11: {=_xlfn.XLOOKUP($B11&H$3,'25-04'!B:B&'25-04'!C:C,'25-04'!D:D,0)} -> 0 | I11: {=_xlfn.XLOOKUP($B11&I$3,'25-04'!B:B&'25-04'!C:C,'25-04'!D:D,0)} -> 0 | J11: =SUM(G11:I11) -> 0 | K11: {=_xlfn.XLOOKUP($B11&K$3,'25-05'!B:B&'25-05'!C:C,'25-05'!D:D,0)} -> 0 | L11: {=_xlfn.XLOOKUP($B11&L$3,'25-05'!B:B&'25-05'!C:C,'25-05'!D:D,0)} -> 0 | M11: {=_xlfn.XLOOKUP($B11&M$3,'25-05'!B:B&'25-05'!C:C,'25-05'!D:D,0)} -> 0 | N11: =SUM(K11:M11) -> 0 | O11: {=_xlfn.XLOOKUP($B11&O$3,'26-06'!B:B&'26-06'!C:C,'26-06'!D:D,0)} -> 0 | P11: {=_xlfn.XLOOKUP($B11&P$3,'26-06'!B:B&'26-06'!C:C,'26-06'!D:D,0)} -> 0 | Q11: {=_xlfn.XLOOKUP($B11&Q$3,'26-06'!B:B&'26-06'!C:C,'26-06'!D:D,0)} -> 0 | R11: =SUM(O11:Q11) -> 0 | S11: {=_xlfn.XLOOKUP($B11&S$3,'25-07'!B:B&'25-07'!C:C,'25-07'!D:D,0)} -> 14 | T11: {=_xlfn.XLOOKUP($B11&T$3,'25-07'!B:B&'25-07'!C:C,'25-07'!D:D,0)} -> 0 | U11: {=_xlfn.XLOOKUP($B11&U$3,'25-07'!B:B&'25-07'!C:C,'25-07'!D:D,0)} -> 0 | V11: =SUM(S11:U11) -> 14 | W11: {=_xlfn.XLOOKUP($B11&W$3,'25-08'!B:B&'25-08'!C:C,'25-08'!D:D,0)} -> 19 | X11: {=_xlfn.XLOOKUP($B11&X$3,'25-08'!B:B&'25-08'!C:C,'25-08'!D:D,0)} -> 0 | Y11: {=_xlfn.XLOOKUP($B11&Y$3,'25-08'!B:B&'25-08'!C:C,'25-08'!D:D,0)} -> 0 | Z11: =SUM(W11:Y11) -> 19 | AA11: {=_xlfn.XLOOKUP($B11&AA$3,'25-09'!B:B&'25-09'!C:C,'25-09'!D:D,0)} -> 47 | AB11: {=_xlfn.XLOOKUP($B11&AB$3,'25-09'!B:B&'25-09'!C:C,'25-09'!D:D,0)} -> 0 | AC11: {=_xlfn.XLOOKUP($B11&AC$3,'25-09'!B:B&'25-09'!C:C,'25-09'!D:D,0)} -> 0 | AD11: =SUM(AA11:AC11) -> 47 | AE11: {=_xlfn.XLOOKUP($B11&AE$3,'25-10'!B:B&'25-10'!C:C,'25-10'!D:D,0)} -> 52 | AF11: {=_xlfn.XLOOKUP($B11&AF$3,'25-10'!B:B&'25-10'!C:C,'25-10'!D:D,0)} -> 25 | AG11: {=_xlfn.XLOOKUP($B11&AG$3,'25-10'!B:B&'25-10'!C:C,'25-10'!D:D,0)} -> 0 | AH11: =SUM(AE11:AG11) -> 77 | AI11: {=_xlfn.XLOOKUP($B11&AI$3,'25-11'!B:B&'25-11'!C:C,'25-11'!D:D,0)} -> 36 | AJ11: {=_xlfn.XLOOKUP($B11&AJ$3,'25-11'!B:B&'25-11'!C:C,'25-11'!D:D,0)} -> 12 | AK11: {=_xlfn.XLOOKUP($B11&AK$3,'25-11'!B:B&'25-11'!C:C,'25-11'!D:D,0)} -> 0 | AL11: =SUM(AI11:AK11) -> 48 | AM11: {=_xlfn.XLOOKUP($B11&AM$3,'25-12'!B:B&'25-12'!C:C,'25-12'!D:D,0)} -> 34 | AN11: {=_xlfn.XLOOKUP($B11&AN$3,'25-12'!B:B&'25-12'!C:C,'25-12'!D:D,0)} -> 27 | AO11: {=_xlfn.XLOOKUP($B11&AO$3,'25-12'!B:B&'25-12'!C:C,'25-12'!D:D,0)} -> 0 | AP11: =SUM(AM11:AO11) -> 61 | AQ11: {=_xlfn.XLOOKUP($B11&AQ$3,'26-01'!B:B&'26-01'!C:C,'26-01'!D:D,0)} -> 24 | AR11: {=_xlfn.XLOOKUP($B11&AR$3,'26-01'!B:B&'26-01'!C:C,'26-01'!D:D,0)} -> 13 | AS11: {=_xlfn.XLOOKUP($B11&AS$3,'26-01'!B:B&'26-01'!C:C,'26-01'!D:D,0)} -> 0 | AT11: =SUM(AQ11:AS11) -> 37 | AU11: {=_xlfn.XLOOKUP($B11&AU$3,'26-02'!B:B&'26-02'!C:C,'26-02'!D:D,0)} -> 20 | AV11: {=_xlfn.XLOOKUP($B11&AV$3,'26-02'!B:B&'26-02'!C:C,'26-02'!D:D,0)} -> 24 | AW11: {=_xlfn.XLOOKUP($B11&AW$3,'26-02'!B:B&'26-02'!C:C,'26-02'!D:D,0)} -> 0 | AX11: =SUM(AU11:AW11) -> 44 | AY11: =SUM(AX11,AT11,AP11,AL11,AH11,AD11,Z11,V11,R11,N11,J11,F11) -> 347 | AZ11: =AVERAGE(AX11,AT11,AP11,AL11,AH11,AD11) -> 52.333333 | BA11: =AVERAGE(AX11,AT11,AP11,AL11,AH11,AD11,Z11,V11,R11,N11,J11) -> 31.545455 | BB11: =AVERAGE(AU11,AQ11,AM11,AI11,AE11,AA11) -> 35.5 | BC11: =AVERAGE(AU11,AQ11,AM11,AI11,AE11,AA11,W11,S11,O11,K11,G11) -> 22.363636 | BD11: =BK11 -> 3 | BE11: =AVERAGE(AV11,AR11,AN11,AJ11,AF11,AB11) -> 16.833333 | BF11: =AVERAGE(AV11,AR11,AN11,AJ11,AF11,AB11) -> 16.833333 | BG11: =BL11 -> 59 | BH11: =AVERAGE(AW11,AS11,AO11,AK11,AG11,AC11) -> 0 | BI11: =AVERAGE(AW11,AS11,AO11,AK11,AG11,AC11) -> 0 | BJ11: =BM11 -> 48 | BK11: =_xlfn.XLOOKUP($B11,'BCS-1-KLG'!C:C,'BCS-1-KLG'!E:E,0) -> 3 | BL11: =_xlfn.XLOOKUP($B11,'BCS-2 PIK 2'!C:C,'BCS-2 PIK 2'!E:E,0) -> 59 | BM11: =_xlfn.XLOOKUP($B11,'BCS HO'!C:C,'BCS HO'!E:E,0) -> 48 | BN11: =SUM(BK11:BM11) -> 110
A12: 9 | B12: SHELL Transmission Oil Spirax S5 CVTX 1L | C12: {=_xlfn.XLOOKUP($B12&$C$3,'25-03'!B:B&'25-03'!C:C,'25-03'!D:D,0)} -> 0 | D12: {=_xlfn.XLOOKUP($B12&$D$3,'25-03'!B:B&'25-03'!C:C,'25-03'!D:D,0)} -> 0 | E12: {=_xlfn.XLOOKUP($B12&E$3,'25-03'!B:B&'25-03'!C:C,'25-03'!D:D,0)} -> 0 | F12: =SUM(C12:E12) -> 0 | G12: {=_xlfn.XLOOKUP($B12&G$3,'25-04'!B:B&'25-04'!C:C,'25-04'!D:D,0)} -> 0 | H12: {=_xlfn.XLOOKUP($B12&H$3,'25-04'!B:B&'25-04'!C:C,'25-04'!D:D,0)} -> 0 | I12: {=_xlfn.XLOOKUP($B12&I$3,'25-04'!B:B&'25-04'!C:C,'25-04'!D:D,0)} -> 0 | J12: =SUM(G12:I12) -> 0 | K12: {=_xlfn.XLOOKUP($B12&K$3,'25-05'!B:B&'25-05'!C:C,'25-05'!D:D,0)} -> 0 | L12: {=_xlfn.XLOOKUP($B12&L$3,'25-05'!B:B&'25-05'!C:C,'25-05'!D:D,0)} -> 0 | M12: {=_xlfn.XLOOKUP($B12&M$3,'25-05'!B:B&'25-05'!C:C,'25-05'!D:D,0)} -> 0 | N12: =SUM(K12:M12) -> 0 | O12: {=_xlfn.XLOOKUP($B12&O$3,'26-06'!B:B&'26-06'!C:C,'26-06'!D:D,0)} -> 0 | P12: {=_xlfn.XLOOKUP($B12&P$3,'26-06'!B:B&'26-06'!C:C,'26-06'!D:D,0)} -> 0 | Q12: {=_xlfn.XLOOKUP($B12&Q$3,'26-06'!B:B&'26-06'!C:C,'26-06'!D:D,0)} -> 0 | R12: =SUM(O12:Q12) -> 0 | S12: {=_xlfn.XLOOKUP($B12&S$3,'25-07'!B:B&'25-07'!C:C,'25-07'!D:D,0)} -> 12 | T12: {=_xlfn.XLOOKUP($B12&T$3,'25-07'!B:B&'25-07'!C:C,'25-07'!D:D,0)} -> 0 | U12: {=_xlfn.XLOOKUP($B12&U$3,'25-07'!B:B&'25-07'!C:C,'25-07'!D:D,0)} -> 0 | V12: =SUM(S12:U12) -> 12 | W12: {=_xlfn.XLOOKUP($B12&W$3,'25-08'!B:B&'25-08'!C:C,'25-08'!D:D,0)} -> 20 | X12: {=_xlfn.XLOOKUP($B12&X$3,'25-08'!B:B&'25-08'!C:C,'25-08'!D:D,0)} -> 0 | Y12: {=_xlfn.XLOOKUP($B12&Y$3,'25-08'!B:B&'25-08'!C:C,'25-08'!D:D,0)} -> 0 | Z12: =SUM(W12:Y12) -> 20 | AA12: {=_xlfn.XLOOKUP($B12&AA$3,'25-09'!B:B&'25-09'!C:C,'25-09'!D:D,0)} -> 15 | AB12: {=_xlfn.XLOOKUP($B12&AB$3,'25-09'!B:B&'25-09'!C:C,'25-09'!D:D,0)} -> 0 | AC12: {=_xlfn.XLOOKUP($B12&AC$3,'25-09'!B:B&'25-09'!C:C,'25-09'!D:D,0)} -> 0 | AD12: =SUM(AA12:AC12) -> 15 | AE12: {=_xlfn.XLOOKUP($B12&AE$3,'25-10'!B:B&'25-10'!C:C,'25-10'!D:D,0)} -> 41 | AF12: {=_xlfn.XLOOKUP($B12&AF$3,'25-10'!B:B&'25-10'!C:C,'25-10'!D:D,0)} -> 4 | AG12: {=_xlfn.XLOOKUP($B12&AG$3,'25-10'!B:B&'25-10'!C:C,'25-10'!D:D,0)} -> 0 | AH12: =SUM(AE12:AG12) -> 45 | AI12: {=_xlfn.XLOOKUP($B12&AI$3,'25-11'!B:B&'25-11'!C:C,'25-11'!D:D,0)} -> 25 | AJ12: {=_xlfn.XLOOKUP($B12&AJ$3,'25-11'!B:B&'25-11'!C:C,'25-11'!D:D,0)} -> 8 | AK12: {=_xlfn.XLOOKUP($B12&AK$3,'25-11'!B:B&'25-11'!C:C,'25-11'!D:D,0)} -> 0 | AL12: =SUM(AI12:AK12) -> 33 | AM12: {=_xlfn.XLOOKUP($B12&AM$3,'25-12'!B:B&'25-12'!C:C,'25-12'!D:D,0)} -> 32 | AN12: {=_xlfn.XLOOKUP($B12&AN$3,'25-12'!B:B&'25-12'!C:C,'25-12'!D:D,0)} -> 4 | AO12: {=_xlfn.XLOOKUP($B12&AO$3,'25-12'!B:B&'25-12'!C:C,'25-12'!D:D,0)} -> 0 | AP12: =SUM(AM12:AO12) -> 36 | AQ12: {=_xlfn.XLOOKUP($B12&AQ$3,'26-01'!B:B&'26-01'!C:C,'26-01'!D:D,0)} -> 43 | AR12: {=_xlfn.XLOOKUP($B12&AR$3,'26-01'!B:B&'26-01'!C:C,'26-01'!D:D,0)} -> 4 | AS12: {=_xlfn.XLOOKUP($B12&AS$3,'26-01'!B:B&'26-01'!C:C,'26-01'!D:D,0)} -> 0 | AT12: =SUM(AQ12:AS12) -> 47 | AU12: {=_xlfn.XLOOKUP($B12&AU$3,'26-02'!B:B&'26-02'!C:C,'26-02'!D:D,0)} -> 12 | AV12: {=_xlfn.XLOOKUP($B12&AV$3,'26-02'!B:B&'26-02'!C:C,'26-02'!D:D,0)} -> 0 | AW12: {=_xlfn.XLOOKUP($B12&AW$3,'26-02'!B:B&'26-02'!C:C,'26-02'!D:D,0)} -> 0 | AX12: =SUM(AU12:AW12) -> 12 | AY12: =SUM(AX12,AT12,AP12,AL12,AH12,AD12,Z12,V12,R12,N12,J12,F12) -> 220 | AZ12: =AVERAGE(AX12,AT12,AP12,AL12,AH12,AD12) -> 31.333333 | BA12: =AVERAGE(AX12,AT12,AP12,AL12,AH12,AD12,Z12,V12,R12,N12,J12) -> 20 | BB12: =AVERAGE(AU12,AQ12,AM12,AI12,AE12,AA12) -> 28 | BC12: =AVERAGE(AU12,AQ12,AM12,AI12,AE12,AA12,W12,S12,O12,K12,G12) -> 18.181818 | BD12: =BK12 -> 5 | BE12: =AVERAGE(AV12,AR12,AN12,AJ12,AF12,AB12) -> 3.3333333 | BF12: =AVERAGE(AV12,AR12,AN12,AJ12,AF12,AB12) -> 3.3333333 | BG12: =BL12 -> 36 | BH12: =AVERAGE(AW12,AS12,AO12,AK12,AG12,AC12) -> 0 | BI12: =AVERAGE(AW12,AS12,AO12,AK12,AG12,AC12) -> 0 | BJ12: =BM12 -> 0 | BK12: =_xlfn.XLOOKUP($B12,'BCS-1-KLG'!C:C,'BCS-1-KLG'!E:E,0) -> 5 | BL12: =_xlfn.XLOOKUP($B12,'BCS-2 PIK 2'!C:C,'BCS-2 PIK 2'!E:E,0) -> 36 | BM12: =_xlfn.XLOOKUP($B12,'BCS HO'!C:C,'BCS HO'!E:E,0) -> 0 | BN12: =SUM(BK12:BM12) -> 41
A13: 10 | B13: SHELL Axle Oil Spirax S2 A 80W-90 1L | C13: {=_xlfn.XLOOKUP($B13&$C$3,'25-03'!B:B&'25-03'!C:C,'25-03'!D:D,0)} -> 0 | D13: {=_xlfn.XLOOKUP($B13&$D$3,'25-03'!B:B&'25-03'!C:C,'25-03'!D:D,0)} -> 0 | E13: {=_xlfn.XLOOKUP($B13&E$3,'25-03'!B:B&'25-03'!C:C,'25-03'!D:D,0)} -> 0 | F13: =SUM(C13:E13) -> 0 | G13: {=_xlfn.XLOOKUP($B13&G$3,'25-04'!B:B&'25-04'!C:C,'25-04'!D:D,0)} -> 0 | H13: {=_xlfn.XLOOKUP($B13&H$3,'25-04'!B:B&'25-04'!C:C,'25-04'!D:D,0)} -> 0 | I13: {=_xlfn.XLOOKUP($B13&I$3,'25-04'!B:B&'25-04'!C:C,'25-04'!D:D,0)} -> 0 | J13: =SUM(G13:I13) -> 0 | K13: {=_xlfn.XLOOKUP($B13&K$3,'25-05'!B:B&'25-05'!C:C,'25-05'!D:D,0)} -> 0 | L13: {=_xlfn.XLOOKUP($B13&L$3,'25-05'!B:B&'25-05'!C:C,'25-05'!D:D,0)} -> 0 | M13: {=_xlfn.XLOOKUP($B13&M$3,'25-05'!B:B&'25-05'!C:C,'25-05'!D:D,0)} -> 0 | N13: =SUM(K13:M13) -> 0 | O13: {=_xlfn.XLOOKUP($B13&O$3,'26-06'!B:B&'26-06'!C:C,'26-06'!D:D,0)} -> 0 | P13: {=_xlfn.XLOOKUP($B13&P$3,'26-06'!B:B&'26-06'!C:C,'26-06'!D:D,0)} -> 0 | Q13: {=_xlfn.XLOOKUP($B13&Q$3,'26-06'!B:B&'26-06'!C:C,'26-06'!D:D,0)} -> 0 | R13: =SUM(O13:Q13) -> 0 | S13: {=_xlfn.XLOOKUP($B13&S$3,'25-07'!B:B&'25-07'!C:C,'25-07'!D:D,0)} -> 0 | T13: {=_xlfn.XLOOKUP($B13&T$3,'25-07'!B:B&'25-07'!C:C,'25-07'!D:D,0)} -> 0 | U13: {=_xlfn.XLOOKUP($B13&U$3,'25-07'!B:B&'25-07'!C:C,'25-07'!D:D,0)} -> 0 | V13: =SUM(S13:U13) -> 0 | W13: {=_xlfn.XLOOKUP($B13&W$3,'25-08'!B:B&'25-08'!C:C,'25-08'!D:D,0)} -> 0 | X13: {=_xlfn.XLOOKUP($B13&X$3,'25-08'!B:B&'25-08'!C:C,'25-08'!D:D,0)} -> 0 | Y13: {=_xlfn.XLOOKUP($B13&Y$3,'25-08'!B:B&'25-08'!C:C,'25-08'!D:D,0)} -> 0 | Z13: =SUM(W13:Y13) -> 0 | AA13: {=_xlfn.XLOOKUP($B13&AA$3,'25-09'!B:B&'25-09'!C:C,'25-09'!D:D,0)} -> 12 | AB13: {=_xlfn.XLOOKUP($B13&AB$3,'25-09'!B:B&'25-09'!C:C,'25-09'!D:D,0)} -> 9 | AC13: {=_xlfn.XLOOKUP($B13&AC$3,'25-09'!B:B&'25-09'!C:C,'25-09'!D:D,0)} -> 0 | AD13: =SUM(AA13:AC13) -> 21 | AE13: {=_xlfn.XLOOKUP($B13&AE$3,'25-10'!B:B&'25-10'!C:C,'25-10'!D:D,0)} -> 26 | AF13: {=_xlfn.XLOOKUP($B13&AF$3,'25-10'!B:B&'25-10'!C:C,'25-10'!D:D,0)} -> 26 | AG13: {=_xlfn.XLOOKUP($B13&AG$3,'25-10'!B:B&'25-10'!C:C,'25-10'!D:D,0)} -> 0 | AH13: =SUM(AE13:AG13) -> 52 | AI13: {=_xlfn.XLOOKUP($B13&AI$3,'25-11'!B:B&'25-11'!C:C,'25-11'!D:D,0)} -> 28 | AJ13: {=_xlfn.XLOOKUP($B13&AJ$3,'25-11'!B:B&'25-11'!C:C,'25-11'!D:D,0)} -> 24 | AK13: {=_xlfn.XLOOKUP($B13&AK$3,'25-11'!B:B&'25-11'!C:C,'25-11'!D:D,0)} -> 0 | AL13: =SUM(AI13:AK13) -> 52 | AM13: {=_xlfn.XLOOKUP($B13&AM$3,'25-12'!B:B&'25-12'!C:C,'25-12'!D:D,0)} -> 27 | AN13: {=_xlfn.XLOOKUP($B13&AN$3,'25-12'!B:B&'25-12'!C:C,'25-12'!D:D,0)} -> 40 | AO13: {=_xlfn.XLOOKUP($B13&AO$3,'25-12'!B:B&'25-12'!C:C,'25-12'!D:D,0)} -> 0 | AP13: =SUM(AM13:AO13) -> 67 | AQ13: {=_xlfn.XLOOKUP($B13&AQ$3,'26-01'!B:B&'26-01'!C:C,'26-01'!D:D,0)} -> 37 | AR13: {=_xlfn.XLOOKUP($B13&AR$3,'26-01'!B:B&'26-01'!C:C,'26-01'!D:D,0)} -> 17 | AS13: {=_xlfn.XLOOKUP($B13&AS$3,'26-01'!B:B&'26-01'!C:C,'26-01'!D:D,0)} -> 0 | AT13: =SUM(AQ13:AS13) -> 54 | AU13: {=_xlfn.XLOOKUP($B13&AU$3,'26-02'!B:B&'26-02'!C:C,'26-02'!D:D,0)} -> 22 | AV13: {=_xlfn.XLOOKUP($B13&AV$3,'26-02'!B:B&'26-02'!C:C,'26-02'!D:D,0)} -> 8 | AW13: {=_xlfn.XLOOKUP($B13&AW$3,'26-02'!B:B&'26-02'!C:C,'26-02'!D:D,0)} -> 0 | AX13: =SUM(AU13:AW13) -> 30 | AY13: =SUM(AX13,AT13,AP13,AL13,AH13,AD13,Z13,V13,R13,N13,J13,F13) -> 276 | AZ13: =AVERAGE(AX13,AT13,AP13,AL13,AH13,AD13) -> 46 | BA13: =AVERAGE(AX13,AT13,AP13,AL13,AH13,AD13,Z13,V13,R13,N13,J13) -> 25.090909 | BB13: =AVERAGE(AU13,AQ13,AM13,AI13,AE13,AA13) -> 25.333333 | BC13: =AVERAGE(AU13,AQ13,AM13,AI13,AE13,AA13,W13,S13,O13,K13,G13) -> 13.818182 | BD13: =BK13 -> 13 | BE13: =AVERAGE(AV13,AR13,AN13,AJ13,AF13,AB13) -> 20.666667 | BF13: =AVERAGE(AV13,AR13,AN13,AJ13,AF13,AB13) -> 20.666667 | BG13: =BL13 -> 48 | BH13: =AVERAGE(AW13,AS13,AO13,AK13,AG13,AC13) -> 0 | BI13: =AVERAGE(AW13,AS13,AO13,AK13,AG13,AC13) -> 0 | BJ13: =BM13 -> 48 | BK13: =_xlfn.XLOOKUP($B13,'BCS-1-KLG'!C:C,'BCS-1-KLG'!E:E,0) -> 13 | BL13: =_xlfn.XLOOKUP($B13,'BCS-2 PIK 2'!C:C,'BCS-2 PIK 2'!E:E,0) -> 48 | BM13: =_xlfn.XLOOKUP($B13,'BCS HO'!C:C,'BCS HO'!E:E,0) -> 48 | BN13: =SUM(BK13:BM13) -> 109
A14: 11 | B14: SHELL Gear Oil Spirax S2 G 80W-90 1L | C14: {=_xlfn.XLOOKUP($B14&$C$3,'25-03'!B:B&'25-03'!C:C,'25-03'!D:D,0)} -> 0 | D14: {=_xlfn.XLOOKUP($B14&$D$3,'25-03'!B:B&'25-03'!C:C,'25-03'!D:D,0)} -> 0 | E14: {=_xlfn.XLOOKUP($B14&E$3,'25-03'!B:B&'25-03'!C:C,'25-03'!D:D,0)} -> 0 | F14: =SUM(C14:E14) -> 0 | G14: {=_xlfn.XLOOKUP($B14&G$3,'25-04'!B:B&'25-04'!C:C,'25-04'!D:D,0)} -> 0 | H14: {=_xlfn.XLOOKUP($B14&H$3,'25-04'!B:B&'25-04'!C:C,'25-04'!D:D,0)} -> 0 | I14: {=_xlfn.XLOOKUP($B14&I$3,'25-04'!B:B&'25-04'!C:C,'25-04'!D:D,0)} -> 0 | J14: =SUM(G14:I14) -> 0 | K14: {=_xlfn.XLOOKUP($B14&K$3,'25-05'!B:B&'25-05'!C:C,'25-05'!D:D,0)} -> 0 | L14: {=_xlfn.XLOOKUP($B14&L$3,'25-05'!B:B&'25-05'!C:C,'25-05'!D:D,0)} -> 0 | M14: {=_xlfn.XLOOKUP($B14&M$3,'25-05'!B:B&'25-05'!C:C,'25-05'!D:D,0)} -> 0 | N14: =SUM(K14:M14) -> 0 | O14: {=_xlfn.XLOOKUP($B14&O$3,'26-06'!B:B&'26-06'!C:C,'26-06'!D:D,0)} -> 0 | P14: {=_xlfn.XLOOKUP($B14&P$3,'26-06'!B:B&'26-06'!C:C,'26-06'!D:D,0)} -> 0 | Q14: {=_xlfn.XLOOKUP($B14&Q$3,'26-06'!B:B&'26-06'!C:C,'26-06'!D:D,0)} -> 0 | R14: =SUM(O14:Q14) -> 0 | S14: {=_xlfn.XLOOKUP($B14&S$3,'25-07'!B:B&'25-07'!C:C,'25-07'!D:D,0)} -> 0 | T14: {=_xlfn.XLOOKUP($B14&T$3,'25-07'!B:B&'25-07'!C:C,'25-07'!D:D,0)} -> 0 | U14: {=_xlfn.XLOOKUP($B14&U$3,'25-07'!B:B&'25-07'!C:C,'25-07'!D:D,0)} -> 0 | V14: =SUM(S14:U14) -> 0 | W14: {=_xlfn.XLOOKUP($B14&W$3,'25-08'!B:B&'25-08'!C:C,'25-08'!D:D,0)} -> 0 | X14: {=_xlfn.XLOOKUP($B14&X$3,'25-08'!B:B&'25-08'!C:C,'25-08'!D:D,0)} -> 0 | Y14: {=_xlfn.XLOOKUP($B14&Y$3,'25-08'!B:B&'25-08'!C:C,'25-08'!D:D,0)} -> 0 | Z14: =SUM(W14:Y14) -> 0 | AA14: {=_xlfn.XLOOKUP($B14&AA$3,'25-09'!B:B&'25-09'!C:C,'25-09'!D:D,0)} -> 7 | AB14: {=_xlfn.XLOOKUP($B14&AB$3,'25-09'!B:B&'25-09'!C:C,'25-09'!D:D,0)} -> 0 | AC14: {=_xlfn.XLOOKUP($B14&AC$3,'25-09'!B:B&'25-09'!C:C,'25-09'!D:D,0)} -> 0 | AD14: =SUM(AA14:AC14) -> 7 | AE14: {=_xlfn.XLOOKUP($B14&AE$3,'25-10'!B:B&'25-10'!C:C,'25-10'!D:D,0)} -> 37 | AF14: {=_xlfn.XLOOKUP($B14&AF$3,'25-10'!B:B&'25-10'!C:C,'25-10'!D:D,0)} -> 13 | AG14: {=_xlfn.XLOOKUP($B14&AG$3,'25-10'!B:B&'25-10'!C:C,'25-10'!D:D,0)} -> 0 | AH14: =SUM(AE14:AG14) -> 50 | AI14: {=_xlfn.XLOOKUP($B14&AI$3,'25-11'!B:B&'25-11'!C:C,'25-11'!D:D,0)} -> 15 | AJ14: {=_xlfn.XLOOKUP($B14&AJ$3,'25-11'!B:B&'25-11'!C:C,'25-11'!D:D,0)} -> 20 | AK14: {=_xlfn.XLOOKUP($B14&AK$3,'25-11'!B:B&'25-11'!C:C,'25-11'!D:D,0)} -> 0 | AL14: =SUM(AI14:AK14) -> 35 | AM14: {=_xlfn.XLOOKUP($B14&AM$3,'25-12'!B:B&'25-12'!C:C,'25-12'!D:D,0)} -> 33 | AN14: {=_xlfn.XLOOKUP($B14&AN$3,'25-12'!B:B&'25-12'!C:C,'25-12'!D:D,0)} -> 36 | AO14: {=_xlfn.XLOOKUP($B14&AO$3,'25-12'!B:B&'25-12'!C:C,'25-12'!D:D,0)} -> 0 | AP14: =SUM(AM14:AO14) -> 69 | AQ14: {=_xlfn.XLOOKUP($B14&AQ$3,'26-01'!B:B&'26-01'!C:C,'26-01'!D:D,0)} -> 19 | AR14: {=_xlfn.XLOOKUP($B14&AR$3,'26-01'!B:B&'26-01'!C:C,'26-01'!D:D,0)} -> 26 | AS14: {=_xlfn.XLOOKUP($B14&AS$3,'26-01'!B:B&'26-01'!C:C,'26-01'!D:D,0)} -> 0 | AT14: =SUM(AQ14:AS14) -> 45 | AU14: {=_xlfn.XLOOKUP($B14&AU$3,'26-02'!B:B&'26-02'!C:C,'26-02'!D:D,0)} -> 30 | AV14: {=_xlfn.XLOOKUP($B14&AV$3,'26-02'!B:B&'26-02'!C:C,'26-02'!D:D,0)} -> 6 | AW14: {=_xlfn.XLOOKUP($B14&AW$3,'26-02'!B:B&'26-02'!C:C,'26-02'!D:D,0)} -> 0 | AX14: =SUM(AU14:AW14) -> 36 | AY14: =SUM(AX14,AT14,AP14,AL14,AH14,AD14,Z14,V14,R14,N14,J14,F14) -> 242 | AZ14: =AVERAGE(AX14,AT14,AP14,AL14,AH14,AD14) -> 40.333333 | BA14: =AVERAGE(AX14,AT14,AP14,AL14,AH14,AD14,Z14,V14,R14,N14,J14) -> 22 | BB14: =AVERAGE(AU14,AQ14,AM14,AI14,AE14,AA14) -> 23.5 | BC14: =AVERAGE(AU14,AQ14,AM14,AI14,AE14,AA14,W14,S14,O14,K14,G14) -> 12.818182 | BD14: =BK14 -> 16 | BE14: =AVERAGE(AV14,AR14,AN14,AJ14,AF14,AB14) -> 16.833333 | BF14: =AVERAGE(AV14,AR14,AN14,AJ14,AF14,AB14) -> 16.833333 | BG14: =BL14 -> 32 | BH14: =AVERAGE(AW14,AS14,AO14,AK14,AG14,AC14) -> 0 | BI14: =AVERAGE(AW14,AS14,AO14,AK14,AG14,AC14) -> 0 | BJ14: =BM14 -> 25 | BK14: =_xlfn.XLOOKUP($B14,'BCS-1-KLG'!C:C,'BCS-1-KLG'!E:E,0) -> 16 | BL14: =_xlfn.XLOOKUP($B14,'BCS-2 PIK 2'!C:C,'BCS-2 PIK 2'!E:E,0) -> 32 | BM14: =_xlfn.XLOOKUP($B14,'BCS HO'!C:C,'BCS HO'!E:E,0) -> 25 | BN14: =SUM(BK14:BM14) -> 73
A15: 12 | B15: CASTROL Brake Fluid DOT 3 - 500ml | C15: {=_xlfn.XLOOKUP($B15&$C$3,'25-03'!B:B&'25-03'!C:C,'25-03'!D:D,0)} -> 4 | D15: {=_xlfn.XLOOKUP($B15&$D$3,'25-03'!B:B&'25-03'!C:C,'25-03'!D:D,0)} -> 0 | E15: {=_xlfn.XLOOKUP($B15&E$3,'25-03'!B:B&'25-03'!C:C,'25-03'!D:D,0)} -> 0 | F15: =SUM(C15:E15) -> 4 | G15: {=_xlfn.XLOOKUP($B15&G$3,'25-04'!B:B&'25-04'!C:C,'25-04'!D:D,0)} -> 0 | H15: {=_xlfn.XLOOKUP($B15&H$3,'25-04'!B:B&'25-04'!C:C,'25-04'!D:D,0)} -> 0 | I15: {=_xlfn.XLOOKUP($B15&I$3,'25-04'!B:B&'25-04'!C:C,'25-04'!D:D,0)} -> 0 | J15: =SUM(G15:I15) -> 0 | K15: {=_xlfn.XLOOKUP($B15&K$3,'25-05'!B:B&'25-05'!C:C,'25-05'!D:D,0)} -> 27 | L15: {=_xlfn.XLOOKUP($B15&L$3,'25-05'!B:B&'25-05'!C:C,'25-05'!D:D,0)} -> 0 | M15: {=_xlfn.XLOOKUP($B15&M$3,'25-05'!B:B&'25-05'!C:C,'25-05'!D:D,0)} -> 0 | N15: =SUM(K15:M15) -> 27 | O15: {=_xlfn.XLOOKUP($B15&O$3,'26-06'!B:B&'26-06'!C:C,'26-06'!D:D,0)} -> 71 | P15: {=_xlfn.XLOOKUP($B15&P$3,'26-06'!B:B&'26-06'!C:C,'26-06'!D:D,0)} -> 0 | Q15: {=_xlfn.XLOOKUP($B15&Q$3,'26-06'!B:B&'26-06'!C:C,'26-06'!D:D,0)} -> 0 | R15: =SUM(O15:Q15) -> 71 | S15: {=_xlfn.XLOOKUP($B15&S$3,'25-07'!B:B&'25-07'!C:C,'25-07'!D:D,0)} -> 97 | T15: {=_xlfn.XLOOKUP($B15&T$3,'25-07'!B:B&'25-07'!C:C,'25-07'!D:D,0)} -> 0 | U15: {=_xlfn.XLOOKUP($B15&U$3,'25-07'!B:B&'25-07'!C:C,'25-07'!D:D,0)} -> 0 | V15: =SUM(S15:U15) -> 97 | W15: {=_xlfn.XLOOKUP($B15&W$3,'25-08'!B:B&'25-08'!C:C,'25-08'!D:D,0)} -> 46 | X15: {=_xlfn.XLOOKUP($B15&X$3,'25-08'!B:B&'25-08'!C:C,'25-08'!D:D,0)} -> 0 | Y15: {=_xlfn.XLOOKUP($B15&Y$3,'25-08'!B:B&'25-08'!C:C,'25-08'!D:D,0)} -> 0 | Z15: =SUM(W15:Y15) -> 46 | AA15: {=_xlfn.XLOOKUP($B15&AA$3,'25-09'!B:B&'25-09'!C:C,'25-09'!D:D,0)} -> 62 | AB15: {=_xlfn.XLOOKUP($B15&AB$3,'25-09'!B:B&'25-09'!C:C,'25-09'!D:D,0)} -> 2 | AC15: {=_xlfn.XLOOKUP($B15&AC$3,'25-09'!B:B&'25-09'!C:C,'25-09'!D:D,0)} -> 0 | AD15: =SUM(AA15:AC15) -> 64 | AE15: {=_xlfn.XLOOKUP($B15&AE$3,'25-10'!B:B&'25-10'!C:C,'25-10'!D:D,0)} -> 2 | AF15: {=_xlfn.XLOOKUP($B15&AF$3,'25-10'!B:B&'25-10'!C:C,'25-10'!D:D,0)} -> 26 | AG15: {=_xlfn.XLOOKUP($B15&AG$3,'25-10'!B:B&'25-10'!C:C,'25-10'!D:D,0)} -> 0 | AH15: =SUM(AE15:AG15) -> 28 | AI15: {=_xlfn.XLOOKUP($B15&AI$3,'25-11'!B:B&'25-11'!C:C,'25-11'!D:D,0)} -> 13 | AJ15: {=_xlfn.XLOOKUP($B15&AJ$3,'25-11'!B:B&'25-11'!C:C,'25-11'!D:D,0)} -> 56 | AK15: {=_xlfn.XLOOKUP($B15&AK$3,'25-11'!B:B&'25-11'!C:C,'25-11'!D:D,0)} -> 0 | AL15: =SUM(AI15:AK15) -> 69 | AM15: {=_xlfn.XLOOKUP($B15&AM$3,'25-12'!B:B&'25-12'!C:C,'25-12'!D:D,0)} -> 14 | AN15: {=_xlfn.XLOOKUP($B15&AN$3,'25-12'!B:B&'25-12'!C:C,'25-12'!D:D,0)} -> 63 | AO15: {=_xlfn.XLOOKUP($B15&AO$3,'25-12'!B:B&'25-12'!C:C,'25-12'!D:D,0)} -> 0 | AP15: =SUM(AM15:AO15) -> 77 | AQ15: {=_xlfn.XLOOKUP($B15&AQ$3,'26-01'!B:B&'26-01'!C:C,'26-01'!D:D,0)} -> 22 | AR15: {=_xlfn.XLOOKUP($B15&AR$3,'26-01'!B:B&'26-01'!C:C,'26-01'!D:D,0)} -> 47 | AS15: {=_xlfn.XLOOKUP($B15&AS$3,'26-01'!B:B&'26-01'!C:C,'26-01'!D:D,0)} -> 0 | AT15: =SUM(AQ15:AS15) -> 69 | AU15: {=_xlfn.XLOOKUP($B15&AU$3,'26-02'!B:B&'26-02'!C:C,'26-02'!D:D,0)} -> 34 | AV15: {=_xlfn.XLOOKUP($B15&AV$3,'26-02'!B:B&'26-02'!C:C,'26-02'!D:D,0)} -> 60 | AW15: {=_xlfn.XLOOKUP($B15&AW$3,'26-02'!B:B&'26-02'!C:C,'26-02'!D:D,0)} -> 0 | AX15: =SUM(AU15:AW15) -> 94 | AY15: =SUM(AX15,AT15,AP15,AL15,AH15,AD15,Z15,V15,R15,N15,J15,F15) -> 646 | AZ15: =AVERAGE(AX15,AT15,AP15,AL15,AH15,AD15) -> 66.833333 | BA15: =AVERAGE(AX15,AT15,AP15,AL15,AH15,AD15,Z15,V15,R15,N15,J15) -> 58.363636 | BB15: =AVERAGE(AU15,AQ15,AM15,AI15,AE15,AA15) -> 24.5 | BC15: =AVERAGE(AU15,AQ15,AM15,AI15,AE15,AA15,W15,S15,O15,K15,G15) -> 35.272727 | BD15: =BK15 -> 0 | BE15: =AVERAGE(AV15,AR15,AN15,AJ15,AF15,AB15) -> 42.333333 | BF15: =AVERAGE(AV15,AR15,AN15,AJ15,AF15,AB15) -> 42.333333 | BG15: =BL15 -> 1 | BH15: =AVERAGE(AW15,AS15,AO15,AK15,AG15,AC15) -> 0 | BI15: =AVERAGE(AW15,AS15,AO15,AK15,AG15,AC15) -> 0 | BJ15: =BM15 -> 0 | BK15: =_xlfn.XLOOKUP($B15,'BCS-1-KLG'!C:C,'BCS-1-KLG'!E:E,0) -> 0 | BL15: =_xlfn.XLOOKUP($B15,'BCS-2 PIK 2'!C:C,'BCS-2 PIK 2'!E:E,0) -> 1 | BM15: =_xlfn.XLOOKUP($B15,'BCS HO'!C:C,'BCS HO'!E:E,0) -> 0 | BN15: =SUM(BK15:BM15) -> 1
... A22: 19 | B22: PRESTONE Brake Fluid DOT 4 - 300ml | C22: {=_xlfn.XLOOKUP($B22&$C$3,'25-03'!B:B&'25-03'!C:C,'25-03'!D:D,0)} -> 0 | D22: {=_xlfn.XLOOKUP($B22&$D$3,'25-03'!B:B&'25-03'!C:C,'25-03'!D:D,0)} -> 0 | E22: {=_xlfn.XLOOKUP($B22&E$3,'25-03'!B:B&'25-03'!C:C,'25-03'!D:D,0)} -> 0 | F22: =SUM(C22:E22) -> 0 | G22: {=_xlfn.XLOOKUP($B22&G$3,'25-04'!B:B&'25-04'!C:C,'25-04'!D:D,0)} -> 0 | H22: {=_xlfn.XLOOKUP($B22&H$3,'25-04'!B:B&'25-04'!C:C,'25-04'!D:D,0)} -> 0 | I22: {=_xlfn.XLOOKUP($B22&I$3,'25-04'!B:B&'25-04'!C:C,'25-04'!D:D,0)} -> 0 | J22: =SUM(G22:I22) -> 0 | K22: {=_xlfn.XLOOKUP($B22&K$3,'25-05'!B:B&'25-05'!C:C,'25-05'!D:D,0)} -> 0 | L22: {=_xlfn.XLOOKUP($B22&L$3,'25-05'!B:B&'25-05'!C:C,'25-05'!D:D,0)} -> 0 | M22: {=_xlfn.XLOOKUP($B22&M$3,'25-05'!B:B&'25-05'!C:C,'25-05'!D:D,0)} -> 0 | N22: =SUM(K22:M22) -> 0 | O22: {=_xlfn.XLOOKUP($B22&O$3,'26-06'!B:B&'26-06'!C:C,'26-06'!D:D,0)} -> 0 | P22: {=_xlfn.XLOOKUP($B22&P$3,'26-06'!B:B&'26-06'!C:C,'26-06'!D:D,0)} -> 0 | Q22: {=_xlfn.XLOOKUP($B22&Q$3,'26-06'!B:B&'26-06'!C:C,'26-06'!D:D,0)} -> 0 | R22: =SUM(O22:Q22) -> 0 | S22: {=_xlfn.XLOOKUP($B22&S$3,'25-07'!B:B&'25-07'!C:C,'25-07'!D:D,0)} -> 0 | T22: {=_xlfn.XLOOKUP($B22&T$3,'25-07'!B:B&'25-07'!C:C,'25-07'!D:D,0)} -> 0 | U22: {=_xlfn.XLOOKUP($B22&U$3,'25-07'!B:B&'25-07'!C:C,'25-07'!D:D,0)} -> 0 | V22: =SUM(S22:U22) -> 0 | W22: {=_xlfn.XLOOKUP($B22&W$3,'25-08'!B:B&'25-08'!C:C,'25-08'!D:D,0)} -> 0 | X22: {=_xlfn.XLOOKUP($B22&X$3,'25-08'!B:B&'25-08'!C:C,'25-08'!D:D,0)} -> 0 | Y22: {=_xlfn.XLOOKUP($B22&Y$3,'25-08'!B:B&'25-08'!C:C,'25-08'!D:D,0)} -> 0 | Z22: =SUM(W22:Y22) -> 0 | AA22: {=_xlfn.XLOOKUP($B22&AA$3,'25-09'!B:B&'25-09'!C:C,'25-09'!D:D,0)} -> 0 | AB22: {=_xlfn.XLOOKUP($B22&AB$3,'25-09'!B:B&'25-09'!C:C,'25-09'!D:D,0)} -> 0 | AC22: {=_xlfn.XLOOKUP($B22&AC$3,'25-09'!B:B&'25-09'!C:C,'25-09'!D:D,0)} -> 0 | AD22: =SUM(AA22:AC22) -> 0 | AE22: {=_xlfn.XLOOKUP($B22&AE$3,'25-10'!B:B&'25-10'!C:C,'25-10'!D:D,0)} -> 0 | AF22: {=_xlfn.XLOOKUP($B22&AF$3,'25-10'!B:B&'25-10'!C:C,'25-10'!D:D,0)} -> 0 | AG22: {=_xlfn.XLOOKUP($B22&AG$3,'25-10'!B:B&'25-10'!C:C,'25-10'!D:D,0)} -> 0 | AH22: =SUM(AE22:AG22) -> 0 | AI22: {=_xlfn.XLOOKUP($B22&AI$3,'25-11'!B:B&'25-11'!C:C,'25-11'!D:D,0)} -> 0 | AJ22: {=_xlfn.XLOOKUP($B22&AJ$3,'25-11'!B:B&'25-11'!C:C,'25-11'!D:D,0)} -> 0 | AK22: {=_xlfn.XLOOKUP($B22&AK$3,'25-11'!B:B&'25-11'!C:C,'25-11'!D:D,0)} -> 0 | AL22: =SUM(AI22:AK22) -> 0 | AM22: {=_xlfn.XLOOKUP($B22&AM$3,'25-12'!B:B&'25-12'!C:C,'25-12'!D:D,0)} -> 0 | AN22: {=_xlfn.XLOOKUP($B22&AN$3,'25-12'!B:B&'25-12'!C:C,'25-12'!D:D,0)} -> 0 | AO22: {=_xlfn.XLOOKUP($B22&AO$3,'25-12'!B:B&'25-12'!C:C,'25-12'!D:D,0)} -> 0 | AP22: =SUM(AM22:AO22) -> 0 | AQ22: {=_xlfn.XLOOKUP($B22&AQ$3,'26-01'!B:B&'26-01'!C:C,'26-01'!D:D,0)} -> 0 | AR22: {=_xlfn.XLOOKUP($B22&AR$3,'26-01'!B:B&'26-01'!C:C,'26-01'!D:D,0)} -> 0 | AS22: {=_xlfn.XLOOKUP($B22&AS$3,'26-01'!B:B&'26-01'!C:C,'26-01'!D:D,0)} -> 0 | AT22: =SUM(AQ22:AS22) -> 0 | AU22: {=_xlfn.XLOOKUP($B22&AU$3,'26-02'!B:B&'26-02'!C:C,'26-02'!D:D,0)} -> 0 | AV22: {=_xlfn.XLOOKUP($B22&AV$3,'26-02'!B:B&'26-02'!C:C,'26-02'!D:D,0)} -> 0 | AW22: {=_xlfn.XLOOKUP($B22&AW$3,'26-02'!B:B&'26-02'!C:C,'26-02'!D:D,0)} -> 0 | AX22: =SUM(AU22:AW22) -> 0 | AY22: =SUM(AX22,AT22,AP22,AL22,AH22,AD22,Z22,V22,R22,N22,J22,F22) -> 0 | AZ22: =AVERAGE(AX22,AT22,AP22,AL22,AH22,AD22) -> 0 | BA22: =AVERAGE(AX22,AT22,AP22,AL22,AH22,AD22,Z22,V22,R22,N22,J22) -> 0 | BB22: =AVERAGE(AU22,AQ22,AM22,AI22,AE22,AA22) -> 0 | BC22: =AVERAGE(AU22,AQ22,AM22,AI22,AE22,AA22,W22,S22,O22,K22,G22) -> 0 | BD22: =BK22 -> 0 | BE22: =AVERAGE(AV22,AR22,AN22,AJ22,AF22,AB22) -> 0 | BF22: =AVERAGE(AV22,AR22,AN22,AJ22,AF22,AB22) -> 0 | BG22: =BL22 -> 0 | BH22: =AVERAGE(AW22,AS22,AO22,AK22,AG22,AC22) -> 0 | BI22: =AVERAGE(AW22,AS22,AO22,AK22,AG22,AC22) -> 0 | BJ22: =BM22 -> 0 | BK22: =_xlfn.XLOOKUP($B22,'BCS-1-KLG'!C:C,'BCS-1-KLG'!E:E,0) -> 0 | BL22: =_xlfn.XLOOKUP($B22,'BCS-2 PIK 2'!C:C,'BCS-2 PIK 2'!E:E,0) -> 0 | BM22: =_xlfn.XLOOKUP($B22,'BCS HO'!C:C,'BCS HO'!E:E,0) -> 0 | BN22: =SUM(BK22:BM22) -> 0

Sheet 25-03
B1: X-MOTORS INTERNATIONAL GROUP | C1: X-MOTORS INTERNATIONAL GROUP | D1: X-MOTORS INTERNATIONAL GROUP | E1: X-MOTORS INTERNATIONAL GROUP
B2: Item Sales per Warehouse | C2: Item Sales per Warehouse | D2: Item Sales per Warehouse | E2: Item Sales per Warehouse
B3: From 01 Mar 2025 until 31 Mar 2025 | C3: From 01 Mar 2025 until 31 Mar 2025 | D3: From 01 Mar 2025 until 31 Mar 2025 | E3: From 01 Mar 2025 until 31 Mar 2025
B4: Branch : [All Branch] | C4: Branch : [All Branch] | D4: Branch : [All Branch] | E4: Branch : [All Branch]
B5: Item Name | C5: Warehouse | D5: Quantity | E5: Sales
B6: BATTERY AMARON 580-24C MF | C6: BCS-1 KELAPA GADING--Central Warehouse | D6: 1 | E6: 2702703
B7: BATTERY AMARON 580-24C MF | C7: Total Warehouse | D7: 1 | E7: 2702703
B8: BOSCH Battery MF Blue 55D23L 12V-60Ah | C8: BCS-1 KELAPA GADING--Central Warehouse | D8: 1 | E8: 1100100
B9: BOSCH Battery MF Blue 55D23L 12V-60Ah | C9: Total Warehouse | D9: 1 | E9: 1100100
B10: BOSCH Battery MF Blue NS60L 46B24L 12V-42Ah | C10: BCS-1 KELAPA GADING--Central Warehouse | D10: 1 | E10: 900880
B11: BOSCH Battery MF Blue NS60L 46B24L 12V-42Ah | C11: Total Warehouse | D11: 1 | E11: 900880
B12: BOSCH Cabin Filter AP-H09 | C12: BCS-1 KELAPA GADING--Central Warehouse | D12: 1 | E12: 228800
B13: BOSCH Cabin Filter AP-H09 | C13: Total Warehouse | D13: 1 | E13: 228800
B14: BOSCH Fuel Filter D 6100 | C14: BCS-1 KELAPA GADING--Central Warehouse | D14: 1 | E14: 90000
B15: BOSCH Fuel Filter D 6100 | C15: Total Warehouse | D15: 1 | E15: 90000
B16: BOSCH Light Bulb H1 12V 55W -P14.5s ECO | C16: BCS-1 KELAPA GADING--Central Warehouse | D16: 1 | E16: 85700
B17: BOSCH Light Bulb H1 12V 55W -P14.5s ECO | C17: Total Warehouse | D17: 1 | E17: 85700
B19: ACCURATE Accounting System Report | C19: ACCURATE Accounting System Report | D19: ACCURATE Accounting System Report | E19: ACCURATE Accounting System Report
B21: Printed on 2 February 2026 - 09:52 | C21: Printed on 2 February 2026 - 09:52 | D21: Printed on 2 February 2026 - 09:52 | E21: Printed on 2 February 2026 - 09:52
B22: Page Break 1 | C22: Page Break 1 | D22: Page Break 1 | E22: Page Break 1
B23: X-MOTORS INTERNATIONAL GROUP | C23: X-MOTORS INTERNATIONAL GROUP | D23: X-MOTORS INTERNATIONAL GROUP | E23: X-MOTORS INTERNATIONAL GROUP
B24: Item Sales per Warehouse | C24: Item Sales per Warehouse | D24: Item Sales per Warehouse | E24: Item Sales per Warehouse
B25: From 01 Mar 2025 until 31 Mar 2025 | C25: From 01 Mar 2025 until 31 Mar 2025 | D25: From 01 Mar 2025 until 31 Mar 2025 | E25: From 01 Mar 2025 until 31 Mar 2025
B26: Branch : [All Branch] | C26: Branch : [All Branch] | D26: Branch : [All Branch] | E26: Branch : [All Branch]
B27: Item Name | C27: Warehouse | D27: Quantity | E27: Sales
B28: BOSCH Light Bulb H4 12V 100/90W -P43t ECO | C28: BCS-1 KELAPA GADING--Central Warehouse | D28: 1 | E28: 31700
B29: BOSCH Light Bulb H4 12V 100/90W -P43t ECO | C29: Total Warehouse | D29: 1 | E29: 31700
B30: BOSCH Light Bulb H4 12V 60/55W -P43t Sportec Bright | C30: BCS-1 KELAPA GADING--Central Warehouse | D30: 1 | E30: 260100
B31: BOSCH Light Bulb H4 12V 60/55W -P43t Sportec Bright | C31: Total Warehouse | D31: 1 | E31: 260100
B32: BOSCH Oil Filter O 0126 | C32: BCS-1 KELAPA GADING--Central Warehouse | D32: 7 | E32: 0
B33: BOSCH Oil Filter O 0126 | C33: Total Warehouse | D33: 7 | E33: 0
B34: BOSCH Oil Filter O 0220 | C34: BCS-1 KELAPA GADING--Central Warehouse | D34: 5 | E34: 81600
B35: BOSCH Oil Filter O 0220 | C35: Total Warehouse | D35: 5 | E35: 81600
B36: BOSCH Oil Filter O 1001 | C36: BCS-1 KELAPA GADING--Central Warehouse | D36: 3 | E36: 0
B37: BOSCH Oil Filter O 1001 | C37: Total Warehouse | D37: 3 | E37: 0
B38: BOSCH Oil Filter O 1014 | C38: BCS-1 KELAPA GADING--Central Warehouse | D38: 8 | E38: 49700
B39: BOSCH Oil Filter O 1014 | C39: Total Warehouse | D39: 8 | E39: 49700
B41: ACCURATE Accounting System Report | C41: ACCURATE Accounting System Report | D41: ACCURATE Accounting System Report | E41: ACCURATE Accounting System Report
B43: Printed on 2 February 2026 - 09:52 | C43: Printed on 2 February 2026 - 09:52 | D43: Printed on 2 February 2026 - 09:52 | E43: Printed on 2 February 2026 - 09:52
B44: Page Break 2 | C44: Page Break 2 | D44: Page Break 2 | E44: Page Break 2
B45: X-MOTORS INTERNATIONAL GROUP | C45: X-MOTORS INTERNATIONAL GROUP | D45: X-MOTORS INTERNATIONAL GROUP | E45: X-MOTORS INTERNATIONAL GROUP
B46: Item Sales per Warehouse | C46: Item Sales per Warehouse | D46: Item Sales per Warehouse | E46: Item Sales per Warehouse
B47: From 01 Mar 2025 until 31 Mar 2025 | C47: From 01 Mar 2025 until 31 Mar 2025 | D47: From 01 Mar 2025 until 31 Mar 2025 | E47: From 01 Mar 2025 until 31 Mar 2025
B48: Branch : [All Branch] | C48: Branch : [All Branch] | D48: Branch : [All Branch] | E48: Branch : [All Branch]
B49: Item Name | C49: Warehouse | D49: Quantity | E49: Sales
B50: BOSCH Oil Filter O 1041 | C50: BCS-1 KELAPA GADING--Central Warehouse | D50: 8 | E50: 0
B51: BOSCH Oil Filter O 1041 | C51: Total Warehouse | D51: 8 | E51: 0
B52: BOSCH Oil Filter O 1042 | C52: BCS-1 KELAPA GADING--Central Warehouse | D52: 5 | E52: 50000
B53: BOSCH Oil Filter O 1042 | C53: Total Warehouse | D53: 5 | E53: 50000
B54: BOSCH Oil Filter O 1043 | C54: BCS-1 KELAPA GADING--Central Warehouse | D54: 1 | E54: 0
B55: BOSCH Oil Filter O 1043 | C55: Total Warehouse | D55: 1 | E55: 0
B56: BOSCH Spark Plug FR8DII33X - Iridium | C56: BCS-1 KELAPA GADING--Central Warehouse | D56: 4 | E56: 500480
B57: BOSCH Spark Plug FR8DII33X - Iridium | C57: Total Warehouse | D57: 4 | E57: 500480
B58: BOSCH Wiper Advantage 14 inch BA14 | C58: BCS-1 KELAPA GADING--Central Warehouse | D58: 2 | E58: 96250
B59: BOSCH Wiper Advantage 14 inch BA14 | C59: Total Warehouse | D59: 2 | E59: 96250
B60: BOSCH Wiper Advantage 16 inch BA16 | C60: BCS-1 KELAPA GADING--Central Warehouse | D60: 3 | E60: 144375
B61: BOSCH Wiper Advantage 16 inch BA16 | C61: Total Warehouse | D61: 3 | E61: 144375
B63: ACCURATE Accounting System Report | C63: ACCURATE Accounting System Report | D63: ACCURATE Accounting System Report | E63: ACCURATE Accounting System Report
B65: Printed on 2 February 2026 - 09:52 | C65: Printed on 2 February 2026 - 09:52 | D65: Printed on 2 February 2026 - 09:52 | E65: Printed on 2 February 2026 - 09:52
B66: Page Break 3 | C66: Page Break 3 | D66: Page Break 3 | E66: Page Break 3
B67: X-MOTORS INTERNATIONAL GROUP | C67: X-MOTORS INTERNATIONAL GROUP | D67: X-MOTORS INTERNATIONAL GROUP | E67: X-MOTORS INTERNATIONAL GROUP
B68: Item Sales per Warehouse | C68: Item Sales per Warehouse | D68: Item Sales per Warehouse | E68: Item Sales per Warehouse
B69: From 01 Mar 2025 until 31 Mar 2025 | C69: From 01 Mar 2025 until 31 Mar 2025 | D69: From 01 Mar 2025 until 31 Mar 2025 | E69: From 01 Mar 2025 until 31 Mar 2025
B70: Branch : [All Branch] | C70: Branch : [All Branch] | D70: Branch : [All Branch] | E70: Branch : [All Branch]
B71: Item Name | C71: Warehouse | D71: Quantity | E71: Sales
B72: BOSCH Wiper Advantage 20 inch BA20 | C72: BCS-1 KELAPA GADING--Central Warehouse | D72: 1 | E72: 54018
B73: BOSCH Wiper Advantage 20 inch BA20 | C73: Total Warehouse | D73: 1 | E73: 54018
B74: BOSCH Wiper Advantage 21 inch BA21 | C74: BCS-1 KELAPA GADING--Central Warehouse | D74: 1 | E74: 60893
B75: BOSCH Wiper Advantage 21 inch BA21 | C75: Total Warehouse | D75: 1 | E75: 60893
B76: BOSCH Wiper Advantage 22 inch BA22 | C76: BCS-1 KELAPA GADING--Central Warehouse | D76: 2 | E76: 137500
B77: BOSCH Wiper Advantage 22 inch BA22 | C77: Total Warehouse | D77: 2 | E77: 137500
B78: BOSCH Wiper Aerotwin Plus 15 inch AP380U | C78: BCS-1 KELAPA GADING--Central Warehouse | D78: 1 | E78: 105468.75
B79: BOSCH Wiper Aerotwin Plus 15 inch AP380U | C79: Total Warehouse | D79: 1 | E79: 105468.75
B80: BOSCH Wiper Aerotwin Retrofit 26 BBA650 | C80: BCS-1 KELAPA GADING--Central Warehouse | D80: 1 | E80: 158202.75
B81: BOSCH Wiper Aerotwin Retrofit 26 BBA650 | C81: Total Warehouse | D81: 1 | E81: 158202.75
B82: BOSCH Wiper Clear Advantage 14 inch BCA14 | C82: BCS-1 KELAPA GADING--Central Warehouse | D82: 3 | E82: 222135
B83: BOSCH Wiper Clear Advantage 14 inch BCA14 | C83: Total Warehouse | D83: 3 | E83: 222135
B85: ACCURATE Accounting System Report | C85: ACCURATE Accounting System Report | D85: ACCURATE Accounting System Report | E85: ACCURATE Accounting System Report
B87: Printed on 2 February 2026 - 09:52 | C87: Printed on 2 February 2026 - 09:52 | D87: Printed on 2 February 2026 - 09:52 | E87: Printed on 2 February 2026 - 09:52
B88: Page Break 4 | C88: Page Break 4 | D88: Page Break 4 | E88: Page Break 4
B89: X-MOTORS INTERNATIONAL GROUP | C89: X-MOTORS INTERNATIONAL GROUP | D89: X-MOTORS INTERNATIONAL GROUP | E89: X-MOTORS INTERNATIONAL GROUP
B90: Item Sales per Warehouse | C90: Item Sales per Warehouse | D90: Item Sales per Warehouse | E90: Item Sales per Warehouse
B91: From 01 Mar 2025 until 31 Mar 2025 | C91: From 01 Mar 2025 until 31 Mar 2025 | D91: From 01 Mar 2025 until 31 Mar 2025 | E91: From 01 Mar 2025 until 31 Mar 2025
B92: Branch : [All Branch] | C92: Branch : [All Branch] | D92: Branch : [All Branch] | E92: Branch : [All Branch]
B93: Item Name | C93: Warehouse | D93: Quantity | E93: Sales
B94: BOSCH Wiper Clear Advantage 16 inch BCA16 | C94: BCS-1 KELAPA GADING--Central Warehouse | D94: 18 | E94: 1332809
B95: BOSCH Wiper Clear Advantage 16 inch BCA16 | C95: Total Warehouse | D95: 18 | E95: 1332809
B96: BOSCH Wiper Clear Advantage 17 inch BCA17 | C96: BCS-1 KELAPA GADING--Central Warehouse | D96: 1 | E96: 86134
B97: BOSCH Wiper Clear Advantage 17 inch BCA17 | C97: Total Warehouse | D97: 1 | E97: 86134
B98: BOSCH Wiper Clear Advantage 18 inch BCA18 | C98: BCS-1 KELAPA GADING--Central Warehouse | D98: 4 | E98: 344536
B99: BOSCH Wiper Clear Advantage 18 inch BCA18 | C99: Total Warehouse | D99: 4 | E99: 344536
B100: BOSCH Wiper Clear Advantage 19 inch BCA19 | C100: BCS-1 KELAPA GADING--Central Warehouse | D100: 1 | E100: 91339
B101: BOSCH Wiper Clear Advantage 19 inch BCA19 | C101: Total Warehouse | D101: 1 | E101: 91339
B102: BOSCH Wiper Clear Advantage 21 inch BCA21 | C102: BCS-1 KELAPA GADING--Central Warehouse | D102: 2 | E102: 184642
B103: BOSCH Wiper Clear Advantage 21 inch BCA21 | C103: Total Warehouse | D103: 2 | E103: 184642
B104: BOSCH Wiper Clear Advantage 22 inch BCA22 | C104: BCS-1 KELAPA GADING--Central Warehouse | D104: 14 | E104: 1388745
B105: BOSCH Wiper Clear Advantage 22 inch BCA22 | C105: Total Warehouse | D105: 14 | E105: 1388745
B107: ACCURATE Accounting System Report | C107: ACCURATE Accounting System Report | D107: ACCURATE Accounting System Report | E107: ACCURATE Accounting System Report
B109: Printed on 2 February 2026 - 09:52 | C109: Printed on 2 February 2026 - 09:52 | D109: Printed on 2 February 2026 - 09:52 | E109: Printed on 2 February 2026 - 09:52
B110: Page Break 5 | C110: Page Break 5 | D110: Page Break 5 | E110: Page Break 5
...

Sheet 25-04
B1: X-MOTORS INTERNATIONAL GROUP | C1: X-MOTORS INTERNATIONAL GROUP | D1: X-MOTORS INTERNATIONAL GROUP | E1: X-MOTORS INTERNATIONAL GROUP
B2: Item Sales per Warehouse | C2: Item Sales per Warehouse | D2: Item Sales per Warehouse | E2: Item Sales per Warehouse
B3: From 01 Apr 2025 until 30 Apr 2025 | C3: From 01 Apr 2025 until 30 Apr 2025 | D3: From 01 Apr 2025 until 30 Apr 2025 | E3: From 01 Apr 2025 until 30 Apr 2025
B4: Branch : [All Branch] | C4: Branch : [All Branch] | D4: Branch : [All Branch] | E4: Branch : [All Branch]
B5: Item Name | C5: Warehouse | D5: Quantity | E5: Sales
B6: BOSCH Air Filter A 2666 | C6: BCS-1 KELAPA GADING--Central Warehouse | D6: 2 | E6: 227600
B7: BOSCH Air Filter A 2666 | C7: Total Warehouse | D7: 2 | E7: 227600
B8: BOSCH Air Filter S 0018 | D8: 1 | E8: 78000
B9: BOSCH Air Filter S 0018 | C9: Total Warehouse | D9: 1 | E9: 78000
B10: BOSCH Battery MF Blue NS40ZL 40B19L 12V | C10: BCS-1 KELAPA GADING--Central Warehouse | D10: 2 | E10: 2058400
B11: BOSCH Battery MF Blue NS40ZL 40B19L 12V | C11: Total Warehouse | D11: 2 | E11: 2058400
B12: BOSCH Battery MF Blue NS60L 46B24L 12V-42Ah | C12: BCS-1 KELAPA GADING--Central Warehouse | D12: 1 | E12: 1126100
B13: BOSCH Battery MF Blue NS60L 46B24L 12V-42Ah | C13: Total Warehouse | D13: 1 | E13: 1126100
B14: BOSCH Battery MF Blue NS60LS 46B24LS 12V-42Ah | C14: BCS-1 KELAPA GADING--Central Warehouse | D14: 1 | E14: 1126100
B15: BOSCH Battery MF Blue NS60LS 46B24LS 12V-42Ah | C15: Total Warehouse | D15: 1 | E15: 1126100
B16: BOSCH CABIN FILTER 0986AF7004 | C16: BCS-1 KELAPA GADING--Central Warehouse | D16: 1 | E16: 228800
B17: BOSCH CABIN FILTER 0986AF7004 | C17: Total Warehouse | D17: 1 | E17: 228800
B18: BOSCH CABIN FILTER 0986AF7011 | C18: BCS-1 KELAPA GADING--Central Warehouse | D18: 1 | E18: 228800
B19: BOSCH CABIN FILTER 0986AF7011 | C19: Total Warehouse | D19: 1 | E19: 228800
B21: ACCURATE Accounting System Report | C21: ACCURATE Accounting System Report | D21: ACCURATE Accounting System Report | E21: ACCURATE Accounting System Report
B23: Printed on 2 February 2026 - 09:52 | C23: Printed on 2 February 2026 - 09:52 | D23: Printed on 2 February 2026 - 09:52 | E23: Printed on 2 February 2026 - 09:52
B24: Page Break 1 | C24: Page Break 1 | D24: Page Break 1 | E24: Page Break 1
B25: X-MOTORS INTERNATIONAL GROUP | C25: X-MOTORS INTERNATIONAL GROUP | D25: X-MOTORS INTERNATIONAL GROUP | E25: X-MOTORS INTERNATIONAL GROUP
B26: Item Sales per Warehouse | C26: Item Sales per Warehouse | D26: Item Sales per Warehouse | E26: Item Sales per Warehouse
B27: From 01 Apr 2025 until 30 Apr 2025 | C27: From 01 Apr 2025 until 30 Apr 2025 | D27: From 01 Apr 2025 until 30 Apr 2025 | E27: From 01 Apr 2025 until 30 Apr 2025
B28: Branch : [All Branch] | C28: Branch : [All Branch] | D28: Branch : [All Branch] | E28: Branch : [All Branch]
B29: Item Name | C29: Warehouse | D29: Quantity | E29: Sales
B30: BOSCH Cabin Filter AP-T07 | D30: 1 | E30: 199000
B31: BOSCH Cabin Filter AP-T07 | C31: Total Warehouse | D31: 1 | E31: 199000
B32: BOSCH Fuel Filter D 6100 | C32: BCS-1 KELAPA GADING--Central Warehouse | D32: 1 | E32: 90000
B33: BOSCH Fuel Filter D 6100 | C33: Total Warehouse | D33: 1 | E33: 90000
B34: BOSCH HORN EC12C STRIDER | C34: BCS-1 KELAPA GADING--Central Warehouse | D34: 1 | E34: 147200
B35: BOSCH HORN EC12C STRIDER | D35: 1 | E35: 184000
B36: BOSCH HORN EC12C STRIDER | C36: Total Warehouse | D36: 2 | E36: 331200
B37: BOSCH Light Bulb H4 12V 100/90W -P43t ECO | C37: BCS-1 KELAPA GADING--Central Warehouse | D37: 6 | E37: 773800
B38: BOSCH Light Bulb H4 12V 100/90W -P43t ECO | C38: Total Warehouse | D38: 6 | E38: 773800
B39: BOSCH Light Bulb P21W 12V 21W -BA15s Auxiliary | D39: 1 | E39: 13514
B40: BOSCH Light Bulb P21W 12V 21W -BA15s Auxiliary | C40: Total Warehouse | D40: 1 | E40: 13514
B41: BOSCH Light Bulb W21W 12V 21W -W3x16d ECO Auxiliary | C41: BCS-1 KELAPA GADING--Central Warehouse | D41: 1 | E41: 13514
B42: BOSCH Light Bulb W21W 12V 21W -W3x16d ECO Auxiliary | C42: Total Warehouse | D42: 1 | E42: 13514
B43: BOSCH Light Bulb W5W 12V 5W -W2,1x9,5d ECO Auxiliary | D43: 1 | E43: 9910
B44: BOSCH Light Bulb W5W 12V 5W -W2,1x9,5d ECO Auxiliary | C44: Total Warehouse | D44: 1 | E44: 9910
B45: BOSCH Oil Filter O 0126 | C45: BCS-1 KELAPA GADING--Central Warehouse | D45: 2 | E45: 43000
B47: ACCURATE Accounting System Report | C47: ACCURATE Accounting System Report | D47: ACCURATE Accounting System Report | E47: ACCURATE Accounting System Report
B49: Printed on 2 February 2026 - 09:52 | C49: Printed on 2 February 2026 - 09:52 | D49: Printed on 2 February 2026 - 09:52 | E49: Printed on 2 February 2026 - 09:52
B50: Page Break 2 | C50: Page Break 2 | D50: Page Break 2 | E50: Page Break 2
B51: X-MOTORS INTERNATIONAL GROUP | C51: X-MOTORS INTERNATIONAL GROUP | D51: X-MOTORS INTERNATIONAL GROUP | E51: X-MOTORS INTERNATIONAL GROUP
B52: Item Sales per Warehouse | C52: Item Sales per Warehouse | D52: Item Sales per Warehouse | E52: Item Sales per Warehouse
B53: From 01 Apr 2025 until 30 Apr 2025 | C53: From 01 Apr 2025 until 30 Apr 2025 | D53: From 01 Apr 2025 until 30 Apr 2025 | E53: From 01 Apr 2025 until 30 Apr 2025
B54: Branch : [All Branch] | C54: Branch : [All Branch] | D54: Branch : [All Branch] | E54: Branch : [All Branch]
B55: Item Name | C55: Warehouse | D55: Quantity | E55: Sales
B56: BOSCH Oil Filter O 0126 | D56: 1 | E56: 43000
B57: BOSCH Oil Filter O 0126 | C57: Total Warehouse | D57: 3 | E57: 86000
B58: BOSCH Oil Filter O 0220 | C58: BCS-1 KELAPA GADING--Central Warehouse | D58: 2 | E58: 629730
B59: BOSCH Oil Filter O 0220 | D59: 4 | E59: 169800
B60: BOSCH Oil Filter O 0220 | C60: Total Warehouse | D60: 6 | E60: 799530
B61: BOSCH Oil Filter O 1014 | D61: 3 | E61: 105200
B62: BOSCH Oil Filter O 1014 | C62: Total Warehouse | D62: 3 | E62: 105200
B63: BOSCH Oil Filter O 1041 | C63: BCS-1 KELAPA GADING--Central Warehouse | D63: 1 | E63: 0
B64: BOSCH Oil Filter O 1041 | D64: 6 | E64: 299189
B65: BOSCH Oil Filter O 1041 | C65: Total Warehouse | D65: 7 | E65: 299189
B66: BOSCH Oil Filter O 1042 | C66: BCS-1 KELAPA GADING--Central Warehouse | D66: 1 | E66: 50000
B67: BOSCH Oil Filter O 1042 | D67: 2 | E67: 56000
B68: BOSCH Oil Filter O 1042 | C68: Total Warehouse | D68: 3 | E68: 106000
B69: BOSCH Oil Filter O 1106 | D69: 1 | E69: 49700
B70: BOSCH Oil Filter O 1106 | C70: Total Warehouse | D70: 1 | E70: 49700
B71: BOSCH Oil Filter P 9122 | D71: 1 | E71: 208389
B72: BOSCH Oil Filter P 9122 | C72: Total Warehouse | D72: 1 | E72: 208389
B74: ACCURATE Accounting System Report | C74: ACCURATE Accounting System Report | D74: ACCURATE Accounting System Report | E74: ACCURATE Accounting System Report
B76: Printed on 2 February 2026 - 09:52 | C76: Printed on 2 February 2026 - 09:52 | D76: Printed on 2 February 2026 - 09:52 | E76: Printed on 2 February 2026 - 09:52
B77: Page Break 3 | C77: Page Break 3 | D77: Page Break 3 | E77: Page Break 3
B78: X-MOTORS INTERNATIONAL GROUP | C78: X-MOTORS INTERNATIONAL GROUP | D78: X-MOTORS INTERNATIONAL GROUP | E78: X-MOTORS INTERNATIONAL GROUP
B79: Item Sales per Warehouse | C79: Item Sales per Warehouse | D79: Item Sales per Warehouse | E79: Item Sales per Warehouse
B80: From 01 Apr 2025 until 30 Apr 2025 | C80: From 01 Apr 2025 until 30 Apr 2025 | D80: From 01 Apr 2025 until 30 Apr 2025 | E80: From 01 Apr 2025 until 30 Apr 2025
B81: Branch : [All Branch] | C81: Branch : [All Branch] | D81: Branch : [All Branch] | E81: Branch : [All Branch]
B82: Item Name | C82: Warehouse | D82: Quantity | E82: Sales
B83: BOSCH Spark Plug FR8MII33X - Iridium | C83: BCS-1 KELAPA GADING--Central Warehouse | D83: 4 | E83: 138560
B84: BOSCH Spark Plug FR8MII33X - Iridium | C84: Total Warehouse | D84: 4 | E84: 138560
B85: BOSCH Wiper Advantage 14 inch BA14 | C85: BCS-1 KELAPA GADING--Central Warehouse | D85: 5 | E85: 266545
B86: BOSCH Wiper Advantage 14 inch BA14 | C86: Total Warehouse | D86: 5 | E86: 266545
B87: BOSCH Wiper Advantage 16 inch BA16 | C87: BCS-1 KELAPA GADING--Central Warehouse | D87: 4 | E87: 270260
B88: BOSCH Wiper Advantage 16 inch BA16 | D88: 1 | E88: 38500
B89: BOSCH Wiper Advantage 16 inch BA16 | C89: Total Warehouse | D89: 5 | E89: 308760
B90: BOSCH Wiper Advantage 17 inch BA17 | C90: BCS-1 KELAPA GADING--Central Warehouse | D90: 1 | E90: 51562
B91: BOSCH Wiper Advantage 17 inch BA17 | C91: Total Warehouse | D91: 1 | E91: 51562
B92: BOSCH Wiper Advantage 18 inch BA18 | C92: BCS-1 KELAPA GADING--Central Warehouse | D92: 2 | E92: 103124
B93: BOSCH Wiper Advantage 18 inch BA18 | C93: Total Warehouse | D93: 2 | E93: 103124
B94: BOSCH Wiper Advantage 20 inch BA20 | C94: BCS-1 KELAPA GADING--Central Warehouse | D94: 2 | E94: 108036
B95: BOSCH Wiper Advantage 20 inch BA20 | D95: 1 | E95: 43215
B96: BOSCH Wiper Advantage 20 inch BA20 | C96: Total Warehouse | D96: 3 | E96: 151251
B98: ACCURATE Accounting System Report | C98: ACCURATE Accounting System Report | D98: ACCURATE Accounting System Report | E98: ACCURATE Accounting System Report
B100: Printed on 2 February 2026 - 09:52 | C100: Printed on 2 February 2026 - 09:52 | D100: Printed on 2 February 2026 - 09:52 | E100: Printed on 2 February 2026 - 09:52
B101: Page Break 4 | C101: Page Break 4 | D101: Page Break 4 | E101: Page Break 4
B102: X-MOTORS INTERNATIONAL GROUP | C102: X-MOTORS INTERNATIONAL GROUP | D102: X-MOTORS INTERNATIONAL GROUP | E102: X-MOTORS INTERNATIONAL GROUP
B103: Item Sales per Warehouse | C103: Item Sales per Warehouse | D103: Item Sales per Warehouse | E103: Item Sales per Warehouse
B104: From 01 Apr 2025 until 30 Apr 2025 | C104: From 01 Apr 2025 until 30 Apr 2025 | D104: From 01 Apr 2025 until 30 Apr 2025 | E104: From 01 Apr 2025 until 30 Apr 2025
B105: Branch : [All Branch] | C105: Branch : [All Branch] | D105: Branch : [All Branch] | E105: Branch : [All Branch]
B106: Item Name | C106: Warehouse | D106: Quantity | E106: Sales
B107: BOSCH Wiper Advantage 21 inch BA21 | C107: BCS-1 KELAPA GADING--Central Warehouse | D107: 7 | E107: 426341
B108: BOSCH Wiper Advantage 21 inch BA21 | D108: 1 | E108: 60893
...

Sheet 25-05
B1: X-MOTORS INTERNATIONAL GROUP | C1: X-MOTORS INTERNATIONAL GROUP | D1: X-MOTORS INTERNATIONAL GROUP | E1: X-MOTORS INTERNATIONAL GROUP
B2: Item Sales per Warehouse | C2: Item Sales per Warehouse | D2: Item Sales per Warehouse | E2: Item Sales per Warehouse
B3: From 01 May 2025 until 31 May 2025 | C3: From 01 May 2025 until 31 May 2025 | D3: From 01 May 2025 until 31 May 2025 | E3: From 01 May 2025 until 31 May 2025
B4: Branch : [All Branch] | C4: Branch : [All Branch] | D4: Branch : [All Branch] | E4: Branch : [All Branch]
B5: Item Name | C5: Warehouse | D5: Quantity | E5: Sales
B6: BOSCH Air Filter S 0507 | C6: BCS-1 KELAPA GADING--Central Warehouse | D6: 1 | E6: 178378.38
B7: BOSCH Air Filter S 0507 | C7: Total Warehouse | D7: 1 | E7: 178378.38
B8: BOSCH BRAKE PAD | C8: BCS-1 KELAPA GADING--Central Warehouse | D8: 1 | E8: 321621.62
B9: BOSCH BRAKE PAD | C9: Total Warehouse | D9: 1 | E9: 321621.62
B10: BOSCH BRAKE PAD BP2377N | C10: BCS-1 KELAPA GADING--Central Warehouse | D10: 1 | E10: 313513.51
B11: BOSCH BRAKE PAD BP2377N | C11: Total Warehouse | D11: 1 | E11: 313513.51
B12: BOSCH Battery MF Blue NS60 46B24R 12V-42Ah | C12: BCS-1 KELAPA GADING--Central Warehouse | D12: 1 | E12: 1134234.2
B13: BOSCH Battery MF Blue NS60 46B24R 12V-42Ah | C13: Total Warehouse | D13: 1 | E13: 1134234.2
B14: BOSCH Battery MF Blue NX11005L 80D26L 12V-70Ah | C14: BCS-1 KELAPA GADING--Central Warehouse | D14: 3 | E14: 3812838
B15: BOSCH Battery MF Blue NX11005L 80D26L 12V-70Ah | C15: Total Warehouse | D15: 3 | E15: 3812838
B16: BOSCH Brake Pad 0986T18184 /BP1405 Front | C16: BCS-1 KELAPA GADING--Central Warehouse | D16: 1 | E16: 333333.33
B17: BOSCH Brake Pad 0986T18184 /BP1405 Front | C17: Total Warehouse | D17: 1 | E17: 333333.33
B19: ACCURATE Accounting System Report | C19: ACCURATE Accounting System Report | D19: ACCURATE Accounting System Report | E19: ACCURATE Accounting System Report
B21: Printed on 2 February 2026 - 09:51 | C21: Printed on 2 February 2026 - 09:51 | D21: Printed on 2 February 2026 - 09:51 | E21: Printed on 2 February 2026 - 09:51
B22: Page Break 1 | C22: Page Break 1 | D22: Page Break 1 | E22: Page Break 1
B23: X-MOTORS INTERNATIONAL GROUP | C23: X-MOTORS INTERNATIONAL GROUP | D23: X-MOTORS INTERNATIONAL GROUP | E23: X-MOTORS INTERNATIONAL GROUP
B24: Item Sales per Warehouse | C24: Item Sales per Warehouse | D24: Item Sales per Warehouse | E24: Item Sales per Warehouse
B25: From 01 May 2025 until 31 May 2025 | C25: From 01 May 2025 until 31 May 2025 | D25: From 01 May 2025 until 31 May 2025 | E25: From 01 May 2025 until 31 May 2025
B26: Branch : [All Branch] | C26: Branch : [All Branch] | D26: Branch : [All Branch] | E26: Branch : [All Branch]
B27: Item Name | C27: Warehouse | D27: Quantity | E27: Sales
B28: BOSCH Cabin Filter AP-H06 | C28: BCS-1 KELAPA GADING--Central Warehouse | D28: 10 | E28: 0
B29: BOSCH Cabin Filter AP-H06 | C29: Total Warehouse | D29: 10 | E29: 0
B30: BOSCH Cabin Filter AP-H09 | C30: BCS-1 KELAPA GADING--Central Warehouse | D30: 9 | E30: 0
B31: BOSCH Cabin Filter AP-H09 | C31: Total Warehouse | D31: 9 | E31: 0
B32: BOSCH Cabin Filter AP-M03 | C32: BCS-1 KELAPA GADING--Central Warehouse | D32: 2 | E32: 0
B33: BOSCH Cabin Filter AP-M03 | C33: Total Warehouse | D33: 2 | E33: 0
B34: BOSCH Cabin Filter AP-T07 | C34: BCS-1 KELAPA GADING--Central Warehouse | D34: 8 | E34: 0
B35: BOSCH Cabin Filter AP-T07 | C35: Total Warehouse | D35: 8 | E35: 0
B36: BOSCH Cabin Filter AP-T10 | C36: BCS-1 KELAPA GADING--Central Warehouse | D36: 2 | E36: 0
B37: BOSCH Cabin Filter AP-T10 | C37: Total Warehouse | D37: 2 | E37: 0
B38: BOSCH Cabin Filter S 4047 | C38: BCS-1 KELAPA GADING--Central Warehouse | D38: 2 | E38: 0
B39: BOSCH Cabin Filter S 4047 | C39: Total Warehouse | D39: 2 | E39: 0
B41: ACCURATE Accounting System Report | C41: ACCURATE Accounting System Report | D41: ACCURATE Accounting System Report | E41: ACCURATE Accounting System Report
B43: Printed on 2 February 2026 - 09:51 | C43: Printed on 2 February 2026 - 09:51 | D43: Printed on 2 February 2026 - 09:51 | E43: Printed on 2 February 2026 - 09:51
B44: Page Break 2 | C44: Page Break 2 | D44: Page Break 2 | E44: Page Break 2
B45: X-MOTORS INTERNATIONAL GROUP | C45: X-MOTORS INTERNATIONAL GROUP | D45: X-MOTORS INTERNATIONAL GROUP | E45: X-MOTORS INTERNATIONAL GROUP
B46: Item Sales per Warehouse | C46: Item Sales per Warehouse | D46: Item Sales per Warehouse | E46: Item Sales per Warehouse
B47: From 01 May 2025 until 31 May 2025 | C47: From 01 May 2025 until 31 May 2025 | D47: From 01 May 2025 until 31 May 2025 | E47: From 01 May 2025 until 31 May 2025
B48: Branch : [All Branch] | C48: Branch : [All Branch] | D48: Branch : [All Branch] | E48: Branch : [All Branch]
B49: Item Name | C49: Warehouse | D49: Quantity | E49: Sales
B50: BOSCH Cabin Filter S 4061 | C50: BCS-1 KELAPA GADING--Central Warehouse | D50: 1 | E50: 0
B51: BOSCH Cabin Filter S 4061 | C51: Total Warehouse | D51: 1 | E51: 0
B52: BOSCH Fuel Filter D 6100 | C52: BCS-1 KELAPA GADING--Central Warehouse | D52: 1 | E52: 90090
B53: BOSCH Fuel Filter D 6100 | C53: Total Warehouse | D53: 1 | E53: 90090
B54: BOSCH Fuel Filter D 6292 | C54: BCS-1 KELAPA GADING--Central Warehouse | D54: 1 | E54: 206306.31
B55: BOSCH Fuel Filter D 6292 | C55: Total Warehouse | D55: 1 | E55: 206306.31
B56: BOSCH HORN EC12C STRIDER | C56: BCS-1 KELAPA GADING--Central Warehouse | D56: 1 | E56: 207770
B57: BOSCH HORN EC12C STRIDER | C57: Total Warehouse | D57: 1 | E57: 207770
B58: BOSCH Light Bulb H1 12V 55W -P14.5s ECO | C58: BCS-1 KELAPA GADING--Central Warehouse | D58: 2 | E58: 172972.49
B59: BOSCH Light Bulb H1 12V 55W -P14.5s ECO | C59: Total Warehouse | D59: 2 | E59: 172972.49
B60: BOSCH Light Bulb H16 12V 19W -PGJ19-3 Standard-Clear | C60: BCS-1 KELAPA GADING--Central Warehouse | D60: 1 | E60: 79279.279
B61: BOSCH Light Bulb H16 12V 19W -PGJ19-3 Standard-Clear | C61: Total Warehouse | D61: 1 | E61: 79279.279
B63: ACCURATE Accounting System Report | C63: ACCURATE Accounting System Report | D63: ACCURATE Accounting System Report | E63: ACCURATE Accounting System Report
B65: Printed on 2 February 2026 - 09:51 | C65: Printed on 2 February 2026 - 09:51 | D65: Printed on 2 February 2026 - 09:51 | E65: Printed on 2 February 2026 - 09:51
B66: Page Break 3 | C66: Page Break 3 | D66: Page Break 3 | E66: Page Break 3
B67: X-MOTORS INTERNATIONAL GROUP | C67: X-MOTORS INTERNATIONAL GROUP | D67: X-MOTORS INTERNATIONAL GROUP | E67: X-MOTORS INTERNATIONAL GROUP
B68: Item Sales per Warehouse | C68: Item Sales per Warehouse | D68: Item Sales per Warehouse | E68: Item Sales per Warehouse
B69: From 01 May 2025 until 31 May 2025 | C69: From 01 May 2025 until 31 May 2025 | D69: From 01 May 2025 until 31 May 2025 | E69: From 01 May 2025 until 31 May 2025
B70: Branch : [All Branch] | C70: Branch : [All Branch] | D70: Branch : [All Branch] | E70: Branch : [All Branch]
B71: Item Name | C71: Warehouse | D71: Quantity | E71: Sales
B72: BOSCH Light Bulb P21/5W 12V 21W/5W -BAY15d Auxiliary | C72: BCS-1 KELAPA GADING--Central Warehouse | D72: 6 | E72: 37837.225
B73: BOSCH Light Bulb P21/5W 12V 21W/5W -BAY15d Auxiliary | C73: Total Warehouse | D73: 6 | E73: 37837.225
B74: BOSCH Light Bulb W16W 12V 16W -W2,1x9,5d ECO Auxiliary | C74: BCS-1 KELAPA GADING--Central Warehouse | D74: 1 | E74: 6306
B75: BOSCH Light Bulb W16W 12V 16W -W2,1x9,5d ECO Auxiliary | C75: Total Warehouse | D75: 1 | E75: 6306
B76: BOSCH Light Bulb W5W 12V 5W -W2,1x9,5d ECO Auxiliary | C76: BCS-1 KELAPA GADING--Central Warehouse | D76: 3 | E76: 13513.514
B77: BOSCH Light Bulb W5W 12V 5W -W2,1x9,5d ECO Auxiliary | C77: Total Warehouse | D77: 3 | E77: 13513.514
B78: BOSCH Oil Filter O 0126 | C78: BCS-1 KELAPA GADING--Central Warehouse | D78: 17 | E78: 43243
B79: BOSCH Oil Filter O 0126 | C79: Total Warehouse | D79: 17 | E79: 43243
B80: BOSCH Oil Filter O 0220 | C80: BCS-1 KELAPA GADING--Central Warehouse | D80: 10 | E80: 0
B81: BOSCH Oil Filter O 0220 | C81: Total Warehouse | D81: 10 | E81: 0
B82: BOSCH Oil Filter O 1001 | C82: BCS-1 KELAPA GADING--Central Warehouse | D82: 3 | E82: 56756.757
B83: BOSCH Oil Filter O 1001 | C83: Total Warehouse | D83: 3 | E83: 56756.757
B85: ACCURATE Accounting System Report | C85: ACCURATE Accounting System Report | D85: ACCURATE Accounting System Report | E85: ACCURATE Accounting System Report
B87: Printed on 2 February 2026 - 09:51 | C87: Printed on 2 February 2026 - 09:51 | D87: Printed on 2 February 2026 - 09:51 | E87: Printed on 2 February 2026 - 09:51
B88: Page Break 4 | C88: Page Break 4 | D88: Page Break 4 | E88: Page Break 4
B89: X-MOTORS INTERNATIONAL GROUP | C89: X-MOTORS INTERNATIONAL GROUP | D89: X-MOTORS INTERNATIONAL GROUP | E89: X-MOTORS INTERNATIONAL GROUP
B90: Item Sales per Warehouse | C90: Item Sales per Warehouse | D90: Item Sales per Warehouse | E90: Item Sales per Warehouse
B91: From 01 May 2025 until 31 May 2025 | C91: From 01 May 2025 until 31 May 2025 | D91: From 01 May 2025 until 31 May 2025 | E91: From 01 May 2025 until 31 May 2025
B92: Branch : [All Branch] | C92: Branch : [All Branch] | D92: Branch : [All Branch] | E92: Branch : [All Branch]
B93: Item Name | C93: Warehouse | D93: Quantity | E93: Sales
B94: BOSCH Oil Filter O 1014 | C94: BCS-1 KELAPA GADING--Central Warehouse | D94: 7 | E94: 0
B95: BOSCH Oil Filter O 1014 | C95: Total Warehouse | D95: 7 | E95: 0
B96: BOSCH Oil Filter O 1019 | C96: BCS-1 KELAPA GADING--Central Warehouse | D96: 2 | E96: 0
B97: BOSCH Oil Filter O 1019 | C97: Total Warehouse | D97: 2 | E97: 0
B98: BOSCH Oil Filter O 1041 | C98: BCS-1 KELAPA GADING--Central Warehouse | D98: 32 | E98: 0
B99: BOSCH Oil Filter O 1041 | C99: Total Warehouse | D99: 32 | E99: 0
B100: BOSCH Oil Filter O 1042 | C100: BCS-1 KELAPA GADING--Central Warehouse | D100: 5 | E100: 0
B101: BOSCH Oil Filter O 1042 | C101: Total Warehouse | D101: 5 | E101: 0
B102: BOSCH Oil Filter O 1043 | C102: BCS-1 KELAPA GADING--Central Warehouse | D102: 1 | E102: 0
B103: BOSCH Oil Filter O 1043 | C103: Total Warehouse | D103: 1 | E103: 0
B104: BOSCH Spark Plug DF7REC2(YR7DC+) - Standard | C104: BCS-1 KELAPA GADING--Central Warehouse | D104: 4 | E104: 72072.072
B105: BOSCH Spark Plug DF7REC2(YR7DC+) - Standard | C105: Total Warehouse | D105: 4 | E105: 72072.072
B107: ACCURATE Accounting System Report | C107: ACCURATE Accounting System Report | D107: ACCURATE Accounting System Report | E107: ACCURATE Accounting System Report
B109: Printed on 2 February 2026 - 09:51 | C109: Printed on 2 February 2026 - 09:51 | D109: Printed on 2 February 2026 - 09:51 | E109: Printed on 2 February 2026 - 09:51
B110: Page Break 5 | C110: Page Break 5 | D110: Page Break 5 | E110: Page Break 5
...

Sheet 26-06
B1: X-MOTORS INTERNATIONAL GROUP | C1: X-MOTORS INTERNATIONAL GROUP | D1: X-MOTORS INTERNATIONAL GROUP | E1: X-MOTORS INTERNATIONAL GROUP
B2: Item Sales per Warehouse | C2: Item Sales per Warehouse | D2: Item Sales per Warehouse | E2: Item Sales per Warehouse
B3: From 01 Jun 2025 until 30 Jun 2025 | C3: From 01 Jun 2025 until 30 Jun 2025 | D3: From 01 Jun 2025 until 30 Jun 2025 | E3: From 01 Jun 2025 until 30 Jun 2025
B4: Branch : [All Branch] | C4: Branch : [All Branch] | D4: Branch : [All Branch] | E4: Branch : [All Branch]
B5: Item Name | C5: Warehouse | D5: Quantity | E5: Sales
B6: 555 LINK STABILIZER (SL-3870) (B 1541 KZM) | C6: BCS-1 KELAPA GADING--Central Warehouse | D6: 1 | E6: 689189.19
B7: 555 LINK STABILIZER (SL-3870) (B 1541 KZM) | C7: Total Warehouse | D7: 1 | E7: 689189.19
B8: ASUKA AMPLAS 80 GRIT | C8: BCS-1 KELAPA GADING--Central Warehouse | D8: 1 | E8: 0
B9: ASUKA AMPLAS 80 GRIT | C9: Total Warehouse | D9: 1 | E9: 0
B10: AXIALGELENK LONG TIE ROD RH (45610) (B 911 CV) | C10: BCS-1 KELAPA GADING--Central Warehouse | D10: 1 | E10: 643500
B11: AXIALGELENK LONG TIE ROD RH (45610) (B 911 CV) | C11: Total Warehouse | D11: 1 | E11: 643500
B12: BOSCH Air Filter A 2180 | C12: BCS-1 KELAPA GADING--Central Warehouse | D12: 1 | E12: 243243.17
B13: BOSCH Air Filter A 2180 | C13: Total Warehouse | D13: 1 | E13: 243243.17
B14: BOSCH BRAKE PAD | C14: BCS-1 KELAPA GADING--Central Warehouse | D14: 1 | E14: 321621.62
B15: BOSCH BRAKE PAD | C15: Total Warehouse | D15: 1 | E15: 321621.62
B16: BOSCH Battery MF Blue 55D23L 12V-60Ah | C16: BCS-1 KELAPA GADING--Central Warehouse | D16: 2 | E16: 2953153.6
B17: BOSCH Battery MF Blue 55D23L 12V-60Ah | C17: Total Warehouse | D17: 2 | E17: 2953153.6
B19: ACCURATE Accounting System Report | C19: ACCURATE Accounting System Report | D19: ACCURATE Accounting System Report | E19: ACCURATE Accounting System Report
B21: Printed on 2 February 2026 - 09:50 | C21: Printed on 2 February 2026 - 09:50 | D21: Printed on 2 February 2026 - 09:50 | E21: Printed on 2 February 2026 - 09:50
B22: Page Break 1 | C22: Page Break 1 | D22: Page Break 1 | E22: Page Break 1
B23: X-MOTORS INTERNATIONAL GROUP | C23: X-MOTORS INTERNATIONAL GROUP | D23: X-MOTORS INTERNATIONAL GROUP | E23: X-MOTORS INTERNATIONAL GROUP
B24: Item Sales per Warehouse | C24: Item Sales per Warehouse | D24: Item Sales per Warehouse | E24: Item Sales per Warehouse
B25: From 01 Jun 2025 until 30 Jun 2025 | C25: From 01 Jun 2025 until 30 Jun 2025 | D25: From 01 Jun 2025 until 30 Jun 2025 | E25: From 01 Jun 2025 until 30 Jun 2025
B26: Branch : [All Branch] | C26: Branch : [All Branch] | D26: Branch : [All Branch] | E26: Branch : [All Branch]
B27: Item Name | C27: Warehouse | D27: Quantity | E27: Sales
B28: BOSCH Battery MF Blue NS40ZL 40B19L 12V | C28: BCS-1 KELAPA GADING--Central Warehouse | D28: 2 | E28: 2072072.1
B29: BOSCH Battery MF Blue NS40ZL 40B19L 12V | C29: Total Warehouse | D29: 2 | E29: 2072072.1
B30: BOSCH Battery MF Blue NS60 46B24R 12V-42Ah | C30: BCS-1 KELAPA GADING--Central Warehouse | D30: 1 | E30: 1134234.7
B31: BOSCH Battery MF Blue NS60 46B24R 12V-42Ah | C31: Total Warehouse | D31: 1 | E31: 1134234.7
B32: BOSCH Battery MF Blue NX11005L 80D26L 12V-70Ah | C32: BCS-1 KELAPA GADING--Central Warehouse | D32: 4 | E32: 5520045.2
B33: BOSCH Battery MF Blue NX11005L 80D26L 12V-70Ah | C33: Total Warehouse | D33: 4 | E33: 5520045.2
B34: BOSCH Brake Pad 0986T18178 /BP8178 Front | C34: BCS-1 KELAPA GADING--Central Warehouse | D34: 1 | E34: 262161.99
B35: BOSCH Brake Pad 0986T18178 /BP8178 Front | C35: Total Warehouse | D35: 1 | E35: 262161.99
B36: BOSCH Cabin Filter AP-T10 | C36: BCS-1 KELAPA GADING--Central Warehouse | D36: 1 | E36: 0
B37: BOSCH Cabin Filter AP-T10 | C37: Total Warehouse | D37: 1 | E37: 0
B38: BOSCH Cabin Filter R 2336 | C38: BCS-1 KELAPA GADING--Central Warehouse | D38: 1 | E38: 0
B39: BOSCH Cabin Filter R 2336 | C39: Total Warehouse | D39: 1 | E39: 0
B41: ACCURATE Accounting System Report | C41: ACCURATE Accounting System Report | D41: ACCURATE Accounting System Report | E41: ACCURATE Accounting System Report
B43: Printed on 2 February 2026 - 09:50 | C43: Printed on 2 February 2026 - 09:50 | D43: Printed on 2 February 2026 - 09:50 | E43: Printed on 2 February 2026 - 09:50
B44: Page Break 2 | C44: Page Break 2 | D44: Page Break 2 | E44: Page Break 2
B45: X-MOTORS INTERNATIONAL GROUP | C45: X-MOTORS INTERNATIONAL GROUP | D45: X-MOTORS INTERNATIONAL GROUP | E45: X-MOTORS INTERNATIONAL GROUP
B46: Item Sales per Warehouse | C46: Item Sales per Warehouse | D46: Item Sales per Warehouse | E46: Item Sales per Warehouse
B47: From 01 Jun 2025 until 30 Jun 2025 | C47: From 01 Jun 2025 until 30 Jun 2025 | D47: From 01 Jun 2025 until 30 Jun 2025 | E47: From 01 Jun 2025 until 30 Jun 2025
B48: Branch : [All Branch] | C48: Branch : [All Branch] | D48: Branch : [All Branch] | E48: Branch : [All Branch]
B49: Item Name | C49: Warehouse | D49: Quantity | E49: Sales
B50: BOSCH Fuel Filter D 6100 | C50: BCS-1 KELAPA GADING--Central Warehouse | D50: 1 | E50: 90090.09
B51: BOSCH Fuel Filter D 6100 | C51: Total Warehouse | D51: 1 | E51: 90090.09
B52: BOSCH Light Bulb H1 12V 55W -P14.5s ECO | C52: BCS-1 KELAPA GADING--Central Warehouse | D52: 1 | E52: 86486.486
B53: BOSCH Light Bulb H1 12V 55W -P14.5s ECO | C53: Total Warehouse | D53: 1 | E53: 86486.486
B54: BOSCH Light Bulb H16 12V 19W -PGJ19-3 Standard-Clear | C54: BCS-1 KELAPA GADING--Central Warehouse | D54: 2 | E54: 158558.56
B55: BOSCH Light Bulb H16 12V 19W -PGJ19-3 Standard-Clear | C55: Total Warehouse | D55: 2 | E55: 158558.56
B56: BOSCH Light Bulb H4 12V 60/55W -P43t Sportec Bright | C56: BCS-1 KELAPA GADING--Central Warehouse | D56: 2 | E56: 520719.99
B57: BOSCH Light Bulb H4 12V 60/55W -P43t Sportec Bright | C57: Total Warehouse | D57: 2 | E57: 520719.99
B58: BOSCH Light Bulb P21/5W 12V 21W/5W -BAY15d Auxiliary | C58: BCS-1 KELAPA GADING--Central Warehouse | D58: 4 | E58: 25224.919
B59: BOSCH Light Bulb P21/5W 12V 21W/5W -BAY15d Auxiliary | C59: Total Warehouse | D59: 4 | E59: 25224.919
B60: BOSCH Light Bulb P21W 12V 21W -BA15s Auxiliary | C60: BCS-1 KELAPA GADING--Central Warehouse | D60: 1 | E60: 6306
B61: BOSCH Light Bulb P21W 12V 21W -BA15s Auxiliary | C61: Total Warehouse | D61: 1 | E61: 6306
B63: ACCURATE Accounting System Report | C63: ACCURATE Accounting System Report | D63: ACCURATE Accounting System Report | E63: ACCURATE Accounting System Report
B65: Printed on 2 February 2026 - 09:50 | C65: Printed on 2 February 2026 - 09:50 | D65: Printed on 2 February 2026 - 09:50 | E65: Printed on 2 February 2026 - 09:50
B66: Page Break 3 | C66: Page Break 3 | D66: Page Break 3 | E66: Page Break 3
B67: X-MOTORS INTERNATIONAL GROUP | C67: X-MOTORS INTERNATIONAL GROUP | D67: X-MOTORS INTERNATIONAL GROUP | E67: X-MOTORS INTERNATIONAL GROUP
B68: Item Sales per Warehouse | C68: Item Sales per Warehouse | D68: Item Sales per Warehouse | E68: Item Sales per Warehouse
B69: From 01 Jun 2025 until 30 Jun 2025 | C69: From 01 Jun 2025 until 30 Jun 2025 | D69: From 01 Jun 2025 until 30 Jun 2025 | E69: From 01 Jun 2025 until 30 Jun 2025
B70: Branch : [All Branch] | C70: Branch : [All Branch] | D70: Branch : [All Branch] | E70: Branch : [All Branch]
B71: Item Name | C71: Warehouse | D71: Quantity | E71: Sales
B72: BOSCH Light Bulb W16W 12V 16W -W2,1x9,5d ECO Auxiliary | C72: BCS-1 KELAPA GADING--Central Warehouse | D72: 2 | E72: 12612.613
B73: BOSCH Light Bulb W16W 12V 16W -W2,1x9,5d ECO Auxiliary | C73: Total Warehouse | D73: 2 | E73: 12612.613
B74: BOSCH Light Bulb W21/5W 12V 21W/5W -W3x16q Auxiliary | C74: BCS-1 KELAPA GADING--Central Warehouse | D74: 3 | E74: 70270.27
B75: BOSCH Light Bulb W21/5W 12V 21W/5W -W3x16q Auxiliary | C75: Total Warehouse | D75: 3 | E75: 70270.27
B76: BOSCH Light Bulb W21W 12V 21W -W3x16d ECO Auxiliary | C76: BCS-1 KELAPA GADING--Central Warehouse | D76: 2 | E76: 32432.784
B77: BOSCH Light Bulb W21W 12V 21W -W3x16d ECO Auxiliary | C77: Total Warehouse | D77: 2 | E77: 32432.784
B78: BOSCH Light Bulb W5W 12V 5W -W2,1x9,5d ECO Auxiliary | C78: BCS-1 KELAPA GADING--Central Warehouse | D78: 4 | E78: 18018.018
B79: BOSCH Light Bulb W5W 12V 5W -W2,1x9,5d ECO Auxiliary | C79: Total Warehouse | D79: 4 | E79: 18018.018
B80: BOSCH Oil Filter O 0126 | C80: BCS-1 KELAPA GADING--Central Warehouse | D80: 31 | E80: 43242.829
B81: BOSCH Oil Filter O 0126 | C81: Total Warehouse | D81: 31 | E81: 43242.829
B82: BOSCH Oil Filter O 0220 | C82: BCS-1 KELAPA GADING--Central Warehouse | D82: 20 | E82: 41441.441
B83: BOSCH Oil Filter O 0220 | C83: Total Warehouse | D83: 20 | E83: 41441.441
B85: ACCURATE Accounting System Report | C85: ACCURATE Accounting System Report | D85: ACCURATE Accounting System Report | E85: ACCURATE Accounting System Report
B87: Printed on 2 February 2026 - 09:50 | C87: Printed on 2 February 2026 - 09:50 | D87: Printed on 2 February 2026 - 09:50 | E87: Printed on 2 February 2026 - 09:50
B88: Page Break 4 | C88: Page Break 4 | D88: Page Break 4 | E88: Page Break 4
B89: X-MOTORS INTERNATIONAL GROUP | C89: X-MOTORS INTERNATIONAL GROUP | D89: X-MOTORS INTERNATIONAL GROUP | E89: X-MOTORS INTERNATIONAL GROUP
B90: Item Sales per Warehouse | C90: Item Sales per Warehouse | D90: Item Sales per Warehouse | E90: Item Sales per Warehouse
B91: From 01 Jun 2025 until 30 Jun 2025 | C91: From 01 Jun 2025 until 30 Jun 2025 | D91: From 01 Jun 2025 until 30 Jun 2025 | E91: From 01 Jun 2025 until 30 Jun 2025
B92: Branch : [All Branch] | C92: Branch : [All Branch] | D92: Branch : [All Branch] | E92: Branch : [All Branch]
B93: Item Name | C93: Warehouse | D93: Quantity | E93: Sales
B94: BOSCH Oil Filter O 1001 | C94: BCS-1 KELAPA GADING--Central Warehouse | D94: 3 | E94: 0
B95: BOSCH Oil Filter O 1001 | C95: Total Warehouse | D95: 3 | E95: 0
B96: BOSCH Oil Filter O 1014 | C96: BCS-1 KELAPA GADING--Central Warehouse | D96: 4 | E96: 0
B97: BOSCH Oil Filter O 1014 | C97: Total Warehouse | D97: 4 | E97: 0
B98: BOSCH Oil Filter O 1041 | C98: BCS-1 KELAPA GADING--Central Warehouse | D98: 69 | E98: 43243.243
B99: BOSCH Oil Filter O 1041 | C99: Total Warehouse | D99: 69 | E99: 43243.243
B100: BOSCH Oil Filter O 1042 | C100: BCS-1 KELAPA GADING--Central Warehouse | D100: 10 | E100: 0
B101: BOSCH Oil Filter O 1042 | C101: Total Warehouse | D101: 10 | E101: 0
B102: BOSCH Oil Filter O 1106 | C102: BCS-1 KELAPA GADING--Central Warehouse | D102: 1 | E102: 0
B103: BOSCH Oil Filter O 1106 | C103: Total Warehouse | D103: 1 | E103: 0
B104: BOSCH Oil Filter O 1508 | C104: BCS-1 KELAPA GADING--Central Warehouse | D104: 1 | E104: 0
B105: BOSCH Oil Filter O 1508 | C105: Total Warehouse | D105: 1 | E105: 0
B107: ACCURATE Accounting System Report | C107: ACCURATE Accounting System Report | D107: ACCURATE Accounting System Report | E107: ACCURATE Accounting System Report
B109: Printed on 2 February 2026 - 09:50 | C109: Printed on 2 February 2026 - 09:50 | D109: Printed on 2 February 2026 - 09:50 | E109: Printed on 2 February 2026 - 09:50
B110: Page Break 5 | C110: Page Break 5 | D110: Page Break 5 | E110: Page Break 5
...

Sheet 25-07
B1: X-MOTORS INTERNATIONAL GROUP | C1: X-MOTORS INTERNATIONAL GROUP | D1: X-MOTORS INTERNATIONAL GROUP | E1: X-MOTORS INTERNATIONAL GROUP
B2: Item Sales per Warehouse | C2: Item Sales per Warehouse | D2: Item Sales per Warehouse | E2: Item Sales per Warehouse
B3: From 01 Jul 2025 until 31 Jul 2025 | C3: From 01 Jul 2025 until 31 Jul 2025 | D3: From 01 Jul 2025 until 31 Jul 2025 | E3: From 01 Jul 2025 until 31 Jul 2025
B4: Branch : [All Branch] | C4: Branch : [All Branch] | D4: Branch : [All Branch] | E4: Branch : [All Branch]
B5: Item Name | C5: Warehouse | D5: Quantity | E5: Sales
B6: 555 LONG TIROD (45503-0K070) (B 1185 TRJ) | C6: BCS-1 KELAPA GADING--Central Warehouse | D6: 1 | E6: 975000
B7: 555 LONG TIROD (45503-0K070) (B 1185 TRJ) | C7: Total Warehouse | D7: 1 | E7: 975000
B8: 555 TIE ROD END (45046-09800) (B 1185 TRJ) | C8: BCS-1 KELAPA GADING--Central Warehouse | D8: 1 | E8: 585000
B9: 555 TIE ROD END (45046-09800) (B 1185 TRJ) | C9: Total Warehouse | D9: 1 | E9: 585000
B10: AUTO FUSE FUSE TANCAP BESAR 30A | C10: BCS-1 KELAPA GADING--Central Warehouse | D10: 1 | E10: 4504.5045
B11: AUTO FUSE FUSE TANCAP BESAR 30A | C11: Total Warehouse | D11: 1 | E11: 4504.5045
B12: BENDIX PADKIT FR (DB1679 GCT) (B 1403 URT) | C12: BCS-1 KELAPA GADING--Central Warehouse | D12: 1 | E12: 630630.63
B13: BENDIX PADKIT FR (DB1679 GCT) (B 1403 URT) | C13: Total Warehouse | D13: 1 | E13: 630630.63
B14: BMW OIL FILTER (11428593186) (B 2751 BYI) | C14: BCS-1 KELAPA GADING--Central Warehouse | D14: 1 | E14: 210810.81
B15: BMW OIL FILTER (11428593186) (B 2751 BYI) | C15: Total Warehouse | D15: 1 | E15: 210810.81
B16: BOSCH Air Filter A 2180 | C16: BCS-1 KELAPA GADING--Central Warehouse | D16: 2 | E16: 486486.49
B17: BOSCH Air Filter A 2180 | C17: Total Warehouse | D17: 2 | E17: 486486.49
B19: ACCURATE Accounting System Report | C19: ACCURATE Accounting System Report | D19: ACCURATE Accounting System Report | E19: ACCURATE Accounting System Report
B21: Printed on 2 February 2026 - 09:44 | C21: Printed on 2 February 2026 - 09:44 | D21: Printed on 2 February 2026 - 09:44 | E21: Printed on 2 February 2026 - 09:44
B22: Page Break 1 | C22: Page Break 1 | D22: Page Break 1 | E22: Page Break 1
B23: X-MOTORS INTERNATIONAL GROUP | C23: X-MOTORS INTERNATIONAL GROUP | D23: X-MOTORS INTERNATIONAL GROUP | E23: X-MOTORS INTERNATIONAL GROUP
B24: Item Sales per Warehouse | C24: Item Sales per Warehouse | D24: Item Sales per Warehouse | E24: Item Sales per Warehouse
B25: From 01 Jul 2025 until 31 Jul 2025 | C25: From 01 Jul 2025 until 31 Jul 2025 | D25: From 01 Jul 2025 until 31 Jul 2025 | E25: From 01 Jul 2025 until 31 Jul 2025
B26: Branch : [All Branch] | C26: Branch : [All Branch] | D26: Branch : [All Branch] | E26: Branch : [All Branch]
B27: Item Name | C27: Warehouse | D27: Quantity | E27: Sales
B28: BOSCH BRAKE PAD | C28: BCS-1 KELAPA GADING--Central Warehouse | D28: 1 | E28: 321621.62
B29: BOSCH BRAKE PAD | C29: Total Warehouse | D29: 1 | E29: 321621.62
B30: BOSCH BRAKE PAD BP1925 KOSONG | C30: BCS-1 KELAPA GADING--Central Warehouse | D30: 1 | E30: 398197.99
B31: BOSCH BRAKE PAD BP1925 KOSONG | C31: Total Warehouse | D31: 1 | E31: 398197.99
B32: BOSCH Battery MF Blue NS40Z 40B19R 12V | C32: BCS-1 KELAPA GADING--Central Warehouse | D32: 2 | E32: 2072071.6
B33: BOSCH Battery MF Blue NS40Z 40B19R 12V | C33: Total Warehouse | D33: 2 | E33: 2072071.6
B34: BOSCH Battery MF Blue NS60 46B24R 12V-42Ah | C34: BCS-1 KELAPA GADING--Central Warehouse | D34: 1 | E34: 1134234.1
B35: BOSCH Battery MF Blue NS60 46B24R 12V-42Ah | C35: Total Warehouse | D35: 1 | E35: 1134234.1
B36: BOSCH Brake Pad 0986T18184 /BP1405 Front | C36: BCS-1 KELAPA GADING--Central Warehouse | D36: 1 | E36: 333333.33
B37: BOSCH Brake Pad 0986T18184 /BP1405 Front | C37: Total Warehouse | D37: 1 | E37: 333333.33
B38: BOSCH Brake Pad 0986T18187 /BP2268 Front | C38: BCS-1 KELAPA GADING--Central Warehouse | D38: 1 | E38: 416216.22
B39: BOSCH Brake Pad 0986T18187 /BP2268 Front | C39: Total Warehouse | D39: 1 | E39: 416216.22
B41: ACCURATE Accounting System Report | C41: ACCURATE Accounting System Report | D41: ACCURATE Accounting System Report | E41: ACCURATE Accounting System Report
B43: Printed on 2 February 2026 - 09:44 | C43: Printed on 2 February 2026 - 09:44 | D43: Printed on 2 February 2026 - 09:44 | E43: Printed on 2 February 2026 - 09:44
B44: Page Break 2 | C44: Page Break 2 | D44: Page Break 2 | E44: Page Break 2
B45: X-MOTORS INTERNATIONAL GROUP | C45: X-MOTORS INTERNATIONAL GROUP | D45: X-MOTORS INTERNATIONAL GROUP | E45: X-MOTORS INTERNATIONAL GROUP
B46: Item Sales per Warehouse | C46: Item Sales per Warehouse | D46: Item Sales per Warehouse | E46: Item Sales per Warehouse
B47: From 01 Jul 2025 until 31 Jul 2025 | C47: From 01 Jul 2025 until 31 Jul 2025 | D47: From 01 Jul 2025 until 31 Jul 2025 | E47: From 01 Jul 2025 until 31 Jul 2025
B48: Branch : [All Branch] | C48: Branch : [All Branch] | D48: Branch : [All Branch] | E48: Branch : [All Branch]
B49: Item Name | C49: Warehouse | D49: Quantity | E49: Sales
B50: BOSCH Cabin Filter AP-H06 | C50: BCS-1 KELAPA GADING--Central Warehouse | D50: 1 | E50: 228800
B51: BOSCH Cabin Filter AP-H06 | C51: Total Warehouse | D51: 1 | E51: 228800
B52: BOSCH Cabin Filter AP-H07 | C52: BCS-1 KELAPA GADING--Central Warehouse | D52: 1 | E52: 0
B53: BOSCH Cabin Filter AP-H07 | C53: Total Warehouse | D53: 1 | E53: 0
B54: BOSCH Cabin Filter AP-T10 | C54: BCS-1 KELAPA GADING--Central Warehouse | D54: 1 | E54: 0
B55: BOSCH Cabin Filter AP-T10 | C55: Total Warehouse | D55: 1 | E55: 0
B56: BOSCH ELECTRIC FUEL PUMP 0986AG1304 | C56: BCS-1 KELAPA GADING--Central Warehouse | D56: 1 | E56: 305338.16
