Workbook

Sheet Master
B1: PRODUCT NAME | C1: Pit Stop 3 | D1: Subur Makmur Ban | E1: Bengkel Pegasus | F1: Autocraft | G1: Autones | H1: ADS Prima | I1: Auto Mekanika | J1: Bengkel Multi Variasi | K1: Euro Galleria | L1: Drivewell | M1: Mersi | N1: K | O1: Auto Service (no sales yet) | P1: CV Sun | Q1: Sumber Timur | R1: Honda Auto Duren Sawit | S1: Lavender Car Solution | T1: Total Demand from all franchise | U1: PRICE | V1: TOTAL AMOUNT | W1: Bosch Part Number
A2: =VLOOKUP(B2,#REF!,5,0) -> #REF! | B2: MOTUL Engine Oil MUGEN MS-A 5W-30 1L | C2: =_xlfn.XLOOKUP(B2,'Pit Stop (cleaned)'!A:A,'Pit Stop (cleaned)'!B:B,0) -> 0 | D2: =_xlfn.XLOOKUP(B2,'Subur Makmur Ban (Agg)'!$F$1:$F$5,'Subur Makmur Ban (Agg)'!$L$1:$L$5,0) -> 0 | E2: =_xlfn.XLOOKUP(B2,'Bengkel Pegasus (Agg)'!F:F,'Bengkel Pegasus (Agg)'!L:L,0) -> 0 | F2: =_xlfn.XLOOKUP(B2,'Autocraft (agg)'!F:F,'Autocraft (agg)'!L:L,0) -> 0 | G2: =_xlfn.XLOOKUP(B2,'Autones (cleaned)'!A:A,'Autones (cleaned)'!B:B,0) -> 0 | H2: =_xlfn.XLOOKUP(B2,'ADS Prima (cleaned)'!A:A,'ADS Prima (cleaned)'!B:B,0) -> 0 | I2: =_xlfn.XLOOKUP(B2,'Auto Mekanika (cleaned)'!A:A,'Auto Mekanika (cleaned)'!B:B,0) -> 0 | J2: =_xlfn.XLOOKUP(B2,'Bengkel Multi Var (cleaned)'!A:A,'Bengkel Multi Var (cleaned)'!B:B,0) -> 0 | K2: 0 | L2: =_xlfn.XLOOKUP(B2,'Drivewell (cleaned)'!A:A,'Drivewell (cleaned)'!B:B,0) -> 0 | M2: 0 | N2: 0 | O2: 0 | P2: =_xlfn.XLOOKUP(B2,'CV Sun (cleaned)'!A:A,'CV Sun (cleaned)'!B:B,0) -> 0 | Q2: =_xlfn.XLOOKUP(B2,'Sumber Timur (clean)'!F:F,'Sumber Timur (clean)'!L:L,0) -> 0 | R2: =_xlfn.XLOOKUP(B2,'Honda Duren (clean)'!F:F,'Honda Duren (clean)'!L:L,0) -> 0 | S2: 0 | T2: =SUM(C2:S2) -> 0
A3: =VLOOKUP(B3,#REF!,5,0) -> #REF! | B3: DENSO Air Filter DXA-1059 | C3: =_xlfn.XLOOKUP(B3,'Pit Stop (cleaned)'!A:A,'Pit Stop (cleaned)'!B:B,0) -> 0 | D3: =_xlfn.XLOOKUP(B3,'Subur Makmur Ban (Agg)'!$F$1:$F$5,'Subur Makmur Ban (Agg)'!$L$1:$L$5,0) -> 0 | E3: =_xlfn.XLOOKUP(B3,'Bengkel Pegasus (Agg)'!F:F,'Bengkel Pegasus (Agg)'!L:L,0) -> 0 | F3: =_xlfn.XLOOKUP(B3,'Autocraft (agg)'!F:F,'Autocraft (agg)'!L:L,0) -> 0 | G3: =_xlfn.XLOOKUP(B3,'Autones (cleaned)'!A:A,'Autones (cleaned)'!B:B,0) -> 0 | H3: =_xlfn.XLOOKUP(B3,'ADS Prima (cleaned)'!A:A,'ADS Prima (cleaned)'!B:B,0) -> 0 | I3: =_xlfn.XLOOKUP(B3,'Auto Mekanika (cleaned)'!A:A,'Auto Mekanika (cleaned)'!B:B,0) -> 0 | J3: =_xlfn.XLOOKUP(B3,'Bengkel Multi Var (cleaned)'!A:A,'Bengkel Multi Var (cleaned)'!B:B,0) -> 0 | K3: 0 | L3: =_xlfn.XLOOKUP(B3,'Drivewell (cleaned)'!A:A,'Drivewell (cleaned)'!B:B,0) -> 0 | M3: 0 | N3: 0 | O3: 0 | P3: =_xlfn.XLOOKUP(B3,'CV Sun (cleaned)'!A:A,'CV Sun (cleaned)'!B:B,0) -> 0 | Q3: =_xlfn.XLOOKUP(B3,'Sumber Timur (clean)'!F:F,'Sumber Timur (clean)'!L:L,0) -> 0 | R3: =_xlfn.XLOOKUP(B3,'Honda Duren (clean)'!F:F,'Honda Duren (clean)'!L:L,0) -> 0 | S3: 0 | T3: =SUM(C3:S3) -> 0
A4: =VLOOKUP(B4,#REF!,5,0) -> #REF! | B4: BOSCH Oil Filter O 1506 | C4: =_xlfn.XLOOKUP(B4,'Pit Stop (cleaned)'!A:A,'Pit Stop (cleaned)'!B:B,0) -> 0 | D4: =_xlfn.XLOOKUP(B4,'Subur Makmur Ban (Agg)'!$F$1:$F$5,'Subur Makmur Ban (Agg)'!$L$1:$L$5,0) -> 0 | E4: =_xlfn.XLOOKUP(B4,'Bengkel Pegasus (Agg)'!F:F,'Bengkel Pegasus (Agg)'!L:L,0) -> 0 | F4: =_xlfn.XLOOKUP(B4,'Autocraft (agg)'!F:F,'Autocraft (agg)'!L:L,0) -> 0 | G4: =_xlfn.XLOOKUP(B4,'Autones (cleaned)'!A:A,'Autones (cleaned)'!B:B,0) -> 0 | H4: =_xlfn.XLOOKUP(B4,'ADS Prima (cleaned)'!A:A,'ADS Prima (cleaned)'!B:B,0) -> 0 | I4: =_xlfn.XLOOKUP(B4,'Auto Mekanika (cleaned)'!A:A,'Auto Mekanika (cleaned)'!B:B,0) -> 0 | J4: =_xlfn.XLOOKUP(B4,'Bengkel Multi Var (cleaned)'!A:A,'Bengkel Multi Var (cleaned)'!B:B,0) -> 0 | K4: 0 | L4: =_xlfn.XLOOKUP(B4,'Drivewell (cleaned)'!A:A,'Drivewell (cleaned)'!B:B,0) -> 0 | M4: 0 | N4: 0 | O4: 0 | P4: =_xlfn.XLOOKUP(B4,'CV Sun (cleaned)'!A:A,'CV Sun (cleaned)'!B:B,0) -> 0 | Q4: =_xlfn.XLOOKUP(B4,'Sumber Timur (clean)'!F:F,'Sumber Timur (clean)'!L:L,0) -> 0 | R4: =_xlfn.XLOOKUP(B4,'Honda Duren (clean)'!F:F,'Honda Duren (clean)'!L:L,0) -> 0 | S4: 0 | T4: =SUM(C4:S4) -> 0
A5: =VLOOKUP(B5,#REF!,5,0) -> #REF! | B5: SHELL Engine Oil HELIX Ultra 5W-30 4L | C5: =_xlfn.XLOOKUP(B5,'Pit Stop (cleaned)'!A:A,'Pit Stop (cleaned)'!B:B,0) -> 0 | D5: =_xlfn.XLOOKUP(B5,'Subur Makmur Ban (Agg)'!$F$1:$F$5,'Subur Makmur Ban (Agg)'!$L$1:$L$5,0) -> 0 | E5: =_xlfn.XLOOKUP(B5,'Bengkel Pegasus (Agg)'!F:F,'Bengkel Pegasus (Agg)'!L:L,0) -> 0 | F5: =_xlfn.XLOOKUP(B5,'Autocraft (agg)'!F:F,'Autocraft (agg)'!L:L,0) -> 0 | G5: =_xlfn.XLOOKUP(B5,'Autones (cleaned)'!A:A,'Autones (cleaned)'!B:B,0) -> 0 | H5: =_xlfn.XLOOKUP(B5,'ADS Prima (cleaned)'!A:A,'ADS Prima (cleaned)'!B:B,0) -> 0 | I5: =_xlfn.XLOOKUP(B5,'Auto Mekanika (cleaned)'!A:A,'Auto Mekanika (cleaned)'!B:B,0) -> 0 | J5: =_xlfn.XLOOKUP(B5,'Bengkel Multi Var (cleaned)'!A:A,'Bengkel Multi Var (cleaned)'!B:B,0) -> 0 | K5: 0 | L5: =_xlfn.XLOOKUP(B5,'Drivewell (cleaned)'!A:A,'Drivewell (cleaned)'!B:B,0) -> 0 | M5: 0 | N5: 0 | O5: 0 | P5: =_xlfn.XLOOKUP(B5,'CV Sun (cleaned)'!A:A,'CV Sun (cleaned)'!B:B,0) -> 0 | Q5: =_xlfn.XLOOKUP(B5,'Sumber Timur (clean)'!F:F,'Sumber Timur (clean)'!L:L,0) -> 0 | R5: =_xlfn.XLOOKUP(B5,'Honda Duren (clean)'!F:F,'Honda Duren (clean)'!L:L,0) -> 0 | S5: 0 | T5: =SUM(C5:S5) -> 0
A6: =VLOOKUP(B6,#REF!,5,0) -> #REF! | B6: DENSO Spark Plug IK16TT - Iridium | C6: =_xlfn.XLOOKUP(B6,'Pit Stop (cleaned)'!A:A,'Pit Stop (cleaned)'!B:B,0) -> 0 | D6: =_xlfn.XLOOKUP(B6,'Subur Makmur Ban (Agg)'!$F$1:$F$5,'Subur Makmur Ban (Agg)'!$L$1:$L$5,0) -> 0 | E6: =_xlfn.XLOOKUP(B6,'Bengkel Pegasus (Agg)'!F:F,'Bengkel Pegasus (Agg)'!L:L,0) -> 0 | F6: =_xlfn.XLOOKUP(B6,'Autocraft (agg)'!F:F,'Autocraft (agg)'!L:L,0) -> 0 | G6: =_xlfn.XLOOKUP(B6,'Autones (cleaned)'!A:A,'Autones (cleaned)'!B:B,0) -> 0 | H6: =_xlfn.XLOOKUP(B6,'ADS Prima (cleaned)'!A:A,'ADS Prima (cleaned)'!B:B,0) -> 0 | I6: =_xlfn.XLOOKUP(B6,'Auto Mekanika (cleaned)'!A:A,'Auto Mekanika (cleaned)'!B:B,0) -> 0 | J6: =_xlfn.XLOOKUP(B6,'Bengkel Multi Var (cleaned)'!A:A,'Bengkel Multi Var (cleaned)'!B:B,0) -> 0 | K6: 0 | L6: =_xlfn.XLOOKUP(B6,'Drivewell (cleaned)'!A:A,'Drivewell (cleaned)'!B:B,0) -> 0 | M6: 0 | N6: 0 | O6: 0 | P6: =_xlfn.XLOOKUP(B6,'CV Sun (cleaned)'!A:A,'CV Sun (cleaned)'!B:B,0) -> 0 | Q6: =_xlfn.XLOOKUP(B6,'Sumber Timur (clean)'!F:F,'Sumber Timur (clean)'!L:L,0) -> 0 | R6: =_xlfn.XLOOKUP(B6,'Honda Duren (clean)'!F:F,'Honda Duren (clean)'!L:L,0) -> 0 | S6: 0 | T6: =SUM(C6:S6) -> 0
A7: =VLOOKUP(B7,#REF!,5,0) -> #REF! | B7: BOSCH Spark Plug YR7PP30 - Iridium | C7: =_xlfn.XLOOKUP(B7,'Pit Stop (cleaned)'!A:A,'Pit Stop (cleaned)'!B:B,0) -> 0 | D7: =_xlfn.XLOOKUP(B7,'Subur Makmur Ban (Agg)'!$F$1:$F$5,'Subur Makmur Ban (Agg)'!$L$1:$L$5,0) -> 0 | E7: =_xlfn.XLOOKUP(B7,'Bengkel Pegasus (Agg)'!F:F,'Bengkel Pegasus (Agg)'!L:L,0) -> 0 | F7: =_xlfn.XLOOKUP(B7,'Autocraft (agg)'!F:F,'Autocraft (agg)'!L:L,0) -> 0 | G7: =_xlfn.XLOOKUP(B7,'Autones (cleaned)'!A:A,'Autones (cleaned)'!B:B,0) -> 0 | H7: =_xlfn.XLOOKUP(B7,'ADS Prima (cleaned)'!A:A,'ADS Prima (cleaned)'!B:B,0) -> 0 | I7: =_xlfn.XLOOKUP(B7,'Auto Mekanika (cleaned)'!A:A,'Auto Mekanika (cleaned)'!B:B,0) -> 0 | J7: =_xlfn.XLOOKUP(B7,'Bengkel Multi Var (cleaned)'!A:A,'Bengkel Multi Var (cleaned)'!B:B,0) -> 0 | K7: 0 | L7: =_xlfn.XLOOKUP(B7,'Drivewell (cleaned)'!A:A,'Drivewell (cleaned)'!B:B,0) -> 0 | M7: 0 | N7: 0 | O7: 0 | P7: =_xlfn.XLOOKUP(B7,'CV Sun (cleaned)'!A:A,'CV Sun (cleaned)'!B:B,0) -> 0 | Q7: =_xlfn.XLOOKUP(B7,'Sumber Timur (clean)'!F:F,'Sumber Timur (clean)'!L:L,0) -> 0 | R7: =_xlfn.XLOOKUP(B7,'Honda Duren (clean)'!F:F,'Honda Duren (clean)'!L:L,0) -> 0 | S7: 0 | T7: =SUM(C7:S7) -> 0
A8: =VLOOKUP(B8,#REF!,5,0) -> #REF! | B8: BOSCH Air Filter A 2180 | C8: =_xlfn.XLOOKUP(B8,'Pit Stop (cleaned)'!A:A,'Pit Stop (cleaned)'!B:B,0) -> 0 | D8: =_xlfn.XLOOKUP(B8,'Subur Makmur Ban (Agg)'!$F$1:$F$5,'Subur Makmur Ban (Agg)'!$L$1:$L$5,0) -> 0 | E8: =_xlfn.XLOOKUP(B8,'Bengkel Pegasus (Agg)'!F:F,'Bengkel Pegasus (Agg)'!L:L,0) -> 0 | F8: =_xlfn.XLOOKUP(B8,'Autocraft (agg)'!F:F,'Autocraft (agg)'!L:L,0) -> 0 | G8: =_xlfn.XLOOKUP(B8,'Autones (cleaned)'!A:A,'Autones (cleaned)'!B:B,0) -> 0 | H8: =_xlfn.XLOOKUP(B8,'ADS Prima (cleaned)'!A:A,'ADS Prima (cleaned)'!B:B,0) -> 0 | I8: =_xlfn.XLOOKUP(B8,'Auto Mekanika (cleaned)'!A:A,'Auto Mekanika (cleaned)'!B:B,0) -> 0 | J8: =_xlfn.XLOOKUP(B8,'Bengkel Multi Var (cleaned)'!A:A,'Bengkel Multi Var (cleaned)'!B:B,0) -> 0 | K8: =_xlfn.XLOOKUP(B8,'[2]EURO GALLARIA'!F:F,'[2]EURO GALLARIA'!L:L,0) -> 0 | L8: =_xlfn.XLOOKUP(B8,'Drivewell (cleaned)'!A:A,'Drivewell (cleaned)'!B:B,0) -> 0 | M8: =_xlfn.XLOOKUP(B8,'[2]Mersi (CLEAN)'!D:D,'[2]Mersi (CLEAN)'!E:E,0) -> 0 | N8: 0 | O8: 0 | P8: =_xlfn.XLOOKUP(B8,'CV Sun (cleaned)'!A:A,'CV Sun (cleaned)'!B:B,0) -> 0 | Q8: =_xlfn.XLOOKUP(B8,'Sumber Timur (clean)'!F:F,'Sumber Timur (clean)'!L:L,0) -> 0 | R8: =_xlfn.XLOOKUP(B8,'Honda Duren (clean)'!F:F,'Honda Duren (clean)'!L:L,0) -> 0 | S8: =_xlfn.XLOOKUP(B8,'[2]LAVANDER CLEAN'!A:A,'[2]LAVANDER CLEAN'!B:B,0) -> 0 | T8: =SUM(C8:S8) -> 0 | U8: 157950 | V8: =IF(T8*U8=0,"",T8*U8) | W8: 0986AF2180
A9: =VLOOKUP(B9,#REF!,5,0) -> #REF! | B9: DENSO Oil Filter DXE-1001 | C9: =_xlfn.XLOOKUP(B9,'Pit Stop (cleaned)'!A:A,'Pit Stop (cleaned)'!B:B,0) -> 0 | D9: =_xlfn.XLOOKUP(B9,'Subur Makmur Ban (Agg)'!$F$1:$F$5,'Subur Makmur Ban (Agg)'!$L$1:$L$5,0) -> 0 | E9: =_xlfn.XLOOKUP(B9,'Bengkel Pegasus (Agg)'!F:F,'Bengkel Pegasus (Agg)'!L:L,0) -> 0 | F9: =_xlfn.XLOOKUP(B9,'Autocraft (agg)'!F:F,'Autocraft (agg)'!L:L,0) -> 0 | G9: =_xlfn.XLOOKUP(B9,'Autones (cleaned)'!A:A,'Autones (cleaned)'!B:B,0) -> 0 | H9: =_xlfn.XLOOKUP(B9,'ADS Prima (cleaned)'!A:A,'ADS Prima (cleaned)'!B:B,0) -> 0 | I9: =_xlfn.XLOOKUP(B9,'Auto Mekanika (cleaned)'!A:A,'Auto Mekanika (cleaned)'!B:B,0) -> 0 | J9: =_xlfn.XLOOKUP(B9,'Bengkel Multi Var (cleaned)'!A:A,'Bengkel Multi Var (cleaned)'!B:B,0) -> 0 | K9: 0 | L9: =_xlfn.XLOOKUP(B9,'Drivewell (cleaned)'!A:A,'Drivewell (cleaned)'!B:B,0) -> 0 | M9: 0 | N9: 0 | O9: 0 | P9: =_xlfn.XLOOKUP(B9,'CV Sun (cleaned)'!A:A,'CV Sun (cleaned)'!B:B,0) -> 0 | Q9: =_xlfn.XLOOKUP(B9,'Sumber Timur (clean)'!F:F,'Sumber Timur (clean)'!L:L,0) -> 0 | R9: =_xlfn.XLOOKUP(B9,'Honda Duren (clean)'!F:F,'Honda Duren (clean)'!L:L,0) -> 0 | S9: 0 | T9: =SUM(C9:S9) -> 0
A10: =VLOOKUP(B10,#REF!,5,0) -> #REF! | B10: BOSCH Spark Plug F6TC(W8DC) - Standard | C10: =_xlfn.XLOOKUP(B10,'Pit Stop (cleaned)'!A:A,'Pit Stop (cleaned)'!B:B,0) -> 0 | D10: =_xlfn.XLOOKUP(B10,'Subur Makmur Ban (Agg)'!$F$1:$F$5,'Subur Makmur Ban (Agg)'!$L$1:$L$5,0) -> 0 | E10: =_xlfn.XLOOKUP(B10,'Bengkel Pegasus (Agg)'!F:F,'Bengkel Pegasus (Agg)'!L:L,0) -> 0 | F10: =_xlfn.XLOOKUP(B10,'Autocraft (agg)'!F:F,'Autocraft (agg)'!L:L,0) -> 0 | G10: =_xlfn.XLOOKUP(B10,'Autones (cleaned)'!A:A,'Autones (cleaned)'!B:B,0) -> 0 | H10: =_xlfn.XLOOKUP(B10,'ADS Prima (cleaned)'!A:A,'ADS Prima (cleaned)'!B:B,0) -> 0 | I10: =_xlfn.XLOOKUP(B10,'Auto Mekanika (cleaned)'!A:A,'Auto Mekanika (cleaned)'!B:B,0) -> 0 | J10: =_xlfn.XLOOKUP(B10,'Bengkel Multi Var (cleaned)'!A:A,'Bengkel Multi Var (cleaned)'!B:B,0) -> 0 | K10: 0 | L10: =_xlfn.XLOOKUP(B10,'Drivewell (cleaned)'!A:A,'Drivewell (cleaned)'!B:B,0) -> 0 | M10: 0 | N10: 0 | O10: 0 | P10: =_xlfn.XLOOKUP(B10,'CV Sun (cleaned)'!A:A,'CV Sun (cleaned)'!B:B,0) -> 0 | Q10: =_xlfn.XLOOKUP(B10,'Sumber Timur (clean)'!F:F,'Sumber Timur (clean)'!L:L,0) -> 0 | R10: =_xlfn.XLOOKUP(B10,'Honda Duren (clean)'!F:F,'Honda Duren (clean)'!L:L,0) -> 0 | S10: 0 | T10: =SUM(C10:S10) -> 0
A11: =VLOOKUP(B11,#REF!,5,0) -> #REF! | B11: BOSCH Battery MF Blue 80D23L 12V-70Ah | C11: =_xlfn.XLOOKUP(B11,'Pit Stop (cleaned)'!A:A,'Pit Stop (cleaned)'!B:B,0) -> 0 | D11: =_xlfn.XLOOKUP(B11,'Subur Makmur Ban (Agg)'!$F$1:$F$5,'Subur Makmur Ban (Agg)'!$L$1:$L$5,0) -> 0 | E11: =_xlfn.XLOOKUP(B11,'Bengkel Pegasus (Agg)'!F:F,'Bengkel Pegasus (Agg)'!L:L,0) -> 0 | F11: =_xlfn.XLOOKUP(B11,'Autocraft (agg)'!F:F,'Autocraft (agg)'!L:L,0) -> 0 | G11: =_xlfn.XLOOKUP(B11,'Autones (cleaned)'!A:A,'Autones (cleaned)'!B:B,0) -> 0 | H11: =_xlfn.XLOOKUP(B11,'ADS Prima (cleaned)'!A:A,'ADS Prima (cleaned)'!B:B,0) -> 0 | I11: =_xlfn.XLOOKUP(B11,'Auto Mekanika (cleaned)'!A:A,'Auto Mekanika (cleaned)'!B:B,0) -> 0 | J11: =_xlfn.XLOOKUP(B11,'Bengkel Multi Var (cleaned)'!A:A,'Bengkel Multi Var (cleaned)'!B:B,0) -> 0 | K11: 0 | L11: =_xlfn.XLOOKUP(B11,'Drivewell (cleaned)'!A:A,'Drivewell (cleaned)'!B:B,0) -> 0 | M11: 0 | N11: 0 | O11: 0 | P11: =_xlfn.XLOOKUP(B11,'CV Sun (cleaned)'!A:A,'CV Sun (cleaned)'!B:B,0) -> 0 | Q11: =_xlfn.XLOOKUP(B11,'Sumber Timur (clean)'!F:F,'Sumber Timur (clean)'!L:L,0) -> 0 | R11: =_xlfn.XLOOKUP(B11,'Honda Duren (clean)'!F:F,'Honda Duren (clean)'!L:L,0) -> 0 | S11: 0 | T11: =SUM(C11:S11) -> 0
A12: =VLOOKUP(B12,#REF!,5,0) -> #REF! | B12: BOSCH Battery MF Blue NS60 46B24R 12V-42Ah | C12: =_xlfn.XLOOKUP(B12,'Pit Stop (cleaned)'!A:A,'Pit Stop (cleaned)'!B:B,0) -> 0 | D12: =_xlfn.XLOOKUP(B12,'Subur Makmur Ban (Agg)'!$F$1:$F$5,'Subur Makmur Ban (Agg)'!$L$1:$L$5,0) -> 0 | E12: =_xlfn.XLOOKUP(B12,'Bengkel Pegasus (Agg)'!F:F,'Bengkel Pegasus (Agg)'!L:L,0) -> 0 | F12: =_xlfn.XLOOKUP(B12,'Autocraft (agg)'!F:F,'Autocraft (agg)'!L:L,0) -> 0 | G12: =_xlfn.XLOOKUP(B12,'Autones (cleaned)'!A:A,'Autones (cleaned)'!B:B,0) -> 0 | H12: =_xlfn.XLOOKUP(B12,'ADS Prima (cleaned)'!A:A,'ADS Prima (cleaned)'!B:B,0) -> 0 | I12: =_xlfn.XLOOKUP(B12,'Auto Mekanika (cleaned)'!A:A,'Auto Mekanika (cleaned)'!B:B,0) -> 0 | J12: =_xlfn.XLOOKUP(B12,'Bengkel Multi Var (cleaned)'!A:A,'Bengkel Multi Var (cleaned)'!B:B,0) -> 0 | K12: =_xlfn.XLOOKUP(B12,'[2]EURO GALLARIA'!F:F,'[2]EURO GALLARIA'!L:L,0) -> 0 | L12: =_xlfn.XLOOKUP(B12,'Drivewell (cleaned)'!A:A,'Drivewell (cleaned)'!B:B,0) -> 0 | M12: =_xlfn.XLOOKUP(B12,'[2]Mersi (CLEAN)'!D:D,'[2]Mersi (CLEAN)'!E:E,0) -> 0 | N12: 0 | O12: 0 | P12: =_xlfn.XLOOKUP(B12,'CV Sun (cleaned)'!A:A,'CV Sun (cleaned)'!B:B,0) -> 0 | Q12: =_xlfn.XLOOKUP(B12,'Sumber Timur (clean)'!F:F,'Sumber Timur (clean)'!L:L,0) -> 0 | R12: =_xlfn.XLOOKUP(B12,'Honda Duren (clean)'!F:F,'Honda Duren (clean)'!L:L,0) -> 0 | S12: =_xlfn.XLOOKUP(B12,'[2]LAVANDER CLEAN'!A:A,'[2]LAVANDER CLEAN'!B:B,0) -> 0 | T12: =SUM(C12:S12) -> 0 | U12: 675660 | V12: =IF(T12*U12=0,"",T12*U12) | W12: 0986A00362
A13: =VLOOKUP(B13,#REF!,5,0) -> #REF! | B13: BOSCH Battery MF Blue NS60LS 46B24LS 12V-42Ah | C13: =_xlfn.XLOOKUP(B13,'Pit Stop (cleaned)'!A:A,'Pit Stop (cleaned)'!B:B,0) -> 0 | D13: =_xlfn.XLOOKUP(B13,'Subur Makmur Ban (Agg)'!$F$1:$F$5,'Subur Makmur Ban (Agg)'!$L$1:$L$5,0) -> 0 | E13: =_xlfn.XLOOKUP(B13,'Bengkel Pegasus (Agg)'!F:F,'Bengkel Pegasus (Agg)'!L:L,0) -> 0 | F13: =_xlfn.XLOOKUP(B13,'Autocraft (agg)'!F:F,'Autocraft (agg)'!L:L,0) -> 0 | G13: =_xlfn.XLOOKUP(B13,'Autones (cleaned)'!A:A,'Autones (cleaned)'!B:B,0) -> 5 | H13: =_xlfn.XLOOKUP(B13,'ADS Prima (cleaned)'!A:A,'ADS Prima (cleaned)'!B:B,0) -> 0 | I13: =_xlfn.XLOOKUP(B13,'Auto Mekanika (cleaned)'!A:A,'Auto Mekanika (cleaned)'!B:B,0) -> 0 | J13: =_xlfn.XLOOKUP(B13,'Bengkel Multi Var (cleaned)'!A:A,'Bengkel Multi Var (cleaned)'!B:B,0) -> 0 | K13: =_xlfn.XLOOKUP(B13,'[2]EURO GALLARIA'!F:F,'[2]EURO GALLARIA'!L:L,0) -> 0 | L13: =_xlfn.XLOOKUP(B13,'Drivewell (cleaned)'!A:A,'Drivewell (cleaned)'!B:B,0) -> 0 | M13: =_xlfn.XLOOKUP(B13,'[2]Mersi (CLEAN)'!D:D,'[2]Mersi (CLEAN)'!E:E,0) -> 0 | N13: 0 | O13: 0 | P13: =_xlfn.XLOOKUP(B13,'CV Sun (cleaned)'!A:A,'CV Sun (cleaned)'!B:B,0) -> 0 | Q13: =_xlfn.XLOOKUP(B13,'Sumber Timur (clean)'!F:F,'Sumber Timur (clean)'!L:L,0) -> 0 | R13: =_xlfn.XLOOKUP(B13,'Honda Duren (clean)'!F:F,'Honda Duren (clean)'!L:L,0) -> 0 | S13: =_xlfn.XLOOKUP(B13,'[2]LAVANDER CLEAN'!A:A,'[2]LAVANDER CLEAN'!B:B,0) -> 0 | T13: =SUM(C13:S13) -> 5 | U13: 675660 | V13: =IF(T13*U13=0,"",T13*U13) -> 3378300 | W13: 0986A00365
A14: =VLOOKUP(B14,#REF!,5,0) -> #REF! | B14: BOSCH Battery MF Blue NX11005L 80D26L 12V-70Ah | C14: =_xlfn.XLOOKUP(B14,'Pit Stop (cleaned)'!A:A,'Pit Stop (cleaned)'!B:B,0) -> 0 | D14: =_xlfn.XLOOKUP(B14,'Subur Makmur Ban (Agg)'!$F$1:$F$5,'Subur Makmur Ban (Agg)'!$L$1:$L$5,0) -> 0 | E14: =_xlfn.XLOOKUP(B14,'Bengkel Pegasus (Agg)'!F:F,'Bengkel Pegasus (Agg)'!L:L,0) -> 0 | F14: =_xlfn.XLOOKUP(B14,'Autocraft (agg)'!F:F,'Autocraft (agg)'!L:L,0) -> 0 | G14: =_xlfn.XLOOKUP(B14,'Autones (cleaned)'!A:A,'Autones (cleaned)'!B:B,0) -> 0 | H14: =_xlfn.XLOOKUP(B14,'ADS Prima (cleaned)'!A:A,'ADS Prima (cleaned)'!B:B,0) -> 0 | I14: =_xlfn.XLOOKUP(B14,'Auto Mekanika (cleaned)'!A:A,'Auto Mekanika (cleaned)'!B:B,0) -> 0 | J14: =_xlfn.XLOOKUP(B14,'Bengkel Multi Var (cleaned)'!A:A,'Bengkel Multi Var (cleaned)'!B:B,0) -> 0 | K14: 0 | L14: =_xlfn.XLOOKUP(B14,'Drivewell (cleaned)'!A:A,'Drivewell (cleaned)'!B:B,0) -> 0 | M14: 0 | N14: 0 | O14: 0 | P14: =_xlfn.XLOOKUP(B14,'CV Sun (cleaned)'!A:A,'CV Sun (cleaned)'!B:B,0) -> 0 | Q14: =_xlfn.XLOOKUP(B14,'Sumber Timur (clean)'!F:F,'Sumber Timur (clean)'!L:L,0) -> 0 | R14: =_xlfn.XLOOKUP(B14,'Honda Duren (clean)'!F:F,'Honda Duren (clean)'!L:L,0) -> 0 | S14: 0 | T14: =SUM(C14:S14) -> 0
A15: =VLOOKUP(B15,#REF!,5,0) -> #REF! | B15: MONROE Shock Absorber 744683SP Front-LH | C15: =_xlfn.XLOOKUP(B15,'Pit Stop (cleaned)'!A:A,'Pit Stop (cleaned)'!B:B,0) -> 0 | D15: =_xlfn.XLOOKUP(B15,'Subur Makmur Ban (Agg)'!$F$1:$F$5,'Subur Makmur Ban (Agg)'!$L$1:$L$5,0) -> 0 | E15: =_xlfn.XLOOKUP(B15,'Bengkel Pegasus (Agg)'!F:F,'Bengkel Pegasus (Agg)'!L:L,0) -> 0 | F15: =_xlfn.XLOOKUP(B15,'Autocraft (agg)'!F:F,'Autocraft (agg)'!L:L,0) -> 0 | G15: =_xlfn.XLOOKUP(B15,'Autones (cleaned)'!A:A,'Autones (cleaned)'!B:B,0) -> 0 | H15: =_xlfn.XLOOKUP(B15,'ADS Prima (cleaned)'!A:A,'ADS Prima (cleaned)'!B:B,0) -> 0 | I15: =_xlfn.XLOOKUP(B15,'Auto Mekanika (cleaned)'!A:A,'Auto Mekanika (cleaned)'!B:B,0) -> 0 | J15: =_xlfn.XLOOKUP(B15,'Bengkel Multi Var (cleaned)'!A:A,'Bengkel Multi Var (cleaned)'!B:B,0) -> 0 | K15: 0 | L15: =_xlfn.XLOOKUP(B15,'Drivewell (cleaned)'!A:A,'Drivewell (cleaned)'!B:B,0) -> 0 | M15: 0 | N15: 0 | O15: 0 | P15: =_xlfn.XLOOKUP(B15,'CV Sun (cleaned)'!A:A,'CV Sun (cleaned)'!B:B,0) -> 0 | Q15: =_xlfn.XLOOKUP(B15,'Sumber Timur (clean)'!F:F,'Sumber Timur (clean)'!L:L,0) -> 0 | R15: =_xlfn.XLOOKUP(B15,'Honda Duren (clean)'!F:F,'Honda Duren (clean)'!L:L,0) -> 0 | S15: 0 | T15: =SUM(C15:S15) -> 0
A16: =VLOOKUP(B16,#REF!,5,0) -> #REF! | B16: MONROE Shock Absorber 744682SP Front-RH | C16: =_xlfn.XLOOKUP(B16,'Pit Stop (cleaned)'!A:A,'Pit Stop (cleaned)'!B:B,0) -> 0 | D16: =_xlfn.XLOOKUP(B16,'Subur Makmur Ban (Agg)'!$F$1:$F$5,'Subur Makmur Ban (Agg)'!$L$1:$L$5,0) -> 0 | E16: =_xlfn.XLOOKUP(B16,'Bengkel Pegasus (Agg)'!F:F,'Bengkel Pegasus (Agg)'!L:L,0) -> 0 | F16: =_xlfn.XLOOKUP(B16,'Autocraft (agg)'!F:F,'Autocraft (agg)'!L:L,0) -> 0 | G16: =_xlfn.XLOOKUP(B16,'Autones (cleaned)'!A:A,'Autones (cleaned)'!B:B,0) -> 0 | H16: =_xlfn.XLOOKUP(B16,'ADS Prima (cleaned)'!A:A,'ADS Prima (cleaned)'!B:B,0) -> 0 | I16: =_xlfn.XLOOKUP(B16,'Auto Mekanika (cleaned)'!A:A,'Auto Mekanika (cleaned)'!B:B,0) -> 0 | J16: =_xlfn.XLOOKUP(B16,'Bengkel Multi Var (cleaned)'!A:A,'Bengkel Multi Var (cleaned)'!B:B,0) -> 0 | K16: 0 | L16: =_xlfn.XLOOKUP(B16,'Drivewell (cleaned)'!A:A,'Drivewell (cleaned)'!B:B,0) -> 0 | M16: 0 | N16: 0 | O16: 0 | P16: =_xlfn.XLOOKUP(B16,'CV Sun (cleaned)'!A:A,'CV Sun (cleaned)'!B:B,0) -> 0 | Q16: =_xlfn.XLOOKUP(B16,'Sumber Timur (clean)'!F:F,'Sumber Timur (clean)'!L:L,0) -> 0 | R16: =_xlfn.XLOOKUP(B16,'Honda Duren (clean)'!F:F,'Honda Duren (clean)'!L:L,0) -> 0 | S16: 0 | T16: =SUM(C16:S16) -> 0
A17: =VLOOKUP(B17,#REF!,5,0) -> #REF! | B17: MONROE Shock Absorber 744641SP Front-LH | C17: =_xlfn.XLOOKUP(B17,'Pit Stop (cleaned)'!A:A,'Pit Stop (cleaned)'!B:B,0) -> 0 | D17: =_xlfn.XLOOKUP(B17,'Subur Makmur Ban (Agg)'!$F$1:$F$5,'Subur Makmur Ban (Agg)'!$L$1:$L$5,0) -> 0 | E17: =_xlfn.XLOOKUP(B17,'Bengkel Pegasus (Agg)'!F:F,'Bengkel Pegasus (Agg)'!L:L,0) -> 0 | F17: =_xlfn.XLOOKUP(B17,'Autocraft (agg)'!F:F,'Autocraft (agg)'!L:L,0) -> 0 | G17: =_xlfn.XLOOKUP(B17,'Autones (cleaned)'!A:A,'Autones (cleaned)'!B:B,0) -> 0 | H17: =_xlfn.XLOOKUP(B17,'ADS Prima (cleaned)'!A:A,'ADS Prima (cleaned)'!B:B,0) -> 0 | I17: =_xlfn.XLOOKUP(B17,'Auto Mekanika (cleaned)'!A:A,'Auto Mekanika (cleaned)'!B:B,0) -> 0 | J17: =_xlfn.XLOOKUP(B17,'Bengkel Multi Var (cleaned)'!A:A,'Bengkel Multi Var (cleaned)'!B:B,0) -> 0 | K17: 0 | L17: =_xlfn.XLOOKUP(B17,'Drivewell (cleaned)'!A:A,'Drivewell (cleaned)'!B:B,0) -> 0 | M17: 0 | N17: 0 | O17: 0 | P17: =_xlfn.XLOOKUP(B17,'CV Sun (cleaned)'!A:A,'CV Sun (cleaned)'!B:B,0) -> 0 | Q17: =_xlfn.XLOOKUP(B17,'Sumber Timur (clean)'!F:F,'Sumber Timur (clean)'!L:L,0) -> 0 | R17: =_xlfn.XLOOKUP(B17,'Honda Duren (clean)'!F:F,'Honda Duren (clean)'!L:L,0) -> 0 | S17: 0 | T17: =SUM(C17:S17) -> 0
A18: =VLOOKUP(B18,#REF!,5,0) -> #REF! | B18: MONROE Shock Absorber 744640SP Front-RH | C18: =_xlfn.XLOOKUP(B18,'Pit Stop (cleaned)'!A:A,'Pit Stop (cleaned)'!B:B,0) -> 0 | D18: =_xlfn.XLOOKUP(B18,'Subur Makmur Ban (Agg)'!$F$1:$F$5,'Subur Makmur Ban (Agg)'!$L$1:$L$5,0) -> 0 | E18: =_xlfn.XLOOKUP(B18,'Bengkel Pegasus (Agg)'!F:F,'Bengkel Pegasus (Agg)'!L:L,0) -> 0 | F18: =_xlfn.XLOOKUP(B18,'Autocraft (agg)'!F:F,'Autocraft (agg)'!L:L,0) -> 0 | G18: =_xlfn.XLOOKUP(B18,'Autones (cleaned)'!A:A,'Autones (cleaned)'!B:B,0) -> 0 | H18: =_xlfn.XLOOKUP(B18,'ADS Prima (cleaned)'!A:A,'ADS Prima (cleaned)'!B:B,0) -> 0 | I18: =_xlfn.XLOOKUP(B18,'Auto Mekanika (cleaned)'!A:A,'Auto Mekanika (cleaned)'!B:B,0) -> 0 | J18: =_xlfn.XLOOKUP(B18,'Bengkel Multi Var (cleaned)'!A:A,'Bengkel Multi Var (cleaned)'!B:B,0) -> 0 | K18: 0 | L18: =_xlfn.XLOOKUP(B18,'Drivewell (cleaned)'!A:A,'Drivewell (cleaned)'!B:B,0) -> 0 | M18: 0 | N18: 0 | O18: 0 | P18: =_xlfn.XLOOKUP(B18,'CV Sun (cleaned)'!A:A,'CV Sun (cleaned)'!B:B,0) -> 0 | Q18: =_xlfn.XLOOKUP(B18,'Sumber Timur (clean)'!F:F,'Sumber Timur (clean)'!L:L,0) -> 0 | R18: =_xlfn.XLOOKUP(B18,'Honda Duren (clean)'!F:F,'Honda Duren (clean)'!L:L,0) -> 0 | S18: 0 | T18: =SUM(C18:S18) -> 0
A19: =VLOOKUP(B19,#REF!,5,0) -> #REF! | B19: MONROE Shock Absorber 744563SP Front-LH | C19: =_xlfn.XLOOKUP(B19,'Pit Stop (cleaned)'!A:A,'Pit Stop (cleaned)'!B:B,0) -> 0 | D19: =_xlfn.XLOOKUP(B19,'Subur Makmur Ban (Agg)'!$F$1:$F$5,'Subur Makmur Ban (Agg)'!$L$1:$L$5,0) -> 0 | E19: =_xlfn.XLOOKUP(B19,'Bengkel Pegasus (Agg)'!F:F,'Bengkel Pegasus (Agg)'!L:L,0) -> 0 | F19: =_xlfn.XLOOKUP(B19,'Autocraft (agg)'!F:F,'Autocraft (agg)'!L:L,0) -> 0 | G19: =_xlfn.XLOOKUP(B19,'Autones (cleaned)'!A:A,'Autones (cleaned)'!B:B,0) -> 0 | H19: =_xlfn.XLOOKUP(B19,'ADS Prima (cleaned)'!A:A,'ADS Prima (cleaned)'!B:B,0) -> 0 | I19: =_xlfn.XLOOKUP(B19,'Auto Mekanika (cleaned)'!A:A,'Auto Mekanika (cleaned)'!B:B,0) -> 0 | J19: =_xlfn.XLOOKUP(B19,'Bengkel Multi Var (cleaned)'!A:A,'Bengkel Multi Var (cleaned)'!B:B,0) -> 0 | K19: 0 | L19: =_xlfn.XLOOKUP(B19,'Drivewell (cleaned)'!A:A,'Drivewell (cleaned)'!B:B,0) -> 0 | M19: 0 | N19: 0 | O19: 0 | P19: =_xlfn.XLOOKUP(B19,'CV Sun (cleaned)'!A:A,'CV Sun (cleaned)'!B:B,0) -> 0 | Q19: =_xlfn.XLOOKUP(B19,'Sumber Timur (clean)'!F:F,'Sumber Timur (clean)'!L:L,0) -> 0 | R19: =_xlfn.XLOOKUP(B19,'Honda Duren (clean)'!F:F,'Honda Duren (clean)'!L:L,0) -> 0 | S19: 0 | T19: =SUM(C19:S19) -> 0
A20: =VLOOKUP(B20,#REF!,5,0) -> #REF! | B20: MASSIV Battery Thunder(MF)-DIN 66 566LN3 12V-66Ah | C20: =_xlfn.XLOOKUP(B20,'Pit Stop (cleaned)'!A:A,'Pit Stop (cleaned)'!B:B,0) -> 0 | D20: =_xlfn.XLOOKUP(B20,'Subur Makmur Ban (Agg)'!$F$1:$F$5,'Subur Makmur Ban (Agg)'!$L$1:$L$5,0) -> 0 | E20: =_xlfn.XLOOKUP(B20,'Bengkel Pegasus (Agg)'!F:F,'Bengkel Pegasus (Agg)'!L:L,0) -> 0 | F20: =_xlfn.XLOOKUP(B20,'Autocraft (agg)'!F:F,'Autocraft (agg)'!L:L,0) -> 0 | G20: =_xlfn.XLOOKUP(B20,'Autones (cleaned)'!A:A,'Autones (cleaned)'!B:B,0) -> 0 | H20: =_xlfn.XLOOKUP(B20,'ADS Prima (cleaned)'!A:A,'ADS Prima (cleaned)'!B:B,0) -> 0 | I20: =_xlfn.XLOOKUP(B20,'Auto Mekanika (cleaned)'!A:A,'Auto Mekanika (cleaned)'!B:B,0) -> 0 | J20: =_xlfn.XLOOKUP(B20,'Bengkel Multi Var (cleaned)'!A:A,'Bengkel Multi Var (cleaned)'!B:B,0) -> 0 | K20: 0 | L20: =_xlfn.XLOOKUP(B20,'Drivewell (cleaned)'!A:A,'Drivewell (cleaned)'!B:B,0) -> 0 | M20: 0 | N20: 0 | O20: 0 | P20: =_xlfn.XLOOKUP(B20,'CV Sun (cleaned)'!A:A,'CV Sun (cleaned)'!B:B,0) -> 0 | Q20: =_xlfn.XLOOKUP(B20,'Sumber Timur (clean)'!F:F,'Sumber Timur (clean)'!L:L,0) -> 0 | R20: =_xlfn.XLOOKUP(B20,'Honda Duren (clean)'!F:F,'Honda Duren (clean)'!L:L,0) -> 0 | S20: 0 | T20: =SUM(C20:S20) -> 0
A21: =VLOOKUP(B21,#REF!,5,0) -> #REF! | B21: MONROE Shock Absorber 744562SP Front-RH | C21: =_xlfn.XLOOKUP(B21,'Pit Stop (cleaned)'!A:A,'Pit Stop (cleaned)'!B:B,0) -> 0 | D21: =_xlfn.XLOOKUP(B21,'Subur Makmur Ban (Agg)'!$F$1:$F$5,'Subur Makmur Ban (Agg)'!$L$1:$L$5,0) -> 0 | E21: =_xlfn.XLOOKUP(B21,'Bengkel Pegasus (Agg)'!F:F,'Bengkel Pegasus (Agg)'!L:L,0) -> 0 | F21: =_xlfn.XLOOKUP(B21,'Autocraft (agg)'!F:F,'Autocraft (agg)'!L:L,0) -> 0 | G21: =_xlfn.XLOOKUP(B21,'Autones (cleaned)'!A:A,'Autones (cleaned)'!B:B,0) -> 0 | H21: =_xlfn.XLOOKUP(B21,'ADS Prima (cleaned)'!A:A,'ADS Prima (cleaned)'!B:B,0) -> 0 | I21: =_xlfn.XLOOKUP(B21,'Auto Mekanika (cleaned)'!A:A,'Auto Mekanika (cleaned)'!B:B,0) -> 0 | J21: =_xlfn.XLOOKUP(B21,'Bengkel Multi Var (cleaned)'!A:A,'Bengkel Multi Var (cleaned)'!B:B,0) -> 0 | K21: 0 | L21: =_xlfn.XLOOKUP(B21,'Drivewell (cleaned)'!A:A,'Drivewell (cleaned)'!B:B,0) -> 0 | M21: 0 | N21: 0 | O21: 0 | P21: =_xlfn.XLOOKUP(B21,'CV Sun (cleaned)'!A:A,'CV Sun (cleaned)'!B:B,0) -> 0 | Q21: =_xlfn.XLOOKUP(B21,'Sumber Timur (clean)'!F:F,'Sumber Timur (clean)'!L:L,0) -> 0 | R21: =_xlfn.XLOOKUP(B21,'Honda Duren (clean)'!F:F,'Honda Duren (clean)'!L:L,0) -> 0 | S21: 0 | T21: =SUM(C21:S21) -> 0
A22: =VLOOKUP(B22,#REF!,5,0) -> #REF! | B22: BOSCH Oil Filter P 9762 | C22: =_xlfn.XLOOKUP(B22,'Pit Stop (cleaned)'!A:A,'Pit Stop (cleaned)'!B:B,0) -> 0 | D22: =_xlfn.XLOOKUP(B22,'Subur Makmur Ban (Agg)'!$F$1:$F$5,'Subur Makmur Ban (Agg)'!$L$1:$L$5,0) -> 0 | E22: =_xlfn.XLOOKUP(B22,'Bengkel Pegasus (Agg)'!F:F,'Bengkel Pegasus (Agg)'!L:L,0) -> 0 | F22: =_xlfn.XLOOKUP(B22,'Autocraft (agg)'!F:F,'Autocraft (agg)'!L:L,0) -> 0 | G22: =_xlfn.XLOOKUP(B22,'Autones (cleaned)'!A:A,'Autones (cleaned)'!B:B,0) -> 0 | H22: =_xlfn.XLOOKUP(B22,'ADS Prima (cleaned)'!A:A,'ADS Prima (cleaned)'!B:B,0) -> 0 | I22: =_xlfn.XLOOKUP(B22,'Auto Mekanika (cleaned)'!A:A,'Auto Mekanika (cleaned)'!B:B,0) -> 0 | J22: =_xlfn.XLOOKUP(B22,'Bengkel Multi Var (cleaned)'!A:A,'Bengkel Multi Var (cleaned)'!B:B,0) -> 0 | K22: 0 | L22: =_xlfn.XLOOKUP(B22,'Drivewell (cleaned)'!A:A,'Drivewell (cleaned)'!B:B,0) -> 0 | M22: 0 | N22: 0 | O22: 0 | P22: =_xlfn.XLOOKUP(B22,'CV Sun (cleaned)'!A:A,'CV Sun (cleaned)'!B:B,0) -> 0 | Q22: =_xlfn.XLOOKUP(B22,'Sumber Timur (clean)'!F:F,'Sumber Timur (clean)'!L:L,0) -> 0 | R22: =_xlfn.XLOOKUP(B22,'Honda Duren (clean)'!F:F,'Honda Duren (clean)'!L:L,0) -> 0 | S22: 0 | T22: =SUM(C22:S22) -> 0
A23: =VLOOKUP(B23,#REF!,5,0) -> #REF! | B23: BOSCH Battery MF Blue 58014 12V-80Ah | C23: =_xlfn.XLOOKUP(B23,'Pit Stop (cleaned)'!A:A,'Pit Stop (cleaned)'!B:B,0) -> 0 | D23: =_xlfn.XLOOKUP(B23,'Subur Makmur Ban (Agg)'!$F$1:$F$5,'Subur Makmur Ban (Agg)'!$L$1:$L$5,0) -> 0 | E23: =_xlfn.XLOOKUP(B23,'Bengkel Pegasus (Agg)'!F:F,'Bengkel Pegasus (Agg)'!L:L,0) -> 0 | F23: =_xlfn.XLOOKUP(B23,'Autocraft (agg)'!F:F,'Autocraft (agg)'!L:L,0) -> 0 | G23: =_xlfn.XLOOKUP(B23,'Autones (cleaned)'!A:A,'Autones (cleaned)'!B:B,0) -> 0 | H23: =_xlfn.XLOOKUP(B23,'ADS Prima (cleaned)'!A:A,'ADS Prima (cleaned)'!B:B,0) -> 0 | I23: =_xlfn.XLOOKUP(B23,'Auto Mekanika (cleaned)'!A:A,'Auto Mekanika (cleaned)'!B:B,0) -> 0 | J23: =_xlfn.XLOOKUP(B23,'Bengkel Multi Var (cleaned)'!A:A,'Bengkel Multi Var (cleaned)'!B:B,0) -> 0 | K23: 0 | L23: =_xlfn.XLOOKUP(B23,'Drivewell (cleaned)'!A:A,'Drivewell (cleaned)'!B:B,0) -> 0 | M23: 0 | N23: 0 | O23: 0 | P23: =_xlfn.XLOOKUP(B23,'CV Sun (cleaned)'!A:A,'CV Sun (cleaned)'!B:B,0) -> 0 | Q23: =_xlfn.XLOOKUP(B23,'Sumber Timur (clean)'!F:F,'Sumber Timur (clean)'!L:L,0) -> 0 | R23: =_xlfn.XLOOKUP(B23,'Honda Duren (clean)'!F:F,'Honda Duren (clean)'!L:L,0) -> 0 | S23: 0 | T23: =SUM(C23:S23) -> 0
A24: =VLOOKUP(B24,#REF!,5,0) -> #REF! | B24: MONROE Shock Absorber 744515SP Front-LH | C24: =_xlfn.XLOOKUP(B24,'Pit Stop (cleaned)'!A:A,'Pit Stop (cleaned)'!B:B,0) -> 0 | D24: =_xlfn.XLOOKUP(B24,'Subur Makmur Ban (Agg)'!$F$1:$F$5,'Subur Makmur Ban (Agg)'!$L$1:$L$5,0) -> 0 | E24: =_xlfn.XLOOKUP(B24,'Bengkel Pegasus (Agg)'!F:F,'Bengkel Pegasus (Agg)'!L:L,0) -> 0 | F24: =_xlfn.XLOOKUP(B24,'Autocraft (agg)'!F:F,'Autocraft (agg)'!L:L,0) -> 0 | G24: =_xlfn.XLOOKUP(B24,'Autones (cleaned)'!A:A,'Autones (cleaned)'!B:B,0) -> 0 | H24: =_xlfn.XLOOKUP(B24,'ADS Prima (cleaned)'!A:A,'ADS Prima (cleaned)'!B:B,0) -> 0 | I24: =_xlfn.XLOOKUP(B24,'Auto Mekanika (cleaned)'!A:A,'Auto Mekanika (cleaned)'!B:B,0) -> 0 | J24: =_xlfn.XLOOKUP(B24,'Bengkel Multi Var (cleaned)'!A:A,'Bengkel Multi Var (cleaned)'!B:B,0) -> 0 | K24: 0 | L24: =_xlfn.XLOOKUP(B24,'Drivewell (cleaned)'!A:A,'Drivewell (cleaned)'!B:B,0) -> 0 | M24: 0 | N24: 0 | O24: 0 | P24: =_xlfn.XLOOKUP(B24,'CV Sun (cleaned)'!A:A,'CV Sun (cleaned)'!B:B,0) -> 0 | Q24: =_xlfn.XLOOKUP(B24,'Sumber Timur (clean)'!F:F,'Sumber Timur (clean)'!L:L,0) -> 0 | R24: =_xlfn.XLOOKUP(B24,'Honda Duren (clean)'!F:F,'Honda Duren (clean)'!L:L,0) -> 0 | S24: 0 | T24: =SUM(C24:S24) -> 0
A25: =VLOOKUP(B25,#REF!,5,0) -> #REF! | B25: MONROE Shock Absorber 744514SP Front-RH | C25: =_xlfn.XLOOKUP(B25,'Pit Stop (cleaned)'!A:A,'Pit Stop (cleaned)'!B:B,0) -> 0 | D25: =_xlfn.XLOOKUP(B25,'Subur Makmur Ban (Agg)'!$F$1:$F$5,'Subur Makmur Ban (Agg)'!$L$1:$L$5,0) -> 0 | E25: =_xlfn.XLOOKUP(B25,'Bengkel Pegasus (Agg)'!F:F,'Bengkel Pegasus (Agg)'!L:L,0) -> 0 | F25: =_xlfn.XLOOKUP(B25,'Autocraft (agg)'!F:F,'Autocraft (agg)'!L:L,0) -> 0 | G25: =_xlfn.XLOOKUP(B25,'Autones (cleaned)'!A:A,'Autones (cleaned)'!B:B,0) -> 0 | H25: =_xlfn.XLOOKUP(B25,'ADS Prima (cleaned)'!A:A,'ADS Prima (cleaned)'!B:B,0) -> 0 | I25: =_xlfn.XLOOKUP(B25,'Auto Mekanika (cleaned)'!A:A,'Auto Mekanika (cleaned)'!B:B,0) -> 0 | J25: =_xlfn.XLOOKUP(B25,'Bengkel Multi Var (cleaned)'!A:A,'Bengkel Multi Var (cleaned)'!B:B,0) -> 0 | K25: 0 | L25: =_xlfn.XLOOKUP(B25,'Drivewell (cleaned)'!A:A,'Drivewell (cleaned)'!B:B,0) -> 0 | M25: 0 | N25: 0 | O25: 0 | P25: =_xlfn.XLOOKUP(B25,'CV Sun (cleaned)'!A:A,'CV Sun (cleaned)'!B:B,0) -> 0 | Q25: =_xlfn.XLOOKUP(B25,'Sumber Timur (clean)'!F:F,'Sumber Timur (clean)'!L:L,0) -> 0 | R25: =_xlfn.XLOOKUP(B25,'Honda Duren (clean)'!F:F,'Honda Duren (clean)'!L:L,0) -> 0 | S25: 0 | T25: =SUM(C25:S25) -> 0
... A40: =VLOOKUP(B40,#REF!,5,0) -> #REF! | B40: DENSO Spark Plug IT20 - Iridium | C40: =_xlfn.XLOOKUP(B40,'Pit Stop (cleaned)'!A:A,'Pit Stop (cleaned)'!B:B,0) -> 0 | D40: =_xlfn.XLOOKUP(B40,'Subur Makmur Ban (Agg)'!$F$1:$F$5,'Subur Makmur Ban (Agg)'!$L$1:$L$5,0) -> 0 | E40: =_xlfn.XLOOKUP(B40,'Bengkel Pegasus (Agg)'!F:F,'Bengkel Pegasus (Agg)'!L:L,0) -> 0 | F40: =_xlfn.XLOOKUP(B40,'Autocraft (agg)'!F:F,'Autocraft (agg)'!L:L,0) -> 0 | G40: =_xlfn.XLOOKUP(B40,'Autones (cleaned)'!A:A,'Autones (cleaned)'!B:B,0) -> 0 | H40: =_xlfn.XLOOKUP(B40,'ADS Prima (cleaned)'!A:A,'ADS Prima (cleaned)'!B:B,0) -> 0 | I40: =_xlfn.XLOOKUP(B40,'Auto Mekanika (cleaned)'!A:A,'Auto Mekanika (cleaned)'!B:B,0) -> 0 | J40: =_xlfn.XLOOKUP(B40,'Bengkel Multi Var (cleaned)'!A:A,'Bengkel Multi Var (cleaned)'!B:B,0) -> 0 | K40: 0 | L40: =_xlfn.XLOOKUP(B40,'Drivewell (cleaned)'!A:A,'Drivewell (cleaned)'!B:B,0) -> 0 | M40: 0 | N40: 0 | O40: 0 | P40: =_xlfn.XLOOKUP(B40,'CV Sun (cleaned)'!A:A,'CV Sun (cleaned)'!B:B,0) -> 0 | Q40: =_xlfn.XLOOKUP(B40,'Sumber Timur (clean)'!F:F,'Sumber Timur (clean)'!L:L,0) -> 0 | R40: =_xlfn.XLOOKUP(B40,'Honda Duren (clean)'!F:F,'Honda Duren (clean)'!L:L,0) -> 0 | S40: 0 | T40: =SUM(C40:S40) -> 0
A41: =VLOOKUP(B41,#REF!,5,0) -> #REF! | B41: BOSCH Battery MF Blue NX100-S6L 55B24L 12V-45Ah | C41: =_xlfn.XLOOKUP(B41,'Pit Stop (cleaned)'!A:A,'Pit Stop (cleaned)'!B:B,0) -> 0 | D41: =_xlfn.XLOOKUP(B41,'Subur Makmur Ban (Agg)'!$F$1:$F$5,'Subur Makmur Ban (Agg)'!$L$1:$L$5,0) -> 0 | E41: =_xlfn.XLOOKUP(B41,'Bengkel Pegasus (Agg)'!F:F,'Bengkel Pegasus (Agg)'!L:L,0) -> 0 | F41: =_xlfn.XLOOKUP(B41,'Autocraft (agg)'!F:F,'Autocraft (agg)'!L:L,0) -> 0 | G41: =_xlfn.XLOOKUP(B41,'Autones (cleaned)'!A:A,'Autones (cleaned)'!B:B,0) -> 0 | H41: =_xlfn.XLOOKUP(B41,'ADS Prima (cleaned)'!A:A,'ADS Prima (cleaned)'!B:B,0) -> 0 | I41: =_xlfn.XLOOKUP(B41,'Auto Mekanika (cleaned)'!A:A,'Auto Mekanika (cleaned)'!B:B,0) -> 5 | J41: =_xlfn.XLOOKUP(B41,'Bengkel Multi Var (cleaned)'!A:A,'Bengkel Multi Var (cleaned)'!B:B,0) -> 0 | K41: =_xlfn.XLOOKUP(B41,'[2]EURO GALLARIA'!F:F,'[2]EURO GALLARIA'!L:L,0) -> 0 | L41: =_xlfn.XLOOKUP(B41,'Drivewell (cleaned)'!A:A,'Drivewell (cleaned)'!B:B,0) -> 0 | M41: =_xlfn.XLOOKUP(B41,'[2]Mersi (CLEAN)'!D:D,'[2]Mersi (CLEAN)'!E:E,0) -> 0 | N41: 0 | O41: 0 | P41: =_xlfn.XLOOKUP(B41,'CV Sun (cleaned)'!A:A,'CV Sun (cleaned)'!B:B,0) -> 0 | Q41: =_xlfn.XLOOKUP(B41,'Sumber Timur (clean)'!F:F,'Sumber Timur (clean)'!L:L,0) -> 0 | R41: =_xlfn.XLOOKUP(B41,'Honda Duren (clean)'!F:F,'Honda Duren (clean)'!L:L,0) -> 3 | S41: =_xlfn.XLOOKUP(B41,'[2]LAVANDER CLEAN'!A:A,'[2]LAVANDER CLEAN'!B:B,0) -> 0 | T41: =SUM(C41:S41) -> 8 | U41: 705060 | V41: =IF(T41*U41=0,"",T41*U41) -> 5640480 | W41: 0986A00406
A42: =VLOOKUP(B42,#REF!,5,0) -> #REF! | B42: BOSCH Battery MF Blue NX100-S6 55B24R 12V-45Ah | C42: =_xlfn.XLOOKUP(B42,'Pit Stop (cleaned)'!A:A,'Pit Stop (cleaned)'!B:B,0) -> 0 | D42: =_xlfn.XLOOKUP(B42,'Subur Makmur Ban (Agg)'!$F$1:$F$5,'Subur Makmur Ban (Agg)'!$L$1:$L$5,0) -> 0 | E42: =_xlfn.XLOOKUP(B42,'Bengkel Pegasus (Agg)'!F:F,'Bengkel Pegasus (Agg)'!L:L,0) -> 0 | F42: =_xlfn.XLOOKUP(B42,'Autocraft (agg)'!F:F,'Autocraft (agg)'!L:L,0) -> 0 | G42: =_xlfn.XLOOKUP(B42,'Autones (cleaned)'!A:A,'Autones (cleaned)'!B:B,0) -> 0 | H42: =_xlfn.XLOOKUP(B42,'ADS Prima (cleaned)'!A:A,'ADS Prima (cleaned)'!B:B,0) -> 0 | I42: =_xlfn.XLOOKUP(B42,'Auto Mekanika (cleaned)'!A:A,'Auto Mekanika (cleaned)'!B:B,0) -> 15 | J42: =_xlfn.XLOOKUP(B42,'Bengkel Multi Var (cleaned)'!A:A,'Bengkel Multi Var (cleaned)'!B:B,0) -> 0 | K42: =_xlfn.XLOOKUP(B42,'[2]EURO GALLARIA'!F:F,'[2]EURO GALLARIA'!L:L,0) -> 0 | L42: =_xlfn.XLOOKUP(B42,'Drivewell (cleaned)'!A:A,'Drivewell (cleaned)'!B:B,0) -> 0 | M42: =_xlfn.XLOOKUP(B42,'[2]Mersi (CLEAN)'!D:D,'[2]Mersi (CLEAN)'!E:E,0) -> 0 | N42: 0 | O42: 0 | P42: =_xlfn.XLOOKUP(B42,'CV Sun (cleaned)'!A:A,'CV Sun (cleaned)'!B:B,0) -> 0 | Q42: =_xlfn.XLOOKUP(B42,'Sumber Timur (clean)'!F:F,'Sumber Timur (clean)'!L:L,0) -> 0 | R42: =_xlfn.XLOOKUP(B42,'Honda Duren (clean)'!F:F,'Honda Duren (clean)'!L:L,0) -> 0 | S42: =_xlfn.XLOOKUP(B42,'[2]LAVANDER CLEAN'!A:A,'[2]LAVANDER CLEAN'!B:B,0) -> 0 | T42: =SUM(C42:S42) -> 15 | U42: 705060 | V42: =IF(T42*U42=0,"",T42*U42) -> 10575900 | W42: 0986A00407
A43: =VLOOKUP(B43,#REF!,5,0) -> #REF! | B43: MONROE Shock Absorber 744453SP Rear-LH | C43: =_xlfn.XLOOKUP(B43,'Pit Stop (cleaned)'!A:A,'Pit Stop (cleaned)'!B:B,0) -> 0 | D43: =_xlfn.XLOOKUP(B43,'Subur Makmur Ban (Agg)'!$F$1:$F$5,'Subur Makmur Ban (Agg)'!$L$1:$L$5,0) -> 0 | E43: =_xlfn.XLOOKUP(B43,'Bengkel Pegasus (Agg)'!F:F,'Bengkel Pegasus (Agg)'!L:L,0) -> 0 | F43: =_xlfn.XLOOKUP(B43,'Autocraft (agg)'!F:F,'Autocraft (agg)'!L:L,0) -> 0 | G43: =_xlfn.XLOOKUP(B43,'Autones (cleaned)'!A:A,'Autones (cleaned)'!B:B,0) -> 0 | H43: =_xlfn.XLOOKUP(B43,'ADS Prima (cleaned)'!A:A,'ADS Prima (cleaned)'!B:B,0) -> 0 | I43: =_xlfn.XLOOKUP(B43,'Auto Mekanika (cleaned)'!A:A,'Auto Mekanika (cleaned)'!B:B,0) -> 0 | J43: =_xlfn.XLOOKUP(B43,'Bengkel Multi Var (cleaned)'!A:A,'Bengkel Multi Var (cleaned)'!B:B,0) -> 0 | K43: 0 | L43: =_xlfn.XLOOKUP(B43,'Drivewell (cleaned)'!A:A,'Drivewell (cleaned)'!B:B,0) -> 0 | M43: 0 | N43: 0 | O43: 0 | P43: =_xlfn.XLOOKUP(B43,'CV Sun (cleaned)'!A:A,'CV Sun (cleaned)'!B:B,0) -> 0 | Q43: =_xlfn.XLOOKUP(B43,'Sumber Timur (clean)'!F:F,'Sumber Timur (clean)'!L:L,0) -> 0 | R43: =_xlfn.XLOOKUP(B43,'Honda Duren (clean)'!F:F,'Honda Duren (clean)'!L:L,0) -> 0 | S43: 0 | T43: =SUM(C43:S43) -> 0
A44: =VLOOKUP(B44,#REF!,5,0) -> #REF! | B44: MONROE Shock Absorber 744452SP Rear-RH | C44: =_xlfn.XLOOKUP(B44,'Pit Stop (cleaned)'!A:A,'Pit Stop (cleaned)'!B:B,0) -> 0 | D44: =_xlfn.XLOOKUP(B44,'Subur Makmur Ban (Agg)'!$F$1:$F$5,'Subur Makmur Ban (Agg)'!$L$1:$L$5,0) -> 0 | E44: =_xlfn.XLOOKUP(B44,'Bengkel Pegasus (Agg)'!F:F,'Bengkel Pegasus (Agg)'!L:L,0) -> 0 | F44: =_xlfn.XLOOKUP(B44,'Autocraft (agg)'!F:F,'Autocraft (agg)'!L:L,0) -> 0 | G44: =_xlfn.XLOOKUP(B44,'Autones (cleaned)'!A:A,'Autones (cleaned)'!B:B,0) -> 0 | H44: =_xlfn.XLOOKUP(B44,'ADS Prima (cleaned)'!A:A,'ADS Prima (cleaned)'!B:B,0) -> 0 | I44: =_xlfn.XLOOKUP(B44,'Auto Mekanika (cleaned)'!A:A,'Auto Mekanika (cleaned)'!B:B,0) -> 0 | J44: =_xlfn.XLOOKUP(B44,'Bengkel Multi Var (cleaned)'!A:A,'Bengkel Multi Var (cleaned)'!B:B,0) -> 0 | K44: 0 | L44: =_xlfn.XLOOKUP(B44,'Drivewell (cleaned)'!A:A,'Drivewell (cleaned)'!B:B,0) -> 0 | M44: 0 | N44: 0 | O44: 0 | P44: =_xlfn.XLOOKUP(B44,'CV Sun (cleaned)'!A:A,'CV Sun (cleaned)'!B:B,0) -> 0 | Q44: =_xlfn.XLOOKUP(B44,'Sumber Timur (clean)'!F:F,'Sumber Timur (clean)'!L:L,0) -> 0 | R44: =_xlfn.XLOOKUP(B44,'Honda Duren (clean)'!F:F,'Honda Duren (clean)'!L:L,0) -> 0 | S44: 0 | T44: =SUM(C44:S44) -> 0
A45: =VLOOKUP(B45,#REF!,5,0) -> #REF! | B45: MONROE Shock Absorber 744451SP Front-LH | C45: =_xlfn.XLOOKUP(B45,'Pit Stop (cleaned)'!A:A,'Pit Stop (cleaned)'!B:B,0) -> 0 | D45: =_xlfn.XLOOKUP(B45,'Subur Makmur Ban (Agg)'!$F$1:$F$5,'Subur Makmur Ban (Agg)'!$L$1:$L$5,0) -> 0 | E45: =_xlfn.XLOOKUP(B45,'Bengkel Pegasus (Agg)'!F:F,'Bengkel Pegasus (Agg)'!L:L,0) -> 0 | F45: =_xlfn.XLOOKUP(B45,'Autocraft (agg)'!F:F,'Autocraft (agg)'!L:L,0) -> 0 | G45: =_xlfn.XLOOKUP(B45,'Autones (cleaned)'!A:A,'Autones (cleaned)'!B:B,0) -> 0 | H45: =_xlfn.XLOOKUP(B45,'ADS Prima (cleaned)'!A:A,'ADS Prima (cleaned)'!B:B,0) -> 0 | I45: =_xlfn.XLOOKUP(B45,'Auto Mekanika (cleaned)'!A:A,'Auto Mekanika (cleaned)'!B:B,0) -> 0 | J45: =_xlfn.XLOOKUP(B45,'Bengkel Multi Var (cleaned)'!A:A,'Bengkel Multi Var (cleaned)'!B:B,0) -> 0 | K45: 0 | L45: =_xlfn.XLOOKUP(B45,'Drivewell (cleaned)'!A:A,'Drivewell (cleaned)'!B:B,0) -> 0 | M45: 0 | N45: 0 | O45: 0 | P45: =_xlfn.XLOOKUP(B45,'CV Sun (cleaned)'!A:A,'CV Sun (cleaned)'!B:B,0) -> 0 | Q45: =_xlfn.XLOOKUP(B45,'Sumber Timur (clean)'!F:F,'Sumber Timur (clean)'!L:L,0) -> 0 | R45: =_xlfn.XLOOKUP(B45,'Honda Duren (clean)'!F:F,'Honda Duren (clean)'!L:L,0) -> 0 | S45: 0 | T45: =SUM(C45:S45) -> 0
A46: =VLOOKUP(B46,#REF!,5,0) -> #REF! | B46: MONROE Shock Absorber 744450SP Front-RH | C46: =_xlfn.XLOOKUP(B46,'Pit Stop (cleaned)'!A:A,'Pit Stop (cleaned)'!B:B,0) -> 0 | D46: =_xlfn.XLOOKUP(B46,'Subur Makmur Ban (Agg)'!$F$1:$F$5,'Subur Makmur Ban (Agg)'!$L$1:$L$5,0) -> 0 | E46: =_xlfn.XLOOKUP(B46,'Bengkel Pegasus (Agg)'!F:F,'Bengkel Pegasus (Agg)'!L:L,0) -> 0 | F46: =_xlfn.XLOOKUP(B46,'Autocraft (agg)'!F:F,'Autocraft (agg)'!L:L,0) -> 0 | G46: =_xlfn.XLOOKUP(B46,'Autones (cleaned)'!A:A,'Autones (cleaned)'!B:B,0) -> 0 | H46: =_xlfn.XLOOKUP(B46,'ADS Prima (cleaned)'!A:A,'ADS Prima (cleaned)'!B:B,0) -> 0 | I46: =_xlfn.XLOOKUP(B46,'Auto Mekanika (cleaned)'!A:A,'Auto Mekanika (cleaned)'!B:B,0) -> 0 | J46: =_xlfn.XLOOKUP(B46,'Bengkel Multi Var (cleaned)'!A:A,'Bengkel Multi Var (cleaned)'!B:B,0) -> 0 | K46: 0 | L46: =_xlfn.XLOOKUP(B46,'Drivewell (cleaned)'!A:A,'Drivewell (cleaned)'!B:B,0) -> 0 | M46: 0 | N46: 0 | O46: 0 | P46: =_xlfn.XLOOKUP(B46,'CV Sun (cleaned)'!A:A,'CV Sun (cleaned)'!B:B,0) -> 0 | Q46: =_xlfn.XLOOKUP(B46,'Sumber Timur (clean)'!F:F,'Sumber Timur (clean)'!L:L,0) -> 0 | R46: =_xlfn.XLOOKUP(B46,'Honda Duren (clean)'!F:F,'Honda Duren (clean)'!L:L,0) -> 0 | S46: 0 | T46: =SUM(C46:S46) -> 0
A47: =VLOOKUP(B47,#REF!,5,0) -> #REF! | B47: MONROE Shock Absorber 744445SP Front | C47: =_xlfn.XLOOKUP(B47,'Pit Stop (cleaned)'!A:A,'Pit Stop (cleaned)'!B:B,0) -> 0 | D47: =_xlfn.XLOOKUP(B47,'Subur Makmur Ban (Agg)'!$F$1:$F$5,'Subur Makmur Ban (Agg)'!$L$1:$L$5,0) -> 0 | E47: =_xlfn.XLOOKUP(B47,'Bengkel Pegasus (Agg)'!F:F,'Bengkel Pegasus (Agg)'!L:L,0) -> 0 | F47: =_xlfn.XLOOKUP(B47,'Autocraft (agg)'!F:F,'Autocraft (agg)'!L:L,0) -> 0 | G47: =_xlfn.XLOOKUP(B47,'Autones (cleaned)'!A:A,'Autones (cleaned)'!B:B,0) -> 0 | H47: =_xlfn.XLOOKUP(B47,'ADS Prima (cleaned)'!A:A,'ADS Prima (cleaned)'!B:B,0) -> 0 | I47: =_xlfn.XLOOKUP(B47,'Auto Mekanika (cleaned)'!A:A,'Auto Mekanika (cleaned)'!B:B,0) -> 0 | J47: =_xlfn.XLOOKUP(B47,'Bengkel Multi Var (cleaned)'!A:A,'Bengkel Multi Var (cleaned)'!B:B,0) -> 0 | K47: 0 | L47: =_xlfn.XLOOKUP(B47,'Drivewell (cleaned)'!A:A,'Drivewell (cleaned)'!B:B,0) -> 0 | M47: 0 | N47: 0 | O47: 0 | P47: =_xlfn.XLOOKUP(B47,'CV Sun (cleaned)'!A:A,'CV Sun (cleaned)'!B:B,0) -> 0 | Q47: =_xlfn.XLOOKUP(B47,'Sumber Timur (clean)'!F:F,'Sumber Timur (clean)'!L:L,0) -> 0 | R47: =_xlfn.XLOOKUP(B47,'Honda Duren (clean)'!F:F,'Honda Duren (clean)'!L:L,0) -> 0 | S47: 0 | T47: =SUM(C47:S47) -> 0
A48: =VLOOKUP(B48,#REF!,5,0) -> #REF! | B48: MONROE Shock Absorber 744444SP Rear | C48: =_xlfn.XLOOKUP(B48,'Pit Stop (cleaned)'!A:A,'Pit Stop (cleaned)'!B:B,0) -> 0 | D48: =_xlfn.XLOOKUP(B48,'Subur Makmur Ban (Agg)'!$F$1:$F$5,'Subur Makmur Ban (Agg)'!$L$1:$L$5,0) -> 0 | E48: =_xlfn.XLOOKUP(B48,'Bengkel Pegasus (Agg)'!F:F,'Bengkel Pegasus (Agg)'!L:L,0) -> 0 | F48: =_xlfn.XLOOKUP(B48,'Autocraft (agg)'!F:F,'Autocraft (agg)'!L:L,0) -> 0 | G48: =_xlfn.XLOOKUP(B48,'Autones (cleaned)'!A:A,'Autones (cleaned)'!B:B,0) -> 0 | H48: =_xlfn.XLOOKUP(B48,'ADS Prima (cleaned)'!A:A,'ADS Prima (cleaned)'!B:B,0) -> 0 | I48: =_xlfn.XLOOKUP(B48,'Auto Mekanika (cleaned)'!A:A,'Auto Mekanika (cleaned)'!B:B,0) -> 0 | J48: =_xlfn.XLOOKUP(B48,'Bengkel Multi Var (cleaned)'!A:A,'Bengkel Multi Var (cleaned)'!B:B,0) -> 0 | K48: 0 | L48: =_xlfn.XLOOKUP(B48,'Drivewell (cleaned)'!A:A,'Drivewell (cleaned)'!B:B,0) -> 0 | M48: 0 | N48: 0 | O48: 0 | P48: =_xlfn.XLOOKUP(B48,'CV Sun (cleaned)'!A:A,'CV Sun (cleaned)'!B:B,0) -> 0 | Q48: =_xlfn.XLOOKUP(B48,'Sumber Timur (clean)'!F:F,'Sumber Timur (clean)'!L:L,0) -> 0 | R48: =_xlfn.XLOOKUP(B48,'Honda Duren (clean)'!F:F,'Honda Duren (clean)'!L:L,0) -> 0 | S48: 0 | T48: =SUM(C48:S48) -> 0
A49: =VLOOKUP(B49,#REF!,5,0) -> #REF! | B49: MOBIL Gear Oil Mobilube-HD 80W-90 1L | C49: =_xlfn.XLOOKUP(B49,'Pit Stop (cleaned)'!A:A,'Pit Stop (cleaned)'!B:B,0) -> 0 | D49: =_xlfn.XLOOKUP(B49,'Subur Makmur Ban (Agg)'!$F$1:$F$5,'Subur Makmur Ban (Agg)'!$L$1:$L$5,0) -> 0 | E49: =_xlfn.XLOOKUP(B49,'Bengkel Pegasus (Agg)'!F:F,'Bengkel Pegasus (Agg)'!L:L,0) -> 0 | F49: =_xlfn.XLOOKUP(B49,'Autocraft (agg)'!F:F,'Autocraft (agg)'!L:L,0) -> 0 | G49: =_xlfn.XLOOKUP(B49,'Autones (cleaned)'!A:A,'Autones (cleaned)'!B:B,0) -> 0 | H49: =_xlfn.XLOOKUP(B49,'ADS Prima (cleaned)'!A:A,'ADS Prima (cleaned)'!B:B,0) -> 0 | I49: =_xlfn.XLOOKUP(B49,'Auto Mekanika (cleaned)'!A:A,'Auto Mekanika (cleaned)'!B:B,0) -> 0 | J49: =_xlfn.XLOOKUP(B49,'Bengkel Multi Var (cleaned)'!A:A,'Bengkel Multi Var (cleaned)'!B:B,0) -> 0 | K49: 0 | L49: =_xlfn.XLOOKUP(B49,'Drivewell (cleaned)'!A:A,'Drivewell (cleaned)'!B:B,0) -> 0 | M49: 0 | N49: 0 | O49: 0 | P49: =_xlfn.XLOOKUP(B49,'CV Sun (cleaned)'!A:A,'CV Sun (cleaned)'!B:B,0) -> 0 | Q49: =_xlfn.XLOOKUP(B49,'Sumber Timur (clean)'!F:F,'Sumber Timur (clean)'!L:L,0) -> 0 | R49: =_xlfn.XLOOKUP(B49,'Honda Duren (clean)'!F:F,'Honda Duren (clean)'!L:L,0) -> 0 | S49: 0 | T49: =SUM(C49:S49) -> 0
A50: =VLOOKUP(B50,#REF!,5,0) -> #REF! | B50: BOSCH Oil Filter O 0203 | C50: =_xlfn.XLOOKUP(B50,'Pit Stop (cleaned)'!A:A,'Pit Stop (cleaned)'!B:B,0) -> 0 | D50: =_xlfn.XLOOKUP(B50,'Subur Makmur Ban (Agg)'!$F$1:$F$5,'Subur Makmur Ban (Agg)'!$L$1:$L$5,0) -> 0 | E50: =_xlfn.XLOOKUP(B50,'Bengkel Pegasus (Agg)'!F:F,'Bengkel Pegasus (Agg)'!L:L,0) -> 0 | F50: =_xlfn.XLOOKUP(B50,'Autocraft (agg)'!F:F,'Autocraft (agg)'!L:L,0) -> 0 | G50: =_xlfn.XLOOKUP(B50,'Autones (cleaned)'!A:A,'Autones (cleaned)'!B:B,0) -> 0 | H50: =_xlfn.XLOOKUP(B50,'ADS Prima (cleaned)'!A:A,'ADS Prima (cleaned)'!B:B,0) -> 0 | I50: =_xlfn.XLOOKUP(B50,'Auto Mekanika (cleaned)'!A:A,'Auto Mekanika (cleaned)'!B:B,0) -> 0 | J50: =_xlfn.XLOOKUP(B50,'Bengkel Multi Var (cleaned)'!A:A,'Bengkel Multi Var (cleaned)'!B:B,0) -> 0 | K50: 0 | L50: =_xlfn.XLOOKUP(B50,'Drivewell (cleaned)'!A:A,'Drivewell (cleaned)'!B:B,0) -> 0 | M50: 0 | N50: 0 | O50: 0 | P50: =_xlfn.XLOOKUP(B50,'CV Sun (cleaned)'!A:A,'CV Sun (cleaned)'!B:B,0) -> 0 | Q50: =_xlfn.XLOOKUP(B50,'Sumber Timur (clean)'!F:F,'Sumber Timur (clean)'!L:L,0) -> 0 | R50: =_xlfn.XLOOKUP(B50,'Honda Duren (clean)'!F:F,'Honda Duren (clean)'!L:L,0) -> 0 | S50: 0 | T50: =SUM(C50:S50) -> 0
A51: =VLOOKUP(B51,#REF!,5,0) -> #REF! | B51: CASTROL Engine Oil MAGNATEC 10W-40 4L | C51: =_xlfn.XLOOKUP(B51,'Pit Stop (cleaned)'!A:A,'Pit Stop (cleaned)'!B:B,0) -> 0 | D51: =_xlfn.XLOOKUP(B51,'Subur Makmur Ban (Agg)'!$F$1:$F$5,'Subur Makmur Ban (Agg)'!$L$1:$L$5,0) -> 0 | E51: =_xlfn.XLOOKUP(B51,'Bengkel Pegasus (Agg)'!F:F,'Bengkel Pegasus (Agg)'!L:L,0) -> 0 | F51: =_xlfn.XLOOKUP(B51,'Autocraft (agg)'!F:F,'Autocraft (agg)'!L:L,0) -> 0 | G51: =_xlfn.XLOOKUP(B51,'Autones (cleaned)'!A:A,'Autones (cleaned)'!B:B,0) -> 0 | H51: =_xlfn.XLOOKUP(B51,'ADS Prima (cleaned)'!A:A,'ADS Prima (cleaned)'!B:B,0) -> 0 | I51: =_xlfn.XLOOKUP(B51,'Auto Mekanika (cleaned)'!A:A,'Auto Mekanika (cleaned)'!B:B,0) -> 0 | J51: =_xlfn.XLOOKUP(B51,'Bengkel Multi Var (cleaned)'!A:A,'Bengkel Multi Var (cleaned)'!B:B,0) -> 0 | K51: 0 | L51: =_xlfn.XLOOKUP(B51,'Drivewell (cleaned)'!A:A,'Drivewell (cleaned)'!B:B,0) -> 0 | M51: 0 | N51: 0 | O51: 0 | P51: =_xlfn.XLOOKUP(B51,'CV Sun (cleaned)'!A:A,'CV Sun (cleaned)'!B:B,0) -> 0 | Q51: =_xlfn.XLOOKUP(B51,'Sumber Timur (clean)'!F:F,'Sumber Timur (clean)'!L:L,0) -> 0 | R51: =_xlfn.XLOOKUP(B51,'Honda Duren (clean)'!F:F,'Honda Duren (clean)'!L:L,0) -> 0 | S51: 0 | T51: =SUM(C51:S51) -> 0
A52: =VLOOKUP(B52,#REF!,5,0) -> #REF! | B52: BOSCH Spark Plug FR7NPP332 - Platinum | C52: =_xlfn.XLOOKUP(B52,'Pit Stop (cleaned)'!A:A,'Pit Stop (cleaned)'!B:B,0) -> 0 | D52: =_xlfn.XLOOKUP(B52,'Subur Makmur Ban (Agg)'!$F$1:$F$5,'Subur Makmur Ban (Agg)'!$L$1:$L$5,0) -> 0 | E52: =_xlfn.XLOOKUP(B52,'Bengkel Pegasus (Agg)'!F:F,'Bengkel Pegasus (Agg)'!L:L,0) -> 0 | F52: =_xlfn.XLOOKUP(B52,'Autocraft (agg)'!F:F,'Autocraft (agg)'!L:L,0) -> 0 | G52: =_xlfn.XLOOKUP(B52,'Autones (cleaned)'!A:A,'Autones (cleaned)'!B:B,0) -> 0 | H52: =_xlfn.XLOOKUP(B52,'ADS Prima (cleaned)'!A:A,'ADS Prima (cleaned)'!B:B,0) -> 0 | I52: =_xlfn.XLOOKUP(B52,'Auto Mekanika (cleaned)'!A:A,'Auto Mekanika (cleaned)'!B:B,0) -> 0 | J52: =_xlfn.XLOOKUP(B52,'Bengkel Multi Var (cleaned)'!A:A,'Bengkel Multi Var (cleaned)'!B:B,0) -> 0 | K52: 0 | L52: =_xlfn.XLOOKUP(B52,'Drivewell (cleaned)'!A:A,'Drivewell (cleaned)'!B:B,0) -> 0 | M52: 0 | N52: 0 | O52: 0 | P52: =_xlfn.XLOOKUP(B52,'CV Sun (cleaned)'!A:A,'CV Sun (cleaned)'!B:B,0) -> 0 | Q52: =_xlfn.XLOOKUP(B52,'Sumber Timur (clean)'!F:F,'Sumber Timur (clean)'!L:L,0) -> 0 | R52: =_xlfn.XLOOKUP(B52,'Honda Duren (clean)'!F:F,'Honda Duren (clean)'!L:L,0) -> 0 | S52: 0 | T52: =SUM(C52:S52) -> 0
A53: =VLOOKUP(B53,#REF!,5,0) -> #REF! | B53: BOSCH Oil Filter O 0209 | C53: =_xlfn.XLOOKUP(B53,'Pit Stop (cleaned)'!A:A,'Pit Stop (cleaned)'!B:B,0) -> 0 | D53: =_xlfn.XLOOKUP(B53,'Subur Makmur Ban (Agg)'!$F$1:$F$5,'Subur Makmur Ban (Agg)'!$L$1:$L$5,0) -> 0 | E53: =_xlfn.XLOOKUP(B53,'Bengkel Pegasus (Agg)'!F:F,'Bengkel Pegasus (Agg)'!L:L,0) -> 0 | F53: =_xlfn.XLOOKUP(B53,'Autocraft (agg)'!F:F,'Autocraft (agg)'!L:L,0) -> 0 | G53: =_xlfn.XLOOKUP(B53,'Autones (cleaned)'!A:A,'Autones (cleaned)'!B:B,0) -> 0 | H53: =_xlfn.XLOOKUP(B53,'ADS Prima (cleaned)'!A:A,'ADS Prima (cleaned)'!B:B,0) -> 0 | I53: =_xlfn.XLOOKUP(B53,'Auto Mekanika (cleaned)'!A:A,'Auto Mekanika (cleaned)'!B:B,0) -> 0 | J53: =_xlfn.XLOOKUP(B53,'Bengkel Multi Var (cleaned)'!A:A,'Bengkel Multi Var (cleaned)'!B:B,0) -> 0 | K53: 0 | L53: =_xlfn.XLOOKUP(B53,'Drivewell (cleaned)'!A:A,'Drivewell (cleaned)'!B:B,0) -> 0 | M53: 0 | N53: 0 | O53: 0 | P53: =_xlfn.XLOOKUP(B53,'CV Sun (cleaned)'!A:A,'CV Sun (cleaned)'!B:B,0) -> 0 | Q53: =_xlfn.XLOOKUP(B53,'Sumber Timur (clean)'!F:F,'Sumber Timur (clean)'!L:L,0) -> 0 | R53: =_xlfn.XLOOKUP(B53,'Honda Duren (clean)'!F:F,'Honda Duren (clean)'!L:L,0) -> 0 | S53: 0 | T53: =SUM(C53:S53) -> 0
A54: =VLOOKUP(B54,#REF!,5,0) -> #REF! | B54: DENSO Air Filter DXA-1039 | C54: =_xlfn.XLOOKUP(B54,'Pit Stop (cleaned)'!A:A,'Pit Stop (cleaned)'!B:B,0) -> 0 | D54: =_xlfn.XLOOKUP(B54,'Subur Makmur Ban (Agg)'!$F$1:$F$5,'Subur Makmur Ban (Agg)'!$L$1:$L$5,0) -> 0 | E54: =_xlfn.XLOOKUP(B54,'Bengkel Pegasus (Agg)'!F:F,'Bengkel Pegasus (Agg)'!L:L,0) -> 0 | F54: =_xlfn.XLOOKUP(B54,'Autocraft (agg)'!F:F,'Autocraft (agg)'!L:L,0) -> 0 | G54: =_xlfn.XLOOKUP(B54,'Autones (cleaned)'!A:A,'Autones (cleaned)'!B:B,0) -> 0 | H54: =_xlfn.XLOOKUP(B54,'ADS Prima (cleaned)'!A:A,'ADS Prima (cleaned)'!B:B,0) -> 0 | I54: =_xlfn.XLOOKUP(B54,'Auto Mekanika (cleaned)'!A:A,'Auto Mekanika (cleaned)'!B:B,0) -> 0 | J54: =_xlfn.XLOOKUP(B54,'Bengkel Multi Var (cleaned)'!A:A,'Bengkel Multi Var (cleaned)'!B:B,0) -> 0 | K54: 0 | L54: =_xlfn.XLOOKUP(B54,'Drivewell (cleaned)'!A:A,'Drivewell (cleaned)'!B:B,0) -> 0 | M54: 0 | N54: 0 | O54: 0 | P54: =_xlfn.XLOOKUP(B54,'CV Sun (cleaned)'!A:A,'CV Sun (cleaned)'!B:B,0) -> 0 | Q54: =_xlfn.XLOOKUP(B54,'Sumber Timur (clean)'!F:F,'Sumber Timur (clean)'!L:L,0) -> 0 | R54: =_xlfn.XLOOKUP(B54,'Honda Duren (clean)'!F:F,'Honda Duren (clean)'!L:L,0) -> 0 | S54: 0 | T54: =SUM(C54:S54) -> 0
... A61: =VLOOKUP(B61,#REF!,5,0) -> #REF! | B61: BOSCH Spark Plug ZR5TPP330 - Platinum | C61: =_xlfn.XLOOKUP(B61,'Pit Stop (cleaned)'!A:A,'Pit Stop (cleaned)'!B:B,0) -> 0 | D61: =_xlfn.XLOOKUP(B61,'Subur Makmur Ban (Agg)'!$F$1:$F$5,'Subur Makmur Ban (Agg)'!$L$1:$L$5,0) -> 0 | E61: =_xlfn.XLOOKUP(B61,'Bengkel Pegasus (Agg)'!F:F,'Bengkel Pegasus (Agg)'!L:L,0) -> 0 | F61: =_xlfn.XLOOKUP(B61,'Autocraft (agg)'!F:F,'Autocraft (agg)'!L:L,0) -> 0 | G61: =_xlfn.XLOOKUP(B61,'Autones (cleaned)'!A:A,'Autones (cleaned)'!B:B,0) -> 0 | H61: =_xlfn.XLOOKUP(B61,'ADS Prima (cleaned)'!A:A,'ADS Prima (cleaned)'!B:B,0) -> 0 | I61: =_xlfn.XLOOKUP(B61,'Auto Mekanika (cleaned)'!A:A,'Auto Mekanika (cleaned)'!B:B,0) -> 0 | J61: =_xlfn.XLOOKUP(B61,'Bengkel Multi Var (cleaned)'!A:A,'Bengkel Multi Var (cleaned)'!B:B,0) -> 0 | K61: 0 | L61: =_xlfn.XLOOKUP(B61,'Drivewell (cleaned)'!A:A,'Drivewell (cleaned)'!B:B,0) -> 0 | M61: 0 | N61: 0 | O61: 0 | P61: =_xlfn.XLOOKUP(B61,'CV Sun (cleaned)'!A:A,'CV Sun (cleaned)'!B:B,0) -> 0 | Q61: =_xlfn.XLOOKUP(B61,'Sumber Timur (clean)'!F:F,'Sumber Timur (clean)'!L:L,0) -> 0 | R61: =_xlfn.XLOOKUP(B61,'Honda Duren (clean)'!F:F,'Honda Duren (clean)'!L:L,0) -> 0 | S61: 0 | T61: =SUM(C61:S61) -> 0
A62: =VLOOKUP(B62,#REF!,5,0) -> #REF! | B62: BOSCH Cabin Filter AP-H09 | C62: =_xlfn.XLOOKUP(B62,'Pit Stop (cleaned)'!A:A,'Pit Stop (cleaned)'!B:B,0) -> 0 | D62: =_xlfn.XLOOKUP(B62,'Subur Makmur Ban (Agg)'!$F$1:$F$5,'Subur Makmur Ban (Agg)'!$L$1:$L$5,0) -> 0 | E62: 1 | F62: =_xlfn.XLOOKUP(B62,'Autocraft (agg)'!F:F,'Autocraft (agg)'!L:L,0) -> 0 | G62: =_xlfn.XLOOKUP(B62,'Autones (cleaned)'!A:A,'Autones (cleaned)'!B:B,0) -> 0 | H62: =_xlfn.XLOOKUP(B62,'ADS Prima (cleaned)'!A:A,'ADS Prima (cleaned)'!B:B,0) -> 0 | I62: =_xlfn.XLOOKUP(B62,'Auto Mekanika (cleaned)'!A:A,'Auto Mekanika (cleaned)'!B:B,0) -> 0 | J62: =_xlfn.XLOOKUP(B62,'Bengkel Multi Var (cleaned)'!A:A,'Bengkel Multi Var (cleaned)'!B:B,0) -> 0 | K62: =_xlfn.XLOOKUP(B62,'[2]EURO GALLARIA'!F:F,'[2]EURO GALLARIA'!L:L,0) -> 0 | L62: =_xlfn.XLOOKUP(B62,'Drivewell (cleaned)'!A:A,'Drivewell (cleaned)'!B:B,0) -> 0 | M62: =_xlfn.XLOOKUP(B62,'[2]Mersi (CLEAN)'!D:D,'[2]Mersi (CLEAN)'!E:E,0) -> 0 | N62: 0 | O62: 0 | P62: =_xlfn.XLOOKUP(B62,'CV Sun (cleaned)'!A:A,'CV Sun (cleaned)'!B:B,0) -> 0 | Q62: =_xlfn.XLOOKUP(B62,'Sumber Timur (clean)'!F:F,'Sumber Timur (clean)'!L:L,0) -> 0 | R62: =_xlfn.XLOOKUP(B62,'Honda Duren (clean)'!F:F,'Honda Duren (clean)'!L:L,0) -> 0 | S62: =_xlfn.XLOOKUP(B62,'[2]LAVANDER CLEAN'!A:A,'[2]LAVANDER CLEAN'!B:B,0) -> 3 | T62: =SUM(C62:S62) -> 4 | U62: 148720 | V62: =IF(T62*U62=0,"",T62*U62) -> 594880 | W62: 0986AF7002
A63: =VLOOKUP(B63,#REF!,5,0) -> #REF! | B63: BOSCH Battery MF EFB Q85 ISS-65A 95D23L 12V | C63: =_xlfn.XLOOKUP(B63,'Pit Stop (cleaned)'!A:A,'Pit Stop (cleaned)'!B:B,0) -> 0 | D63: =_xlfn.XLOOKUP(B63,'Subur Makmur Ban (Agg)'!$F$1:$F$5,'Subur Makmur Ban (Agg)'!$L$1:$L$5,0) -> 0 | E63: =_xlfn.XLOOKUP(B63,'Bengkel Pegasus (Agg)'!F:F,'Bengkel Pegasus (Agg)'!L:L,0) -> 0 | F63: =_xlfn.XLOOKUP(B63,'Autocraft (agg)'!F:F,'Autocraft (agg)'!L:L,0) -> 0 | G63: =_xlfn.XLOOKUP(B63,'Autones (cleaned)'!A:A,'Autones (cleaned)'!B:B,0) -> 0 | H63: =_xlfn.XLOOKUP(B63,'ADS Prima (cleaned)'!A:A,'ADS Prima (cleaned)'!B:B,0) -> 0 | I63: =_xlfn.XLOOKUP(B63,'Auto Mekanika (cleaned)'!A:A,'Auto Mekanika (cleaned)'!B:B,0) -> 0 | J63: =_xlfn.XLOOKUP(B63,'Bengkel Multi Var (cleaned)'!A:A,'Bengkel Multi Var (cleaned)'!B:B,0) -> 0 | K63: =_xlfn.XLOOKUP(B63,'[2]EURO GALLARIA'!F:F,'[2]EURO GALLARIA'!L:L,0) -> 0 | L63: =_xlfn.XLOOKUP(B63,'Drivewell (cleaned)'!A:A,'Drivewell (cleaned)'!B:B,0) -> 0 | M63: =_xlfn.XLOOKUP(B63,'[2]Mersi (CLEAN)'!D:D,'[2]Mersi (CLEAN)'!E:E,0) -> 0 | N63: 0 | O63: 0 | P63: =_xlfn.XLOOKUP(B63,'CV Sun (cleaned)'!A:A,'CV Sun (cleaned)'!B:B,0) -> 0 | Q63: =_xlfn.XLOOKUP(B63,'Sumber Timur (clean)'!F:F,'Sumber Timur (clean)'!L:L,0) -> 0 | R63: =_xlfn.XLOOKUP(B63,'Honda Duren (clean)'!F:F,'Honda Duren (clean)'!L:L,0) -> 0 | S63: =_xlfn.XLOOKUP(B63,'[2]LAVANDER CLEAN'!A:A,'[2]LAVANDER CLEAN'!B:B,0) -> 0 | T63: =SUM(C63:S63) -> 0 | U63: 1463964 | V63: =IF(T63*U63=0,"",T63*U63) | W63: 0092S67106
A64: =VLOOKUP(B64,#REF!,5,0) -> #REF! | B64: MOBIL Transmission Oil CVTF Multi-Vehicle 1L | C64: =_xlfn.XLOOKUP(B64,'Pit Stop (cleaned)'!A:A,'Pit Stop (cleaned)'!B:B,0) -> 0 | D64: =_xlfn.XLOOKUP(B64,'Subur Makmur Ban (Agg)'!$F$1:$F$5,'Subur Makmur Ban (Agg)'!$L$1:$L$5,0) -> 0 | E64: =_xlfn.XLOOKUP(B64,'Bengkel Pegasus (Agg)'!F:F,'Bengkel Pegasus (Agg)'!L:L,0) -> 0 | F64: =_xlfn.XLOOKUP(B64,'Autocraft (agg)'!F:F,'Autocraft (agg)'!L:L,0) -> 0 | G64: =_xlfn.XLOOKUP(B64,'Autones (cleaned)'!A:A,'Autones (cleaned)'!B:B,0) -> 0 | H64: =_xlfn.XLOOKUP(B64,'ADS Prima (cleaned)'!A:A,'ADS Prima (cleaned)'!B:B,0) -> 0 | I64: =_xlfn.XLOOKUP(B64,'Auto Mekanika (cleaned)'!A:A,'Auto Mekanika (cleaned)'!B:B,0) -> 0 | J64: =_xlfn.XLOOKUP(B64,'Bengkel Multi Var (cleaned)'!A:A,'Bengkel Multi Var (cleaned)'!B:B,0) -> 0 | K64: 0 | L64: =_xlfn.XLOOKUP(B64,'Drivewell (cleaned)'!A:A,'Drivewell (cleaned)'!B:B,0) -> 0 | M64: 0 | N64: 0 | O64: 0 | P64: =_xlfn.XLOOKUP(B64,'CV Sun (cleaned)'!A:A,'CV Sun (cleaned)'!B:B,0) -> 0 | Q64: =_xlfn.XLOOKUP(B64,'Sumber Timur (clean)'!F:F,'Sumber Timur (clean)'!L:L,0) -> 0 | R64: =_xlfn.XLOOKUP(B64,'Honda Duren (clean)'!F:F,'Honda Duren (clean)'!L:L,0) -> 0 | S64: 0 | T64: =SUM(C64:S64) -> 0
A65: =VLOOKUP(B65,#REF!,5,0) -> #REF! | B65: SHELL Gear Oil Spirax S2 G 80W-90 1L | C65: =_xlfn.XLOOKUP(B65,'Pit Stop (cleaned)'!A:A,'Pit Stop (cleaned)'!B:B,0) -> 0 | D65: =_xlfn.XLOOKUP(B65,'Subur Makmur Ban (Agg)'!$F$1:$F$5,'Subur Makmur Ban (Agg)'!$L$1:$L$5,0) -> 0 | E65: =_xlfn.XLOOKUP(B65,'Bengkel Pegasus (Agg)'!F:F,'Bengkel Pegasus (Agg)'!L:L,0) -> 0 | F65: =_xlfn.XLOOKUP(B65,'Autocraft (agg)'!F:F,'Autocraft (agg)'!L:L,0) -> 0 | G65: =_xlfn.XLOOKUP(B65,'Autones (cleaned)'!A:A,'Autones (cleaned)'!B:B,0) -> 0 | H65: =_xlfn.XLOOKUP(B65,'ADS Prima (cleaned)'!A:A,'ADS Prima (cleaned)'!B:B,0) -> 0 | I65: =_xlfn.XLOOKUP(B65,'Auto Mekanika (cleaned)'!A:A,'Auto Mekanika (cleaned)'!B:B,0) -> 0 | J65: =_xlfn.XLOOKUP(B65,'Bengkel Multi Var (cleaned)'!A:A,'Bengkel Multi Var (cleaned)'!B:B,0) -> 0 | K65: 0 | L65: =_xlfn.XLOOKUP(B65,'Drivewell (cleaned)'!A:A,'Drivewell (cleaned)'!B:B,0) -> 0 | M65: 0 | N65: 0 | O65: 0 | P65: =_xlfn.XLOOKUP(B65,'CV Sun (cleaned)'!A:A,'CV Sun (cleaned)'!B:B,0) -> 0 | Q65: =_xlfn.XLOOKUP(B65,'Sumber Timur (clean)'!F:F,'Sumber Timur (clean)'!L:L,0) -> 0 | R65: =_xlfn.XLOOKUP(B65,'Honda Duren (clean)'!F:F,'Honda Duren (clean)'!L:L,0) -> 0 | S65: 0 | T65: =SUM(C65:S65) -> 0
A66: =VLOOKUP(B66,#REF!,5,0) -> #REF! | B66: MASSIV Battery Thunder(MF)-36B20L NS40ZL 12V-35Ah | C66: =_xlfn.XLOOKUP(B66,'Pit Stop (cleaned)'!A:A,'Pit Stop (cleaned)'!B:B,0) -> 0 | D66: =_xlfn.XLOOKUP(B66,'Subur Makmur Ban (Agg)'!$F$1:$F$5,'Subur Makmur Ban (Agg)'!$L$1:$L$5,0) -> 0 | E66: =_xlfn.XLOOKUP(B66,'Bengkel Pegasus (Agg)'!F:F,'Bengkel Pegasus (Agg)'!L:L,0) -> 0 | F66: =_xlfn.XLOOKUP(B66,'Autocraft (agg)'!F:F,'Autocraft (agg)'!L:L,0) -> 0 | G66: =_xlfn.XLOOKUP(B66,'Autones (cleaned)'!A:A,'Autones (cleaned)'!B:B,0) -> 0 | H66: =_xlfn.XLOOKUP(B66,'ADS Prima (cleaned)'!A:A,'ADS Prima (cleaned)'!B:B,0) -> 0 | I66: =_xlfn.XLOOKUP(B66,'Auto Mekanika (cleaned)'!A:A,'Auto Mekanika (cleaned)'!B:B,0) -> 0 | J66: =_xlfn.XLOOKUP(B66,'Bengkel Multi Var (cleaned)'!A:A,'Bengkel Multi Var (cleaned)'!B:B,0) -> 0 | K66: 0 | L66: =_xlfn.XLOOKUP(B66,'Drivewell (cleaned)'!A:A,'Drivewell (cleaned)'!B:B,0) -> 0 | M66: 0 | N66: 0 | O66: 0 | P66: =_xlfn.XLOOKUP(B66,'CV Sun (cleaned)'!A:A,'CV Sun (cleaned)'!B:B,0) -> 0 | Q66: =_xlfn.XLOOKUP(B66,'Sumber Timur (clean)'!F:F,'Sumber Timur (clean)'!L:L,0) -> 0 | R66: =_xlfn.XLOOKUP(B66,'Honda Duren (clean)'!F:F,'Honda Duren (clean)'!L:L,0) -> 0 | S66: 0 | T66: =SUM(C66:S66) -> 0
A67: =VLOOKUP(B67,#REF!,5,0) -> #REF! | B67: MONROE Shock Absorber 744429SP Front-LH | C67: =_xlfn.XLOOKUP(B67,'Pit Stop (cleaned)'!A:A,'Pit Stop (cleaned)'!B:B,0) -> 0 | D67: =_xlfn.XLOOKUP(B67,'Subur Makmur Ban (Agg)'!$F$1:$F$5,'Subur Makmur Ban (Agg)'!$L$1:$L$5,0) -> 0 | E67: =_xlfn.XLOOKUP(B67,'Bengkel Pegasus (Agg)'!F:F,'Bengkel Pegasus (Agg)'!L:L,0) -> 0 | F67: =_xlfn.XLOOKUP(B67,'Autocraft (agg)'!F:F,'Autocraft (agg)'!L:L,0) -> 0 | G67: =_xlfn.XLOOKUP(B67,'Autones (cleaned)'!A:A,'Autones (cleaned)'!B:B,0) -> 0 | H67: =_xlfn.XLOOKUP(B67,'ADS Prima (cleaned)'!A:A,'ADS Prima (cleaned)'!B:B,0) -> 0 | I67: =_xlfn.XLOOKUP(B67,'Auto Mekanika (cleaned)'!A:A,'Auto Mekanika (cleaned)'!B:B,0) -> 0 | J67: =_xlfn.XLOOKUP(B67,'Bengkel Multi Var (cleaned)'!A:A,'Bengkel Multi Var (cleaned)'!B:B,0) -> 0 | K67: 0 | L67: =_xlfn.XLOOKUP(B67,'Drivewell (cleaned)'!A:A,'Drivewell (cleaned)'!B:B,0) -> 0 | M67: 0 | N67: 0 | O67: 0 | P67: =_xlfn.XLOOKUP(B67,'CV Sun (cleaned)'!A:A,'CV Sun (cleaned)'!B:B,0) -> 0 | Q67: =_xlfn.XLOOKUP(B67,'Sumber Timur (clean)'!F:F,'Sumber Timur (clean)'!L:L,0) -> 0 | R67: =_xlfn.XLOOKUP(B67,'Honda Duren (clean)'!F:F,'Honda Duren (clean)'!L:L,0) -> 0 | S67: 0 | T67: =SUM(C67:S67) -> 0
A68: =VLOOKUP(B68,#REF!,5,0) -> #REF! | B68: MONROE Shock Absorber 744428SP Front-RH | C68: =_xlfn.XLOOKUP(B68,'Pit Stop (cleaned)'!A:A,'Pit Stop (cleaned)'!B:B,0) -> 0 | D68: =_xlfn.XLOOKUP(B68,'Subur Makmur Ban (Agg)'!$F$1:$F$5,'Subur Makmur Ban (Agg)'!$L$1:$L$5,0) -> 0 | E68: =_xlfn.XLOOKUP(B68,'Bengkel Pegasus (Agg)'!F:F,'Bengkel Pegasus (Agg)'!L:L,0) -> 0 | F68: =_xlfn.XLOOKUP(B68,'Autocraft (agg)'!F:F,'Autocraft (agg)'!L:L,0) -> 0 | G68: =_xlfn.XLOOKUP(B68,'Autones (cleaned)'!A:A,'Autones (cleaned)'!B:B,0) -> 0 | H68: =_xlfn.XLOOKUP(B68,'ADS Prima (cleaned)'!A:A,'ADS Prima (cleaned)'!B:B,0) -> 0 | I68: =_xlfn.XLOOKUP(B68,'Auto Mekanika (cleaned)'!A:A,'Auto Mekanika (cleaned)'!B:B,0) -> 0 | J68: =_xlfn.XLOOKUP(B68,'Bengkel Multi Var (cleaned)'!A:A,'Bengkel Multi Var (cleaned)'!B:B,0) -> 0 | K68: 0 | L68: =_xlfn.XLOOKUP(B68,'Drivewell (cleaned)'!A:A,'Drivewell (cleaned)'!B:B,0) -> 0 | M68: 0 | N68: 0 | O68: 0 | P68: =_xlfn.XLOOKUP(B68,'CV Sun (cleaned)'!A:A,'CV Sun (cleaned)'!B:B,0) -> 0 | Q68: =_xlfn.XLOOKUP(B68,'Sumber Timur (clean)'!F:F,'Sumber Timur (clean)'!L:L,0) -> 0 | R68: =_xlfn.XLOOKUP(B68,'Honda Duren (clean)'!F:F,'Honda Duren (clean)'!L:L,0) -> 0 | S68: 0 | T68: =SUM(C68:S68) -> 0
A69: =VLOOKUP(B69,#REF!,5,0) -> #REF! | B69: MONROE Shock Absorber 744421SP Front-LH | C69: =_xlfn.XLOOKUP(B69,'Pit Stop (cleaned)'!A:A,'Pit Stop (cleaned)'!B:B,0) -> 0 | D69: =_xlfn.XLOOKUP(B69,'Subur Makmur Ban (Agg)'!$F$1:$F$5,'Subur Makmur Ban (Agg)'!$L$1:$L$5,0) -> 0 | E69: =_xlfn.XLOOKUP(B69,'Bengkel Pegasus (Agg)'!F:F,'Bengkel Pegasus (Agg)'!L:L,0) -> 0 | F69: =_xlfn.XLOOKUP(B69,'Autocraft (agg)'!F:F,'Autocraft (agg)'!L:L,0) -> 0 | G69: =_xlfn.XLOOKUP(B69,'Autones (cleaned)'!A:A,'Autones (cleaned)'!B:B,0) -> 0 | H69: =_xlfn.XLOOKUP(B69,'ADS Prima (cleaned)'!A:A,'ADS Prima (cleaned)'!B:B,0) -> 0 | I69: =_xlfn.XLOOKUP(B69,'Auto Mekanika (cleaned)'!A:A,'Auto Mekanika (cleaned)'!B:B,0) -> 0 | J69: =_xlfn.XLOOKUP(B69,'Bengkel Multi Var (cleaned)'!A:A,'Bengkel Multi Var (cleaned)'!B:B,0) -> 0 | K69: 0 | L69: =_xlfn.XLOOKUP(B69,'Drivewell (cleaned)'!A:A,'Drivewell (cleaned)'!B:B,0) -> 0 | M69: 0 | N69: 0 | O69: 0 | P69: =_xlfn.XLOOKUP(B69,'CV Sun (cleaned)'!A:A,'CV Sun (cleaned)'!B:B,0) -> 0 | Q69: =_xlfn.XLOOKUP(B69,'Sumber Timur (clean)'!F:F,'Sumber Timur (clean)'!L:L,0) -> 0 | R69: =_xlfn.XLOOKUP(B69,'Honda Duren (clean)'!F:F,'Honda Duren (clean)'!L:L,0) -> 0 | S69: 0 | T69: =SUM(C69:S69) -> 0
A70: =VLOOKUP(B70,#REF!,5,0) -> #REF! | B70: MONROE Shock Absorber 744420SP Front-RH | C70: =_xlfn.XLOOKUP(B70,'Pit Stop (cleaned)'!A:A,'Pit Stop (cleaned)'!B:B,0) -> 0 | D70: =_xlfn.XLOOKUP(B70,'Subur Makmur Ban (Agg)'!$F$1:$F$5,'Subur Makmur Ban (Agg)'!$L$1:$L$5,0) -> 0 | E70: =_xlfn.XLOOKUP(B70,'Bengkel Pegasus (Agg)'!F:F,'Bengkel Pegasus (Agg)'!L:L,0) -> 0 | F70: =_xlfn.XLOOKUP(B70,'Autocraft (agg)'!F:F,'Autocraft (agg)'!L:L,0) -> 0 | G70: =_xlfn.XLOOKUP(B70,'Autones (cleaned)'!A:A,'Autones (cleaned)'!B:B,0) -> 0 | H70: =_xlfn.XLOOKUP(B70,'ADS Prima (cleaned)'!A:A,'ADS Prima (cleaned)'!B:B,0) -> 0 | I70: =_xlfn.XLOOKUP(B70,'Auto Mekanika (cleaned)'!A:A,'Auto Mekanika (cleaned)'!B:B,0) -> 0 | J70: =_xlfn.XLOOKUP(B70,'Bengkel Multi Var (cleaned)'!A:A,'Bengkel Multi Var (cleaned)'!B:B,0) -> 0 | K70: 0 | L70: =_xlfn.XLOOKUP(B70,'Drivewell (cleaned)'!A:A,'Drivewell (cleaned)'!B:B,0) -> 0 | M70: 0 | N70: 0 | O70: 0 | P70: =_xlfn.XLOOKUP(B70,'CV Sun (cleaned)'!A:A,'CV Sun (cleaned)'!B:B,0) -> 0 | Q70: =_xlfn.XLOOKUP(B70,'Sumber Timur (clean)'!F:F,'Sumber Timur (clean)'!L:L,0) -> 0 | R70: =_xlfn.XLOOKUP(B70,'Honda Duren (clean)'!F:F,'Honda Duren (clean)'!L:L,0) -> 0 | S70: 0 | T70: =SUM(C70:S70) -> 0
A71: =VLOOKUP(B71,#REF!,5,0) -> #REF! | B71: MONROE Shock Absorber 744419SP Front-LH | C71: =_xlfn.XLOOKUP(B71,'Pit Stop (cleaned)'!A:A,'Pit Stop (cleaned)'!B:B,0) -> 0 | D71: =_xlfn.XLOOKUP(B71,'Subur Makmur Ban (Agg)'!$F$1:$F$5,'Subur Makmur Ban (Agg)'!$L$1:$L$5,0) -> 0 | E71: =_xlfn.XLOOKUP(B71,'Bengkel Pegasus (Agg)'!F:F,'Bengkel Pegasus (Agg)'!L:L,0) -> 0 | F71: =_xlfn.XLOOKUP(B71,'Autocraft (agg)'!F:F,'Autocraft (agg)'!L:L,0) -> 0 | G71: =_xlfn.XLOOKUP(B71,'Autones (cleaned)'!A:A,'Autones (cleaned)'!B:B,0) -> 0 | H71: =_xlfn.XLOOKUP(B71,'ADS Prima (cleaned)'!A:A,'ADS Prima (cleaned)'!B:B,0) -> 0 | I71: =_xlfn.XLOOKUP(B71,'Auto Mekanika (cleaned)'!A:A,'Auto Mekanika (cleaned)'!B:B,0) -> 0 | J71: =_xlfn.XLOOKUP(B71,'Bengkel Multi Var (cleaned)'!A:A,'Bengkel Multi Var (cleaned)'!B:B,0) -> 0 | K71: 0 | L71: =_xlfn.XLOOKUP(B71,'Drivewell (cleaned)'!A:A,'Drivewell (cleaned)'!B:B,0) -> 0 | M71: 0 | N71: 0 | O71: 0 | P71: =_xlfn.XLOOKUP(B71,'CV Sun (cleaned)'!A:A,'CV Sun (cleaned)'!B:B,0) -> 0 | Q71: =_xlfn.XLOOKUP(B71,'Sumber Timur (clean)'!F:F,'Sumber Timur (clean)'!L:L,0) -> 0 | R71: =_xlfn.XLOOKUP(B71,'Honda Duren (clean)'!F:F,'Honda Duren (clean)'!L:L,0) -> 0 | S71: 0 | T71: =SUM(C71:S71) -> 0
A72: =VLOOKUP(B72,#REF!,5,0) -> #REF! | B72: BOSCH Spark Plug VR8SII30X - Iridium | C72: =_xlfn.XLOOKUP(B72,'Pit Stop (cleaned)'!A:A,'Pit Stop (cleaned)'!B:B,0) -> 10 | D72: =_xlfn.XLOOKUP(B72,'Subur Makmur Ban (Agg)'!$F$1:$F$5,'Subur Makmur Ban (Agg)'!$L$1:$L$5,0) -> 0 | E72: =_xlfn.XLOOKUP(B72,'Bengkel Pegasus (Agg)'!F:F,'Bengkel Pegasus (Agg)'!L:L,0) -> 0 | F72: =_xlfn.XLOOKUP(B72,'Autocraft (agg)'!F:F,'Autocraft (agg)'!L:L,0) -> 0 | G72: =_xlfn.XLOOKUP(B72,'Autones (cleaned)'!A:A,'Autones (cleaned)'!B:B,0) -> 0 | H72: =_xlfn.XLOOKUP(B72,'ADS Prima (cleaned)'!A:A,'ADS Prima (cleaned)'!B:B,0) -> 0 | I72: =_xlfn.XLOOKUP(B72,'Auto Mekanika (cleaned)'!A:A,'Auto Mekanika (cleaned)'!B:B,0) -> 0 | J72: =_xlfn.XLOOKUP(B72,'Bengkel Multi Var (cleaned)'!A:A,'Bengkel Multi Var (cleaned)'!B:B,0) -> 0 | K72: =_xlfn.XLOOKUP(B72,'[2]EURO GALLARIA'!F:F,'[2]EURO GALLARIA'!L:L,0) -> 0 | L72: 28 | M72: =_xlfn.XLOOKUP(B72,'[2]Mersi (CLEAN)'!D:D,'[2]Mersi (CLEAN)'!E:E,0) -> 0 | N72: 0 | O72: 0 | P72: =_xlfn.XLOOKUP(B72,'CV Sun (cleaned)'!A:A,'CV Sun (cleaned)'!B:B,0) -> 0 | Q72: =_xlfn.XLOOKUP(B72,'Sumber Timur (clean)'!F:F,'Sumber Timur (clean)'!L:L,0) -> 0 | R72: =_xlfn.XLOOKUP(B72,'Honda Duren (clean)'!F:F,'Honda Duren (clean)'!L:L,0) -> 0 | S72: =_xlfn.XLOOKUP(B72,'[2]LAVANDER CLEAN'!A:A,'[2]LAVANDER CLEAN'!B:B,0) -> 20 | T72: =SUM(C72:S72) -> 58 | U72: 107510 | V72: =IF(T72*U72=0,"",T72*U72) -> 6235580 | W72: 0242129522
A73: =VLOOKUP(B73,#REF!,5,0) -> #REF! | B73: MOBIL Engine Oil Super AIO PROTECTION 5W-30 1L | C73: =_xlfn.XLOOKUP(B73,'Pit Stop (cleaned)'!A:A,'Pit Stop (cleaned)'!B:B,0) -> 0 | D73: =_xlfn.XLOOKUP(B73,'Subur Makmur Ban (Agg)'!$F$1:$F$5,'Subur Makmur Ban (Agg)'!$L$1:$L$5,0) -> 0 | E73: =_xlfn.XLOOKUP(B73,'Bengkel Pegasus (Agg)'!F:F,'Bengkel Pegasus (Agg)'!L:L,0) -> 0 | F73: =_xlfn.XLOOKUP(B73,'Autocraft (agg)'!F:F,'Autocraft (agg)'!L:L,0) -> 0 | G73: =_xlfn.XLOOKUP(B73,'Autones (cleaned)'!A:A,'Autones (cleaned)'!B:B,0) -> 0 | H73: =_xlfn.XLOOKUP(B73,'ADS Prima (cleaned)'!A:A,'ADS Prima (cleaned)'!B:B,0) -> 0 | I73: =_xlfn.XLOOKUP(B73,'Auto Mekanika (cleaned)'!A:A,'Auto Mekanika (cleaned)'!B:B,0) -> 0 | J73: =_xlfn.XLOOKUP(B73,'Bengkel Multi Var (cleaned)'!A:A,'Bengkel Multi Var (cleaned)'!B:B,0) -> 0 | K73: 0 | L73: =_xlfn.XLOOKUP(B73,'Drivewell (cleaned)'!A:A,'Drivewell (cleaned)'!B:B,0) -> 0 | M73: 0 | N73: 0 | O73: 0 | P73: =_xlfn.XLOOKUP(B73,'CV Sun (cleaned)'!A:A,'CV Sun (cleaned)'!B:B,0) -> 0 | Q73: =_xlfn.XLOOKUP(B73,'Sumber Timur (clean)'!F:F,'Sumber Timur (clean)'!L:L,0) -> 0 | R73: =_xlfn.XLOOKUP(B73,'Honda Duren (clean)'!F:F,'Honda Duren (clean)'!L:L,0) -> 0 | S73: 0 | T73: =SUM(C73:S73) -> 0
A74: =VLOOKUP(B74,#REF!,5,0) -> #REF! | B74: SHELL Engine Oil HELIX HX6 10W-40 4L | C74: =_xlfn.XLOOKUP(B74,'Pit Stop (cleaned)'!A:A,'Pit Stop (cleaned)'!B:B,0) -> 0 | D74: =_xlfn.XLOOKUP(B74,'Subur Makmur Ban (Agg)'!$F$1:$F$5,'Subur Makmur Ban (Agg)'!$L$1:$L$5,0) -> 0 | E74: =_xlfn.XLOOKUP(B74,'Bengkel Pegasus (Agg)'!F:F,'Bengkel Pegasus (Agg)'!L:L,0) -> 0 | F74: =_xlfn.XLOOKUP(B74,'Autocraft (agg)'!F:F,'Autocraft (agg)'!L:L,0) -> 0 | G74: =_xlfn.XLOOKUP(B74,'Autones (cleaned)'!A:A,'Autones (cleaned)'!B:B,0) -> 0 | H74: =_xlfn.XLOOKUP(B74,'ADS Prima (cleaned)'!A:A,'ADS Prima (cleaned)'!B:B,0) -> 0 | I74: =_xlfn.XLOOKUP(B74,'Auto Mekanika (cleaned)'!A:A,'Auto Mekanika (cleaned)'!B:B,0) -> 0 | J74: =_xlfn.XLOOKUP(B74,'Bengkel Multi Var (cleaned)'!A:A,'Bengkel Multi Var (cleaned)'!B:B,0) -> 0 | K74: 0 | L74: =_xlfn.XLOOKUP(B74,'Drivewell (cleaned)'!A:A,'Drivewell (cleaned)'!B:B,0) -> 0 | M74: 0 | N74: 0 | O74: 0 | P74: =_xlfn.XLOOKUP(B74,'CV Sun (cleaned)'!A:A,'CV Sun (cleaned)'!B:B,0) -> 0 | Q74: =_xlfn.XLOOKUP(B74,'Sumber Timur (clean)'!F:F,'Sumber Timur (clean)'!L:L,0) -> 0 | R74: =_xlfn.XLOOKUP(B74,'Honda Duren (clean)'!F:F,'Honda Duren (clean)'!L:L,0) -> 0 | S74: 0 | T74: =SUM(C74:S74) -> 0
A75: =VLOOKUP(B75,#REF!,5,0) -> #REF! | B75: MOTUL Transmission Oil Multi CVTF 1L | C75: =_xlfn.XLOOKUP(B75,'Pit Stop (cleaned)'!A:A,'Pit Stop (cleaned)'!B:B,0) -> 0 | D75: =_xlfn.XLOOKUP(B75,'Subur Makmur Ban (Agg)'!$F$1:$F$5,'Subur Makmur Ban (Agg)'!$L$1:$L$5,0) -> 0 | E75: =_xlfn.XLOOKUP(B75,'Bengkel Pegasus (Agg)'!F:F,'Bengkel Pegasus (Agg)'!L:L,0) -> 0 | F75: =_xlfn.XLOOKUP(B75,'Autocraft (agg)'!F:F,'Autocraft (agg)'!L:L,0) -> 0 | G75: =_xlfn.XLOOKUP(B75,'Autones (cleaned)'!A:A,'Autones (cleaned)'!B:B,0) -> 0 | H75: =_xlfn.XLOOKUP(B75,'ADS Prima (cleaned)'!A:A,'ADS Prima (cleaned)'!B:B,0) -> 0 | I75: =_xlfn.XLOOKUP(B75,'Auto Mekanika (cleaned)'!A:A,'Auto Mekanika (cleaned)'!B:B,0) -> 0 | J75: =_xlfn.XLOOKUP(B75,'Bengkel Multi Var (cleaned)'!A:A,'Bengkel Multi Var (cleaned)'!B:B,0) -> 0 | K75: 0 | L75: =_xlfn.XLOOKUP(B75,'Drivewell (cleaned)'!A:A,'Drivewell (cleaned)'!B:B,0) -> 0 | M75: 0 | N75: 0 | O75: 0 | P75: =_xlfn.XLOOKUP(B75,'CV Sun (cleaned)'!A:A,'CV Sun (cleaned)'!B:B,0) -> 0 | Q75: =_xlfn.XLOOKUP(B75,'Sumber Timur (clean)'!F:F,'Sumber Timur (clean)'!L:L,0) -> 0 | R75: =_xlfn.XLOOKUP(B75,'Honda Duren (clean)'!F:F,'Honda Duren (clean)'!L:L,0) -> 0 | S75: 0 | T75: =SUM(C75:S75) -> 0
A76: =VLOOKUP(B76,#REF!,5,0) -> #REF! | B76: MOTUL Engine Oil MUGEN MS-A 5W-40 1L | C76: =_xlfn.XLOOKUP(B76,'Pit Stop (cleaned)'!A:A,'Pit Stop (cleaned)'!B:B,0) -> 0 | D76: =_xlfn.XLOOKUP(B76,'Subur Makmur Ban (Agg)'!$F$1:$F$5,'Subur Makmur Ban (Agg)'!$L$1:$L$5,0) -> 0 | E76: =_xlfn.XLOOKUP(B76,'Bengkel Pegasus (Agg)'!F:F,'Bengkel Pegasus (Agg)'!L:L,0) -> 0 | F76: =_xlfn.XLOOKUP(B76,'Autocraft (agg)'!F:F,'Autocraft (agg)'!L:L,0) -> 0 | G76: =_xlfn.XLOOKUP(B76,'Autones (cleaned)'!A:A,'Autones (cleaned)'!B:B,0) -> 0 | H76: =_xlfn.XLOOKUP(B76,'ADS Prima (cleaned)'!A:A,'ADS Prima (cleaned)'!B:B,0) -> 0 | I76: =_xlfn.XLOOKUP(B76,'Auto Mekanika (cleaned)'!A:A,'Auto Mekanika (cleaned)'!B:B,0) -> 0 | J76: =_xlfn.XLOOKUP(B76,'Bengkel Multi Var (cleaned)'!A:A,'Bengkel Multi Var (cleaned)'!B:B,0) -> 0 | K76: 0 | L76: =_xlfn.XLOOKUP(B76,'Drivewell (cleaned)'!A:A,'Drivewell (cleaned)'!B:B,0) -> 0 | M76: 0 | N76: 0 | O76: 0 | P76: =_xlfn.XLOOKUP(B76,'CV Sun (cleaned)'!A:A,'CV Sun (cleaned)'!B:B,0) -> 0 | Q76: =_xlfn.XLOOKUP(B76,'Sumber Timur (clean)'!F:F,'Sumber Timur (clean)'!L:L,0) -> 0 | R76: =_xlfn.XLOOKUP(B76,'Honda Duren (clean)'!F:F,'Honda Duren (clean)'!L:L,0) -> 0 | S76: 0 | T76: =SUM(C76:S76) -> 0
A77: =VLOOKUP(B77,#REF!,5,0) -> #REF! | B77: MOTUL Engine Oil Multigrade Plus 10W-40 1L | C77: =_xlfn.XLOOKUP(B77,'Pit Stop (cleaned)'!A:A,'Pit Stop (cleaned)'!B:B,0) -> 0 | D77: =_xlfn.XLOOKUP(B77,'Subur Makmur Ban (Agg)'!$F$1:$F$5,'Subur Makmur Ban (Agg)'!$L$1:$L$5,0) -> 0 | E77: =_xlfn.XLOOKUP(B77,'Bengkel Pegasus (Agg)'!F:F,'Bengkel Pegasus (Agg)'!L:L,0) -> 0 | F77: =_xlfn.XLOOKUP(B77,'Autocraft (agg)'!F:F,'Autocraft (agg)'!L:L,0) -> 0 | G77: =_xlfn.XLOOKUP(B77,'Autones (cleaned)'!A:A,'Autones (cleaned)'!B:B,0) -> 0 | H77: =_xlfn.XLOOKUP(B77,'ADS Prima (cleaned)'!A:A,'ADS Prima (cleaned)'!B:B,0) -> 0 | I77: =_xlfn.XLOOKUP(B77,'Auto Mekanika (cleaned)'!A:A,'Auto Mekanika (cleaned)'!B:B,0) -> 0 | J77: =_xlfn.XLOOKUP(B77,'Bengkel Multi Var (cleaned)'!A:A,'Bengkel Multi Var (cleaned)'!B:B,0) -> 0 | K77: 0 | L77: =_xlfn.XLOOKUP(B77,'Drivewell (cleaned)'!A:A,'Drivewell (cleaned)'!B:B,0) -> 0 | M77: 0 | N77: 0 | O77: 0 | P77: =_xlfn.XLOOKUP(B77,'CV Sun (cleaned)'!A:A,'CV Sun (cleaned)'!B:B,0) -> 0 | Q77: =_xlfn.XLOOKUP(B77,'Sumber Timur (clean)'!F:F,'Sumber Timur (clean)'!L:L,0) -> 0 | R77: =_xlfn.XLOOKUP(B77,'Honda Duren (clean)'!F:F,'Honda Duren (clean)'!L:L,0) -> 0 | S77: 0 | T77: =SUM(C77:S77) -> 0
A78: =VLOOKUP(B78,#REF!,5,0) -> #REF! | B78: MOTUL Diesel Engine Oil TEKMA TURBO POWER 15W-40 1L | C78: =_xlfn.XLOOKUP(B78,'Pit Stop (cleaned)'!A:A,'Pit Stop (cleaned)'!B:B,0) -> 0 | D78: =_xlfn.XLOOKUP(B78,'Subur Makmur Ban (Agg)'!$F$1:$F$5,'Subur Makmur Ban (Agg)'!$L$1:$L$5,0) -> 0 | E78: =_xlfn.XLOOKUP(B78,'Bengkel Pegasus (Agg)'!F:F,'Bengkel Pegasus (Agg)'!L:L,0) -> 0 | F78: =_xlfn.XLOOKUP(B78,'Autocraft (agg)'!F:F,'Autocraft (agg)'!L:L,0) -> 0 | G78: =_xlfn.XLOOKUP(B78,'Autones (cleaned)'!A:A,'Autones (cleaned)'!B:B,0) -> 0 | H78: =_xlfn.XLOOKUP(B78,'ADS Prima (cleaned)'!A:A,'ADS Prima (cleaned)'!B:B,0) -> 0 | I78: =_xlfn.XLOOKUP(B78,'Auto Mekanika (cleaned)'!A:A,'Auto Mekanika (cleaned)'!B:B,0) -> 0 | J78: =_xlfn.XLOOKUP(B78,'Bengkel Multi Var (cleaned)'!A:A,'Bengkel Multi Var (cleaned)'!B:B,0) -> 0 | K78: 0 | L78: =_xlfn.XLOOKUP(B78,'Drivewell (cleaned)'!A:A,'Drivewell (cleaned)'!B:B,0) -> 0 | M78: 0 | N78: 0 | O78: 0 | P78: =_xlfn.XLOOKUP(B78,'CV Sun (cleaned)'!A:A,'CV Sun (cleaned)'!B:B,0) -> 0 | Q78: =_xlfn.XLOOKUP(B78,'Sumber Timur (clean)'!F:F,'Sumber Timur (clean)'!L:L,0) -> 0 | R78: =_xlfn.XLOOKUP(B78,'Honda Duren (clean)'!F:F,'Honda Duren (clean)'!L:L,0) -> 0 | S78: 0 | T78: =SUM(C78:S78) -> 0
A79: =VLOOKUP(B79,#REF!,5,0) -> #REF! | B79: MOTUL Diesel Engine Oil TEKMA MEGA X 15W-40 1L | C79: =_xlfn.XLOOKUP(B79,'Pit Stop (cleaned)'!A:A,'Pit Stop (cleaned)'!B:B,0) -> 0 | D79: =_xlfn.XLOOKUP(B79,'Subur Makmur Ban (Agg)'!$F$1:$F$5,'Subur Makmur Ban (Agg)'!$L$1:$L$5,0) -> 0 | E79: =_xlfn.XLOOKUP(B79,'Bengkel Pegasus (Agg)'!F:F,'Bengkel Pegasus (Agg)'!L:L,0) -> 0 | F79: =_xlfn.XLOOKUP(B79,'Autocraft (agg)'!F:F,'Autocraft (agg)'!L:L,0) -> 0 | G79: =_xlfn.XLOOKUP(B79,'Autones (cleaned)'!A:A,'Autones (cleaned)'!B:B,0) -> 0 | H79: =_xlfn.XLOOKUP(B79,'ADS Prima (cleaned)'!A:A,'ADS Prima (cleaned)'!B:B,0) -> 0 | I79: =_xlfn.XLOOKUP(B79,'Auto Mekanika (cleaned)'!A:A,'Auto Mekanika (cleaned)'!B:B,0) -> 0 | J79: =_xlfn.XLOOKUP(B79,'Bengkel Multi Var (cleaned)'!A:A,'Bengkel Multi Var (cleaned)'!B:B,0) -> 0 | K79: 0 | L79: =_xlfn.XLOOKUP(B79,'Drivewell (cleaned)'!A:A,'Drivewell (cleaned)'!B:B,0) -> 0 | M79: 0 | N79: 0 | O79: 0 | P79: =_xlfn.XLOOKUP(B79,'CV Sun (cleaned)'!A:A,'CV Sun (cleaned)'!B:B,0) -> 0 | Q79: =_xlfn.XLOOKUP(B79,'Sumber Timur (clean)'!F:F,'Sumber Timur (clean)'!L:L,0) -> 0 | R79: =_xlfn.XLOOKUP(B79,'Honda Duren (clean)'!F:F,'Honda Duren (clean)'!L:L,0) -> 0 | S79: 0 | T79: =SUM(C79:S79) -> 0
A80: =VLOOKUP(B80,#REF!,5,0) -> #REF! | B80: MOTUL Transmission Oil ATF VI 1L | C80: =_xlfn.XLOOKUP(B80,'Pit Stop (cleaned)'!A:A,'Pit Stop (cleaned)'!B:B,0) -> 0 | D80: =_xlfn.XLOOKUP(B80,'Subur Makmur Ban (Agg)'!$F$1:$F$5,'Subur Makmur Ban (Agg)'!$L$1:$L$5,0) -> 0 | E80: =_xlfn.XLOOKUP(B80,'Bengkel Pegasus (Agg)'!F:F,'Bengkel Pegasus (Agg)'!L:L,0) -> 0 | F80: =_xlfn.XLOOKUP(B80,'Autocraft (agg)'!F:F,'Autocraft (agg)'!L:L,0) -> 0 | G80: =_xlfn.XLOOKUP(B80,'Autones (cleaned)'!A:A,'Autones (cleaned)'!B:B,0) -> 0 | H80: =_xlfn.XLOOKUP(B80,'ADS Prima (cleaned)'!A:A,'ADS Prima (cleaned)'!B:B,0) -> 0 | I80: =_xlfn.XLOOKUP(B80,'Auto Mekanika (cleaned)'!A:A,'Auto Mekanika (cleaned)'!B:B,0) -> 0 | J80: =_xlfn.XLOOKUP(B80,'Bengkel Multi Var (cleaned)'!A:A,'Bengkel Multi Var (cleaned)'!B:B,0) -> 0 | K80: 0 | L80: =_xlfn.XLOOKUP(B80,'Drivewell (cleaned)'!A:A,'Drivewell (cleaned)'!B:B,0) -> 0 | M80: 0 | N80: 0 | O80: 0 | P80: =_xlfn.XLOOKUP(B80,'CV Sun (cleaned)'!A:A,'CV Sun (cleaned)'!B:B,0) -> 0 | Q80: =_xlfn.XLOOKUP(B80,'Sumber Timur (clean)'!F:F,'Sumber Timur (clean)'!L:L,0) -> 0 | R80: =_xlfn.XLOOKUP(B80,'Honda Duren (clean)'!F:F,'Honda Duren (clean)'!L:L,0) -> 0 | S80: 0 | T80: =SUM(C80:S80) -> 0
A81: =VLOOKUP(B81,#REF!,5,0) -> #REF! | B81: MOTUL Engine Oil Multipower Plus 10W-40 1L | C81: =_xlfn.XLOOKUP(B81,'Pit Stop (cleaned)'!A:A,'Pit Stop (cleaned)'!B:B,0) -> 0 | D81: =_xlfn.XLOOKUP(B81,'Subur Makmur Ban (Agg)'!$F$1:$F$5,'Subur Makmur Ban (Agg)'!$L$1:$L$5,0) -> 0 | E81: =_xlfn.XLOOKUP(B81,'Bengkel Pegasus (Agg)'!F:F,'Bengkel Pegasus (Agg)'!L:L,0) -> 0 | F81: =_xlfn.XLOOKUP(B81,'Autocraft (agg)'!F:F,'Autocraft (agg)'!L:L,0) -> 0 | G81: =_xlfn.XLOOKUP(B81,'Autones (cleaned)'!A:A,'Autones (cleaned)'!B:B,0) -> 0 | H81: =_xlfn.XLOOKUP(B81,'ADS Prima (cleaned)'!A:A,'ADS Prima (cleaned)'!B:B,0) -> 0 | I81: =_xlfn.XLOOKUP(B81,'Auto Mekanika (cleaned)'!A:A,'Auto Mekanika (cleaned)'!B:B,0) -> 0 | J81: =_xlfn.XLOOKUP(B81,'Bengkel Multi Var (cleaned)'!A:A,'Bengkel Multi Var (cleaned)'!B:B,0) -> 0 | K81: 0 | L81: =_xlfn.XLOOKUP(B81,'Drivewell (cleaned)'!A:A,'Drivewell (cleaned)'!B:B,0) -> 0 | M81: 0 | N81: 0 | O81: 0 | P81: =_xlfn.XLOOKUP(B81,'CV Sun (cleaned)'!A:A,'CV Sun (cleaned)'!B:B,0) -> 0 | Q81: =_xlfn.XLOOKUP(B81,'Sumber Timur (clean)'!F:F,'Sumber Timur (clean)'!L:L,0) -> 0 | R81: =_xlfn.XLOOKUP(B81,'Honda Duren (clean)'!F:F,'Honda Duren (clean)'!L:L,0) -> 0 | S81: 0 | T81: =SUM(C81:S81) -> 0
A82: =VLOOKUP(B82,#REF!,5,0) -> #REF! | B82: CASTROL Engine Oil MAGNATEC 5W-30 1L | C82: =_xlfn.XLOOKUP(B82,'Pit Stop (cleaned)'!A:A,'Pit Stop (cleaned)'!B:B,0) -> 0 | D82: =_xlfn.XLOOKUP(B82,'Subur Makmur Ban (Agg)'!$F$1:$F$5,'Subur Makmur Ban (Agg)'!$L$1:$L$5,0) -> 0 | E82: =_xlfn.XLOOKUP(B82,'Bengkel Pegasus (Agg)'!F:F,'Bengkel Pegasus (Agg)'!L:L,0) -> 0 | F82: =_xlfn.XLOOKUP(B82,'Autocraft (agg)'!F:F,'Autocraft (agg)'!L:L,0) -> 0 | G82: =_xlfn.XLOOKUP(B82,'Autones (cleaned)'!A:A,'Autones (cleaned)'!B:B,0) -> 0 | H82: =_xlfn.XLOOKUP(B82,'ADS Prima (cleaned)'!A:A,'ADS Prima (cleaned)'!B:B,0) -> 0 | I82: =_xlfn.XLOOKUP(B82,'Auto Mekanika (cleaned)'!A:A,'Auto Mekanika (cleaned)'!B:B,0) -> 0 | J82: =_xlfn.XLOOKUP(B82,'Bengkel Multi Var (cleaned)'!A:A,'Bengkel Multi Var (cleaned)'!B:B,0) -> 0 | K82: 0 | L82: =_xlfn.XLOOKUP(B82,'Drivewell (cleaned)'!A:A,'Drivewell (cleaned)'!B:B,0) -> 0 | M82: 0 | N82: 0 | O82: 0 | P82: =_xlfn.XLOOKUP(B82,'CV Sun (cleaned)'!A:A,'CV Sun (cleaned)'!B:B,0) -> 0 | Q82: =_xlfn.XLOOKUP(B82,'Sumber Timur (clean)'!F:F,'Sumber Timur (clean)'!L:L,0) -> 0 | R82: =_xlfn.XLOOKUP(B82,'Honda Duren (clean)'!F:F,'Honda Duren (clean)'!L:L,0) -> 0 | S82: 0 | T82: =SUM(C82:S82) -> 0
A83: =VLOOKUP(B83,#REF!,5,0) -> #REF! | B83: MOBIL Engine Oil Super AIO PROTECTION 5W-30 4L | C83: =_xlfn.XLOOKUP(B83,'Pit Stop (cleaned)'!A:A,'Pit Stop (cleaned)'!B:B,0) -> 0 | D83: =_xlfn.XLOOKUP(B83,'Subur Makmur Ban (Agg)'!$F$1:$F$5,'Subur Makmur Ban (Agg)'!$L$1:$L$5,0) -> 0 | E83: =_xlfn.XLOOKUP(B83,'Bengkel Pegasus (Agg)'!F:F,'Bengkel Pegasus (Agg)'!L:L,0) -> 0 | F83: =_xlfn.XLOOKUP(B83,'Autocraft (agg)'!F:F,'Autocraft (agg)'!L:L,0) -> 0 | G83: =_xlfn.XLOOKUP(B83,'Autones (cleaned)'!A:A,'Autones (cleaned)'!B:B,0) -> 0 | H83: =_xlfn.XLOOKUP(B83,'ADS Prima (cleaned)'!A:A,'ADS Prima (cleaned)'!B:B,0) -> 0 | I83: =_xlfn.XLOOKUP(B83,'Auto Mekanika (cleaned)'!A:A,'Auto Mekanika (cleaned)'!B:B,0) -> 0 | J83: =_xlfn.XLOOKUP(B83,'Bengkel Multi Var (cleaned)'!A:A,'Bengkel Multi Var (cleaned)'!B:B,0) -> 0 | K83: 0 | L83: =_xlfn.XLOOKUP(B83,'Drivewell (cleaned)'!A:A,'Drivewell (cleaned)'!B:B,0) -> 0 | M83: 0 | N83: 0 | O83: 0 | P83: =_xlfn.XLOOKUP(B83,'CV Sun (cleaned)'!A:A,'CV Sun (cleaned)'!B:B,0) -> 0 | Q83: =_xlfn.XLOOKUP(B83,'Sumber Timur (clean)'!F:F,'Sumber Timur (clean)'!L:L,0) -> 0 | R83: =_xlfn.XLOOKUP(B83,'Honda Duren (clean)'!F:F,'Honda Duren (clean)'!L:L,0) -> 0 | S83: 0 | T83: =SUM(C83:S83) -> 0
A84: =VLOOKUP(B84,#REF!,5,0) -> #REF! | B84: BOSCH Cabin Filter AP-H06 | C84: =_xlfn.XLOOKUP(B84,'Pit Stop (cleaned)'!A:A,'Pit Stop (cleaned)'!B:B,0) -> 0 | D84: =_xlfn.XLOOKUP(B84,'Subur Makmur Ban (Agg)'!$F$1:$F$5,'Subur Makmur Ban (Agg)'!$L$1:$L$5,0) -> 0 | E84: 1 | F84: =_xlfn.XLOOKUP(B84,'Autocraft (agg)'!F:F,'Autocraft (agg)'!L:L,0) -> 0 | G84: =_xlfn.XLOOKUP(B84,'Autones (cleaned)'!A:A,'Autones (cleaned)'!B:B,0) -> 0 | H84: =_xlfn.XLOOKUP(B84,'ADS Prima (cleaned)'!A:A,'ADS Prima (cleaned)'!B:B,0) -> 0 | I84: =_xlfn.XLOOKUP(B84,'Auto Mekanika (cleaned)'!A:A,'Auto Mekanika (cleaned)'!B:B,0) -> 0 | J84: =_xlfn.XLOOKUP(B84,'Bengkel Multi Var (cleaned)'!A:A,'Bengkel Multi Var (cleaned)'!B:B,0) -> 0 | K84: =_xlfn.XLOOKUP(B84,'[2]EURO GALLARIA'!F:F,'[2]EURO GALLARIA'!L:L,0) -> 0 | L84: =_xlfn.XLOOKUP(B84,'Drivewell (cleaned)'!A:A,'Drivewell (cleaned)'!B:B,0) -> 0 | M84: =_xlfn.XLOOKUP(B84,'[2]Mersi (CLEAN)'!D:D,'[2]Mersi (CLEAN)'!E:E,0) -> 0 | N84: 0 | O84: 0 | P84: =_xlfn.XLOOKUP(B84,'CV Sun (cleaned)'!A:A,'CV Sun (cleaned)'!B:B,0) -> 0 | Q84: =_xlfn.XLOOKUP(B84,'Sumber Timur (clean)'!F:F,'Sumber Timur (clean)'!L:L,0) -> 0 | R84: =_xlfn.XLOOKUP(B84,'Honda Duren (clean)'!F:F,'Honda Duren (clean)'!L:L,0) -> 0 | S84: =_xlfn.XLOOKUP(B84,'[2]LAVANDER CLEAN'!A:A,'[2]LAVANDER CLEAN'!B:B,0) -> 3 | T84: 1 | U84: 148720 | V84: =IF(T84*U84=0,"",T84*U84) -> 148720 | W84: 0986AF7001
A85: =VLOOKUP(B85,#REF!,5,0) -> #REF! | B85: CASTROL Engine Oil MAGNATEC SUV 5W-40 1L | C85: =_xlfn.XLOOKUP(B85,'Pit Stop (cleaned)'!A:A,'Pit Stop (cleaned)'!B:B,0) -> 0 | D85: =_xlfn.XLOOKUP(B85,'Subur Makmur Ban (Agg)'!$F$1:$F$5,'Subur Makmur Ban (Agg)'!$L$1:$L$5,0) -> 0 | E85: =_xlfn.XLOOKUP(B85,'Bengkel Pegasus (Agg)'!F:F,'Bengkel Pegasus (Agg)'!L:L,0) -> 0 | F85: =_xlfn.XLOOKUP(B85,'Autocraft (agg)'!F:F,'Autocraft (agg)'!L:L,0) -> 0 | G85: =_xlfn.XLOOKUP(B85,'Autones (cleaned)'!A:A,'Autones (cleaned)'!B:B,0) -> 0 | H85: =_xlfn.XLOOKUP(B85,'ADS Prima (cleaned)'!A:A,'ADS Prima (cleaned)'!B:B,0) -> 0 | I85: =_xlfn.XLOOKUP(B85,'Auto Mekanika (cleaned)'!A:A,'Auto Mekanika (cleaned)'!B:B,0) -> 0 | J85: =_xlfn.XLOOKUP(B85,'Bengkel Multi Var (cleaned)'!A:A,'Bengkel Multi Var (cleaned)'!B:B,0) -> 0 | K85: 0 | L85: =_xlfn.XLOOKUP(B85,'Drivewell (cleaned)'!A:A,'Drivewell (cleaned)'!B:B,0) -> 0 | M85: 0 | N85: 0 | O85: 0 | P85: =_xlfn.XLOOKUP(B85,'CV Sun (cleaned)'!A:A,'CV Sun (cleaned)'!B:B,0) -> 0 | Q85: =_xlfn.XLOOKUP(B85,'Sumber Timur (clean)'!F:F,'Sumber Timur (clean)'!L:L,0) -> 0 | R85: =_xlfn.XLOOKUP(B85,'Honda Duren (clean)'!F:F,'Honda Duren (clean)'!L:L,0) -> 0 | S85: 0 | T85: =SUM(C85:S85) -> 0
A86: =VLOOKUP(B86,#REF!,5,0) -> #REF! | B86: SHELL Engine Oil HELIX ECO PLUS 5W-30 0.5L | C86: =_xlfn.XLOOKUP(B86,'Pit Stop (cleaned)'!A:A,'Pit Stop (cleaned)'!B:B,0) -> 0 | D86: =_xlfn.XLOOKUP(B86,'Subur Makmur Ban (Agg)'!$F$1:$F$5,'Subur Makmur Ban (Agg)'!$L$1:$L$5,0) -> 0 | E86: =_xlfn.XLOOKUP(B86,'Bengkel Pegasus (Agg)'!F:F,'Bengkel Pegasus (Agg)'!L:L,0) -> 0 | F86: =_xlfn.XLOOKUP(B86,'Autocraft (agg)'!F:F,'Autocraft (agg)'!L:L,0) -> 0 | G86: =_xlfn.XLOOKUP(B86,'Autones (cleaned)'!A:A,'Autones (cleaned)'!B:B,0) -> 0 | H86: =_xlfn.XLOOKUP(B86,'ADS Prima (cleaned)'!A:A,'ADS Prima (cleaned)'!B:B,0) -> 0 | I86: =_xlfn.XLOOKUP(B86,'Auto Mekanika (cleaned)'!A:A,'Auto Mekanika (cleaned)'!B:B,0) -> 0 | J86: =_xlfn.XLOOKUP(B86,'Bengkel Multi Var (cleaned)'!A:A,'Bengkel Multi Var (cleaned)'!B:B,0) -> 0 | K86: 0 | L86: =_xlfn.XLOOKUP(B86,'Drivewell (cleaned)'!A:A,'Drivewell (cleaned)'!B:B,0) -> 0 | M86: 0 | N86: 0 | O86: 0 | P86: =_xlfn.XLOOKUP(B86,'CV Sun (cleaned)'!A:A,'CV Sun (cleaned)'!B:B,0) -> 0 | Q86: =_xlfn.XLOOKUP(B86,'Sumber Timur (clean)'!F:F,'Sumber Timur (clean)'!L:L,0) -> 0 | R86: =_xlfn.XLOOKUP(B86,'Honda Duren (clean)'!F:F,'Honda Duren (clean)'!L:L,0) -> 0 | S86: 0 | T86: =SUM(C86:S86) -> 0
A87: =VLOOKUP(B87,#REF!,5,0) -> #REF! | B87: DENSO Cabin Filter 145520-2370 | C87: =_xlfn.XLOOKUP(B87,'Pit Stop (cleaned)'!A:A,'Pit Stop (cleaned)'!B:B,0) -> 0 | D87: =_xlfn.XLOOKUP(B87,'Subur Makmur Ban (Agg)'!$F$1:$F$5,'Subur Makmur Ban (Agg)'!$L$1:$L$5,0) -> 0 | E87: =_xlfn.XLOOKUP(B87,'Bengkel Pegasus (Agg)'!F:F,'Bengkel Pegasus (Agg)'!L:L,0) -> 0 | F87: =_xlfn.XLOOKUP(B87,'Autocraft (agg)'!F:F,'Autocraft (agg)'!L:L,0) -> 0 | G87: =_xlfn.XLOOKUP(B87,'Autones (cleaned)'!A:A,'Autones (cleaned)'!B:B,0) -> 0 | H87: =_xlfn.XLOOKUP(B87,'ADS Prima (cleaned)'!A:A,'ADS Prima (cleaned)'!B:B,0) -> 0 | I87: =_xlfn.XLOOKUP(B87,'Auto Mekanika (cleaned)'!A:A,'Auto Mekanika (cleaned)'!B:B,0) -> 0 | J87: =_xlfn.XLOOKUP(B87,'Bengkel Multi Var (cleaned)'!A:A,'Bengkel Multi Var (cleaned)'!B:B,0) -> 0 | K87: 0 | L87: =_xlfn.XLOOKUP(B87,'Drivewell (cleaned)'!A:A,'Drivewell (cleaned)'!B:B,0) -> 0 | M87: 0 | N87: 0 | O87: 0 | P87: =_xlfn.XLOOKUP(B87,'CV Sun (cleaned)'!A:A,'CV Sun (cleaned)'!B:B,0) -> 0 | Q87: =_xlfn.XLOOKUP(B87,'Sumber Timur (clean)'!F:F,'Sumber Timur (clean)'!L:L,0) -> 0 | R87: =_xlfn.XLOOKUP(B87,'Honda Duren (clean)'!F:F,'Honda Duren (clean)'!L:L,0) -> 0 | S87: 0 | T87: =SUM(C87:S87) -> 0
A88: =VLOOKUP(B88,#REF!,5,0) -> #REF! | B88: BOSCH Spark Plug VR7NII33X - Iridium | C88: =_xlfn.XLOOKUP(B88,'Pit Stop (cleaned)'!A:A,'Pit Stop (cleaned)'!B:B,0) -> 0 | D88: =_xlfn.XLOOKUP(B88,'Subur Makmur Ban (Agg)'!$F$1:$F$5,'Subur Makmur Ban (Agg)'!$L$1:$L$5,0) -> 0 | E88: =_xlfn.XLOOKUP(B88,'Bengkel Pegasus (Agg)'!F:F,'Bengkel Pegasus (Agg)'!L:L,0) -> 0 | F88: =_xlfn.XLOOKUP(B88,'Autocraft (agg)'!F:F,'Autocraft (agg)'!L:L,0) -> 0 | G88: =_xlfn.XLOOKUP(B88,'Autones (cleaned)'!A:A,'Autones (cleaned)'!B:B,0) -> 0 | H88: =_xlfn.XLOOKUP(B88,'ADS Prima (cleaned)'!A:A,'ADS Prima (cleaned)'!B:B,0) -> 0 | I88: =_xlfn.XLOOKUP(B88,'Auto Mekanika (cleaned)'!A:A,'Auto Mekanika (cleaned)'!B:B,0) -> 0 | J88: =_xlfn.XLOOKUP(B88,'Bengkel Multi Var (cleaned)'!A:A,'Bengkel Multi Var (cleaned)'!B:B,0) -> 0 | K88: 0 | L88: =_xlfn.XLOOKUP(B88,'Drivewell (cleaned)'!A:A,'Drivewell (cleaned)'!B:B,0) -> 0 | M88: 0 | N88: 0 | O88: 0 | P88: =_xlfn.XLOOKUP(B88,'CV Sun (cleaned)'!A:A,'CV Sun (cleaned)'!B:B,0) -> 0 | Q88: =_xlfn.XLOOKUP(B88,'Sumber Timur (clean)'!F:F,'Sumber Timur (clean)'!L:L,0) -> 0 | R88: =_xlfn.XLOOKUP(B88,'Honda Duren (clean)'!F:F,'Honda Duren (clean)'!L:L,0) -> 0 | S88: 0 | T88: =SUM(C88:S88) -> 0
A89: =VLOOKUP(B89,#REF!,5,0) -> #REF! | B89: BOSCH Oil Filter O 1043 | C89: =_xlfn.XLOOKUP(B89,'Pit Stop (cleaned)'!A:A,'Pit Stop (cleaned)'!B:B,0) -> 0 | D89: =_xlfn.XLOOKUP(B89,'Subur Makmur Ban (Agg)'!$F$1:$F$5,'Subur Makmur Ban (Agg)'!$L$1:$L$5,0) -> 0 | E89: =_xlfn.XLOOKUP(B89,'Bengkel Pegasus (Agg)'!F:F,'Bengkel Pegasus (Agg)'!L:L,0) -> 0 | F89: =_xlfn.XLOOKUP(B89,'Autocraft (agg)'!F:F,'Autocraft (agg)'!L:L,0) -> 0 | G89: =_xlfn.XLOOKUP(B89,'Autones (cleaned)'!A:A,'Autones (cleaned)'!B:B,0) -> 0 | H89: =_xlfn.XLOOKUP(B89,'ADS Prima (cleaned)'!A:A,'ADS Prima (cleaned)'!B:B,0) -> 0 | I89: =_xlfn.XLOOKUP(B89,'Auto Mekanika (cleaned)'!A:A,'Auto Mekanika (cleaned)'!B:B,0) -> 0 | J89: =_xlfn.XLOOKUP(B89,'Bengkel Multi Var (cleaned)'!A:A,'Bengkel Multi Var (cleaned)'!B:B,0) -> 0 | K89: 0 | L89: =_xlfn.XLOOKUP(B89,'Drivewell (cleaned)'!A:A,'Drivewell (cleaned)'!B:B,0) -> 0 | M89: 0 | N89: 0 | O89: 0 | P89: =_xlfn.XLOOKUP(B89,'CV Sun (cleaned)'!A:A,'CV Sun (cleaned)'!B:B,0) -> 0 | Q89: =_xlfn.XLOOKUP(B89,'Sumber Timur (clean)'!F:F,'Sumber Timur (clean)'!L:L,0) -> 0 | R89: =_xlfn.XLOOKUP(B89,'Honda Duren (clean)'!F:F,'Honda Duren (clean)'!L:L,0) -> 0 | S89: 0 | T89: =SUM(C89:S89) -> 0
A90: =VLOOKUP(B90,#REF!,5,0) -> #REF! | B90: BOSCH Cabin Filter AP-T10 | C90: =_xlfn.XLOOKUP(B90,'Pit Stop (cleaned)'!A:A,'Pit Stop (cleaned)'!B:B,0) -> 0 | D90: =_xlfn.XLOOKUP(B90,'Subur Makmur Ban (Agg)'!$F$1:$F$5,'Subur Makmur Ban (Agg)'!$L$1:$L$5,0) -> 0 | E90: 1 | F90: =_xlfn.XLOOKUP(B90,'Autocraft (agg)'!F:F,'Autocraft (agg)'!L:L,0) -> 0 | G90: =_xlfn.XLOOKUP(B90,'Autones (cleaned)'!A:A,'Autones (cleaned)'!B:B,0) -> 0 | H90: =_xlfn.XLOOKUP(B90,'ADS Prima (cleaned)'!A:A,'ADS Prima (cleaned)'!B:B,0) -> 0 | I90: =_xlfn.XLOOKUP(B90,'Auto Mekanika (cleaned)'!A:A,'Auto Mekanika (cleaned)'!B:B,0) -> 0 | J90: =_xlfn.XLOOKUP(B90,'Bengkel Multi Var (cleaned)'!A:A,'Bengkel Multi Var (cleaned)'!B:B,0) -> 0 | K90: =_xlfn.XLOOKUP(B90,'[2]EURO GALLARIA'!F:F,'[2]EURO GALLARIA'!L:L,0) -> 0 | L90: =_xlfn.XLOOKUP(B90,'Drivewell (cleaned)'!A:A,'Drivewell (cleaned)'!B:B,0) -> 0 | M90: =_xlfn.XLOOKUP(B90,'[2]Mersi (CLEAN)'!D:D,'[2]Mersi (CLEAN)'!E:E,0) -> 0 | N90: 0 | O90: 0 | P90: =_xlfn.XLOOKUP(B90,'CV Sun (cleaned)'!A:A,'CV Sun (cleaned)'!B:B,0) -> 0 | Q90: =_xlfn.XLOOKUP(B90,'Sumber Timur (clean)'!F:F,'Sumber Timur (clean)'!L:L,0) -> 0 | R90: =_xlfn.XLOOKUP(B90,'Honda Duren (clean)'!F:F,'Honda Duren (clean)'!L:L,0) -> 0 | S90: =_xlfn.XLOOKUP(B90,'[2]LAVANDER CLEAN'!A:A,'[2]LAVANDER CLEAN'!B:B,0) -> 5 | T90: =SUM(C90:S90) -> 6 | U90: 148720 | V90: =IF(T90*U90=0,"",T90*U90) -> 892320 | W90: 0986AF7011
A91: =VLOOKUP(B91,#REF!,5,0) -> #REF! | B91: CASTROL Engine Oil MAGNATEC SUV 5W-40 4L | C91: =_xlfn.XLOOKUP(B91,'Pit Stop (cleaned)'!A:A,'Pit Stop (cleaned)'!B:B,0) -> 0 | D91: =_xlfn.XLOOKUP(B91,'Subur Makmur Ban (Agg)'!$F$1:$F$5,'Subur Makmur Ban (Agg)'!$L$1:$L$5,0) -> 0 | E91: =_xlfn.XLOOKUP(B91,'Bengkel Pegasus (Agg)'!F:F,'Bengkel Pegasus (Agg)'!L:L,0) -> 0 | F91: =_xlfn.XLOOKUP(B91,'Autocraft (agg)'!F:F,'Autocraft (agg)'!L:L,0) -> 0 | G91: =_xlfn.XLOOKUP(B91,'Autones (cleaned)'!A:A,'Autones (cleaned)'!B:B,0) -> 0 | H91: =_xlfn.XLOOKUP(B91,'ADS Prima (cleaned)'!A:A,'ADS Prima (cleaned)'!B:B,0) -> 0 | I91: =_xlfn.XLOOKUP(B91,'Auto Mekanika (cleaned)'!A:A,'Auto Mekanika (cleaned)'!B:B,0) -> 0 | J91: =_xlfn.XLOOKUP(B91,'Bengkel Multi Var (cleaned)'!A:A,'Bengkel Multi Var (cleaned)'!B:B,0) -> 0 | K91: 0 | L91: =_xlfn.XLOOKUP(B91,'Drivewell (cleaned)'!A:A,'Drivewell (cleaned)'!B:B,0) -> 0 | M91: 0 | N91: 0 | O91: 0 | P91: =_xlfn.XLOOKUP(B91,'CV Sun (cleaned)'!A:A,'CV Sun (cleaned)'!B:B,0) -> 0 | Q91: =_xlfn.XLOOKUP(B91,'Sumber Timur (clean)'!F:F,'Sumber Timur (clean)'!L:L,0) -> 0 | R91: =_xlfn.XLOOKUP(B91,'Honda Duren (clean)'!F:F,'Honda Duren (clean)'!L:L,0) -> 0 | S91: 0 | T91: =SUM(C91:S91) -> 0
A92: =VLOOKUP(B92,#REF!,5,0) -> #REF! | B92: BOSCH Battery MF Blue 55D23L 12V-60Ah | C92: =_xlfn.XLOOKUP(B92,'Pit Stop (cleaned)'!A:A,'Pit Stop (cleaned)'!B:B,0) -> 0 | D92: =_xlfn.XLOOKUP(B92,'Subur Makmur Ban (Agg)'!$F$1:$F$5,'Subur Makmur Ban (Agg)'!$L$1:$L$5,0) -> 0 | E92: =_xlfn.XLOOKUP(B92,'Bengkel Pegasus (Agg)'!F:F,'Bengkel Pegasus (Agg)'!L:L,0) -> 0 | F92: =_xlfn.XLOOKUP(B92,'Autocraft (agg)'!F:F,'Autocraft (agg)'!L:L,0) -> 0 | G92: =_xlfn.XLOOKUP(B92,'Autones (cleaned)'!A:A,'Autones (cleaned)'!B:B,0) -> 5 | H92: =_xlfn.XLOOKUP(B92,'ADS Prima (cleaned)'!A:A,'ADS Prima (cleaned)'!B:B,0) -> 0 | I92: =_xlfn.XLOOKUP(B92,'Auto Mekanika (cleaned)'!A:A,'Auto Mekanika (cleaned)'!B:B,0) -> 10 | J92: =_xlfn.XLOOKUP(B92,'Bengkel Multi Var (cleaned)'!A:A,'Bengkel Multi Var (cleaned)'!B:B,0) -> 0 | K92: =_xlfn.XLOOKUP(B92,'[2]EURO GALLARIA'!F:F,'[2]EURO GALLARIA'!L:L,0) -> 0 | L92: =_xlfn.XLOOKUP(B92,'Drivewell (cleaned)'!A:A,'Drivewell (cleaned)'!B:B,0) -> 0 | M92: =_xlfn.XLOOKUP(B92,'[2]Mersi (CLEAN)'!D:D,'[2]Mersi (CLEAN)'!E:E,0) -> 0 | N92: 0 | O92: 0 | P92: =_xlfn.XLOOKUP(B92,'CV Sun (cleaned)'!A:A,'CV Sun (cleaned)'!B:B,0) -> 0 | Q92: =_xlfn.XLOOKUP(B92,'Sumber Timur (clean)'!F:F,'Sumber Timur (clean)'!L:L,0) -> 0 | R92: =_xlfn.XLOOKUP(B92,'Honda Duren (clean)'!F:F,'Honda Duren (clean)'!L:L,0) -> 0 | S92: =_xlfn.XLOOKUP(B92,'[2]LAVANDER CLEAN'!A:A,'[2]LAVANDER CLEAN'!B:B,0) -> 0 | T92: =SUM(C92:S92) -> 15 | U92: 880080 | V92: =IF(T92*U92=0,"",T92*U92) -> 13201200 | W92: 0986A00369
A93: =VLOOKUP(B93,#REF!,5,0) -> #REF! | B93: BOSCH Oil Filter O 1041 | C93: =_xlfn.XLOOKUP(B93,'Pit Stop (cleaned)'!A:A,'Pit Stop (cleaned)'!B:B,0) -> 60 | D93: =_xlfn.XLOOKUP(B93,'Subur Makmur Ban (Agg)'!$F$1:$F$5,'Subur Makmur Ban (Agg)'!$L$1:$L$5,0) -> 80 | E93: =_xlfn.XLOOKUP(B93,'Bengkel Pegasus (Agg)'!F:F,'Bengkel Pegasus (Agg)'!L:L,0) -> 0 | F93: =_xlfn.XLOOKUP(B93,'Autocraft (agg)'!F:F,'Autocraft (agg)'!L:L,0) -> 0 | G93: =_xlfn.XLOOKUP(B93,'Autones (cleaned)'!A:A,'Autones (cleaned)'!B:B,0) -> 0 | H93: =_xlfn.XLOOKUP(B93,'ADS Prima (cleaned)'!A:A,'ADS Prima (cleaned)'!B:B,0) -> 0 | I93: =_xlfn.XLOOKUP(B93,'Auto Mekanika (cleaned)'!A:A,'Auto Mekanika (cleaned)'!B:B,0) -> 0 | J93: =_xlfn.XLOOKUP(B93,'Bengkel Multi Var (cleaned)'!A:A,'Bengkel Multi Var (cleaned)'!B:B,0) -> 40 | K93: =_xlfn.XLOOKUP(B93,'[2]EURO GALLARIA'!F:F,'[2]EURO GALLARIA'!L:L,0) -> 0 | L93: =_xlfn.XLOOKUP(B93,'Drivewell (cleaned)'!A:A,'Drivewell (cleaned)'!B:B,0) -> 20 | M93: =_xlfn.XLOOKUP(B93,'[2]Mersi (CLEAN)'!D:D,'[2]Mersi (CLEAN)'!E:E,0) -> 0 | N93: 0 | O93: 0 | P93: =_xlfn.XLOOKUP(B93,'CV Sun (cleaned)'!A:A,'CV Sun (cleaned)'!B:B,0) -> 50 | Q93: =_xlfn.XLOOKUP(B93,'Sumber Timur (clean)'!F:F,'Sumber Timur (clean)'!L:L,0) -> 30 | R93: =_xlfn.XLOOKUP(B93,'Honda Duren (clean)'!F:F,'Honda Duren (clean)'!L:L,0) -> 0 | S93: =_xlfn.XLOOKUP(B93,'[2]LAVANDER CLEAN'!A:A,'[2]LAVANDER CLEAN'!B:B,0) -> 25 | T93: =SUM(C93:S93) -> 305 | U93: 27950 | V93: =IF(T93*U93=0,"",T93*U93) -> 8524750 | W93: 0986AF1041
A94: =VLOOKUP(B94,#REF!,5,0) -> #REF! | B94: DENSO Cabin Filter 145520-4960 | C94: =_xlfn.XLOOKUP(B94,'Pit Stop (cleaned)'!A:A,'Pit Stop (cleaned)'!B:B,0) -> 0 | D94: =_xlfn.XLOOKUP(B94,'Subur Makmur Ban (Agg)'!$F$1:$F$5,'Subur Makmur Ban (Agg)'!$L$1:$L$5,0) -> 0 | E94: =_xlfn.XLOOKUP(B94,'Bengkel Pegasus (Agg)'!F:F,'Bengkel Pegasus (Agg)'!L:L,0) -> 0 | F94: =_xlfn.XLOOKUP(B94,'Autocraft (agg)'!F:F,'Autocraft (agg)'!L:L,0) -> 0 | G94: =_xlfn.XLOOKUP(B94,'Autones (cleaned)'!A:A,'Autones (cleaned)'!B:B,0) -> 0 | H94: =_xlfn.XLOOKUP(B94,'ADS Prima (cleaned)'!A:A,'ADS Prima (cleaned)'!B:B,0) -> 0 | I94: =_xlfn.XLOOKUP(B94,'Auto Mekanika (cleaned)'!A:A,'Auto Mekanika (cleaned)'!B:B,0) -> 0 | J94: =_xlfn.XLOOKUP(B94,'Bengkel Multi Var (cleaned)'!A:A,'Bengkel Multi Var (cleaned)'!B:B,0) -> 0 | K94: 0 | L94: =_xlfn.XLOOKUP(B94,'Drivewell (cleaned)'!A:A,'Drivewell (cleaned)'!B:B,0) -> 0 | M94: 0 | N94: 0 | O94: 0 | P94: =_xlfn.XLOOKUP(B94,'CV Sun (cleaned)'!A:A,'CV Sun (cleaned)'!B:B,0) -> 0 | Q94: =_xlfn.XLOOKUP(B94,'Sumber Timur (clean)'!F:F,'Sumber Timur (clean)'!L:L,0) -> 0 | R94: =_xlfn.XLOOKUP(B94,'Honda Duren (clean)'!F:F,'Honda Duren (clean)'!L:L,0) -> 0 | S94: 0 | T94: =SUM(C94:S94) -> 0
A95: =VLOOKUP(B95,#REF!,5,0) -> #REF! | B95: MOBIL Engine Oil Super AIO PROTECTION 0W-20 1L | C95: =_xlfn.XLOOKUP(B95,'Pit Stop (cleaned)'!A:A,'Pit Stop (cleaned)'!B:B,0) -> 0 | D95: =_xlfn.XLOOKUP(B95,'Subur Makmur Ban (Agg)'!$F$1:$F$5,'Subur Makmur Ban (Agg)'!$L$1:$L$5,0) -> 0 | E95: =_xlfn.XLOOKUP(B95,'Bengkel Pegasus (Agg)'!F:F,'Bengkel Pegasus (Agg)'!L:L,0) -> 0 | F95: =_xlfn.XLOOKUP(B95,'Autocraft (agg)'!F:F,'Autocraft (agg)'!L:L,0) -> 0 | G95: =_xlfn.XLOOKUP(B95,'Autones (cleaned)'!A:A,'Autones (cleaned)'!B:B,0) -> 0 | H95: =_xlfn.XLOOKUP(B95,'ADS Prima (cleaned)'!A:A,'ADS Prima (cleaned)'!B:B,0) -> 0 | I95: =_xlfn.XLOOKUP(B95,'Auto Mekanika (cleaned)'!A:A,'Auto Mekanika (cleaned)'!B:B,0) -> 0 | J95: =_xlfn.XLOOKUP(B95,'Bengkel Multi Var (cleaned)'!A:A,'Bengkel Multi Var (cleaned)'!B:B,0) -> 0 | K95: 0 | L95: =_xlfn.XLOOKUP(B95,'Drivewell (cleaned)'!A:A,'Drivewell (cleaned)'!B:B,0) -> 0 | M95: 0 | N95: 0 | O95: 0 | P95: =_xlfn.XLOOKUP(B95,'CV Sun (cleaned)'!A:A,'CV Sun (cleaned)'!B:B,0) -> 0 | Q95: =_xlfn.XLOOKUP(B95,'Sumber Timur (clean)'!F:F,'Sumber Timur (clean)'!L:L,0) -> 0 | R95: =_xlfn.XLOOKUP(B95,'Honda Duren (clean)'!F:F,'Honda Duren (clean)'!L:L,0) -> 0 | S95: 0 | T95: =SUM(C95:S95) -> 0
A96: =VLOOKUP(B96,#REF!,5,0) -> #REF! | B96: BOSCH Oil Filter O 0126 | C96: =_xlfn.XLOOKUP(B96,'Pit Stop (cleaned)'!A:A,'Pit Stop (cleaned)'!B:B,0) -> 0 | D96: =_xlfn.XLOOKUP(B96,'Subur Makmur Ban (Agg)'!$F$1:$F$5,'Subur Makmur Ban (Agg)'!$L$1:$L$5,0) -> 0 | E96: =_xlfn.XLOOKUP(B96,'Bengkel Pegasus (Agg)'!F:F,'Bengkel Pegasus (Agg)'!L:L,0) -> 0 | F96: =_xlfn.XLOOKUP(B96,'Autocraft (agg)'!F:F,'Autocraft (agg)'!L:L,0) -> 20 | G96: =_xlfn.XLOOKUP(B96,'Autones (cleaned)'!A:A,'Autones (cleaned)'!B:B,0) -> 0 | H96: =_xlfn.XLOOKUP(B96,'ADS Prima (cleaned)'!A:A,'ADS Prima (cleaned)'!B:B,0) -> 60 | I96: =_xlfn.XLOOKUP(B96,'Auto Mekanika (cleaned)'!A:A,'Auto Mekanika (cleaned)'!B:B,0) -> 0 | J96: =_xlfn.XLOOKUP(B96,'Bengkel Multi Var (cleaned)'!A:A,'Bengkel Multi Var (cleaned)'!B:B,0) -> 0 | K96: =_xlfn.XLOOKUP(B96,'[2]EURO GALLARIA'!F:F,'[2]EURO GALLARIA'!L:L,0) -> 0 | L96: =_xlfn.XLOOKUP(B96,'Drivewell (cleaned)'!A:A,'Drivewell (cleaned)'!B:B,0) -> 20 | M96: =_xlfn.XLOOKUP(B96,'[2]Mersi (CLEAN)'!D:D,'[2]Mersi (CLEAN)'!E:E,0) -> 0 | N96: 0 | O96: 0 | P96: =_xlfn.XLOOKUP(B96,'CV Sun (cleaned)'!A:A,'CV Sun (cleaned)'!B:B,0) -> 50 | Q96: =_xlfn.XLOOKUP(B96,'Sumber Timur (clean)'!F:F,'Sumber Timur (clean)'!L:L,0) -> 0 | R96: =_xlfn.XLOOKUP(B96,'Honda Duren (clean)'!F:F,'Honda Duren (clean)'!L:L,0) -> 0 | S96: =_xlfn.XLOOKUP(B96,'[2]LAVANDER CLEAN'!A:A,'[2]LAVANDER CLEAN'!B:B,0) -> 0 | T96: =SUM(C96:S96) -> 150 | U96: 27950 | V96: =IF(T96*U96=0,"",T96*U96) -> 4192500 | W96: 0986AF0126
A97: =VLOOKUP(B97,#REF!,5,0) -> #REF! | B97: DENSO Cabin Filter 145520-2550 | C97: =_xlfn.XLOOKUP(B97,'Pit Stop (cleaned)'!A:A,'Pit Stop (cleaned)'!B:B,0) -> 0 | D97: =_xlfn.XLOOKUP(B97,'Subur Makmur Ban (Agg)'!$F$1:$F$5,'Subur Makmur Ban (Agg)'!$L$1:$L$5,0) -> 0 | E97: =_xlfn.XLOOKUP(B97,'Bengkel Pegasus (Agg)'!F:F,'Bengkel Pegasus (Agg)'!L:L,0) -> 0 | F97: =_xlfn.XLOOKUP(B97,'Autocraft (agg)'!F:F,'Autocraft (agg)'!L:L,0) -> 0 | G97: =_xlfn.XLOOKUP(B97,'Autones (cleaned)'!A:A,'Autones (cleaned)'!B:B,0) -> 0 | H97: =_xlfn.XLOOKUP(B97,'ADS Prima (cleaned)'!A:A,'ADS Prima (cleaned)'!B:B,0) -> 0 | I97: =_xlfn.XLOOKUP(B97,'Auto Mekanika (cleaned)'!A:A,'Auto Mekanika (cleaned)'!B:B,0) -> 0 | J97: =_xlfn.XLOOKUP(B97,'Bengkel Multi Var (cleaned)'!A:A,'Bengkel Multi Var (cleaned)'!B:B,0) -> 0 | K97: 0 | L97: =_xlfn.XLOOKUP(B97,'Drivewell (cleaned)'!A:A,'Drivewell (cleaned)'!B:B,0) -> 0 | M97: 0 | N97: 0 | O97: 0 | P97: =_xlfn.XLOOKUP(B97,'CV Sun (cleaned)'!A:A,'CV Sun (cleaned)'!B:B,0) -> 0 | Q97: =_xlfn.XLOOKUP(B97,'Sumber Timur (clean)'!F:F,'Sumber Timur (clean)'!L:L,0) -> 0 | R97: =_xlfn.XLOOKUP(B97,'Honda Duren (clean)'!F:F,'Honda Duren (clean)'!L:L,0) -> 0 | S97: 0 | T97: =SUM(C97:S97) -> 0
A98: =VLOOKUP(B98,#REF!,5,0) -> #REF! | B98: SHELL Engine Oil HELIX HX7 Plus 5W-40 1L | C98: =_xlfn.XLOOKUP(B98,'Pit Stop (cleaned)'!A:A,'Pit Stop (cleaned)'!B:B,0) -> 0 | D98: =_xlfn.XLOOKUP(B98,'Subur Makmur Ban (Agg)'!$F$1:$F$5,'Subur Makmur Ban (Agg)'!$L$1:$L$5,0) -> 0 | E98: =_xlfn.XLOOKUP(B98,'Bengkel Pegasus (Agg)'!F:F,'Bengkel Pegasus (Agg)'!L:L,0) -> 0 | F98: =_xlfn.XLOOKUP(B98,'Autocraft (agg)'!F:F,'Autocraft (agg)'!L:L,0) -> 0 | G98: =_xlfn.XLOOKUP(B98,'Autones (cleaned)'!A:A,'Autones (cleaned)'!B:B,0) -> 0 | H98: =_xlfn.XLOOKUP(B98,'ADS Prima (cleaned)'!A:A,'ADS Prima (cleaned)'!B:B,0) -> 0 | I98: =_xlfn.XLOOKUP(B98,'Auto Mekanika (cleaned)'!A:A,'Auto Mekanika (cleaned)'!B:B,0) -> 0 | J98: =_xlfn.XLOOKUP(B98,'Bengkel Multi Var (cleaned)'!A:A,'Bengkel Multi Var (cleaned)'!B:B,0) -> 0 | K98: 0 | L98: =_xlfn.XLOOKUP(B98,'Drivewell (cleaned)'!A:A,'Drivewell (cleaned)'!B:B,0) -> 0 | M98: 0 | N98: 0 | O98: 0 | P98: =_xlfn.XLOOKUP(B98,'CV Sun (cleaned)'!A:A,'CV Sun (cleaned)'!B:B,0) -> 0 | Q98: =_xlfn.XLOOKUP(B98,'Sumber Timur (clean)'!F:F,'Sumber Timur (clean)'!L:L,0) -> 0 | R98: =_xlfn.XLOOKUP(B98,'Honda Duren (clean)'!F:F,'Honda Duren (clean)'!L:L,0) -> 0 | S98: 0 | T98: =SUM(C98:S98) -> 0
A99: =VLOOKUP(B99,#REF!,5,0) -> #REF! | B99: SHELL Transmission Oil Spirax ATF 6 1L | C99: =_xlfn.XLOOKUP(B99,'Pit Stop (cleaned)'!A:A,'Pit Stop (cleaned)'!B:B,0) -> 0 | D99: =_xlfn.XLOOKUP(B99,'Subur Makmur Ban (Agg)'!$F$1:$F$5,'Subur Makmur Ban (Agg)'!$L$1:$L$5,0) -> 0 | E99: =_xlfn.XLOOKUP(B99,'Bengkel Pegasus (Agg)'!F:F,'Bengkel Pegasus (Agg)'!L:L,0) -> 0 | F99: =_xlfn.XLOOKUP(B99,'Autocraft (agg)'!F:F,'Autocraft (agg)'!L:L,0) -> 0 | G99: =_xlfn.XLOOKUP(B99,'Autones (cleaned)'!A:A,'Autones (cleaned)'!B:B,0) -> 0 | H99: =_xlfn.XLOOKUP(B99,'ADS Prima (cleaned)'!A:A,'ADS Prima (cleaned)'!B:B,0) -> 0 | I99: =_xlfn.XLOOKUP(B99,'Auto Mekanika (cleaned)'!A:A,'Auto Mekanika (cleaned)'!B:B,0) -> 0 | J99: =_xlfn.XLOOKUP(B99,'Bengkel Multi Var (cleaned)'!A:A,'Bengkel Multi Var (cleaned)'!B:B,0) -> 0 | K99: 0 | L99: =_xlfn.XLOOKUP(B99,'Drivewell (cleaned)'!A:A,'Drivewell (cleaned)'!B:B,0) -> 0 | M99: 0 | N99: 0 | O99: 0 | P99: =_xlfn.XLOOKUP(B99,'CV Sun (cleaned)'!A:A,'CV Sun (cleaned)'!B:B,0) -> 0 | Q99: =_xlfn.XLOOKUP(B99,'Sumber Timur (clean)'!F:F,'Sumber Timur (clean)'!L:L,0) -> 0 | R99: =_xlfn.XLOOKUP(B99,'Honda Duren (clean)'!F:F,'Honda Duren (clean)'!L:L,0) -> 0 | S99: 0 | T99: =SUM(C99:S99) -> 0
A100: =VLOOKUP(B100,#REF!,5,0) -> #REF! | B100: SHELL Engine Oil HELIX HX6 10W-40 1L | C100: =_xlfn.XLOOKUP(B100,'Pit Stop (cleaned)'!A:A,'Pit Stop (cleaned)'!B:B,0) -> 0 | D100: =_xlfn.XLOOKUP(B100,'Subur Makmur Ban (Agg)'!$F$1:$F$5,'Subur Makmur Ban (Agg)'!$L$1:$L$5,0) -> 0 | E100: =_xlfn.XLOOKUP(B100,'Bengkel Pegasus (Agg)'!F:F,'Bengkel Pegasus (Agg)'!L:L,0) -> 0 | F100: =_xlfn.XLOOKUP(B100,'Autocraft (agg)'!F:F,'Autocraft (agg)'!L:L,0) -> 0 | G100: =_xlfn.XLOOKUP(B100,'Autones (cleaned)'!A:A,'Autones (cleaned)'!B:B,0) -> 0 | H100: =_xlfn.XLOOKUP(B100,'ADS Prima (cleaned)'!A:A,'ADS Prima (cleaned)'!B:B,0) -> 0 | I100: =_xlfn.XLOOKUP(B100,'Auto Mekanika (cleaned)'!A:A,'Auto Mekanika (cleaned)'!B:B,0) -> 0 | J100: =_xlfn.XLOOKUP(B100,'Bengkel Multi Var (cleaned)'!A:A,'Bengkel Multi Var (cleaned)'!B:B,0) -> 0 | K100: 0 | L100: =_xlfn.XLOOKUP(B100,'Drivewell (cleaned)'!A:A,'Drivewell (cleaned)'!B:B,0) -> 0 | M100: 0 | N100: 0 | O100: 0 | P100: =_xlfn.XLOOKUP(B100,'CV Sun (cleaned)'!A:A,'CV Sun (cleaned)'!B:B,0) -> 0 | Q100: =_xlfn.XLOOKUP(B100,'Sumber Timur (clean)'!F:F,'Sumber Timur (clean)'!L:L,0) -> 0 | R100: =_xlfn.XLOOKUP(B100,'Honda Duren (clean)'!F:F,'Honda Duren (clean)'!L:L,0) -> 0 | S100: 0 | T100: =SUM(C100:S100) -> 0
A101: =VLOOKUP(B101,#REF!,5,0) -> #REF! | B101: MOBIL Engine Oil Super AIO PROTECTION 10W-40 4L | C101: =_xlfn.XLOOKUP(B101,'Pit Stop (cleaned)'!A:A,'Pit Stop (cleaned)'!B:B,0) -> 0 | D101: =_xlfn.XLOOKUP(B101,'Subur Makmur Ban (Agg)'!$F$1:$F$5,'Subur Makmur Ban (Agg)'!$L$1:$L$5,0) -> 0 | E101: =_xlfn.XLOOKUP(B101,'Bengkel Pegasus (Agg)'!F:F,'Bengkel Pegasus (Agg)'!L:L,0) -> 0 | F101: =_xlfn.XLOOKUP(B101,'Autocraft (agg)'!F:F,'Autocraft (agg)'!L:L,0) -> 0 | G101: =_xlfn.XLOOKUP(B101,'Autones (cleaned)'!A:A,'Autones (cleaned)'!B:B,0) -> 0 | H101: =_xlfn.XLOOKUP(B101,'ADS Prima (cleaned)'!A:A,'ADS Prima (cleaned)'!B:B,0) -> 0 | I101: =_xlfn.XLOOKUP(B101,'Auto Mekanika (cleaned)'!A:A,'Auto Mekanika (cleaned)'!B:B,0) -> 0 | J101: =_xlfn.XLOOKUP(B101,'Bengkel Multi Var (cleaned)'!A:A,'Bengkel Multi Var (cleaned)'!B:B,0) -> 0 | K101: 0 | L101: =_xlfn.XLOOKUP(B101,'Drivewell (cleaned)'!A:A,'Drivewell (cleaned)'!B:B,0) -> 0 | M101: 0 | N101: 0 | O101: 0 | P101: =_xlfn.XLOOKUP(B101,'CV Sun (cleaned)'!A:A,'CV Sun (cleaned)'!B:B,0) -> 0 | Q101: =_xlfn.XLOOKUP(B101,'Sumber Timur (clean)'!F:F,'Sumber Timur (clean)'!L:L,0) -> 0 | R101: =_xlfn.XLOOKUP(B101,'Honda Duren (clean)'!F:F,'Honda Duren (clean)'!L:L,0) -> 0 | S101: 0 | T101: =SUM(C101:S101) -> 0
A102: =VLOOKUP(B102,#REF!,5,0) -> #REF! | B102: DENSO Cabin Filter 145520-4010 | C102: =_xlfn.XLOOKUP(B102,'Pit Stop (cleaned)'!A:A,'Pit Stop (cleaned)'!B:B,0) -> 0 | D102: =_xlfn.XLOOKUP(B102,'Subur Makmur Ban (Agg)'!$F$1:$F$5,'Subur Makmur Ban (Agg)'!$L$1:$L$5,0) -> 0 | E102: =_xlfn.XLOOKUP(B102,'Bengkel Pegasus (Agg)'!F:F,'Bengkel Pegasus (Agg)'!L:L,0) -> 0 | F102: =_xlfn.XLOOKUP(B102,'Autocraft (agg)'!F:F,'Autocraft (agg)'!L:L,0) -> 0 | G102: =_xlfn.XLOOKUP(B102,'Autones (cleaned)'!A:A,'Autones (cleaned)'!B:B,0) -> 0 | H102: =_xlfn.XLOOKUP(B102,'ADS Prima (cleaned)'!A:A,'ADS Prima (cleaned)'!B:B,0) -> 0 | I102: =_xlfn.XLOOKUP(B102,'Auto Mekanika (cleaned)'!A:A,'Auto Mekanika (cleaned)'!B:B,0) -> 0 | J102: =_xlfn.XLOOKUP(B102,'Bengkel Multi Var (cleaned)'!A:A,'Bengkel Multi Var (cleaned)'!B:B,0) -> 0 | K102: 0 | L102: =_xlfn.XLOOKUP(B102,'Drivewell (cleaned)'!A:A,'Drivewell (cleaned)'!B:B,0) -> 0 | M102: 0 | N102: 0 | O102: 0 | P102: =_xlfn.XLOOKUP(B102,'CV Sun (cleaned)'!A:A,'CV Sun (cleaned)'!B:B,0) -> 0 | Q102: =_xlfn.XLOOKUP(B102,'Sumber Timur (clean)'!F:F,'Sumber Timur (clean)'!L:L,0) -> 0 | R102: =_xlfn.XLOOKUP(B102,'Honda Duren (clean)'!F:F,'Honda Duren (clean)'!L:L,0) -> 0 | S102: 0 | T102: =SUM(C102:S102) -> 0
A103: =VLOOKUP(B103,#REF!,5,0) -> #REF! | B103: SHELL Transmission Oil Spirax S5 CVTX 1L | C103: =_xlfn.XLOOKUP(B103,'Pit Stop (cleaned)'!A:A,'Pit Stop (cleaned)'!B:B,0) -> 0 | D103: =_xlfn.XLOOKUP(B103,'Subur Makmur Ban (Agg)'!$F$1:$F$5,'Subur Makmur Ban (Agg)'!$L$1:$L$5,0) -> 0 | E103: =_xlfn.XLOOKUP(B103,'Bengkel Pegasus (Agg)'!F:F,'Bengkel Pegasus (Agg)'!L:L,0) -> 0 | F103: =_xlfn.XLOOKUP(B103,'Autocraft (agg)'!F:F,'Autocraft (agg)'!L:L,0) -> 0 | G103: =_xlfn.XLOOKUP(B103,'Autones (cleaned)'!A:A,'Autones (cleaned)'!B:B,0) -> 0 | H103: =_xlfn.XLOOKUP(B103,'ADS Prima (cleaned)'!A:A,'ADS Prima (cleaned)'!B:B,0) -> 0 | I103: =_xlfn.XLOOKUP(B103,'Auto Mekanika (cleaned)'!A:A,'Auto Mekanika (cleaned)'!B:B,0) -> 0 | J103: =_xlfn.XLOOKUP(B103,'Bengkel Multi Var (cleaned)'!A:A,'Bengkel Multi Var (cleaned)'!B:B,0) -> 0 | K103: 0 | L103: =_xlfn.XLOOKUP(B103,'Drivewell (cleaned)'!A:A,'Drivewell (cleaned)'!B:B,0) -> 0 | M103: 0 | N103: 0 | O103: 0 | P103: =_xlfn.XLOOKUP(B103,'CV Sun (cleaned)'!A:A,'CV Sun (cleaned)'!B:B,0) -> 0 | Q103: =_xlfn.XLOOKUP(B103,'Sumber Timur (clean)'!F:F,'Sumber Timur (clean)'!L:L,0) -> 0 | R103: =_xlfn.XLOOKUP(B103,'Honda Duren (clean)'!F:F,'Honda Duren (clean)'!L:L,0) -> 0 | S103: 0 | T103: =SUM(C103:S103) -> 0
A104: =VLOOKUP(B104,#REF!,5,0) -> #REF! | B104: MOTUL Diesel Engine Oil TRD SPORT 5W-40 4L | C104: =_xlfn.XLOOKUP(B104,'Pit Stop (cleaned)'!A:A,'Pit Stop (cleaned)'!B:B,0) -> 0 | D104: =_xlfn.XLOOKUP(B104,'Subur Makmur Ban (Agg)'!$F$1:$F$5,'Subur Makmur Ban (Agg)'!$L$1:$L$5,0) -> 0 | E104: =_xlfn.XLOOKUP(B104,'Bengkel Pegasus (Agg)'!F:F,'Bengkel Pegasus (Agg)'!L:L,0) -> 0 | F104: =_xlfn.XLOOKUP(B104,'Autocraft (agg)'!F:F,'Autocraft (agg)'!L:L,0) -> 0 | G104: =_xlfn.XLOOKUP(B104,'Autones (cleaned)'!A:A,'Autones (cleaned)'!B:B,0) -> 0 | H104: =_xlfn.XLOOKUP(B104,'ADS Prima (cleaned)'!A:A,'ADS Prima (cleaned)'!B:B,0) -> 0 | I104: =_xlfn.XLOOKUP(B104,'Auto Mekanika (cleaned)'!A:A,'Auto Mekanika (cleaned)'!B:B,0) -> 0 | J104: =_xlfn.XLOOKUP(B104,'Bengkel Multi Var (cleaned)'!A:A,'Bengkel Multi Var (cleaned)'!B:B,0) -> 0 | K104: 0 | L104: =_xlfn.XLOOKUP(B104,'Drivewell (cleaned)'!A:A,'Drivewell (cleaned)'!B:B,0) -> 0 | M104: 0 | N104: 0 | O104: 0 | P104: =_xlfn.XLOOKUP(B104,'CV Sun (cleaned)'!A:A,'CV Sun (cleaned)'!B:B,0) -> 0 | Q104: =_xlfn.XLOOKUP(B104,'Sumber Timur (clean)'!F:F,'Sumber Timur (clean)'!L:L,0) -> 0 | R104: =_xlfn.XLOOKUP(B104,'Honda Duren (clean)'!F:F,'Honda Duren (clean)'!L:L,0) -> 0 | S104: 0 | T104: =SUM(C104:S104) -> 0
A105: =VLOOKUP(B105,#REF!,5,0) -> #REF! | B105: BOSCH Cabin Filter S 4454 | C105: =_xlfn.XLOOKUP(B105,'Pit Stop (cleaned)'!A:A,'Pit Stop (cleaned)'!B:B,0) -> 0 | D105: =_xlfn.XLOOKUP(B105,'Subur Makmur Ban (Agg)'!$F$1:$F$5,'Subur Makmur Ban (Agg)'!$L$1:$L$5,0) -> 0 | E105: =_xlfn.XLOOKUP(B105,'Bengkel Pegasus (Agg)'!F:F,'Bengkel Pegasus (Agg)'!L:L,0) -> 0 | F105: =_xlfn.XLOOKUP(B105,'Autocraft (agg)'!F:F,'Autocraft (agg)'!L:L,0) -> 0 | G105: =_xlfn.XLOOKUP(B105,'Autones (cleaned)'!A:A,'Autones (cleaned)'!B:B,0) -> 0 | H105: =_xlfn.XLOOKUP(B105,'ADS Prima (cleaned)'!A:A,'ADS Prima (cleaned)'!B:B,0) -> 0 | I105: =_xlfn.XLOOKUP(B105,'Auto Mekanika (cleaned)'!A:A,'Auto Mekanika (cleaned)'!B:B,0) -> 0 | J105: =_xlfn.XLOOKUP(B105,'Bengkel Multi Var (cleaned)'!A:A,'Bengkel Multi Var (cleaned)'!B:B,0) -> 0 | K105: 0 | L105: =_xlfn.XLOOKUP(B105,'Drivewell (cleaned)'!A:A,'Drivewell (cleaned)'!B:B,0) -> 0 | M105: 0 | N105: 0 | O105: 0 | P105: =_xlfn.XLOOKUP(B105,'CV Sun (cleaned)'!A:A,'CV Sun (cleaned)'!B:B,0) -> 0 | Q105: =_xlfn.XLOOKUP(B105,'Sumber Timur (clean)'!F:F,'Sumber Timur (clean)'!L:L,0) -> 0 | R105: =_xlfn.XLOOKUP(B105,'Honda Duren (clean)'!F:F,'Honda Duren (clean)'!L:L,0) -> 0 | S105: 0 | T105: =SUM(C105:S105) -> 0
A106: =VLOOKUP(B106,#REF!,5,0) -> #REF! | B106: DENSO Oil Filter DXE-1007 | C106: =_xlfn.XLOOKUP(B106,'Pit Stop (cleaned)'!A:A,'Pit Stop (cleaned)'!B:B,0) -> 0 | D106: =_xlfn.XLOOKUP(B106,'Subur Makmur Ban (Agg)'!$F$1:$F$5,'Subur Makmur Ban (Agg)'!$L$1:$L$5,0) -> 0 | E106: =_xlfn.XLOOKUP(B106,'Bengkel Pegasus (Agg)'!F:F,'Bengkel Pegasus (Agg)'!L:L,0) -> 0 | F106: =_xlfn.XLOOKUP(B106,'Autocraft (agg)'!F:F,'Autocraft (agg)'!L:L,0) -> 0 | G106: =_xlfn.XLOOKUP(B106,'Autones (cleaned)'!A:A,'Autones (cleaned)'!B:B,0) -> 0 | H106: =_xlfn.XLOOKUP(B106,'ADS Prima (cleaned)'!A:A,'ADS Prima (cleaned)'!B:B,0) -> 0 | I106: =_xlfn.XLOOKUP(B106,'Auto Mekanika (cleaned)'!A:A,'Auto Mekanika (cleaned)'!B:B,0) -> 0 | J106: =_xlfn.XLOOKUP(B106,'Bengkel Multi Var (cleaned)'!A:A,'Bengkel Multi Var (cleaned)'!B:B,0) -> 0 | K106: 0 | L106: =_xlfn.XLOOKUP(B106,'Drivewell (cleaned)'!A:A,'Drivewell (cleaned)'!B:B,0) -> 0 | M106: 0 | N106: 0 | O106: 0 | P106: =_xlfn.XLOOKUP(B106,'CV Sun (cleaned)'!A:A,'CV Sun (cleaned)'!B:B,0) -> 0 | Q106: =_xlfn.XLOOKUP(B106,'Sumber Timur (clean)'!F:F,'Sumber Timur (clean)'!L:L,0) -> 0 | R106: =_xlfn.XLOOKUP(B106,'Honda Duren (clean)'!F:F,'Honda Duren (clean)'!L:L,0) -> 0 | S106: 0 | T106: =SUM(C106:S106) -> 0
A107: =VLOOKUP(B107,#REF!,5,0) -> #REF! | B107: BOSCH Cabin Filter S 4061 | C107: =_xlfn.XLOOKUP(B107,'Pit Stop (cleaned)'!A:A,'Pit Stop (cleaned)'!B:B,0) -> 0 | D107: =_xlfn.XLOOKUP(B107,'Subur Makmur Ban (Agg)'!$F$1:$F$5,'Subur Makmur Ban (Agg)'!$L$1:$L$5,0) -> 0 | E107: =_xlfn.XLOOKUP(B107,'Bengkel Pegasus (Agg)'!F:F,'Bengkel Pegasus (Agg)'!L:L,0) -> 0 | F107: =_xlfn.XLOOKUP(B107,'Autocraft (agg)'!F:F,'Autocraft (agg)'!L:L,0) -> 0 | G107: =_xlfn.XLOOKUP(B107,'Autones (cleaned)'!A:A,'Autones (cleaned)'!B:B,0) -> 0 | H107: =_xlfn.XLOOKUP(B107,'ADS Prima (cleaned)'!A:A,'ADS Prima (cleaned)'!B:B,0) -> 0 | I107: =_xlfn.XLOOKUP(B107,'Auto Mekanika (cleaned)'!A:A,'Auto Mekanika (cleaned)'!B:B,0) -> 0 | J107: =_xlfn.XLOOKUP(B107,'Bengkel Multi Var (cleaned)'!A:A,'Bengkel Multi Var (cleaned)'!B:B,0) -> 0 | K107: 0 | L107: =_xlfn.XLOOKUP(B107,'Drivewell (cleaned)'!A:A,'Drivewell (cleaned)'!B:B,0) -> 0 | M107: 0 | N107: 0 | O107: 0 | P107: =_xlfn.XLOOKUP(B107,'CV Sun (cleaned)'!A:A,'CV Sun (cleaned)'!B:B,0) -> 0 | Q107: =_xlfn.XLOOKUP(B107,'Sumber Timur (clean)'!F:F,'Sumber Timur (clean)'!L:L,0) -> 0 | R107: =_xlfn.XLOOKUP(B107,'Honda Duren (clean)'!F:F,'Honda Duren (clean)'!L:L,0) -> 0 | S107: 0 | T107: =SUM(C107:S107) -> 0
A108: =VLOOKUP(B108,#REF!,5,0) -> #REF! | B108: BOSCH Cabin Filter S 4047 | C108: =_xlfn.XLOOKUP(B108,'Pit Stop (cleaned)'!A:A,'Pit Stop (cleaned)'!B:B,0) -> 0 | D108: =_xlfn.XLOOKUP(B108,'Subur Makmur Ban (Agg)'!$F$1:$F$5,'Subur Makmur Ban (Agg)'!$L$1:$L$5,0) -> 0 | E108: =_xlfn.XLOOKUP(B108,'Bengkel Pegasus (Agg)'!F:F,'Bengkel Pegasus (Agg)'!L:L,0) -> 0 | F108: =_xlfn.XLOOKUP(B108,'Autocraft (agg)'!F:F,'Autocraft (agg)'!L:L,0) -> 0 | G108: =_xlfn.XLOOKUP(B108,'Autones (cleaned)'!A:A,'Autones (cleaned)'!B:B,0) -> 0 | H108: =_xlfn.XLOOKUP(B108,'ADS Prima (cleaned)'!A:A,'ADS Prima (cleaned)'!B:B,0) -> 0 | I108: =_xlfn.XLOOKUP(B108,'Auto Mekanika (cleaned)'!A:A,'Auto Mekanika (cleaned)'!B:B,0) -> 0 | J108: =_xlfn.XLOOKUP(B108,'Bengkel Multi Var (cleaned)'!A:A,'Bengkel Multi Var (cleaned)'!B:B,0) -> 0 | K108: 0 | L108: =_xlfn.XLOOKUP(B108,'Drivewell (cleaned)'!A:A,'Drivewell (cleaned)'!B:B,0) -> 0 | M108: 0 | N108: 0 | O108: 0 | P108: =_xlfn.XLOOKUP(B108,'CV Sun (cleaned)'!A:A,'CV Sun (cleaned)'!B:B,0) -> 0 | Q108: =_xlfn.XLOOKUP(B108,'Sumber Timur (clean)'!F:F,'Sumber Timur (clean)'!L:L,0) -> 0 | R108: =_xlfn.XLOOKUP(B108,'Honda Duren (clean)'!F:F,'Honda Duren (clean)'!L:L,0) -> 0 | S108: 0 | T108: =SUM(C108:S108) -> 0
... A113: =VLOOKUP(B113,#REF!,5,0) -> #REF! | B113: DENSO Cabin Filter 145520-3700 | C113: =_xlfn.XLOOKUP(B113,'Pit Stop (cleaned)'!A:A,'Pit Stop (cleaned)'!B:B,0) -> 0 | D113: =_xlfn.XLOOKUP(B113,'Subur Makmur Ban (Agg)'!$F$1:$F$5,'Subur Makmur Ban (Agg)'!$L$1:$L$5,0) -> 0 | E113: =_xlfn.XLOOKUP(B113,'Bengkel Pegasus (Agg)'!F:F,'Bengkel Pegasus (Agg)'!L:L,0) -> 0 | F113: =_xlfn.XLOOKUP(B113,'Autocraft (agg)'!F:F,'Autocraft (agg)'!L:L,0) -> 0 | G113: =_xlfn.XLOOKUP(B113,'Autones (cleaned)'!A:A,'Autones (cleaned)'!B:B,0) -> 0 | H113: =_xlfn.XLOOKUP(B113,'ADS Prima (cleaned)'!A:A,'ADS Prima (cleaned)'!B:B,0) -> 0 | I113: =_xlfn.XLOOKUP(B113,'Auto Mekanika (cleaned)'!A:A,'Auto Mekanika (cleaned)'!B:B,0) -> 0 | J113: =_xlfn.XLOOKUP(B113,'Bengkel Multi Var (cleaned)'!A:A,'Bengkel Multi Var (cleaned)'!B:B,0) -> 0 | K113: 0 | L113: =_xlfn.XLOOKUP(B113,'Drivewell (cleaned)'!A:A,'Drivewell (cleaned)'!B:B,0) -> 0 | M113: 0 | N113: 0 | O113: 0 | P113: =_xlfn.XLOOKUP(B113,'CV Sun (cleaned)'!A:A,'CV Sun (cleaned)'!B:B,0) -> 0 | Q113: =_xlfn.XLOOKUP(B113,'Sumber Timur (clean)'!F:F,'Sumber Timur (clean)'!L:L,0) -> 0 | R113: =_xlfn.XLOOKUP(B113,'Honda Duren (clean)'!F:F,'Honda Duren (clean)'!L:L,0) -> 0 | S113: 0 | T113: =SUM(C113:S113) -> 0
A114: =VLOOKUP(B114,#REF!,5,0) -> #REF! | B114: BOSCH Oil Filter O 1001 | C114: =_xlfn.XLOOKUP(B114,'Pit Stop (cleaned)'!A:A,'Pit Stop (cleaned)'!B:B,0) -> 50 | D114: =_xlfn.XLOOKUP(B114,'Subur Makmur Ban (Agg)'!$F$1:$F$5,'Subur Makmur Ban (Agg)'!$L$1:$L$5,0) -> 0 | E114: =_xlfn.XLOOKUP(B114,'Bengkel Pegasus (Agg)'!F:F,'Bengkel Pegasus (Agg)'!L:L,0) -> 0 | F114: =_xlfn.XLOOKUP(B114,'Autocraft (agg)'!F:F,'Autocraft (agg)'!L:L,0) -> 0 | G114: =_xlfn.XLOOKUP(B114,'Autones (cleaned)'!A:A,'Autones (cleaned)'!B:B,0) -> 0 | H114: =_xlfn.XLOOKUP(B114,'ADS Prima (cleaned)'!A:A,'ADS Prima (cleaned)'!B:B,0) -> 0 | I114: =_xlfn.XLOOKUP(B114,'Auto Mekanika (cleaned)'!A:A,'Auto Mekanika (cleaned)'!B:B,0) -> 0 | J114: =_xlfn.XLOOKUP(B114,'Bengkel Multi Var (cleaned)'!A:A,'Bengkel Multi Var (cleaned)'!B:B,0) -> 20 | K114: =_xlfn.XLOOKUP(B114,'[2]EURO GALLARIA'!F:F,'[2]EURO GALLARIA'!L:L,0) -> 0 | L114: =_xlfn.XLOOKUP(B114,'Drivewell (cleaned)'!A:A,'Drivewell (cleaned)'!B:B,0) -> 0 | M114: =_xlfn.XLOOKUP(B114,'[2]Mersi (CLEAN)'!D:D,'[2]Mersi (CLEAN)'!E:E,0) -> 0 | N114: 0 | O114: 0 | P114: =_xlfn.XLOOKUP(B114,'CV Sun (cleaned)'!A:A,'CV Sun (cleaned)'!B:B,0) -> 0 | Q114: =_xlfn.XLOOKUP(B114,'Sumber Timur (clean)'!F:F,'Sumber Timur (clean)'!L:L,0) -> 20 | R114: =_xlfn.XLOOKUP(B114,'Honda Duren (clean)'!F:F,'Honda Duren (clean)'!L:L,0) -> 0 | S114: =_xlfn.XLOOKUP(B114,'[2]LAVANDER CLEAN'!A:A,'[2]LAVANDER CLEAN'!B:B,0) -> 15 | T114: =SUM(C114:S114) -> 105 | U114: 36400 | V114: =IF(T114*U114=0,"",T114*U114) -> 3822000 | W114: 0986AF1001
A115: =VLOOKUP(B115,#REF!,5,0) -> #REF! | B115: BOSCH Oil Filter O 1019 | C115: =_xlfn.XLOOKUP(B115,'Pit Stop (cleaned)'!A:A,'Pit Stop (cleaned)'!B:B,0) -> 0 | D115: =_xlfn.XLOOKUP(B115,'Subur Makmur Ban (Agg)'!$F$1:$F$5,'Subur Makmur Ban (Agg)'!$L$1:$L$5,0) -> 0 | E115: =_xlfn.XLOOKUP(B115,'Bengkel Pegasus (Agg)'!F:F,'Bengkel Pegasus (Agg)'!L:L,0) -> 0 | F115: =_xlfn.XLOOKUP(B115,'Autocraft (agg)'!F:F,'Autocraft (agg)'!L:L,0) -> 0 | G115: =_xlfn.XLOOKUP(B115,'Autones (cleaned)'!A:A,'Autones (cleaned)'!B:B,0) -> 0 | H115: =_xlfn.XLOOKUP(B115,'ADS Prima (cleaned)'!A:A,'ADS Prima (cleaned)'!B:B,0) -> 60 | I115: =_xlfn.XLOOKUP(B115,'Auto Mekanika (cleaned)'!A:A,'Auto Mekanika (cleaned)'!B:B,0) -> 0 | J115: =_xlfn.XLOOKUP(B115,'Bengkel Multi Var (cleaned)'!A:A,'Bengkel Multi Var (cleaned)'!B:B,0) -> 40 | K115: =_xlfn.XLOOKUP(B115,'[2]EURO GALLARIA'!F:F,'[2]EURO GALLARIA'!L:L,0) -> 0 | L115: =_xlfn.XLOOKUP(B115,'Drivewell (cleaned)'!A:A,'Drivewell (cleaned)'!B:B,0) -> 0 | M115: =_xlfn.XLOOKUP(B115,'[2]Mersi (CLEAN)'!D:D,'[2]Mersi (CLEAN)'!E:E,0) -> 0 | N115: 0 | O115: 0 | P115: =_xlfn.XLOOKUP(B115,'CV Sun (cleaned)'!A:A,'CV Sun (cleaned)'!B:B,0) -> 0 | Q115: =_xlfn.XLOOKUP(B115,'Sumber Timur (clean)'!F:F,'Sumber Timur (clean)'!L:L,0) -> 0 | R115: =_xlfn.XLOOKUP(B115,'Honda Duren (clean)'!F:F,'Honda Duren (clean)'!L:L,0) -> 0 | S115: =_xlfn.XLOOKUP(B115,'[2]LAVANDER CLEAN'!A:A,'[2]LAVANDER CLEAN'!B:B,0) -> 20 | T115: =SUM(C115:S115) -> 120 | U115: 61750 | V115: =IF(T115*U115=0,"",T115*U115) -> 7410000 | W115: 0986AF1019
A116: =VLOOKUP(B116,#REF!,5,0) -> #REF! | B116: BOSCH Oil Filter O 1507 | C116: =_xlfn.XLOOKUP(B116,'Pit Stop (cleaned)'!A:A,'Pit Stop (cleaned)'!B:B,0) -> 0 | D116: =_xlfn.XLOOKUP(B116,'Subur Makmur Ban (Agg)'!$F$1:$F$5,'Subur Makmur Ban (Agg)'!$L$1:$L$5,0) -> 0 | E116: =_xlfn.XLOOKUP(B116,'Bengkel Pegasus (Agg)'!F:F,'Bengkel Pegasus (Agg)'!L:L,0) -> 0 | F116: =_xlfn.XLOOKUP(B116,'Autocraft (agg)'!F:F,'Autocraft (agg)'!L:L,0) -> 0 | G116: =_xlfn.XLOOKUP(B116,'Autones (cleaned)'!A:A,'Autones (cleaned)'!B:B,0) -> 0 | H116: =_xlfn.XLOOKUP(B116,'ADS Prima (cleaned)'!A:A,'ADS Prima (cleaned)'!B:B,0) -> 0 | I116: =_xlfn.XLOOKUP(B116,'Auto Mekanika (cleaned)'!A:A,'Auto Mekanika (cleaned)'!B:B,0) -> 0 | J116: =_xlfn.XLOOKUP(B116,'Bengkel Multi Var (cleaned)'!A:A,'Bengkel Multi Var (cleaned)'!B:B,0) -> 0 | K116: 0 | L116: =_xlfn.XLOOKUP(B116,'Drivewell (cleaned)'!A:A,'Drivewell (cleaned)'!B:B,0) -> 0 | M116: 0 | N116: 0 | O116: 0 | P116: =_xlfn.XLOOKUP(B116,'CV Sun (cleaned)'!A:A,'CV Sun (cleaned)'!B:B,0) -> 0 | Q116: =_xlfn.XLOOKUP(B116,'Sumber Timur (clean)'!F:F,'Sumber Timur (clean)'!L:L,0) -> 0 | R116: =_xlfn.XLOOKUP(B116,'Honda Duren (clean)'!F:F,'Honda Duren (clean)'!L:L,0) -> 0 | S116: 0 | T116: =SUM(C116:S116) -> 0
A117: =VLOOKUP(B117,#REF!,5,0) -> #REF! | B117: BOSCH Air Filter A 2666 | C117: =_xlfn.XLOOKUP(B117,'Pit Stop (cleaned)'!A:A,'Pit Stop (cleaned)'!B:B,0) -> 0 | D117: =_xlfn.XLOOKUP(B117,'Subur Makmur Ban (Agg)'!$F$1:$F$5,'Subur Makmur Ban (Agg)'!$L$1:$L$5,0) -> 0 | E117: =_xlfn.XLOOKUP(B117,'Bengkel Pegasus (Agg)'!F:F,'Bengkel Pegasus (Agg)'!L:L,0) -> 0 | F117: =_xlfn.XLOOKUP(B117,'Autocraft (agg)'!F:F,'Autocraft (agg)'!L:L,0) -> 0 | G117: =_xlfn.XLOOKUP(B117,'Autones (cleaned)'!A:A,'Autones (cleaned)'!B:B,0) -> 0 | H117: =_xlfn.XLOOKUP(B117,'ADS Prima (cleaned)'!A:A,'ADS Prima (cleaned)'!B:B,0) -> 0 | I117: =_xlfn.XLOOKUP(B117,'Auto Mekanika (cleaned)'!A:A,'Auto Mekanika (cleaned)'!B:B,0) -> 0 | J117: =_xlfn.XLOOKUP(B117,'Bengkel Multi Var (cleaned)'!A:A,'Bengkel Multi Var (cleaned)'!B:B,0) -> 0 | K117: 0 | L117: =_xlfn.XLOOKUP(B117,'Drivewell (cleaned)'!A:A,'Drivewell (cleaned)'!B:B,0) -> 0 | M117: 0 | N117: 0 | O117: 0 | P117: =_xlfn.XLOOKUP(B117,'CV Sun (cleaned)'!A:A,'CV Sun (cleaned)'!B:B,0) -> 0 | Q117: =_xlfn.XLOOKUP(B117,'Sumber Timur (clean)'!F:F,'Sumber Timur (clean)'!L:L,0) -> 0 | R117: =_xlfn.XLOOKUP(B117,'Honda Duren (clean)'!F:F,'Honda Duren (clean)'!L:L,0) -> 0 | S117: 0 | T117: =SUM(C117:S117) -> 0
A118: =VLOOKUP(B118,#REF!,5,0) -> #REF! | B118: BOSCH Oil Filter O 1042 | C118: =_xlfn.XLOOKUP(B118,'Pit Stop (cleaned)'!A:A,'Pit Stop (cleaned)'!B:B,0) -> 80 | D118: =_xlfn.XLOOKUP(B118,'Subur Makmur Ban (Agg)'!$F$1:$F$5,'Subur Makmur Ban (Agg)'!$L$1:$L$5,0) -> 0 | E118: =_xlfn.XLOOKUP(B118,'Bengkel Pegasus (Agg)'!F:F,'Bengkel Pegasus (Agg)'!L:L,0) -> 0 | F118: =_xlfn.XLOOKUP(B118,'Autocraft (agg)'!F:F,'Autocraft (agg)'!L:L,0) -> 0 | G118: =_xlfn.XLOOKUP(B118,'Autones (cleaned)'!A:A,'Autones (cleaned)'!B:B,0) -> 0 | H118: =_xlfn.XLOOKUP(B118,'ADS Prima (cleaned)'!A:A,'ADS Prima (cleaned)'!B:B,0) -> 100 | I118: =_xlfn.XLOOKUP(B118,'Auto Mekanika (cleaned)'!A:A,'Auto Mekanika (cleaned)'!B:B,0) -> 0 | J118: =_xlfn.XLOOKUP(B118,'Bengkel Multi Var (cleaned)'!A:A,'Bengkel Multi Var (cleaned)'!B:B,0) -> 40 | K118: =_xlfn.XLOOKUP(B118,'[2]EURO GALLARIA'!F:F,'[2]EURO GALLARIA'!L:L,0) -> 0 | L118: =_xlfn.XLOOKUP(B118,'Drivewell (cleaned)'!A:A,'Drivewell (cleaned)'!B:B,0) -> 0 | M118: =_xlfn.XLOOKUP(B118,'[2]Mersi (CLEAN)'!D:D,'[2]Mersi (CLEAN)'!E:E,0) -> 0 | N118: 0 | O118: 0 | P118: =_xlfn.XLOOKUP(B118,'CV Sun (cleaned)'!A:A,'CV Sun (cleaned)'!B:B,0) -> 0 | Q118: =_xlfn.XLOOKUP(B118,'Sumber Timur (clean)'!F:F,'Sumber Timur (clean)'!L:L,0) -> 0 | R118: =_xlfn.XLOOKUP(B118,'Honda Duren (clean)'!F:F,'Honda Duren (clean)'!L:L,0) -> 0 | S118: =_xlfn.XLOOKUP(B118,'[2]LAVANDER CLEAN'!A:A,'[2]LAVANDER CLEAN'!B:B,0) -> 25 | T118: =SUM(C118:S118) -> 245 | U118: 32500 | V118: =IF(T118*U118=0,"",T118*U118) -> 7962500 | W118: 0986AF1042
A119: =VLOOKUP(B119,#REF!,5,0) -> #REF! | B119: CASTROL Engine Oil MAGNATEC 10W-40 1L | C119: =_xlfn.XLOOKUP(B119,'Pit Stop (cleaned)'!A:A,'Pit Stop (cleaned)'!B:B,0) -> 0 | D119: =_xlfn.XLOOKUP(B119,'Subur Makmur Ban (Agg)'!$F$1:$F$5,'Subur Makmur Ban (Agg)'!$L$1:$L$5,0) -> 0 | E119: =_xlfn.XLOOKUP(B119,'Bengkel Pegasus (Agg)'!F:F,'Bengkel Pegasus (Agg)'!L:L,0) -> 0 | F119: =_xlfn.XLOOKUP(B119,'Autocraft (agg)'!F:F,'Autocraft (agg)'!L:L,0) -> 0 | G119: =_xlfn.XLOOKUP(B119,'Autones (cleaned)'!A:A,'Autones (cleaned)'!B:B,0) -> 0 | H119: =_xlfn.XLOOKUP(B119,'ADS Prima (cleaned)'!A:A,'ADS Prima (cleaned)'!B:B,0) -> 0 | I119: =_xlfn.XLOOKUP(B119,'Auto Mekanika (cleaned)'!A:A,'Auto Mekanika (cleaned)'!B:B,0) -> 0 | J119: =_xlfn.XLOOKUP(B119,'Bengkel Multi Var (cleaned)'!A:A,'Bengkel Multi Var (cleaned)'!B:B,0) -> 0 | K119: 0 | L119: =_xlfn.XLOOKUP(B119,'Drivewell (cleaned)'!A:A,'Drivewell (cleaned)'!B:B,0) -> 0 | M119: 0 | N119: 0 | O119: 0 | P119: =_xlfn.XLOOKUP(B119,'CV Sun (cleaned)'!A:A,'CV Sun (cleaned)'!B:B,0) -> 0 | Q119: =_xlfn.XLOOKUP(B119,'Sumber Timur (clean)'!F:F,'Sumber Timur (clean)'!L:L,0) -> 0 | R119: =_xlfn.XLOOKUP(B119,'Honda Duren (clean)'!F:F,'Honda Duren (clean)'!L:L,0) -> 0 | S119: 0 | T119: =SUM(C119:S119) -> 0
A120: =VLOOKUP(B120,#REF!,5,0) -> #REF! | B120: BOSCH Fuel Filter D 6100 | C120: =_xlfn.XLOOKUP(B120,'Pit Stop (cleaned)'!A:A,'Pit Stop (cleaned)'!B:B,0) -> 0 | D120: =_xlfn.XLOOKUP(B120,'Subur Makmur Ban (Agg)'!$F$1:$F$5,'Subur Makmur Ban (Agg)'!$L$1:$L$5,0) -> 0 | E120: =_xlfn.XLOOKUP(B120,'Bengkel Pegasus (Agg)'!F:F,'Bengkel Pegasus (Agg)'!L:L,0) -> 0 | F120: =_xlfn.XLOOKUP(B120,'Autocraft (agg)'!F:F,'Autocraft (agg)'!L:L,0) -> 0 | G120: =_xlfn.XLOOKUP(B120,'Autones (cleaned)'!A:A,'Autones (cleaned)'!B:B,0) -> 0 | H120: 40 | I120: =_xlfn.XLOOKUP(B120,'Auto Mekanika (cleaned)'!A:A,'Auto Mekanika (cleaned)'!B:B,0) -> 0 | J120: =_xlfn.XLOOKUP(B120,'Bengkel Multi Var (cleaned)'!A:A,'Bengkel Multi Var (cleaned)'!B:B,0) -> 0 | K120: =_xlfn.XLOOKUP(B120,'[2]EURO GALLARIA'!F:F,'[2]EURO GALLARIA'!L:L,0) -> 0 | L120: =_xlfn.XLOOKUP(B120,'Drivewell (cleaned)'!A:A,'Drivewell (cleaned)'!B:B,0) -> 0 | M120: =_xlfn.XLOOKUP(B120,'[2]Mersi (CLEAN)'!D:D,'[2]Mersi (CLEAN)'!E:E,0) -> 0 | N120: 0 | O120: 0 | P120: =_xlfn.XLOOKUP(B120,'CV Sun (cleaned)'!A:A,'CV Sun (cleaned)'!B:B,0) -> 0 | Q120: =_xlfn.XLOOKUP(B120,'Sumber Timur (clean)'!F:F,'Sumber Timur (clean)'!L:L,0) -> 0 | R120: =_xlfn.XLOOKUP(B120,'Honda Duren (clean)'!F:F,'Honda Duren (clean)'!L:L,0) -> 0 | S120: =_xlfn.XLOOKUP(B120,'[2]LAVANDER CLEAN'!A:A,'[2]LAVANDER CLEAN'!B:B,0) -> 0 | T120: =SUM(C120:S120) -> 40 | U120: 58500 | V120: =IF(T120*U120=0,"",T120*U120) -> 2340000 | W120: 0986AF6100
A121: =VLOOKUP(B121,#REF!,5,0) -> #REF! | B121: SHELL Engine Oil HELIX CITY 0W-20 1L | C121: =_xlfn.XLOOKUP(B121,'Pit Stop (cleaned)'!A:A,'Pit Stop (cleaned)'!B:B,0) -> 0 | D121: =_xlfn.XLOOKUP(B121,'Subur Makmur Ban (Agg)'!$F$1:$F$5,'Subur Makmur Ban (Agg)'!$L$1:$L$5,0) -> 0 | E121: =_xlfn.XLOOKUP(B121,'Bengkel Pegasus (Agg)'!F:F,'Bengkel Pegasus (Agg)'!L:L,0) -> 0 | F121: =_xlfn.XLOOKUP(B121,'Autocraft (agg)'!F:F,'Autocraft (agg)'!L:L,0) -> 0 | G121: =_xlfn.XLOOKUP(B121,'Autones (cleaned)'!A:A,'Autones (cleaned)'!B:B,0) -> 0 | H121: =_xlfn.XLOOKUP(B121,'ADS Prima (cleaned)'!A:A,'ADS Prima (cleaned)'!B:B,0) -> 0 | I121: =_xlfn.XLOOKUP(B121,'Auto Mekanika (cleaned)'!A:A,'Auto Mekanika (cleaned)'!B:B,0) -> 0 | J121: =_xlfn.XLOOKUP(B121,'Bengkel Multi Var (cleaned)'!A:A,'Bengkel Multi Var (cleaned)'!B:B,0) -> 0 | K121: 0 | L121: =_xlfn.XLOOKUP(B121,'Drivewell (cleaned)'!A:A,'Drivewell (cleaned)'!B:B,0) -> 0 | M121: 0 | N121: 0 | O121: 0 | P121: =_xlfn.XLOOKUP(B121,'CV Sun (cleaned)'!A:A,'CV Sun (cleaned)'!B:B,0) -> 0 | Q121: =_xlfn.XLOOKUP(B121,'Sumber Timur (clean)'!F:F,'Sumber Timur (clean)'!L:L,0) -> 0 | R121: =_xlfn.XLOOKUP(B121,'Honda Duren (clean)'!F:F,'Honda Duren (clean)'!L:L,0) -> 0 | S121: 0 | T121: =SUM(C121:S121) -> 0
A122: =VLOOKUP(B122,#REF!,5,0) -> #REF! | B122: DENSO Cabin Filter 145520-5850 | C122: =_xlfn.XLOOKUP(B122,'Pit Stop (cleaned)'!A:A,'Pit Stop (cleaned)'!B:B,0) -> 0 | D122: =_xlfn.XLOOKUP(B122,'Subur Makmur Ban (Agg)'!$F$1:$F$5,'Subur Makmur Ban (Agg)'!$L$1:$L$5,0) -> 0 | E122: =_xlfn.XLOOKUP(B122,'Bengkel Pegasus (Agg)'!F:F,'Bengkel Pegasus (Agg)'!L:L,0) -> 0 | F122: =_xlfn.XLOOKUP(B122,'Autocraft (agg)'!F:F,'Autocraft (agg)'!L:L,0) -> 0 | G122: =_xlfn.XLOOKUP(B122,'Autones (cleaned)'!A:A,'Autones (cleaned)'!B:B,0) -> 0 | H122: =_xlfn.XLOOKUP(B122,'ADS Prima (cleaned)'!A:A,'ADS Prima (cleaned)'!B:B,0) -> 0 | I122: =_xlfn.XLOOKUP(B122,'Auto Mekanika (cleaned)'!A:A,'Auto Mekanika (cleaned)'!B:B,0) -> 0 | J122: =_xlfn.XLOOKUP(B122,'Bengkel Multi Var (cleaned)'!A:A,'Bengkel Multi Var (cleaned)'!B:B,0) -> 0 | K122: 0 | L122: =_xlfn.XLOOKUP(B122,'Drivewell (cleaned)'!A:A,'Drivewell (cleaned)'!B:B,0) -> 0 | M122: 0 | N122: 0 | O122: 0 | P122: =_xlfn.XLOOKUP(B122,'CV Sun (cleaned)'!A:A,'CV Sun (cleaned)'!B:B,0) -> 0 | Q122: =_xlfn.XLOOKUP(B122,'Sumber Timur (clean)'!F:F,'Sumber Timur (clean)'!L:L,0) -> 0 | R122: =_xlfn.XLOOKUP(B122,'Honda Duren (clean)'!F:F,'Honda Duren (clean)'!L:L,0) -> 0 | S122: 0 | T122: =SUM(C122:S122) -> 0
A123: =VLOOKUP(B123,#REF!,5,0) -> #REF! | B123: DENSO Cabin Filter 145520-5840 | C123: =_xlfn.XLOOKUP(B123,'Pit Stop (cleaned)'!A:A,'Pit Stop (cleaned)'!B:B,0) -> 0 | D123: =_xlfn.XLOOKUP(B123,'Subur Makmur Ban (Agg)'!$F$1:$F$5,'Subur Makmur Ban (Agg)'!$L$1:$L$5,0) -> 0 | E123: =_xlfn.XLOOKUP(B123,'Bengkel Pegasus (Agg)'!F:F,'Bengkel Pegasus (Agg)'!L:L,0) -> 0 | F123: =_xlfn.XLOOKUP(B123,'Autocraft (agg)'!F:F,'Autocraft (agg)'!L:L,0) -> 0 | G123: =_xlfn.XLOOKUP(B123,'Autones (cleaned)'!A:A,'Autones (cleaned)'!B:B,0) -> 0 | H123: =_xlfn.XLOOKUP(B123,'ADS Prima (cleaned)'!A:A,'ADS Prima (cleaned)'!B:B,0) -> 0 | I123: =_xlfn.XLOOKUP(B123,'Auto Mekanika (cleaned)'!A:A,'Auto Mekanika (cleaned)'!B:B,0) -> 0 | J123: =_xlfn.XLOOKUP(B123,'Bengkel Multi Var (cleaned)'!A:A,'Bengkel Multi Var (cleaned)'!B:B,0) -> 0 | K123: 0 | L123: =_xlfn.XLOOKUP(B123,'Drivewell (cleaned)'!A:A,'Drivewell (cleaned)'!B:B,0) -> 0 | M123: 0 | N123: 0 | O123: 0 | P123: =_xlfn.XLOOKUP(B123,'CV Sun (cleaned)'!A:A,'CV Sun (cleaned)'!B:B,0) -> 0 | Q123: =_xlfn.XLOOKUP(B123,'Sumber Timur (clean)'!F:F,'Sumber Timur (clean)'!L:L,0) -> 0 | R123: =_xlfn.XLOOKUP(B123,'Honda Duren (clean)'!F:F,'Honda Duren (clean)'!L:L,0) -> 0 | S123: 0 | T123: =SUM(C123:S123) -> 0
A124: =VLOOKUP(B124,#REF!,5,0) -> #REF! | B124: DENSO Air Filter DXA-1009 | C124: =_xlfn.XLOOKUP(B124,'Pit Stop (cleaned)'!A:A,'Pit Stop (cleaned)'!B:B,0) -> 0 | D124: =_xlfn.XLOOKUP(B124,'Subur Makmur Ban (Agg)'!$F$1:$F$5,'Subur Makmur Ban (Agg)'!$L$1:$L$5,0) -> 0 | E124: =_xlfn.XLOOKUP(B124,'Bengkel Pegasus (Agg)'!F:F,'Bengkel Pegasus (Agg)'!L:L,0) -> 0 | F124: =_xlfn.XLOOKUP(B124,'Autocraft (agg)'!F:F,'Autocraft (agg)'!L:L,0) -> 0 | G124: =_xlfn.XLOOKUP(B124,'Autones (cleaned)'!A:A,'Autones (cleaned)'!B:B,0) -> 0 | H124: =_xlfn.XLOOKUP(B124,'ADS Prima (cleaned)'!A:A,'ADS Prima (cleaned)'!B:B,0) -> 0 | I124: =_xlfn.XLOOKUP(B124,'Auto Mekanika (cleaned)'!A:A,'Auto Mekanika (cleaned)'!B:B,0) -> 0 | J124: =_xlfn.XLOOKUP(B124,'Bengkel Multi Var (cleaned)'!A:A,'Bengkel Multi Var (cleaned)'!B:B,0) -> 0 | K124: 0 | L124: =_xlfn.XLOOKUP(B124,'Drivewell (cleaned)'!A:A,'Drivewell (cleaned)'!B:B,0) -> 0 | M124: 0 | N124: 0 | O124: 0 | P124: =_xlfn.XLOOKUP(B124,'CV Sun (cleaned)'!A:A,'CV Sun (cleaned)'!B:B,0) -> 0 | Q124: =_xlfn.XLOOKUP(B124,'Sumber Timur (clean)'!F:F,'Sumber Timur (clean)'!L:L,0) -> 0 | R124: =_xlfn.XLOOKUP(B124,'Honda Duren (clean)'!F:F,'Honda Duren (clean)'!L:L,0) -> 0 | S124: 0 | T124: =SUM(C124:S124) -> 0
...

Sheet FRANCHISEE PER MONTH
F6: SALES DATE EXCLUDE TAX
G7: NOV | H7: DEC | I7: JAN | J7: FEB | K7: Total
F8: Pit Stop 3 | G8: =SUMIF('Pit Stop (Agregated)'!$A:$A,G$7,'Pit Stop (Agregated)'!$AA:$AA) -> 23002681 | H8: =SUMIF('Pit Stop (Agregated)'!$A:$A,H$7,'Pit Stop (Agregated)'!$AA:$AA) -> 4520100 | I8: =SUMIF('Pit Stop (Agregated)'!$A:$A,I$7,'Pit Stop (Agregated)'!$AA:$AA) -> 5970536 | J8: =SUMIF('Pit Stop (Agregated)'!$A:$A,J$7,'Pit Stop (Agregated)'!$AA:$AA) -> 0 | K8: =SUM(G8:J8) -> 33493317
F9: Subur Makmur Ban | G9: =SUMIF('Subur Makmur Ban (Agg)'!$A:$A,G$7,'Subur Makmur Ban (Agg)'!$AA:$AA) -> 0 | H9: =SUMIF('Subur Makmur Ban (Agg)'!$A:$A,H$7,'Subur Makmur Ban (Agg)'!$AA:$AA) -> 0 | I9: =SUMIF('Subur Makmur Ban (Agg)'!$A:$A,I$7,'Subur Makmur Ban (Agg)'!$AA:$AA) -> 5648170 | J9: =SUMIF('Subur Makmur Ban (Agg)'!$A:$A,J$7,'Subur Makmur Ban (Agg)'!$AA:$AA) -> 0 | K9: =SUM(G9:J9) -> 5648170
F10: Bengkel Pegasus | G10: =SUMIF('Bengkel Pegasus (Agg)'!$A:$A,G$7,'Bengkel Pegasus (Agg)'!$AA:$AA) -> 0 | H10: =SUMIF('Bengkel Pegasus (Agg)'!$A:$A,H$7,'Bengkel Pegasus (Agg)'!$AA:$AA) -> 0 | I10: =SUMIF('Bengkel Pegasus (Agg)'!$A:$A,I$7,'Bengkel Pegasus (Agg)'!$AA:$AA) -> 1337960 | J10: =SUMIF('Bengkel Pegasus (Agg)'!$A:$A,J$7,'Bengkel Pegasus (Agg)'!$AA:$AA) -> 14226024 | K10: =SUM(G10:J10) -> 15563984
F11: Autocraft | G11: =SUMIF('Autocraft (agg)'!$A:$A,G$7,'Autocraft (agg)'!$AA:$AA) -> 0 | H11: =SUMIF('Autocraft (agg)'!$A:$A,H$7,'Autocraft (agg)'!$AA:$AA) -> 2919100 | I11: =SUMIF('Autocraft (agg)'!$A:$A,I$7,'Autocraft (agg)'!$AA:$AA) -> 0 | J11: =SUMIF('Autocraft (agg)'!$A:$A,J$7,'Autocraft (agg)'!$AA:$AA) -> 0 | K11: =SUM(G11:J11) -> 2919100
F12: Autones | G12: =SUMIF('Autones (agg)'!$A:$A,G$7,'Autones (agg)'!$AA:$AA) -> 17372940 | H12: =SUMIF('Autones (agg)'!$A:$A,H$7,'Autones (agg)'!$AA:$AA) -> 7508003.8 | I12: =SUMIF('Autones (agg)'!$A:$A,I$7,'Autones (agg)'!$AA:$AA) -> 5215847 | J12: =SUMIF('Autones (agg)'!$A:$A,J$7,'Autones (agg)'!$AA:$AA) -> 0 | K12: =SUM(G12:J12) -> 30096791
F13: ADS Prima | G13: =SUMIF('ADS Prima (agg)'!$A:$A,G$7,'ADS Prima (agg)'!$AA:$AA) -> 49304337 | H13: =SUMIF('ADS Prima (agg)'!$A:$A,H$7,'ADS Prima (agg)'!$AA:$AA) -> 0 | I13: =SUMIF('ADS Prima (agg)'!$A:$A,I$7,'ADS Prima (agg)'!$AA:$AA) -> 3438500 | J13: =SUMIF('ADS Prima (agg)'!$A:$A,J$7,'ADS Prima (agg)'!$AA:$AA) -> 5339379.5 | K13: =SUM(G13:J13) -> 58082216
F14: Auto Mekanika | G14: =SUMIF('Auto Mekanika (agg)'!$A:$A,G$7,'Auto Mekanika (agg)'!$AA:$AA) -> 15928672 | H14: =SUMIF('Auto Mekanika (agg)'!$A:$A,H$7,'Auto Mekanika (agg)'!$AA:$AA) -> 11203394 | I14: =SUMIF('Auto Mekanika (agg)'!$A:$A,I$7,'Auto Mekanika (agg)'!$AA:$AA) -> 17351100 | J14: =SUMIF('Auto Mekanika (agg)'!$A:$A,J$7,'Auto Mekanika (agg)'!$AA:$AA) -> 8911994 | K14: =SUM(G14:J14) -> 53395160
F15: Bengkel Multi Variasi | G15: =SUMIF('Bengkel Multi Var (agg)'!$A:$A,G$7,'Bengkel Multi Var (agg)'!$AA:$AA) -> 0 | H15: =SUMIF('Bengkel Multi Var (agg)'!$A:$A,H$7,'Bengkel Multi Var (agg)'!$AA:$AA) -> 23418512 | I15: =SUMIF('Bengkel Multi Var (agg)'!$A:$A,I$7,'Bengkel Multi Var (agg)'!$AA:$AA) -> 6192569.5 | J15: =SUMIF('Bengkel Multi Var (agg)'!$A:$A,J$7,'Bengkel Multi Var (agg)'!$AA:$AA) -> 3667716 | K15: =SUM(G15:J15) -> 33278798
F16: Euro Galleria | G16: =SUMIF('[2]EURO GALLARIA'!$A:$A,G$7,'[2]EURO GALLARIA'!$AA:$AA) -> 0 | H16: =SUMIF('[2]EURO GALLARIA'!$A:$A,H$7,'[2]EURO GALLARIA'!$AA:$AA) -> 2088785.4 | I16: =SUMIF('[2]EURO GALLARIA'!$A:$A,I$7,'[2]EURO GALLARIA'!$AA:$AA) -> 6151600 | J16: =SUMIF('[2]EURO GALLARIA'!$A:$A,J$7,'[2]EURO GALLARIA'!$AA:$AA) -> 0 | K16: =SUM(G16:J16) -> 8240385.4
F17: Drivewell | G17: =SUMIF('Drivewell (agg)'!$A:$A,G$7,'Drivewell (agg)'!$AA:$AA) -> 15232704 | H17: =SUMIF('Drivewell (agg)'!$A:$A,H$7,'Drivewell (agg)'!$AA:$AA) -> 0 | I17: =SUMIF('Drivewell (agg)'!$A:$A,I$7,'Drivewell (agg)'!$AA:$AA) -> 1968850 | J17: =SUMIF('Drivewell (agg)'!$A:$A,J$7,'Drivewell (agg)'!$AA:$AA) -> 8690500 | K17: =SUM(G17:J17) -> 25892054
F18: Mersi (no sales yet) | G18: =SUMIF('[2]Mersi '!$A:$A,G$7,'[2]Mersi '!$AA:$AA) -> 0 | H18: =SUMIF('[2]Mersi '!$A:$A,H$7,'[2]Mersi '!$AA:$AA) -> 712614 | I18: =SUMIF('[2]Mersi '!$A:$A,I$7,'[2]Mersi '!$AA:$AA) -> 703783.5 | J18: =SUMIF('[2]Mersi '!$A:$A,J$7,'[2]Mersi '!$AA:$AA) -> 0 | K18: =SUM(G18:J18) -> 1416397.5
F19: K (No sales yet) | G19: - | H19: - | I19: - | K19: =SUM(G19:J19) -> 0
F20: Auto Service (no sales yet) | G20: - | H20: - | I20: - | K20: =SUM(G20:J20) -> 0
F21: CV Sun | G21: =SUMIF('CV Sun (agg)'!$A:$A,G$7,'CV Sun (agg)'!$AA:$AA) -> 0 | H21: =SUMIF('CV Sun (agg)'!$A:$A,H$7,'CV Sun (agg)'!$AA:$AA) -> 18081336 | I21: =SUMIF('CV Sun (agg)'!$A:$A,I$7,'CV Sun (agg)'!$AA:$AA) -> 68491777 | J21: =SUMIF('CV Sun (agg)'!$A:$A,J$7,'CV Sun (agg)'!$AA:$AA) -> 0 | K21: =SUM(G21:J21) -> 86573113
F22: Sumber Timur | G22: =SUMIF('Sumber Timur (clean)'!$A:$A,G$7,'Sumber Timur (clean)'!$AA:$AA) -> 0 | H22: =SUMIF('Sumber Timur (clean)'!$A:$A,H$7,'Sumber Timur (clean)'!$AA:$AA) -> 3062618 | I22: =SUMIF('Sumber Timur (clean)'!$A:$A,I$7,'Sumber Timur (clean)'!$AA:$AA) -> 3117400 | J22: =SUMIF('Sumber Timur (clean)'!$A:$A,J$7,'Sumber Timur (clean)'!$AA:$AA) -> 0 | K22: =SUM(G22:J22) -> 6180018
F23: Honda Auto Duren Sawit | G23: =SUMIF('Honda Duren (clean)'!$A:$A,G$7,'Honda Duren (clean)'!$AA:$AA) -> 0 | H23: =SUMIF('Honda Duren (clean)'!$A:$A,H$7,'Honda Duren (clean)'!$AA:$AA) -> 2675920 | I23: =SUMIF('Honda Duren (clean)'!$A:$A,I$7,'Honda Duren (clean)'!$AA:$AA) -> 0 | J23: =SUMIF('Honda Duren (clean)'!$A:$A,J$7,'Honda Duren (clean)'!$AA:$AA) -> 9256981.5 | K23: =SUM(G23:J23) -> 11932902
F24: Lavender Car Solution | G24: =SUMIF('Lavender（Agg）'!$A:$A,G7,'Lavender（Agg）'!$AA:$AA) -> 1075100 | H24: =SUMIF('Lavender（Agg）'!$A:$A,H7,'Lavender（Agg）'!$AA:$AA) -> 4081174.5 | I24: =SUMIF('Lavender（Agg）'!$A:$A,I7,'Lavender（Agg）'!$AA:$AA) -> 6204861 | J24: =SUMIF('Lavender（Agg）'!$A:$A,J7,'Lavender（Agg）'!$AA:$AA) -> 2618850 | K24: =SUM(G24:J24) -> 13979986
F25: Total | G25: =SUM(G8:G24) -> 1.2191643e+08 | H25: =SUM(H8:H24) -> 80271557 | I25: =SUM(I8:I24) -> 1.3179295e+08 | J25: =SUM(J8:J24) -> 52711444 | K25: =SUM(K8:K24) -> 386692390
F26: PPN 11%
F27: Total | K27: =K25*1.11 -> 4.2922855e+08

Sheet Pit Stop (Agregated)
A1: MONTH | B1: Kode Barang | F1: Nama Barang | L1: Kts. | P1: @Harga | T1: Diskon | AA1: Total Harga
A2: NOV | B2: 101761 | F2: BOSCH Wiper Clear Advantage 14 inch BCA14 | L2: 10 | P2: 77928 | T2: =L2*P2*35% -> 272748 | AA2: =L2*P2-T2 -> 506532
A3: NOV | B3: 101762 | F3: BOSCH Wiper Clear Advantage 16 inch BCA16 | L3: 10 | P3: 77928 | T3: =L3*P3*35% -> 272748 | AA3: =L3*P3-T3 -> 506532
A4: NOV | B4: 101769 | F4: BOSCH Wiper Clear Advantage 17 inch BCA17 | L4: 10 | P4: 90090 | T4: =L4*P4*35% -> 315315 | AA4: =L4*P4-T4 -> 585585
A5: NOV | B5: 101770 | F5: BOSCH Wiper Clear Advantage 18 inch BCA18 | L5: 10 | P5: 90090 | T5: =L5*P5*35% -> 315315 | AA5: =L5*P5-T5 -> 585585
A6: NOV | B6: 101778 | F6: BOSCH Wiper Clear Advantage 19 inch BCA19 | L6: 10 | P6: 96396 | T6: =L6*P6*35% -> 337386 | AA6: =L6*P6-T6 -> 626574
A7: NOV | B7: 101779 | F7: BOSCH Wiper Clear Advantage 20 inch BCA20 | L7: 10 | P7: 96396 | T7: =L7*P7*35% -> 337386 | AA7: =L7*P7-T7 -> 626574
A8: NOV | B8: 101780 | F8: BOSCH Wiper Clear Advantage 21 inch BCA21 | L8: 10 | P8: 98198 | T8: =L8*P8*35% -> 343693 | AA8: =L8*P8-T8 -> 638287
A9: NOV | B9: 101787 | F9: BOSCH Wiper Clear Advantage 22 inch BCA22 | L9: 10 | P9: 104955 | T9: =L9*P9*35% -> 367342.5 | AA9: =L9*P9-T9 -> 682207.5
A10: NOV | B10: 101788 | F10: BOSCH Wiper Clear Advantage 24 inch BCA24 | L10: 10 | P10: 104955 | T10: =L10*P10*35% -> 367342.5 | AA10: =L10*P10-T10 -> 682207.5
A11: NOV | B11: 101791 | F11: BOSCH Wiper Clear Advantage 26 inch BCA26 | L11: 10 | P11: 110811 | T11: =L11*P11*35% -> 387838.5 | AA11: =L11*P11-T11 -> 720271.5
A12: NOV | B12: 101740 | F12: BOSCH Wiper Advantage 14 inch BA14 | L12: 10 | P12: 50901 | T12: =L12*P12*35% -> 178153.5 | AA12: =L12*P12-T12 -> 330856.5
A13: NOV | B13: 101741 | F13: BOSCH Wiper Advantage 16 inch BA16 | L13: 10 | P13: 50901 | T13: =L13*P13*35% -> 178153.5 | AA13: =L13*P13-T13 -> 330856.5
... A25: NOV | B25: 101807 | F25: BOSCH Spark Plug VR8SII30X - Iridium | L25: 10 | P25: 165400 | T25: =L25*P25*35% -> 578900 | AA25: =L25*P25-T25 -> 1075100
B27: Kode Barang | F27: Nama Barang | L27: Kts. | P27: @Harga | T27: Diskon | AA27: Total Harga
A28: NOV | B28: 101740 | F28: BOSCH Wiper Advantage 14 inch BA14 | L28: 20 | P28: 50901 | T28: =L28*P28*35% -> 356307 | AA28: =L28*P28-T28 -> 661713
A29: NOV | B29: 101745 | F29: BOSCH Wiper Advantage 17 inch BA17 | L29: 30 | P29: 54505 | T29: =L29*P29*35% -> 572302.5 | AA29: =L29*P29-T29 -> 1062847.5
A30: NOV | B30: 101759 | F30: BOSCH Wiper Advantage 22 inch BA22 | L30: 20 | P30: 72793 | T30: =L30*P30*35% -> 509551 | AA30: =L30*P30-T30 -> 946309
A31: NOV | B31: 101761 | F31: BOSCH Wiper Clear Advantage 14 inch BCA14 | L31: 30 | P31: 77928 | T31: =L31*P31*35% -> 818244 | AA31: =L31*P31-T31 -> 1519596
A32: NOV | B32: 101762 | F32: BOSCH Wiper Clear Advantage 16 inch BCA16 | L32: 20 | P32: 77928 | T32: =L32*P32*35% -> 545496 | AA32: =L32*P32-T32 -> 1013064
A33: NOV | B33: 101769 | F33: BOSCH Wiper Clear Advantage 17 inch BCA17 | L33: 10 | P33: 90090 | T33: =L33*P33*35% -> 315315 | AA33: =L33*P33-T33 -> 585585
A34: NOV | B34: 101770 | F34: BOSCH Wiper Clear Advantage 18 inch BCA18 | L34: 10 | P34: 90090 | T34: =L34*P34*35% -> 315315 | AA34: =L34*P34-T34 -> 585585
A35: NOV | B35: 101778 | F35: BOSCH Wiper Clear Advantage 19 inch BCA19 | L35: 10 | P35: 96396 | T35: =L35*P35*35% -> 337386 | AA35: =L35*P35-T35 -> 626574
A36: NOV | B36: 101788 | F36: BOSCH Wiper Clear Advantage 24 inch BCA24 | L36: 20 | P36: 104955 | T36: =L36*P36*35% -> 734685 | AA36: =L36*P36-T36 -> 1364415
A37: NOV | B37: 101791 | F37: BOSCH Wiper Clear Advantage 26 inch BCA26 | L37: 20 | P37: 110811 | T37: =L37*P37*35% -> 775677 | AA37: =L37*P37-T37 -> 1440543
A38: NOV | B38: 101742 | F38: BOSCH Oil Filter O 1014 | L38: 10 | P38: 49700 | T38: =L38*P38*35% -> 173950 | AA38: =L38*P38-T38 -> 323050
A39: NOV | B39: 101737 | F39: BOSCH Oil Filter O 1041 | L39: 10 | P39: 43000 | T39: =L39*P39*35% -> 150500 | AA39: =L39*P39-T39 -> 279500
A40: NOV | B40: 101743 | F40: BOSCH Oil Filter O 1042 | L40: 10 | P40: 50000 | T40: =L40*P40*35% -> 175000 | AA40: =L40*P40-T40 -> 325000
B42: Kode Barang | F42: Nama Barang | L42: Kts. | P42: @Harga | T42: Diskon | AA42: Total Harga
A43: DEC | B43: 101743 | F43: BOSCH Oil Filter O 1042 | L43: 20 | P43: 50000 | T43: =L43*P43*35% -> 350000 | AA43: =L43*P43-T43 -> 650000
A44: DEC | B44: 101737 | F44: BOSCH Oil Filter O 1041 | L44: 20 | P44: 43000 | T44: =L44*P44*35% -> 301000 | AA44: =L44*P44-T44 -> 559000
A45: DEC | B45: 101742 | F45: BOSCH Oil Filter O 1014 | L45: 20 | P45: 49700 | T45: =L45*P45*35% -> 347900 | AA45: =L45*P45-T45 -> 646100
A46: DEC | B46: 101750 | F46: BOSCH Oil Filter O 1001 | L46: 20 | P46: 56000 | T46: =L46*P46*35% -> 392000 | AA46: =L46*P46-T46 -> 728000
B48: Kode Barang | F48: Nama Barang | L48: Kts. | P48: @Harga | T48: Diskon | AA48: Total Harga
A49: DEC | B49: 101743 | F49: BOSCH Oil Filter O 1042 | L49: 20 | P49: 50000 | T49: =L49*P49*35% -> 350000 | AA49: =L49*P49-T49 -> 650000
A50: DEC | B50: 101737 | F50: BOSCH Oil Filter O 1041 | L50: 20 | P50: 43000 | T50: =L50*P50*35% -> 301000 | AA50: =L50*P50-T50 -> 559000
A51: DEC | B51: 101750 | F51: BOSCH Oil Filter O 1001 | L51: 20 | P51: 56000 | T51: =L51*P51*35% -> 392000 | AA51: =L51*P51-T51 -> 728000
B53: Kode Barang | F53: Nama Barang | L53: Kts. | P53: @Harga | T53: Diskon | AA53: Total Harga
A54: JAN | B54: 101762 | F54: BOSCH Wiper Clear Advantage 16 inch BCA16 | L54: 15 | P54: 77928 | T54: =L54*P54*35% -> 409122 | AA54: =L54*P54-T54 -> 759798
A55: JAN | B55: 101779 | F55: BOSCH Wiper Clear Advantage 20 inch BCA20 | L55: 15 | P55: 96396 | T55: =L55*P55*35% -> 506079 | AA55: =L55*P55-T55 -> 939861
A56: JAN | B56: 101787 | F56: BOSCH Wiper Clear Advantage 22 inch BCA22 | L56: 20 | P56: 104955 | T56: =L56*P56*35% -> 734685 | AA56: =L56*P56-T56 -> 1364415
A57: JAN | B57: 101741 | F57: BOSCH Wiper Advantage 16 inch BA16 | L57: 20 | P57: 50901 | T57: =L57*P57*35% -> 356307 | AA57: =L57*P57-T57 -> 661713
A58: JAN | B58: 101758 | F58: BOSCH Wiper Advantage 24 inch BA24 | L58: 20 | P58: 72973 | T58: =L58*P58*35% -> 510811 | AA58: =L58*P58-T58 -> 948649
A59: JAN | B59: 101742 | F59: BOSCH Oil Filter O 1014 | L59: 20 | P59: 49700 | T59: =L59*P59*35% -> 347900 | AA59: =L59*P59-T59 -> 646100
A60: JAN | B60: 101743 | F60: BOSCH Oil Filter O 1042 | L60: 20 | P60: 50000 | T60: =L60*P60*35% -> 350000 | AA60: =L60*P60-T60 -> 650000

Sheet Pit Stop (cleaned)
A1: {=_xlfn.UNIQUE('Pit Stop (Agregated)'!F:F)} -> Nama Barang | B1: QTY | D1: Exist in Master
A2: BOSCH Wiper Clear Advantage 14 inch BCA14 | B2: =SUMIF('Pit Stop (Agregated)'!F:F,'Pit Stop (cleaned)'!A2,'Pit Stop (Agregated)'!L:L) -> 40 | D2: =_xlfn.XLOOKUP(A2,Master!B:B,Master!B:B,"Hehe") -> BOSCH Wiper Clear Advantage 14 inch BCA14
A3: BOSCH Wiper Clear Advantage 16 inch BCA16 | B3: =SUMIF('Pit Stop (Agregated)'!F:F,'Pit Stop (cleaned)'!A3,'Pit Stop (Agregated)'!L:L) -> 45 | D3: =_xlfn.XLOOKUP(A3,Master!B:B,Master!B:B,"Hehe") -> BOSCH Wiper Clear Advantage 16 inch BCA16
A4: BOSCH Wiper Clear Advantage 17 inch BCA17 | B4: =SUMIF('Pit Stop (Agregated)'!F:F,'Pit Stop (cleaned)'!A4,'Pit Stop (Agregated)'!L:L) -> 20 | D4: =_xlfn.XLOOKUP(A4,Master!B:B,Master!B:B,"Hehe") -> BOSCH Wiper Clear Advantage 17 inch BCA17
A5: BOSCH Wiper Clear Advantage 18 inch BCA18 | B5: =SUMIF('Pit Stop (Agregated)'!F:F,'Pit Stop (cleaned)'!A5,'Pit Stop (Agregated)'!L:L) -> 20 | D5: =_xlfn.XLOOKUP(A5,Master!B:B,Master!B:B,"Hehe") -> BOSCH Wiper Clear Advantage 18 inch BCA18
A6: BOSCH Wiper Clear Advantage 19 inch BCA19 | B6: =SUMIF('Pit Stop (Agregated)'!F:F,'Pit Stop (cleaned)'!A6,'Pit Stop (Agregated)'!L:L) -> 20 | D6: =_xlfn.XLOOKUP(A6,Master!B:B,Master!B:B,"Hehe") -> BOSCH Wiper Clear Advantage 19 inch BCA19
A7: BOSCH Wiper Clear Advantage 20 inch BCA20 | B7: =SUMIF('Pit Stop (Agregated)'!F:F,'Pit Stop (cleaned)'!A7,'Pit Stop (Agregated)'!L:L) -> 25 | D7: =_xlfn.XLOOKUP(A7,Master!B:B,Master!B:B,"Hehe") -> BOSCH Wiper Clear Advantage 20 inch BCA20
A8: BOSCH Wiper Clear Advantage 21 inch BCA21 | B8: =SUMIF('Pit Stop (Agregated)'!F:F,'Pit Stop (cleaned)'!A8,'Pit Stop (Agregated)'!L:L) -> 10 | D8: =_xlfn.XLOOKUP(A8,Master!B:B,Master!B:B,"Hehe") -> BOSCH Wiper Clear Advantage 21 inch BCA21
A9: BOSCH Wiper Clear Advantage 22 inch BCA22 | B9: =SUMIF('Pit Stop (Agregated)'!F:F,'Pit Stop (cleaned)'!A9,'Pit Stop (Agregated)'!L:L) -> 30 | D9: =_xlfn.XLOOKUP(A9,Master!B:B,Master!B:B,"Hehe") -> BOSCH Wiper Clear Advantage 22 inch BCA22
A10: BOSCH Wiper Clear Advantage 24 inch BCA24 | B10: =SUMIF('Pit Stop (Agregated)'!F:F,'Pit Stop (cleaned)'!A10,'Pit Stop (Agregated)'!L:L) -> 30 | D10: =_xlfn.XLOOKUP(A10,Master!B:B,Master!B:B,"Hehe") -> BOSCH Wiper Clear Advantage 24 inch BCA24
A11: BOSCH Wiper Clear Advantage 26 inch BCA26 | B11: =SUMIF('Pit Stop (Agregated)'!F:F,'Pit Stop (cleaned)'!A11,'Pit Stop (Agregated)'!L:L) -> 30 | D11: =_xlfn.XLOOKUP(A11,Master!B:B,Master!B:B,"Hehe") -> BOSCH Wiper Clear Advantage 26 inch BCA26
A12: BOSCH Wiper Advantage 14 inch BA14 | B12: =SUMIF('Pit Stop (Agregated)'!F:F,'Pit Stop (cleaned)'!A12,'Pit Stop (Agregated)'!L:L) -> 30 | D12: =_xlfn.XLOOKUP(A12,Master!B:B,Master!B:B,"Hehe") -> BOSCH Wiper Advantage 14 inch BA14
A13: BOSCH Wiper Advantage 16 inch BA16 | B13: =SUMIF('Pit Stop (Agregated)'!F:F,'Pit Stop (cleaned)'!A13,'Pit Stop (Agregated)'!L:L) -> 30 | D13: =_xlfn.XLOOKUP(A13,Master!B:B,Master!B:B,"Hehe") -> BOSCH Wiper Advantage 16 inch BA16
... A25: BOSCH Spark Plug VR8SII30X - Iridium | B25: =SUMIF('Pit Stop (Agregated)'!F:F,'Pit Stop (cleaned)'!A25,'Pit Stop (Agregated)'!L:L) -> 10 | D25: =_xlfn.XLOOKUP(A25,Master!B:B,Master!B:B,"Hehe") -> BOSCH Spark Plug VR8SII30X - Iridium
A26: 0 | B26: =SUMIF('Pit Stop (Agregated)'!F:F,'Pit Stop (cleaned)'!A26,'Pit Stop (Agregated)'!L:L) -> 0 | D26: =_xlfn.XLOOKUP(A26,Master!B:B,Master!B:B,"Hehe") -> Hehe
A27: BOSCH Wiper Advantage 17 inch BA17 | B27: =SUMIF('Pit Stop (Agregated)'!F:F,'Pit Stop (cleaned)'!A27,'Pit Stop (Agregated)'!L:L) -> 30 | D27: =_xlfn.XLOOKUP(A27,Master!B:B,Master!B:B,"Hehe") -> BOSCH Wiper Advantage 17 inch BA17

Sheet Subur Makmur Ban (Agg)
B1: Kode Barang | F1: Nama Barang | L1: Kts. | P1: @Harga | T1: Diskon | AA1: Total Harga
A2: JAN | B2: 101737 | F2: BOSCH Oil Filter O 1041 | L2: 80 | P2: 43000 | T2: =L2*P2*35% -> 1204000 | AA2: =L2*P2-T2 -> 2236000
B4: Kode Barang | F4: Nama Barang | L4: Kts. | P4: @Harga | T4: Diskon | AA4: Total Harga
A5: JAN | B5: 101859 | F5: BOSCH Cabin Filter AP-N02 | L5: 15 | P5: 244600 | T5: 256830 | AA5: =L5*P5-T5 -> 3412170
B7: Nama Barang | C7: Exist in Master
B8: BOSCH Oil Filter O 1041 | C8: =_xlfn.XLOOKUP(B8,Master!B:B,Master!B:B,"Hehe") -> BOSCH Oil Filter O 1041
C9: =_xlfn.XLOOKUP(B9,Master!B:B,Master!B:B,"Hehe") -> 0
B10: Nama Barang | C10: =_xlfn.XLOOKUP(B10,Master!B:B,Master!B:B,"Hehe") -> Hehe
B11: BOSCH Cabin Filter AP-N02 | C11: =_xlfn.XLOOKUP(B11,Master!B:B,Master!B:B,"Hehe") -> BOSCH Cabin Filter AP-N02

Sheet Bengkel Pegasus (Agg)
B1: Kode Barang | F1: Nama Barang | L1: Kts. | P1: @Harga | T1: Diskon | AA1: Total Harga
A2: JAN | B2: 102134 | F2: BOSCH Battery MF Blue NS40ZL 40B19L 12V | L2: 2 | P2: 1029200 | T2: =L2*P2*35% -> 720440 | AA2: =L2*P2-T2 -> 1337960
B4: Nama Barang | C4: Exist in Master
B5: BOSCH Battery MF Blue NS40ZL 40B19L 12V | C5: =_xlfn.XLOOKUP(B5,Master!B:B,Master!B:B,"Hehe") -> BOSCH Battery MF Blue NS40ZL 40B19L 12V
B8: Kode Barang | F8: Nama Barang | L8: Kts. | P8: @Harga | T8: Diskon | AA8: Total Harga
A9: FEB | B9: 101851 | F9: BOSCH Cabin Filter AP-H06 | L9: 5 | P9: 228800 | T9: =L9*P9*35% -> 400400 | AA9: =L9*P9-T9 -> 743600
A10: FEB | B10: 107798 | F10: BOSCH Cabin Filter AP-H07 | L10: 5 | P10: 228800 | T10: =L10*P10*35% -> 400400 | AA10: =L10*P10-T10 -> 743600
A11: FEB | B11: 101852 | F11: BOSCH Cabin Filter AP-H09 | L11: 5 | P11: 228800 | T11: =L11*P11*35% -> 400400 | AA11: =L11*P11-T11 -> 743600
A12: FEB | B12: 101853 | F12: BOSCH Cabin Filter AP-T02 | L12: 5 | P12: 228800 | T12: =L12*P12*35% -> 400400 | AA12: =L12*P12-T12 -> 743600
A13: FEB | B13: 101843 | F13: BOSCH Cabin Filter AP-T07 | L13: 5 | P13: 199000 | T13: =L13*P13*35% -> 348250 | AA13: =L13*P13-T13 -> 646750
A14: FEB | B14: 101854 | F14: BOSCH Cabin Filter AP-T10 | L14: 5 | P14: 228800 | T14: =L14*P14*35% -> 400400 | AA14: =L14*P14-T14 -> 743600
A15: FEB | B15: 101741 | F15: BOSCH Wiper Advantage 16 inch BA16 | L15: 50 | P15: 50901 | T15: =L15*P15*35% -> 890767.5 | AA15: =L15*P15-T15 -> 1654282.5
A16: FEB | B16: 101745 | F16: BOSCH Wiper Advantage 17 inch BA17 | L16: 40 | P16: 54505 | T16: =L16*P16*35% -> 763070 | AA16: =L16*P16-T16 -> 1417130
A17: FEB | B17: 101746 | F17: BOSCH Wiper Advantage 18 inch BA18 | L17: 40 | P17: 54505 | T17: =L17*P17*35% -> 763070 | AA17: =L17*P17-T17 -> 1417130
A18: FEB | B18: 101752 | F18: BOSCH Wiper Advantage 21 inch BA21 | L18: 50 | P18: 64414 | T18: =L18*P18*35% -> 1127245 | AA18: =L18*P18-T18 -> 2093455
A19: FEB | B19: 101758 | F19: BOSCH Wiper Advantage 24 inch BA24 | L19: 40 | P19: 72973 | T19: =L19*P19*35% -> 1021622 | AA19: =L19*P19-T19 -> 1897298
A20: FEB | B20: 107898 | F20: BOSCH Wiper Advantage 28 inch BA28 | L20: 20 | P20: 106306 | T20: =L20*P20*35% -> 744142 | AA20: =L20*P20-T20 -> 1381978
B23: Terbilang :
D24: Satu juta lima ratus lima puluh satu ribu tiga ratus tujuh puluh lima koma dua puluh
R25: Sub Total | AA25: 1397635.2

Sheet Autocraft (agg)
B1: Kode Barang | F1: Nama Barang | L1: Kts. | P1: @Harga | T1: Diskon | AA1: Total Harga
A2: DEC | B2: 108280 | F2: SHELL Engine Oil HELIX CITY 0W-20 4L | L2: 1 | P2: 337000 | T2: 0 | AA2: =L2*P2-T2 -> 337000
A3: DEC | B3: 101969 | F3: MOBIL Engine Oil Mobil 1 5W-30 4L | L3: 1 | P3: 515000 | T3: 0 | AA3: =L3*P3-T3 -> 515000
A4: DEC | B4: 108282 | F4: SHELL Engine Oil HELIX HX7 Plus 5W-40 4L | L4: 1 | P4: 343000 | T4: 0 | AA4: =L4*P4-T4 -> 343000
A5: DEC | B5: 101947 | F5: CASTROL Engine Oil MAGNATEC 5W-30 4L | L5: 1 | P5: 519000 | T5: 0 | AA5: =L5*P5-T5 -> 519000
A6: DEC | B6: 101736 | F6: BOSCH Oil Filter O 0126 | L6: 20 | P6: 43000 | T6: =L6*P6*35% -> 301000 | AA6: =L6*P6-T6 -> 559000
A7: DEC | B7: 101742 | F7: BOSCH Oil Filter O 1014 | L7: 20 | P7: 49700 | T7: =L7*P7*35% -> 347900 | AA7: =L7*P7-T7 -> 646100
B9: Nama Barang | C9: Exist in Master
B10: SHELL Engine Oil HELIX CITY 0W-20 4L | C10: =_xlfn.XLOOKUP(B10,Master!B:B,Master!B:B,"Hehe") -> Hehe
B11: MOBIL Engine Oil Mobil 1 5W-30 4L | C11: =_xlfn.XLOOKUP(B11,Master!B:B,Master!B:B,"Hehe") -> Hehe
B12: SHELL Engine Oil HELIX HX7 Plus 5W-40 4L | C12: =_xlfn.XLOOKUP(B12,Master!B:B,Master!B:B,"Hehe") -> Hehe
B13: CASTROL Engine Oil MAGNATEC 5W-30 4L | C13: =_xlfn.XLOOKUP(B13,Master!B:B,Master!B:B,"Hehe") -> Hehe
B14: BOSCH Oil Filter O 0126 | C14: =_xlfn.XLOOKUP(B14,Master!B:B,Master!B:B,"Hehe") -> BOSCH Oil Filter O 0126
B15: BOSCH Oil Filter O 1014 | C15: =_xlfn.XLOOKUP(B15,Master!B:B,Master!B:B,"Hehe") -> BOSCH Oil Filter O 1014

Sheet Autones (agg)
B1: Kode Barang | F1: Nama Barang | L1: Kts. | P1: @Harga | T1: Diskon | AA1: Total Harga
A2: NOV | B2: 102134 | F2: BOSCH Battery MF Blue NS40ZL 40B19L 12V | L2: 8 | P2: 1029200 | T2: =L2*P2*35% -> 2881760 | AA2: =L2*P2-T2 -> 5351840
A3: NOV | B3: 102131 | F3: BOSCH Battery MF Blue 55D23L 12V-60Ah | L3: 5 | P3: 1466800 | T3: =L3*P3*35% -> 2566900 | AA3: =L3*P3-T3 -> 4767100
A4: NOV | B4: 108121 | F4: BOSCH Battery MF Hightech AGM DIN70 LN3 12V-70Ah | L4: 3 | P4: 3720000 | T4: =L4*P4*35% -> 3906000 | AA4: =L4*P4-T4 -> 7254000
B6: Kode Barang | F6: Nama Barang | L6: Kts. | P6: @Harga | T6: Diskon | AA6: Total Harga
A7: DEC | B7: 101780 | F7: BOSCH Wiper Clear Advantage 21 inch BCA21 | L7: 10 | P7: 98198 | T7: =L7*P7*35% -> 343693 | AA7: =L7*P7-T7 -> 638287
A8: DEC | B8: 101787 | F8: BOSCH Wiper Clear Advantage 22 inch BCA22 | L8: 7 | P8: 104955 | T8: =L8*P8*35% -> 257139.75 | AA8: =L8*P8-T8 -> 477545.25
A9: DEC | B9: 101770 | F9: BOSCH Wiper Clear Advantage 18 inch BCA18 | L9: 10 | P9: 90090 | T9: =L9*P9*35% -> 315315 | AA9: =L9*P9-T9 -> 585585
B11: Kode Barang | F11: Nama Barang | L11: Kts. | P11: @Harga | T11: Diskon | AA11: Total Harga
A12: DEC | B12: 101761 | F12: BOSCH Wiper Clear Advantage 14 inch BCA14 | L12: 10 | P12: 77928 | T12: =L12*P12*35% -> 272748 | AA12: =L12*P12-T12 -> 506532
A13: DEC | B13: 102136 | F13: BOSCH Battery MF Blue NS60LS 46B24LS 12V-42Ah | L13: 5 | P13: 1126100 | T13: =L13*P13*35% -> 1970675 | AA13: =L13*P13-T13 -> 3659825
B15: Kode Barang | F15: Nama Barang | L15: Kts. | P15: @Harga | T15: Diskon | AA15: Total Harga
A16: DEC | B16: 101787 | F16: BOSCH Wiper Clear Advantage 22 inch BCA22 | L16: 7 | P16: 104955 | T16: =L16*P16*35% -> 257139.75 | AA16: =L16*P16-T16 -> 477545.25
A17: DEC | B17: 101788 | F17: BOSCH Wiper Clear Advantage 24 inch BCA24 | L17: 7 | P17: 104955 | T17: =L17*P17*35% -> 257139.75 | AA17: =L17*P17-T17 -> 477545.25
A18: DEC | B18: 101741 | F18: BOSCH Wiper Advantage 16 inch BA16 | L18: 10 | P18: 50901 | T18: =L18*P18*35% -> 178153.5 | AA18: =L18*P18-T18 -> 330856.5
A19: DEC | B19: 101746 | F19: BOSCH Wiper Advantage 18 inch BA18 | L19: 10 | P19: 54505 | T19: =L19*P19*35% -> 190767.5 | AA19: =L19*P19-T19 -> 354282.5
B21: Kode Barang | F21: Nama Barang | L21: Kts. | P21: @Harga | T21: Diskon | AA21: Total Harga
A22: JAN | B22: 101787 | F22: BOSCH Wiper Clear Advantage 22 inch BCA22 | L22: 10 | P22: 104955 | T22: =L22*P22*35% -> 367342.5 | AA22: =L22*P22-T22 -> 682207.5
B24: Kode Barang | F24: Nama Barang | L24: Kts. | P24: @Harga | T24: Diskon | AA24: Total Harga
A25: JAN | B25: 102134 | F25: BOSCH Battery MF Blue NS40ZL 40B19L 12V | L25: 5 | P25: 1029200 | T25: =L25*P25*35% -> 1801100 | AA25: =L25*P25-T25 -> 3344900
A26: JAN | B26: 101762 | F26: BOSCH Wiper Clear Advantage 16 inch BCA16 | L26: 10 | P26: 77928 | T26: =L26*P26*35% -> 272748 | AA26: =L26*P26-T26 -> 506532
A27: JAN | B27: 101788 | F27: BOSCH Wiper Clear Advantage 24 inch BCA24 | L27: 10 | P27: 104955 | T27: =L27*P27*35% -> 367342.5 | AA27: =L27*P27-T27 -> 682207.5

Sheet Autones (cleaned)
A1: {=_xlfn.UNIQUE('Autones (agg)'!F1:F27)} -> Nama Barang | B1: Total QTY | C1: Exist in Master
A2: BOSCH Battery MF Blue NS40ZL 40B19L 12V | B2: =SUMIF('Autones (agg)'!F:F,'Autones (cleaned)'!A2,'Autones (agg)'!L:L) -> 13 | C2: =_xlfn.XLOOKUP(A2,Master!B:B,Master!B:B,"Hehe") -> BOSCH Battery MF Blue NS40ZL 40B19L 12V
A3: BOSCH Battery MF Blue 55D23L 12V-60Ah | B3: =SUMIF('Autones (agg)'!F:F,'Autones (cleaned)'!A3,'Autones (agg)'!L:L) -> 5 | C3: =_xlfn.XLOOKUP(A3,Master!B:B,Master!B:B,"Hehe") -> BOSCH Battery MF Blue 55D23L 12V-60Ah
A4: BOSCH Battery MF Hightech AGM DIN70 LN3 12V-70Ah | B4: =SUMIF('Autones (agg)'!F:F,'Autones (cleaned)'!A4,'Autones (agg)'!L:L) -> 3 | C4: =_xlfn.XLOOKUP(A4,Master!B:B,Master!B:B,"Hehe") -> BOSCH Battery MF Hightech AGM DIN70 LN3 12V-70Ah
A5: 0 | B5: =SUMIF('Autones (agg)'!F:F,'Autones (cleaned)'!A5,'Autones (agg)'!L:L) -> 0 | C5: =_xlfn.XLOOKUP(A5,Master!B:B,Master!B:B,"Hehe") -> Hehe
A6: BOSCH Wiper Clear Advantage 21 inch BCA21 | B6: =SUMIF('Autones (agg)'!F:F,'Autones (cleaned)'!A6,'Autones (agg)'!L:L) -> 10 | C6: =_xlfn.XLOOKUP(A6,Master!B:B,Master!B:B,"Hehe") -> BOSCH Wiper Clear Advantage 21 inch BCA21
A7: BOSCH Wiper Clear Advantage 22 inch BCA22 | B7: =SUMIF('Autones (agg)'!F:F,'Autones (cleaned)'!A7,'Autones (agg)'!L:L) -> 24 | C7: =_xlfn.XLOOKUP(A7,Master!B:B,Master!B:B,"Hehe") -> BOSCH Wiper Clear Advantage 22 inch BCA22
A8: BOSCH Wiper Clear Advantage 18 inch BCA18 | B8: =SUMIF('Autones (agg)'!F:F,'Autones (cleaned)'!A8,'Autones (agg)'!L:L) -> 10 | C8: =_xlfn.XLOOKUP(A8,Master!B:B,Master!B:B,"Hehe") -> BOSCH Wiper Clear Advantage 18 inch BCA18
A9: BOSCH Wiper Clear Advantage 14 inch BCA14 | B9: =SUMIF('Autones (agg)'!F:F,'Autones (cleaned)'!A9,'Autones (agg)'!L:L) -> 10 | C9: =_xlfn.XLOOKUP(A9,Master!B:B,Master!B:B,"Hehe") -> BOSCH Wiper Clear Advantage 14 inch BCA14
A10: BOSCH Battery MF Blue NS60LS 46B24LS 12V-42Ah | B10: =SUMIF('Autones (agg)'!F:F,'Autones (cleaned)'!A10,'Autones (agg)'!L:L) -> 5 | C10: =_xlfn.XLOOKUP(A10,Master!B:B,Master!B:B,"Hehe") -> BOSCH Battery MF Blue NS60LS 46B24LS 12V-42Ah
A11: BOSCH Wiper Clear Advantage 24 inch BCA24 | B11: =SUMIF('Autones (agg)'!F:F,'Autones (cleaned)'!A11,'Autones (agg)'!L:L) -> 17 | C11: =_xlfn.XLOOKUP(A11,Master!B:B,Master!B:B,"Hehe") -> BOSCH Wiper Clear Advantage 24 inch BCA24
A12: BOSCH Wiper Advantage 16 inch BA16 | B12: =SUMIF('Autones (agg)'!F:F,'Autones (cleaned)'!A12,'Autones (agg)'!L:L) -> 10 | C12: =_xlfn.XLOOKUP(A12,Master!B:B,Master!B:B,"Hehe") -> BOSCH Wiper Advantage 16 inch BA16
A13: BOSCH Wiper Advantage 18 inch BA18 | B13: =SUMIF('Autones (agg)'!F:F,'Autones (cleaned)'!A13,'Autones (agg)'!L:L) -> 10 | C13: =_xlfn.XLOOKUP(A13,Master!B:B,Master!B:B,"Hehe") -> BOSCH Wiper Advantage 18 inch BA18
A14: BOSCH Wiper Clear Advantage 16 inch BCA16 | B14: =SUMIF('Autones (agg)'!F:F,'Autones (cleaned)'!A14,'Autones (agg)'!L:L) -> 10 | C14: =_xlfn.XLOOKUP(A14,Master!B:B,Master!B:B,"Hehe") -> BOSCH Wiper Clear Advantage 16 inch BCA16
B15: =SUMIF('Autones (agg)'!F:F,'Autones (cleaned)'!A15,'Autones (agg)'!L:L) -> 0 | C15: =_xlfn.XLOOKUP(A15,Master!B:B,Master!B:B,"Hehe") -> 0

Sheet ADS Prima (agg)
B1: Kode Barang | F1: Nama Barang | L1: Kts. | P1: @Harga | T1: Diskon | AA1: Total Harga
A2: NOV | B2: 101761 | F2: BOSCH Wiper Clear Advantage 14 inch BCA14 | L2: 30 | P2: 77928 | T2: =L2*P2*35% -> 818244 | AA2: =L2*P2-T2 -> 1519596
A3: NOV | B3: 101762 | F3: BOSCH Wiper Clear Advantage 16 inch BCA16 | L3: 30 | P3: 77928 | T3: =L3*P3*35% -> 818244 | AA3: =L3*P3-T3 -> 1519596
A4: NOV | B4: 101770 | F4: BOSCH Wiper Clear Advantage 18 inch BCA18 | L4: 30 | P4: 90090 | T4: =L4*P4*35% -> 945945 | AA4: =L4*P4-T4 -> 1756755
A5: NOV | B5: 101778 | F5: BOSCH Wiper Clear Advantage 19 inch BCA19 | L5: 30 | P5: 96396 | T5: =L5*P5*35% -> 1012158 | AA5: =L5*P5-T5 -> 1879722
A6: NOV | B6: 101779 | F6: BOSCH Wiper Clear Advantage 20 inch BCA20 | L6: 30 | P6: 96396 | T6: =L6*P6*35% -> 1012158 | AA6: =L6*P6-T6 -> 1879722
A7: NOV | B7: 101780 | F7: BOSCH Wiper Clear Advantage 21 inch BCA21 | L7: 30 | P7: 98198 | T7: =L7*P7*35% -> 1031079 | AA7: =L7*P7-T7 -> 1914861
A8: NOV | B8: 101787 | F8: BOSCH Wiper Clear Advantage 22 inch BCA22 | L8: 30 | P8: 104955 | T8: =L8*P8*35% -> 1102027.5 | AA8: =L8*P8-T8 -> 2046622.5
A9: NOV | B9: 101788 | F9: BOSCH Wiper Clear Advantage 24 inch BCA24 | L9: 30 | P9: 104955 | T9: =L9*P9*35% -> 1102027.5 | AA9: =L9*P9-T9 -> 2046622.5
A10: NOV | B10: 101791 | F10: BOSCH Wiper Clear Advantage 26 inch BCA26 | L10: 30 | P10: 110811 | T10: =L10*P10*35% -> 1163515.5 | AA10: =L10*P10-T10 -> 2160814.5
A11: NOV | B11: 101740 | F11: BOSCH Wiper Advantage 14 inch BA14 | L11: 30 | P11: 50901 | T11: =L11*P11*35% -> 534460.5 | AA11: =L11*P11-T11 -> 992569.5
A12: NOV | B12: 101741 | F12: BOSCH Wiper Advantage 16 inch BA16 | L12: 30 | P12: 50901 | T12: =L12*P12*35% -> 534460.5 | AA12: =L12*P12-T12 -> 992569.5
A13: NOV | B13: 101752 | F13: BOSCH Wiper Advantage 21 inch BA21 | L13: 30 | P13: 64414 | T13: =L13*P13*35% -> 676347 | AA13: =L13*P13-T13 -> 1256073
... A22: NOV | B22: 101743 | F22: BOSCH Oil Filter O 1042 | L22: 40 | P22: 50000 | T22: =L22*P22*35% -> 700000 | AA22: =L22*P22-T22 -> 1300000
B24: Kode Barang | F24: Nama Barang | L24: Kts. | P24: @Harga | T24: Diskon | AA24: Total Harga
A25: NOV | B25: 101847 | F25: BOSCH FUEL FILTER D 6292 | L25: 5 | P25: 206000 | T25: =L25*P25*35% -> 360500 | AA25: =L25*P25-T25 -> 669500
A26: NOV | B26: 101776 | F26: BOSCH FUEL FILTER D 6100 | L26: 15 | P26: 90000 | T26: =L26*P26*35% -> 472500 | AA26: =L26*P26-T26 -> 877500
A27: NOV | B27: 101743 | F27: BOSCH Oil Filter O 1042 | L27: 30 | P27: 50000 | T27: =L27*P27*35% -> 525000 | AA27: =L27*P27-T27 -> 975000
B29: Kode Barang | F29: Nama Barang | L29: Kts. | P29: @Harga | T29: Diskon | AA29: Total Harga
A30: NOV | B30: 101745 | F30: BOSCH Wiper Advantage 17 inch BA17 | L30: 30 | P30: 54505 | T30: =L30*P30*35% -> 572302.5 | AA30: =L30*P30-T30 -> 1062847.5
A31: NOV | B31: 101746 | F31: BOSCH Wiper Advantage 18 inch BA18 | L31: 30 | P31: 54505 | T31: 95383.75 | AA31: =L31*P31-T31 -> 1539766.2
A32: NOV | B32: 101747 | F32: BOSCH Wiper Advantage 19 inch BA19 | L32: 30 | P32: 57207 | T32: 100112.25 | AA32: =L32*P32-T32 -> 1616097.8
A33: NOV | B33: 101748 | F33: BOSCH Wiper Advantage 20 inch BA20 | L33: 30 | P33: 57207 | T33: 100112.25 | AA33: =L33*P33-T33 -> 1616097.8
A34: NOV | B34: 101769 | F34: BOSCH Wiper Clear Advantage 17 inch BCA17 | L34: 30 | P34: 90090 | T34: 157657.5 | AA34: =L34*P34-T34 -> 2545042.5
A35: NOV | B35: 101788 | F35: BOSCH Wiper Clear Advantage 24 inch BCA24 | L35: 20 | P35: 104955 | T35: 73468.5 | AA35: =L35*P35-T35 -> 2025631.5
B37: Kode Barang | F37: Nama Barang | L37: Kts. | P37: @Harga | T37: Diskon | AA37: Total Harga
A38: JAN | B38: 101847 | F38: BOSCH FUEL FILTER D 6292 | L38: 5 | P38: 206000 | T38: =L38*P38*35% -> 360500 | AA38: =L38*P38-T38 -> 669500
A39: JAN | B39: 101743 | F39: BOSCH Oil Filter O 1042 | L39: 30 | P39: 50000 | T39: =L39*P39*35% -> 525000 | AA39: =L39*P39-T39 -> 975000
A40: JAN | B40: 101736 | F40: BOSCH OIL FILTER O 0126 | L40: 20 | P40: 43000 | T40: =L40*P40*35% -> 301000 | AA40: =L40*P40-T40 -> 559000
A41: JAN | B41: 101782 | F41: BOSCH Oil Filter O 1019 | L41: 20 | P41: 95000 | T41: =L41*P41*35% -> 665000 | AA41: =L41*P41-T41 -> 1235000
B43: Kode Barang | F43: Nama Barang | L43: Kts. | P43: @Harga | T43: Diskon | AA43: Total Harga
A44: FEB | B44: 101776 | F44: BOSCH Fuel Filter D 6100 | L44: 20 | P44: 90000 | T44: =L44*P44*35% -> 630000 | AA44: =L44*P44-T44 -> 1170000
A45: FEB | B45: 101746 | F45: BOSCH Wiper Advantage 18 inch BA18 | L45: 20 | P45: 54505 | T45: =L45*P45*35% -> 381535 | AA45: =L45*P45-T45 -> 708565
A46: FEB | B46: 101741 | F46: BOSCH Wiper Advantage 16 inch BA16 | L46: 30 | P46: 50901 | T46: =L46*P46*35% -> 534460.5 | AA46: =L46*P46-T46 -> 992569.5
A47: FEB | B47: 101758 | F47: BOSCH Wiper Advantage 24 inch BA24 | L47: 20 | P47: 72973 | T47: =L47*P47*35% -> 510811 | AA47: =L47*P47-T47 -> 948649
A48: FEB | B48: 101762 | F48: BOSCH Wiper Clear Advantage 16 inch BCA16 | L48: 30 | P48: 77928 | T48: =L48*P48*35% -> 818244 | AA48: =L48*P48-T48 -> 1519596

Sheet ADS Prima (cleaned)
A1: {=_xlfn.UNIQUE('ADS Prima (agg)'!F1:F41)} -> Nama Barang | B1: Total QTY | C1: Exist in Master
A2: BOSCH Wiper Clear Advantage 14 inch BCA14 | B2: =SUMIF('ADS Prima (agg)'!F:F,'ADS Prima (cleaned)'!A2,'ADS Prima (agg)'!L:L) -> 30 | C2: =_xlfn.XLOOKUP(A2,Master!B:B,Master!B:B,"Hehe") -> BOSCH Wiper Clear Advantage 14 inch BCA14
A3: BOSCH Wiper Clear Advantage 16 inch BCA16 | B3: =SUMIF('ADS Prima (agg)'!F:F,'ADS Prima (cleaned)'!A3,'ADS Prima (agg)'!L:L) -> 60 | C3: =_xlfn.XLOOKUP(A3,Master!B:B,Master!B:B,"Hehe") -> BOSCH Wiper Clear Advantage 16 inch BCA16
A4: BOSCH Wiper Clear Advantage 18 inch BCA18 | B4: =SUMIF('ADS Prima (agg)'!F:F,'ADS Prima (cleaned)'!A4,'ADS Prima (agg)'!L:L) -> 30 | C4: =_xlfn.XLOOKUP(A4,Master!B:B,Master!B:B,"Hehe") -> BOSCH Wiper Clear Advantage 18 inch BCA18
A5: BOSCH Wiper Clear Advantage 19 inch BCA19 | B5: =SUMIF('ADS Prima (agg)'!F:F,'ADS Prima (cleaned)'!A5,'ADS Prima (agg)'!L:L) -> 30 | C5: =_xlfn.XLOOKUP(A5,Master!B:B,Master!B:B,"Hehe") -> BOSCH Wiper Clear Advantage 19 inch BCA19
A6: BOSCH Wiper Clear Advantage 20 inch BCA20 | B6: =SUMIF('ADS Prima (agg)'!F:F,'ADS Prima (cleaned)'!A6,'ADS Prima (agg)'!L:L) -> 30 | C6: =_xlfn.XLOOKUP(A6,Master!B:B,Master!B:B,"Hehe") -> BOSCH Wiper Clear Advantage 20 inch BCA20
A7: BOSCH Wiper Clear Advantage 21 inch BCA21 | B7: =SUMIF('ADS Prima (agg)'!F:F,'ADS Prima (cleaned)'!A7,'ADS Prima (agg)'!L:L) -> 30 | C7: =_xlfn.XLOOKUP(A7,Master!B:B,Master!B:B,"Hehe") -> BOSCH Wiper Clear Advantage 21 inch BCA21
A8: BOSCH Wiper Clear Advantage 22 inch BCA22 | B8: =SUMIF('ADS Prima (agg)'!F:F,'ADS Prima (cleaned)'!A8,'ADS Prima (agg)'!L:L) -> 30 | C8: =_xlfn.XLOOKUP(A8,Master!B:B,Master!B:B,"Hehe") -> BOSCH Wiper Clear Advantage 22 inch BCA22
A9: BOSCH Wiper Clear Advantage 24 inch BCA24 | B9: =SUMIF('ADS Prima (agg)'!F:F,'ADS Prima (cleaned)'!A9,'ADS Prima (agg)'!L:L) -> 50 | C9: =_xlfn.XLOOKUP(A9,Master!B:B,Master!B:B,"Hehe") -> BOSCH Wiper Clear Advantage 24 inch BCA24
A10: BOSCH Wiper Clear Advantage 26 inch BCA26 | B10: =SUMIF('ADS Prima (agg)'!F:F,'ADS Prima (cleaned)'!A10,'ADS Prima (agg)'!L:L) -> 30 | C10: =_xlfn.XLOOKUP(A10,Master!B:B,Master!B:B,"Hehe") -> BOSCH Wiper Clear Advantage 26 inch BCA26
A11: BOSCH Wiper Advantage 14 inch BA14 | B11: =SUMIF('ADS Prima (agg)'!F:F,'ADS Prima (cleaned)'!A11,'ADS Prima (agg)'!L:L) -> 30 | C11: =_xlfn.XLOOKUP(A11,Master!B:B,Master!B:B,"Hehe") -> BOSCH Wiper Advantage 14 inch BA14
A12: BOSCH Wiper Advantage 16 inch BA16 | B12: =SUMIF('ADS Prima (agg)'!F:F,'ADS Prima (cleaned)'!A12,'ADS Prima (agg)'!L:L) -> 60 | C12: =_xlfn.XLOOKUP(A12,Master!B:B,Master!B:B,"Hehe") -> BOSCH Wiper Advantage 16 inch BA16
A13: BOSCH Wiper Advantage 21 inch BA21 | B13: =SUMIF('ADS Prima (agg)'!F:F,'ADS Prima (cleaned)'!A13,'ADS Prima (agg)'!L:L) -> 30 | C13: =_xlfn.XLOOKUP(A13,Master!B:B,Master!B:B,"Hehe") -> BOSCH Wiper Advantage 21 inch BA21
... A22: BOSCH Oil Filter O 1042 | B22: =SUMIF('ADS Prima (agg)'!F:F,'ADS Prima (cleaned)'!A22,'ADS Prima (agg)'!L:L) -> 100 | C22: =_xlfn.XLOOKUP(A22,Master!B:B,Master!B:B,"Hehe") -> BOSCH Oil Filter O 1042
A23: 0 | B23: =SUMIF('ADS Prima (agg)'!F:F,'ADS Prima (cleaned)'!A23,'ADS Prima (agg)'!L:L) -> 0 | C23: =_xlfn.XLOOKUP(A23,Master!B:B,Master!B:B,"Hehe") -> Hehe
A24: BOSCH Wiper Advantage 17 inch BA17 | B24: =SUMIF('ADS Prima (agg)'!F:F,'ADS Prima (cleaned)'!A24,'ADS Prima (agg)'!L:L) -> 30 | C24: =_xlfn.XLOOKUP(A24,Master!B:B,Master!B:B,"Hehe") -> BOSCH Wiper Advantage 17 inch BA17
A25: BOSCH Wiper Advantage 18 inch BA18 | B25: =SUMIF('ADS Prima (agg)'!F:F,'ADS Prima (cleaned)'!A25,'ADS Prima (agg)'!L:L) -> 50 | C25: =_xlfn.XLOOKUP(A25,Master!B:B,Master!B:B,"Hehe") -> BOSCH Wiper Advantage 18 inch BA18
A26: BOSCH Wiper Advantage 19 inch BA19 | B26: =SUMIF('ADS Prima (agg)'!F:F,'ADS Prima (cleaned)'!A26,'ADS Prima (agg)'!L:L) -> 30 | C26: =_xlfn.XLOOKUP(A26,Master!B:B,Master!B:B,"Hehe") -> BOSCH Wiper Advantage 19 inch BA19
A27: BOSCH Wiper Advantage 20 inch BA20 | B27: =SUMIF('ADS Prima (agg)'!F:F,'ADS Prima (cleaned)'!A27,'ADS Prima (agg)'!L:L) -> 30 | C27: =_xlfn.XLOOKUP(A27,Master!B:B,Master!B:B,"Hehe") -> BOSCH Wiper Advantage 20 inch BA20
A28: BOSCH Wiper Clear Advantage 17 inch BCA17 | B28: =SUMIF('ADS Prima (agg)'!F:F,'ADS Prima (cleaned)'!A28,'ADS Prima (agg)'!L:L) -> 30 | C28: =_xlfn.XLOOKUP(A28,Master!B:B,Master!B:B,"Hehe") -> BOSCH Wiper Clear Advantage 17 inch BCA17

Sheet Auto Mekanika (agg)
B1: Kode Barang | F1: Nama Barang | L1: Kts. | P1: @Harga | T1: Diskon | AA1: Total Harga
A2: NOV | B2: 102131 | F2: BOSCH Battery MF Blue 55D23L 12V-60Ah | L2: 5 | P2: 880080 | T2: =L2*P2*35% -> 1540140 | AA2: =L2*P2-T2 -> 2860260
A3: NOV | B3: 102134 | F3: BOSCH Battery MF Blue NS40ZL 40B19L 12V | L3: 5 | P3: 617520 | T3: =L3*P3*35% -> 1080660 | AA3: =L3*P3-T3 -> 2006940
A4: NOV | B4: 102133 | F4: BOSCH Battery MF Blue NS40Z 40B19R 12V | L4: 5 | P4: 617520 | T4: =L4*P4*35% -> 1080660 | AA4: =L4*P4-T4 -> 2006940
A5: NOV | B5: 101741 | F5: BOSCH Wiper Advantage 16 inch BA16 | L5: 10 | P5: 33086 | T5: =L5*P5*35% -> 115801 | AA5: =L5*P5-T5 -> 215059
A6: NOV | B6: 101758 | F6: BOSCH Wiper Advantage 24 inch BA24 | L6: 10 | P6: 47432 | T6: =L6*P6*35% -> 166012 | AA6: =L6*P6-T6 -> 308308
B8: Kode Barang | F8: Nama Barang | L8: Kts. | P8: @Harga | T8: Diskon | AA8: Total Harga
A9: NOV | B9: 109885 | F9: BOSCH Battery MF Blue NX100-S6L 55B24L 12V-45Ah | L9: 5 | P9: 1175100 | T9: =L9*P9*35% -> 2056425 | AA9: =L9*P9-T9 -> 3819075
A10: NOV | B10: 109886 | F10: BOSCH Battery MF Blue NX100-S6 55B24R 12V-45Ah | L10: 5 | P10: 1175100 | T10: =L10*P10*35% -> 2056425 | AA10: =L10*P10-T10 -> 3819075
A11: NOV | B11: 101765 | F11: BOSCH Wiper-Rear 429/Lock 2 12 inch H307 | L11: 10 | P11: 86486 | T11: =L11*P11*35% -> 302701 | AA11: =L11*P11-T11 -> 562159
A12: NOV | B12: 101785 | F12: BOSCH Wiper-Rear 432/Lock 3 12 inch H306 | L12: 5 | P12: 101802 | T12: =L12*P12*35% -> 178153.5 | AA12: =L12*P12-T12 -> 330856.5
B14: Kode Barang | F14: Nama Barang | L14: Kts. | P14: @Harga | T14: Diskon | AA14: Total Harga
A15: DEC | B15: 102134 | F15: BOSCH Battery MF Blue NS40ZL 40B19L 12V | L15: 4 | P15: 1029200 | T15: =L15*P15*35% -> 1440880 | AA15: =L15*P15-T15 -> 2675920
A16: DEC | B16: 102133 | F16: BOSCH Battery MF Blue NS40Z 40B19R 12V | L16: 4 | P16: 1029200 | T16: =L16*P16*35% -> 1440880 | AA16: =L16*P16-T16 -> 2675920
A17: DEC | B17: 101746 | F17: BOSCH Wiper Advantage 18 inch BA18 | L17: 10 | P17: 54505 | T17: =L17*P17*35% -> 190767.5 | AA17: =L17*P17-T17 -> 354282.5
A18: DEC | B18: 101752 | F18: BOSCH Wiper Advantage 21 inch BA21 | L18: 10 | P18: 64414 | T18: =L18*P18*35% -> 225449 | AA18: =L18*P18-T18 -> 418691
A19: DEC | B19: 109883 | F19: BOSCH Battery MF Blue NX11005 80D26R 12V-70Ah | L19: 4 | P19: 1695300 | T19: =L19*P19*35% -> 2373420 | AA19: =L19*P19-T19 -> 4407780
A20: DEC | B20: 101724 | F20: BOSCH Light Bulb P21/5W 12V 21W/5W -BAY15d Auxiliary | L20: 30 | P20: 6200 | T20: =L20*P20*35% -> 65100 | AA20: =L20*P20-T20 -> 120900
A21: DEC | B21: 110671 | F21: BOSCH Light Bulb P21W 24V 21W -BA15s ECO Auxiliary | L21: 30 | P21: 5000 | T21: =L21*P21*35% -> 52500 | AA21: =L21*P21-T21 -> 97500
A22: DEC | B22: 110657 | F22: BOSCH Light Bulb H4 12V 60/55W -P43t ECO | L22: 20 | P22: 28800 | T22: =L22*P22*35% -> 201600 | AA22: =L22*P22-T22 -> 374400
A23: DEC | B23: 102047 | F23: BOSCH Light Bulb W16W 12V 16W -W2,1x9,5d ECO Auxiliary | L23: 20 | P23: 6000 | T23: =L23*P23*35% -> 42000 | AA23: =L23*P23-T23 -> 78000
B25: Kode Barang | F25: Nama Barang | L25: Kts. | P25: @Harga | T25: Diskon | AA25: Total Harga
A26: JAN | B26: 102134 | F26: BOSCH Battery MF Blue NS40ZL 40B19L 12V | L26: 5 | P26: 1029200 | T26: =L26*P26*35% -> 1801100 | AA26: =L26*P26-T26 -> 3344900
B28: Kode Barang | F28: Nama Barang | L28: Kts. | P28: @Harga | T28: Diskon | AA28: Total Harga
A29: JAN | B29: 109886 | F29: BOSCH Battery MF Blue NX100-S6 55B24R 12V-45Ah | L29: 5 | P29: 1175100 | T29: =L29*P29*35% -> 2056425 | AA29: =L29*P29-T29 -> 3819075
A30: JAN | B30: 102131 | F30: BOSCH Battery MF Blue 55D23L 12V-60Ah | L30: 5 | P30: 1466800 | T30: =L30*P30*35% -> 2566900 | AA30: =L30*P30-T30 -> 4767100
A31: JAN | B31: 108122 | F31: BOSCH Battery MF Blue 55559 12V-55Ah | L31: 5 | P31: 1667700 | T31: =L31*P31*35% -> 2918475 | AA31: =L31*P31-T31 -> 5420025
B35: Kode Barang | F35: Nama Barang | L35: Kts. | P35: @Harga | T35: Diskon | AA35: Total Harga
A36: FEB | B36: 109883 | F36: BOSCH Battery MF Blue NX11005 80D26R 12V-70Ah | L36: 4 | P36: 1695300 | T36: =L36*P36*35% -> 2373420 | AA36: =L36*P36-T36 -> 4407780
A37: FEB | B37: 101741 | F37: BOSCH Wiper Advantage 16 inch BA16 | L37: 10 | P37: 50901 | T37: =L37*P37*35% -> 178153.5 | AA37: =L37*P37-T37 -> 330856.5
A38: FEB | B38: 101746 | F38: BOSCH Wiper Advantage 18 inch BA18 | L38: 10 | P38: 54505 | T38: =L38*P38*35% -> 190767.5 | AA38: =L38*P38-T38 -> 354282.5
B40: Kode Barang | F40: Nama Barang | L40: Kts. | P40: @Harga | T40: Diskon | AA40: Total Harga
A41: FEB | B41: 109886 | F41: BOSCH Battery MF Blue NX100-S6 55B24R 12V-45Ah | L41: 5 | P41: 1175100 | T41: =L41*P41*35% -> 2056425 | AA41: =L41*P41-T41 -> 3819075

Sheet Auto Mekanika (cleaned)
A1: {=_xlfn.UNIQUE('Auto Mekanika (agg)'!F:F)} -> Nama Barang | B1: Total QTY | C1: Exist in Master
A2: BOSCH Battery MF Blue 55D23L 12V-60Ah | B2: =SUMIF('Auto Mekanika (agg)'!F:F,'Auto Mekanika (cleaned)'!A2,'Auto Mekanika (agg)'!L:L) -> 10 | C2: =_xlfn.XLOOKUP(A2,Master!B:B,Master!B:B,"Hehe") -> BOSCH Battery MF Blue 55D23L 12V-60Ah
A3: BOSCH Battery MF Blue NS40ZL 40B19L 12V | B3: =SUMIF('Auto Mekanika (agg)'!F:F,'Auto Mekanika (cleaned)'!A3,'Auto Mekanika (agg)'!L:L) -> 14 | C3: =_xlfn.XLOOKUP(A3,Master!B:B,Master!B:B,"Hehe") -> BOSCH Battery MF Blue NS40ZL 40B19L 12V
A4: BOSCH Battery MF Blue NS40Z 40B19R 12V | B4: =SUMIF('Auto Mekanika (agg)'!F:F,'Auto Mekanika (cleaned)'!A4,'Auto Mekanika (agg)'!L:L) -> 9 | C4: =_xlfn.XLOOKUP(A4,Master!B:B,Master!B:B,"Hehe") -> BOSCH Battery MF Blue NS40Z 40B19R 12V
A5: BOSCH Wiper Advantage 16 inch BA16 | B5: =SUMIF('Auto Mekanika (agg)'!F:F,'Auto Mekanika (cleaned)'!A5,'Auto Mekanika (agg)'!L:L) -> 20 | C5: =_xlfn.XLOOKUP(A5,Master!B:B,Master!B:B,"Hehe") -> BOSCH Wiper Advantage 16 inch BA16
A6: BOSCH Wiper Advantage 24 inch BA24 | B6: =SUMIF('Auto Mekanika (agg)'!F:F,'Auto Mekanika (cleaned)'!A6,'Auto Mekanika (agg)'!L:L) -> 10 | C6: =_xlfn.XLOOKUP(A6,Master!B:B,Master!B:B,"Hehe") -> BOSCH Wiper Advantage 24 inch BA24
A7: 0 | B7: =SUMIF('Auto Mekanika (agg)'!F:F,'Auto Mekanika (cleaned)'!A7,'Auto Mekanika (agg)'!L:L) -> 0 | C7: =_xlfn.XLOOKUP(A7,Master!B:B,Master!B:B,"Hehe") -> Hehe
A8: BOSCH Battery MF Blue NX100-S6L 55B24L 12V-45Ah | B8: =SUMIF('Auto Mekanika (agg)'!F:F,'Auto Mekanika (cleaned)'!A8,'Auto Mekanika (agg)'!L:L) -> 5 | C8: =_xlfn.XLOOKUP(A8,Master!B:B,Master!B:B,"Hehe") -> BOSCH Battery MF Blue NX100-S6L 55B24L 12V-45Ah
A9: BOSCH Battery MF Blue NX100-S6 55B24R 12V-45Ah | B9: =SUMIF('Auto Mekanika (agg)'!F:F,'Auto Mekanika (cleaned)'!A9,'Auto Mekanika (agg)'!L:L) -> 15 | C9: =_xlfn.XLOOKUP(A9,Master!B:B,Master!B:B,"Hehe") -> BOSCH Battery MF Blue NX100-S6 55B24R 12V-45Ah
A10: BOSCH Wiper-Rear 429/Lock 2 12 inch H307 | B10: =SUMIF('Auto Mekanika (agg)'!F:F,'Auto Mekanika (cleaned)'!A10,'Auto Mekanika (agg)'!L:L) -> 10 | C10: =_xlfn.XLOOKUP(A10,Master!B:B,Master!B:B,"Hehe") -> BOSCH Wiper-Rear 429/Lock 2 12 inch H307
A11: BOSCH Wiper-Rear 432/Lock 3 12 inch H306 | B11: =SUMIF('Auto Mekanika (agg)'!F:F,'Auto Mekanika (cleaned)'!A11,'Auto Mekanika (agg)'!L:L) -> 5 | C11: =_xlfn.XLOOKUP(A11,Master!B:B,Master!B:B,"Hehe") -> BOSCH Wiper-Rear 432/Lock 3 12 inch H306
A12: BOSCH Wiper Advantage 18 inch BA18 | B12: =SUMIF('Auto Mekanika (agg)'!F:F,'Auto Mekanika (cleaned)'!A12,'Auto Mekanika (agg)'!L:L) -> 20 | C12: =_xlfn.XLOOKUP(A12,Master!B:B,Master!B:B,"Hehe") -> BOSCH Wiper Advantage 18 inch BA18
A13: BOSCH Wiper Advantage 21 inch BA21 | B13: =SUMIF('Auto Mekanika (agg)'!F:F,'Auto Mekanika (cleaned)'!A13,'Auto Mekanika (agg)'!L:L) -> 10 | C13: =_xlfn.XLOOKUP(A13,Master!B:B,Master!B:B,"Hehe") -> BOSCH Wiper Advantage 21 inch BA21
A14: BOSCH Battery MF Blue NX11005 80D26R 12V-70Ah | B14: =SUMIF('Auto Mekanika (agg)'!F:F,'Auto Mekanika (cleaned)'!A14,'Auto Mekanika (agg)'!L:L) -> 8 | C14: =_xlfn.XLOOKUP(A14,Master!B:B,Master!B:B,"Hehe") -> BOSCH Battery MF Blue NX11005 80D26R 12V-70Ah
A15: BOSCH Light Bulb P21/5W 12V 21W/5W -BAY15d Auxiliary | B15: =SUMIF('Auto Mekanika (agg)'!F:F,'Auto Mekanika (cleaned)'!A15,'Auto Mekanika (agg)'!L:L) -> 30 | C15: =_xlfn.XLOOKUP(A15,Master!B:B,Master!B:B,"Hehe") -> BOSCH Light Bulb P21/5W 12V 21W/5W -BAY15d Auxiliary
A16: BOSCH Light Bulb P21W 24V 21W -BA15s ECO Auxiliary | B16: =SUMIF('Auto Mekanika (agg)'!F:F,'Auto Mekanika (cleaned)'!A16,'Auto Mekanika (agg)'!L:L) -> 30 | C16: =_xlfn.XLOOKUP(A16,Master!B:B,Master!B:B,"Hehe") -> BOSCH Light Bulb P21W 24V 21W -BA15s ECO Auxiliary
A17: BOSCH Light Bulb H4 12V 60/55W -P43t ECO | B17: =SUMIF('Auto Mekanika (agg)'!F:F,'Auto Mekanika (cleaned)'!A17,'Auto Mekanika (agg)'!L:L) -> 20 | C17: =_xlfn.XLOOKUP(A17,Master!B:B,Master!B:B,"Hehe") -> BOSCH Light Bulb H4 12V 60/55W -P43t ECO
A18: BOSCH Light Bulb W16W 12V 16W -W2,1x9,5d ECO Auxiliary | B18: =SUMIF('Auto Mekanika (agg)'!F:F,'Auto Mekanika (cleaned)'!A18,'Auto Mekanika (agg)'!L:L) -> 20 | C18: =_xlfn.XLOOKUP(A18,Master!B:B,Master!B:B,"Hehe") -> BOSCH Light Bulb W16W 12V 16W -W2,1x9,5d ECO Auxiliary
A19: BOSCH Battery MF Blue 55559 12V-55Ah | B19: =SUMIF('Auto Mekanika (agg)'!F:F,'Auto Mekanika (cleaned)'!A19,'Auto Mekanika (agg)'!L:L) -> 5 | C19: =_xlfn.XLOOKUP(A19,Master!B:B,Master!B:B,"Hehe") -> BOSCH Battery MF Blue 55559 12V-55Ah
C20: =_xlfn.XLOOKUP(A20,Master!B:B,Master!B:B,"Hehe") -> 0
C21: =_xlfn.XLOOKUP(A21,Master!B:B,Master!B:B,"Hehe") -> 0

Sheet Bengkel Multi Var (agg)
B1: Kode Barang | F1: Nama Barang | L1: Kts. | P1: @Harga | T1: Diskon | AA1: Total Harga
A2: DEC | B2: 101740 | F2: BOSCH Wiper Advantage 14 inch BA14 | L2: 50 | P2: 50901 | T2: =L2*P2*35% -> 890767.5 | AA2: =L2*P2-T2 -> 1654282.5
A3: DEC | B3: 101741 | F3: BOSCH Wiper Advantage 16 inch BA16 | L3: 50 | P3: 50901 | T3: =L3*P3*35% -> 890767.5 | AA3: =L3*P3-T3 -> 1654282.5
A4: DEC | B4: 101746 | F4: BOSCH Wiper Advantage 18 inch BA18 | L4: 50 | P4: 54505 | T4: =L4*P4*35% -> 953837.5 | AA4: =L4*P4-T4 -> 1771412.5
A5: DEC | B5: 101748 | F5: BOSCH Wiper Advantage 20 inch BA20 | L5: 40 | P5: 57207 | T5: =L5*P5*35% -> 800898 | AA5: =L5*P5-T5 -> 1487382
A6: DEC | B6: 101759 | F6: BOSCH Wiper Advantage 22 inch BA22 | L6: 40 | P6: 72973 | T6: =L6*P6*35% -> 1021622 | AA6: =L6*P6-T6 -> 1897298
A7: DEC | B7: 101758 | F7: BOSCH Wiper Advantage 24 inch BA24 | L7: 30 | P7: 72973 | T7: =L7*P7*35% -> 766216.5 | AA7: =L7*P7-T7 -> 1422973.5
A8: DEC | B8: 101777 | F8: BOSCH Wiper Advantage 26 inch BA26 | L8: 20 | P8: 94595 | T8: =L8*P8*35% -> 662165 | AA8: =L8*P8-T8 -> 1229735
A9: DEC | B9: 101761 | F9: BOSCH Wiper Clear Advantage 14 inch BCA14 | L9: 20 | P9: 77928 | T9: =L9*P9*35% -> 545496 | AA9: =L9*P9-T9 -> 1013064
A10: DEC | B10: 101762 | F10: BOSCH Wiper Clear Advantage 16 inch BCA16 | L10: 20 | P10: 77928 | T10: =L10*P10*35% -> 545496 | AA10: =L10*P10-T10 -> 1013064
A11: DEC | B11: 101770 | F11: BOSCH Wiper Clear Advantage 18 inch BCA18 | L11: 20 | P11: 90090 | T11: =L11*P11*35% -> 630630 | AA11: =L11*P11-T11 -> 1171170
A12: DEC | B12: 101779 | F12: BOSCH Wiper Clear Advantage 20 inch BCA20 | L12: 20 | P12: 96396 | T12: =L12*P12*35% -> 674772 | AA12: =L12*P12-T12 -> 1253148
A13: DEC | B13: 101743 | F13: BOSCH Oil Filter O 1042 | L13: 40 | P13: 50000 | T13: =L13*P13*35% -> 700000 | AA13: =L13*P13-T13 -> 1300000
... A18: DEC | B18: 109790 | F18: BOSCH Oil Filter O 1066 | L18: 20 | P18: 72500 | T18: =L18*P18*35% -> 507500 | AA18: =L18*P18-T18 -> 942500
B20: Kode Barang | F20: Nama Barang | L20: Kts. | P20: @Harga | T20: Diskon | AA20: Total Harga
A21: JAN | B21: 101740 | F21: BOSCH Wiper Advantage 14 inch BA14 | L21: 10 | P21: 50901 | T21: =L21*P21*35% -> 178153.5 | AA21: =L21*P21-T21 -> 330856.5
A22: JAN | B22: 101748 | F22: BOSCH Wiper Advantage 20 inch BA20 | L22: 20 | P22: 57207 | T22: =L22*P22*35% -> 400449 | AA22: =L22*P22-T22 -> 743691
A23: JAN | B23: 101758 | F23: BOSCH Wiper Advantage 24 inch BA24 | L23: 20 | P23: 72973 | T23: =L23*P23*35% -> 510811 | AA23: =L23*P23-T23 -> 948649
A24: JAN | B24: 101787 | F24: BOSCH Wiper Clear Advantage 22 inch BCA22 | L24: 20 | P24: 104955 | T24: =L24*P24*35% -> 734685 | AA24: =L24*P24-T24 -> 1364415
A25: JAN | B25: 101788 | F25: BOSCH Wiper Clear Advantage 24 inch BCA24 | L25: 20 | P25: 104955 | T25: =L25*P25*35% -> 734685 | AA25: =L25*P25-T25 -> 1364415
A26: JAN | B26: 101791 | F26: BOSCH Wiper Clear Advantage 26 inch BCA26 | L26: 20 | P26: 110811 | T26: =L26*P26*35% -> 775677 | AA26: =L26*P26-T26 -> 1440543
B29: Kode Barang | F29: Nama Barang | L29: Kts. | P29: @Harga | T29: Diskon | AA29: Total Harga
A30: FEB | B30: 101877 | F30: BOSCH Brake Pad 0986T18190 /BP1620N Front | L30: 4 | P30: 464200 | T30: =L30*P30*35% -> 649880 | AA30: =L30*P30-T30 -> 1206920
A31: FEB | B31: 101797 | F31: BOSCH WHEEL BRAKE CYLINDER WC-T21 | L31: 10 | P31: 144800 | T31: =L31*P31*35% -> 506800 | AA31: =L31*P31-T31 -> 941200
A32: FEB | B32: 101762 | F32: BOSCH Wiper Clear Advantage 16 inch BCA16 | L32: 30 | P32: 77928 | T32: =L32*P32*35% -> 818244 | AA32: =L32*P32-T32 -> 1519596

Sheet Bengkel Multi Var (cleaned)
A1: {=_xlfn.UNIQUE('Bengkel Multi Var (agg)'!F:F)} -> Nama Barang | B1: Total QTY | C1: Exist in Master
A2: BOSCH Wiper Advantage 14 inch BA14 | B2: =SUMIF('Bengkel Multi Var (agg)'!F:F,'Bengkel Multi Var (cleaned)'!A2,'Bengkel Multi Var (agg)'!L:L) -> 60 | C2: =_xlfn.XLOOKUP(A2,Master!B:B,Master!B:B,"Hehe") -> BOSCH Wiper Advantage 14 inch BA14
A3: BOSCH Wiper Advantage 16 inch BA16 | B3: =SUMIF('Bengkel Multi Var (agg)'!F:F,'Bengkel Multi Var (cleaned)'!A3,'Bengkel Multi Var (agg)'!L:L) -> 50 | C3: =_xlfn.XLOOKUP(A3,Master!B:B,Master!B:B,"Hehe") -> BOSCH Wiper Advantage 16 inch BA16
A4: BOSCH Wiper Advantage 18 inch BA18 | B4: =SUMIF('Bengkel Multi Var (agg)'!F:F,'Bengkel Multi Var (cleaned)'!A4,'Bengkel Multi Var (agg)'!L:L) -> 50 | C4: =_xlfn.XLOOKUP(A4,Master!B:B,Master!B:B,"Hehe") -> BOSCH Wiper Advantage 18 inch BA18
A5: BOSCH Wiper Advantage 20 inch BA20 | B5: =SUMIF('Bengkel Multi Var (agg)'!F:F,'Bengkel Multi Var (cleaned)'!A5,'Bengkel Multi Var (agg)'!L:L) -> 60 | C5: =_xlfn.XLOOKUP(A5,Master!B:B,Master!B:B,"Hehe") -> BOSCH Wiper Advantage 20 inch BA20
A6: BOSCH Wiper Advantage 22 inch BA22 | B6: =SUMIF('Bengkel Multi Var (agg)'!F:F,'Bengkel Multi Var (cleaned)'!A6,'Bengkel Multi Var (agg)'!L:L) -> 40 | C6: =_xlfn.XLOOKUP(A6,Master!B:B,Master!B:B,"Hehe") -> BOSCH Wiper Advantage 22 inch BA22
A7: BOSCH Wiper Advantage 24 inch BA24 | B7: =SUMIF('Bengkel Multi Var (agg)'!F:F,'Bengkel Multi Var (cleaned)'!A7,'Bengkel Multi Var (agg)'!L:L) -> 50 | C7: =_xlfn.XLOOKUP(A7,Master!B:B,Master!B:B,"Hehe") -> BOSCH Wiper Advantage 24 inch BA24
A8: BOSCH Wiper Advantage 26 inch BA26 | B8: =SUMIF('Bengkel Multi Var (agg)'!F:F,'Bengkel Multi Var (cleaned)'!A8,'Bengkel Multi Var (agg)'!L:L) -> 20 | C8: =_xlfn.XLOOKUP(A8,Master!B:B,Master!B:B,"Hehe") -> BOSCH Wiper Advantage 26 inch BA26
A9: BOSCH Wiper Clear Advantage 14 inch BCA14 | B9: =SUMIF('Bengkel Multi Var (agg)'!F:F,'Bengkel Multi Var (cleaned)'!A9,'Bengkel Multi Var (agg)'!L:L) -> 20 | C9: =_xlfn.XLOOKUP(A9,Master!B:B,Master!B:B,"Hehe") -> BOSCH Wiper Clear Advantage 14 inch BCA14
A10: BOSCH Wiper Clear Advantage 16 inch BCA16 | B10: =SUMIF('Bengkel Multi Var (agg)'!F:F,'Bengkel Multi Var (cleaned)'!A10,'Bengkel Multi Var (agg)'!L:L) -> 50 | C10: =_xlfn.XLOOKUP(A10,Master!B:B,Master!B:B,"Hehe") -> BOSCH Wiper Clear Advantage 16 inch BCA16
A11: BOSCH Wiper Clear Advantage 18 inch BCA18 | B11: =SUMIF('Bengkel Multi Var (agg)'!F:F,'Bengkel Multi Var (cleaned)'!A11,'Bengkel Multi Var (agg)'!L:L) -> 20 | C11: =_xlfn.XLOOKUP(A11,Master!B:B,Master!B:B,"Hehe") -> BOSCH Wiper Clear Advantage 18 inch BCA18
A12: BOSCH Wiper Clear Advantage 20 inch BCA20 | B12: =SUMIF('Bengkel Multi Var (agg)'!F:F,'Bengkel Multi Var (cleaned)'!A12,'Bengkel Multi Var (agg)'!L:L) -> 20 | C12: =_xlfn.XLOOKUP(A12,Master!B:B,Master!B:B,"Hehe") -> BOSCH Wiper Clear Advantage 20 inch BCA20
A13: BOSCH Oil Filter O 1042 | B13: =SUMIF('Bengkel Multi Var (agg)'!F:F,'Bengkel Multi Var (cleaned)'!A13,'Bengkel Multi Var (agg)'!L:L) -> 40 | C13: =_xlfn.XLOOKUP(A13,Master!B:B,Master!B:B,"Hehe") -> BOSCH Oil Filter O 1042
... A18: BOSCH Oil Filter O 1066 | B18: =SUMIF('Bengkel Multi Var (agg)'!F:F,'Bengkel Multi Var (cleaned)'!A18,'Bengkel Multi Var (agg)'!L:L) -> 20 | C18: =_xlfn.XLOOKUP(A18,Master!B:B,Master!B:B,"Hehe") -> BOSCH Oil Filter O 1066
A19: 0 | B19: =SUMIF('Bengkel Multi Var (agg)'!F:F,'Bengkel Multi Var (cleaned)'!A19,'Bengkel Multi Var (agg)'!L:L) -> 0 | C19: =_xlfn.XLOOKUP(A19,Master!B:B,Master!B:B,"Hehe") -> Hehe
A20: BOSCH Wiper Clear Advantage 22 inch BCA22 | B20: =SUMIF('Bengkel Multi Var (agg)'!F:F,'Bengkel Multi Var (cleaned)'!A20,'Bengkel Multi Var (agg)'!L:L) -> 20 | C20: =_xlfn.XLOOKUP(A20,Master!B:B,Master!B:B,"Hehe") -> BOSCH Wiper Clear Advantage 22 inch BCA22
A21: BOSCH Wiper Clear Advantage 24 inch BCA24 | B21: =SUMIF('Bengkel Multi Var (agg)'!F:F,'Bengkel Multi Var (cleaned)'!A21,'Bengkel Multi Var (agg)'!L:L) -> 20 | C21: =_xlfn.XLOOKUP(A21,Master!B:B,Master!B:B,"Hehe") -> BOSCH Wiper Clear Advantage 24 inch BCA24
A22: BOSCH Wiper Clear Advantage 26 inch BCA26 | B22: =SUMIF('Bengkel Multi Var (agg)'!F:F,'Bengkel Multi Var (cleaned)'!A22,'Bengkel Multi Var (agg)'!L:L) -> 20 | C22: =_xlfn.XLOOKUP(A22,Master!B:B,Master!B:B,"Hehe") -> BOSCH Wiper Clear Advantage 26 inch BCA26

Sheet Drivewell (agg)
B1: Kode Barang | F1: Nama Barang | L1: Kts. | P1: @Harga | T1: Diskon | AA1: Total Harga
A2: NOV | B2: 101737 | F2: BOSCH Oil Filter O 1041 | L2: 20 | P2: 43000 | T2: =L2*P2*35% -> 301000 | AA2: =L2*P2-T2 -> 559000
A3: NOV | B3: 101736 | F3: BOSCH OIL FILTER O 0126 | L3: 20 | P3: 43000 | T3: =L3*P3*35% -> 301000 | AA3: =L3*P3-T3 -> 559000
A4: NOV | B4: 101726 | F4: BOSCH Spark Plug DF7REC2(YR7DC+) - Standard | L4: 30 | P4: 22900 | T4: =L4*P4*35% -> 240450 | AA4: =L4*P4-T4 -> 446550
A5: NOV | B5: 101864 | F5: BOSCH Brake Pad 0986T18178 /BP8178 Front | L5: 20 | P5: 349200 | T5: =L5*P5*35% -> 2444400 | AA5: =L5*P5-T5 -> 4539600
A6: NOV | B6: 101761 | F6: BOSCH Wiper Clear Advantage 14 inch BCA14 | L6: 20 | P6: 50901 | T6: =L6*P6*35% -> 356307 | AA6: =L6*P6-T6 -> 661713
A7: NOV | B7: 101762 | F7: BOSCH Wiper Clear Advantage 16 inch BCA16 | L7: 20 | P7: 50901 | T7: =L7*P7*35% -> 356307 | AA7: =L7*P7-T7 -> 661713
A8: NOV | B8: 101769 | F8: BOSCH Wiper Clear Advantage 17 inch BCA17 | L8: 20 | P8: 54505 | T8: =L8*P8*35% -> 381535 | AA8: =L8*P8-T8 -> 708565
A9: NOV | B9: 101770 | F9: BOSCH Wiper Clear Advantage 18 inch BCA18 | L9: 20 | P9: 54505 | T9: =L9*P9*35% -> 381535 | AA9: =L9*P9-T9 -> 708565
A10: NOV | B10: 101778 | F10: BOSCH Wiper Clear Advantage 19 inch BCA19 | L10: 20 | P10: 57207 | T10: =L10*P10*35% -> 400449 | AA10: =L10*P10-T10 -> 743691
A11: NOV | B11: 101779 | F11: BOSCH Wiper Clear Advantage 20 inch BCA20 | L11: 20 | P11: 57207 | T11: =L11*P11*35% -> 400449 | AA11: =L11*P11-T11 -> 743691
A12: NOV | B12: 101780 | F12: BOSCH Wiper Clear Advantage 21 inch BCA21 | L12: 20 | P12: 64414 | T12: =L12*P12*35% -> 450898 | AA12: =L12*P12-T12 -> 837382
A13: NOV | B13: 101787 | F13: BOSCH Wiper Clear Advantage 22 inch BCA22 | L13: 20 | P13: 72973 | T13: =L13*P13*35% -> 510811 | AA13: =L13*P13-T13 -> 948649
... A17: NOV | B17: 101807 | F17: BOSCH Spark Plug VR8SII30X - Iridium | L17: 8 | P17: 165400 | T17: =L17*P17*35% -> 463120 | AA17: =L17*P17-T17 -> 860080
B19: Kode Barang | F19: Nama Barang | L19: Kts. | P19: @Harga | T19: Diskon | AA19: Total Harga
A20: JAN | B20: 101814 | F20: BOSCH HORN EC12C STRIDER | L20: 8 | P20: 184000 | T20: =L20*P20*35% -> 515200 | AA20: =L20*P20-T20 -> 956800
A21: JAN | B21: 101727 | F21: BOSCH Spark Plug K6TC0R(FR8DCX+) - Standard | L21: 30 | P21: 28500 | T21: =L21*P21*35% -> 299250 | AA21: =L21*P21-T21 -> 555750
A22: JAN | B22: 110657 | F22: BOSCH Light Bulb H4 12V 60/55W -P43t ECO | L22: 20 | P22: 28800 | T22: =L22*P22*35% -> 201600 | AA22: =L22*P22-T22 -> 374400
A23: JAN | B23: 101725 | F23: BOSCH Light Bulb P21W 12V 21W -BA15s Auxiliary | L23: 20 | P23: 6300 | T23: =L23*P23*35% -> 44100 | AA23: =L23*P23-T23 -> 81900
B27: Kode Barang | F27: Nama Barang | L27: Kts. | P27: @Harga | T27: Diskon | AA27: Total Harga
A28: FEB | B28: 101807 | F28: BOSCH Spark Plug VR8SII30X - Iridium | L28: 30 | P28: 165400 | T28: =L28*P28*35% -> 1736700 | AA28: =L28*P28-T28 -> 3225300
B31: Kode Barang | F31: Nama Barang | L31: Kts. | P31: @Harga | T31: Diskon | AA31: Total Harga
A32: FEB | B32: 110659 | F32: BOSCH Light Bulb H8 12V 35W -PGJ19-1 ECO | L32: 20 | P32: 87000 | T32: =L32*P32*35% -> 609000 | AA32: =L32*P32-T32 -> 1131000
A33: FEB | B33: 110660 | F33: BOSCH Light Bulb H11 12V 55W -PGJ19-2 ECO | L33: 20 | P33: 85700 | T33: =L33*P33*35% -> 599900 | AA33: =L33*P33-T33 -> 1114100
A34: FEB | B34: 102043 | F34: BOSCH Light Bulb H16 12V 19W -PGJ19-3 Standard-Clear | L34: 20 | P34: 110500 | T34: =L34*P34*35% -> 773500 | AA34: =L34*P34-T34 -> 1436500
A35: FEB | B35: 110645 | F35: BOSCH Light Bulb H4 24V 100/90W -P43t Trucklight | L35: 20 | P35: 40000 | T35: =L35*P35*35% -> 280000 | AA35: =L35*P35-T35 -> 520000
A36: FEB | B36: 110680 | F36: BOSCH Light Bulb H11 24V 70W -PGJ19-2 Trucklight | L36: 20 | P36: 89000 | T36: =L36*P36*35% -> 623000 | AA36: =L36*P36-T36 -> 1157000
A37: FEB | B37: 110671 | F37: BOSCH Light Bulb P21W 24V 21W -BA15s ECO Auxiliary | L37: 20 | P37: 8200 | T37: =L37*P37*35% -> 57400 | AA37: =L37*P37-T37 -> 106600

Sheet Drivewell (cleaned)
A1: {=_xlfn.UNIQUE('Drivewell (agg)'!F1:F23)} -> Nama Barang | B1: Total QTY | C1: Exist in Master
A2: BOSCH Oil Filter O 1041 | B2: =SUMIF('Drivewell (agg)'!F:F,'Drivewell (cleaned)'!A2,'Drivewell (agg)'!L:L) -> 20 | C2: =_xlfn.XLOOKUP(A2,Master!B:B,Master!B:B,"Hehe") -> BOSCH Oil Filter O 1041
A3: BOSCH OIL FILTER O 0126 | B3: =SUMIF('Drivewell (agg)'!F:F,'Drivewell (cleaned)'!A3,'Drivewell (agg)'!L:L) -> 20 | C3: =_xlfn.XLOOKUP(A3,Master!B:B,Master!B:B,"Hehe") -> BOSCH Oil Filter O 0126
A4: BOSCH Spark Plug DF7REC2(YR7DC+) - Standard | B4: =SUMIF('Drivewell (agg)'!F:F,'Drivewell (cleaned)'!A4,'Drivewell (agg)'!L:L) -> 30 | C4: =_xlfn.XLOOKUP(A4,Master!B:B,Master!B:B,"Hehe") -> BOSCH Spark Plug DF7REC2(YR7DC+) - Standard
A5: BOSCH Brake Pad 0986T18178 /BP8178 Front | B5: =SUMIF('Drivewell (agg)'!F:F,'Drivewell (cleaned)'!A5,'Drivewell (agg)'!L:L) -> 20 | C5: =_xlfn.XLOOKUP(A5,Master!B:B,Master!B:B,"Hehe") -> BOSCH Brake Pad 0986T18178 /BP8178 Front
A6: BOSCH Wiper Clear Advantage 14 inch BCA14 | B6: =SUMIF('Drivewell (agg)'!F:F,'Drivewell (cleaned)'!A6,'Drivewell (agg)'!L:L) -> 20 | C6: =_xlfn.XLOOKUP(A6,Master!B:B,Master!B:B,"Hehe") -> BOSCH Wiper Clear Advantage 14 inch BCA14
A7: BOSCH Wiper Clear Advantage 16 inch BCA16 | B7: =SUMIF('Drivewell (agg)'!F:F,'Drivewell (cleaned)'!A7,'Drivewell (agg)'!L:L) -> 20 | C7: =_xlfn.XLOOKUP(A7,Master!B:B,Master!B:B,"Hehe") -> BOSCH Wiper Clear Advantage 16 inch BCA16
A8: BOSCH Wiper Clear Advantage 17 inch BCA17 | B8: =SUMIF('Drivewell (agg)'!F:F,'Drivewell (cleaned)'!A8,'Drivewell (agg)'!L:L) -> 20 | C8: =_xlfn.XLOOKUP(A8,Master!B:B,Master!B:B,"Hehe") -> BOSCH Wiper Clear Advantage 17 inch BCA17
A9: BOSCH Wiper Clear Advantage 18 inch BCA18 | B9: =SUMIF('Drivewell (agg)'!F:F,'Drivewell (cleaned)'!A9,'Drivewell (agg)'!L:L) -> 20 | C9: =_xlfn.XLOOKUP(A9,Master!B:B,Master!B:B,"Hehe") -> BOSCH Wiper Clear Advantage 18 inch BCA18
A10: BOSCH Wiper Clear Advantage 19 inch BCA19 | B10: =SUMIF('Drivewell (agg)'!F:F,'Drivewell (cleaned)'!A10,'Drivewell (agg)'!L:L) -> 20 | C10: =_xlfn.XLOOKUP(A10,Master!B:B,Master!B:B,"Hehe") -> BOSCH Wiper Clear Advantage 19 inch BCA19
A11: BOSCH Wiper Clear Advantage 20 inch BCA20 | B11: =SUMIF('Drivewell (agg)'!F:F,'Drivewell (cleaned)'!A11,'Drivewell (agg)'!L:L) -> 20 | C11: =_xlfn.XLOOKUP(A11,Master!B:B,Master!B:B,"Hehe") -> BOSCH Wiper Clear Advantage 20 inch BCA20
A12: BOSCH Wiper Clear Advantage 21 inch BCA21 | B12: =SUMIF('Drivewell (agg)'!F:F,'Drivewell (cleaned)'!A12,'Drivewell (agg)'!L:L) -> 20 | C12: =_xlfn.XLOOKUP(A12,Master!B:B,Master!B:B,"Hehe") -> BOSCH Wiper Clear Advantage 21 inch BCA21
A13: BOSCH Wiper Clear Advantage 22 inch BCA22 | B13: =SUMIF('Drivewell (agg)'!F:F,'Drivewell (cleaned)'!A13,'Drivewell (agg)'!L:L) -> 20 | C13: =_xlfn.XLOOKUP(A13,Master!B:B,Master!B:B,"Hehe") -> BOSCH Wiper Clear Advantage 22 inch BCA22
... A17: BOSCH Spark Plug VR8SII30X - Iridium | B17: =SUMIF('Drivewell (agg)'!F:F,'Drivewell (cleaned)'!A17,'Drivewell (agg)'!L:L) -> 38 | C17: =_xlfn.XLOOKUP(A17,Master!B:B,Master!B:B,"Hehe") -> BOSCH Spark Plug VR8SII30X - Iridium
A18: 0 | B18: =SUMIF('Drivewell (agg)'!F:F,'Drivewell (cleaned)'!A18,'Drivewell (agg)'!L:L) -> 0 | C18: =_xlfn.XLOOKUP(A18,Master!B:B,Master!B:B,"Hehe") -> Hehe
A19: BOSCH HORN EC12C STRIDER | B19: =SUMIF('Drivewell (agg)'!F:F,'Drivewell (cleaned)'!A19,'Drivewell (agg)'!L:L) -> 8 | C19: =_xlfn.XLOOKUP(A19,Master!B:B,Master!B:B,"Hehe") -> BOSCH HORN EC12C STRIDER
A20: BOSCH Spark Plug K6TC0R(FR8DCX+) - Standard | B20: =SUMIF('Drivewell (agg)'!F:F,'Drivewell (cleaned)'!A20,'Drivewell (agg)'!L:L) -> 30 | C20: =_xlfn.XLOOKUP(A20,Master!B:B,Master!B:B,"Hehe") -> BOSCH Spark Plug K6TC0R(FR8DCX+) - Standard
A21: BOSCH Light Bulb H4 12V 60/55W -P43t ECO | B21: =SUMIF('Drivewell (agg)'!F:F,'Drivewell (cleaned)'!A21,'Drivewell (agg)'!L:L) -> 20 | C21: =_xlfn.XLOOKUP(A21,Master!B:B,Master!B:B,"Hehe") -> BOSCH Light Bulb H4 12V 60/55W -P43t ECO
A22: BOSCH Light Bulb P21W 12V 21W -BA15s Auxiliary | B22: =SUMIF('Drivewell (agg)'!F:F,'Drivewell (cleaned)'!A22,'Drivewell (agg)'!L:L) -> 20 | C22: =_xlfn.XLOOKUP(A22,Master!B:B,Master!B:B,"Hehe") -> BOSCH Light Bulb P21W 12V 21W -BA15s Auxiliary

Sheet CV Sun (agg)
B1: Kode Barang | F1: Nama Barang | L1: Kts. | P1: @Harga | T1: Diskon | AA1: Total Harga
A2: DEC | B2: 101737 | F2: BOSCH Oil Filter O 1041 | L2: 50 | P2: 43000 | T2: =L2*P2*35% -> 752500 | AA2: =L2*P2-T2 -> 1397500
A3: DEC | B3: 101736 | F3: BOSCH OIL FILTER O 0126 | L3: 50 | P3: 43000 | T3: =L3*P3*35% -> 752500 | AA3: =L3*P3-T3 -> 1397500
A4: DEC | F4: BOSCH Oil Filter O 0220 | L4: 50 | P4: 40800 | T4: =L4*P4*35% -> 714000 | AA4: =L4*P4-T4 -> 1326000
A5: DEC | F5: BOSCH Wiper Clear Advantage 14 inch BCA14 | L5: 40 | P5: 77928 | T5: =L5*P5*35% -> 1090992 | AA5: =L5*P5-T5 -> 2026128
A6: DEC | F6: BOSCH Wiper Clear Advantage 16 inch BCA16 | L6: 40 | P6: 77928 | T6: =L6*P6*35% -> 1090992 | AA6: =L6*P6-T6 -> 2026128
A7: DEC | F7: BOSCH Wiper Clear Advantage 18 inch BCA18 | L7: 40 | P7: 90090 | T7: =L7*P7*35% -> 1261260 | AA7: =L7*P7-T7 -> 2342340
A8: DEC | F8: BOSCH Wiper Clear Advantage 19 inch BCA19 | L8: 40 | P8: 96396 | T8: =L8*P8*35% -> 1349544 | AA8: =L8*P8-T8 -> 2506296
A9: DEC | F9: BOSCH Wiper Clear Advantage 20 inch BCA20 | L9: 40 | P9: 96396 | T9: =L9*P9*35% -> 1349544 | AA9: =L9*P9-T9 -> 2506296
A10: DEC | F10: BOSCH Wiper Clear Advantage 21 inch BCA21 | L10: 40 | P10: 98198 | T10: =L10*P10*35% -> 1374772 | AA10: =L10*P10-T10 -> 2553148
F11: BOSCH Wiper Clear Advantage 22 inch BCA22 | L11: 40 | P11: 104955 | T11: =L11*P11*35% -> 1469370 | AA11: =L11*P11-T11 -> 2728830
F12: BOSCH Wiper Clear Advantage 24 inch BCA24 | L12: 40 | P12: 104955 | T12: =L12*P12*35% -> 1469370 | AA12: =L12*P12-T12 -> 2728830
F13: BOSCH Wiper Clear Advantage 26 inch BCA26 | L13: 20 | P13: 110811 | T13: =L13*P13*35% -> 775677 | AA13: =L13*P13-T13 -> 1440543
A15: JAN | B15: 102132 | F15: BOSCH Battery MF Blue NS60 46B24R 12V-42Ah | L15: 8 | P15: 1126100 | T15: =L15*P15*35% -> 3153080 | AA15: =L15*P15-T15 -> 5855720
A16: JAN | B16: 102135 | F16: BOSCH Battery MF Blue NS60L 46B24L 12V-42Ah | L16: 8 | P16: 1126100 | T16: =L16*P16*35% -> 3153080 | AA16: =L16*P16-T16 -> 5855720
A17: JAN | B17: 108121 | F17: BOSCH Battery MF Hightech AGM DIN70 LN3 12V-70Ah | L17: 8 | P17: 3720000 | T17: =L17*P17*35% -> 10416000 | AA17: =L17*P17-T17 -> 19344000
A18: JAN | B18: 102131 | F18: BOSCH Battery MF Blue 55D23L 12V-60Ah | L18: 4 | P18: 1466800 | T18: =L18*P18*35% -> 2053520 | AA18: =L18*P18-T18 -> 3813680
A19: JAN | B19: 102133 | F19: BOSCH Battery MF Blue NS40Z 40B19R 12V | L19: 4 | P19: 1029200 | T19: =L19*P19*35% -> 1440880 | AA19: =L19*P19-T19 -> 2675920
A20: JAN | B20: 101858 | F20: BOSCH Air Filter A 2180 | L20: 5 | P20: 243000 | T20: =L20*P20*35% -> 425250 | AA20: =L20*P20-T20 -> 789750
A21: JAN | B21: 101831 | F21: BOSCH Air Filter S 0507 | L21: 5 | P21: 178000 | T21: =L21*P21*35% -> 311500 | AA21: =L21*P21-T21 -> 578500
A22: JAN | B22: 101776 | F22: BOSCH FUEL FILTER D 6100 | L22: 6 | P22: 90000 | T22: =L22*P22*35% -> 189000 | AA22: =L22*P22-T22 -> 351000
B24: Kode Barang | F24: Nama Barang | L24: Kts. | P24: @Harga | T24: Diskon | AA24: Total Harga
A25: JAN | B25: 102131 | F25: BOSCH Battery MF Blue 55D23L 12V-60Ah | L25: 5 | P25: 1466800 | T25: =L25*P25*35% -> 2566900 | AA25: =L25*P25-T25 -> 4767100
A26: JAN | B26: 108121 | F26: BOSCH Battery MF Hightech AGM DIN70 LN3 12V-70Ah | L26: 3 | P26: 3720000 | T26: =L26*P26*35% -> 3906000 | AA26: =L26*P26-T26 -> 7254000
A27: JAN | B27: 101847 | F27: BOSCH FUEL FILTER D 6292 | L27: 8 | P27: 206000 | T27: =L27*P27*35% -> 576800 | AA27: =L27*P27-T27 -> 1071200
B29: Kode Barang | F29: Nama Barang | L29: Kts. | P29: @Harga | T29: Diskon | AA29: Total Harga
A30: JAN | B30: 109871 | F30: BOSCH Battery MF EFB Q85 ISS-65A 95D23L 12V | L30: 7 | P30: 2252252 | T30: =L30*P30*35% -> 5518017.4 | AA30: =L30*P30-T30 -> 10247747
B32: Kode Barang | F32: Nama Barang | L32: Kts. | P32: @Harga | T32: Diskon | AA32: Total Harga
A33: JAN | B33: 102133 | F33: BOSCH Battery MF Blue NS40Z 40B19R 12V | L33: 3 | P33: 1029200 | T33: =L33*P33*35% -> 1080660 | AA33: =L33*P33-T33 -> 2006940
A34: JAN | B34: 101843 | F34: BOSCH Cabin Filter AP-T07 | L34: 30 | P34: 199000 | T34: =L34*P34*35% -> 2089500 | AA34: =L34*P34-T34 -> 3880500

Sheet CV Sun (cleaned)
A1: {=_xlfn.UNIQUE('CV Sun (agg)'!F1:F34)} -> Nama Barang | B1: Total QTY | C1: Exist in Master
A2: BOSCH Oil Filter O 1041 | B2: =SUMIF('CV Sun (agg)'!F:F,'CV Sun (cleaned)'!A2,'CV Sun (agg)'!L:L) -> 50 | C2: =_xlfn.XLOOKUP(A2,Master!B:B,Master!B:B,"Hehe") -> BOSCH Oil Filter O 1041
A3: BOSCH OIL FILTER O 0126 | B3: =SUMIF('CV Sun (agg)'!F:F,'CV Sun (cleaned)'!A3,'CV Sun (agg)'!L:L) -> 50 | C3: =_xlfn.XLOOKUP(A3,Master!B:B,Master!B:B,"Hehe") -> BOSCH Oil Filter O 0126
A4: BOSCH Oil Filter O 0220 | B4: =SUMIF('CV Sun (agg)'!F:F,'CV Sun (cleaned)'!A4,'CV Sun (agg)'!L:L) -> 50 | C4: =_xlfn.XLOOKUP(A4,Master!B:B,Master!B:B,"Hehe") -> BOSCH Oil Filter O 0220
A5: BOSCH Wiper Clear Advantage 14 inch BCA14 | B5: =SUMIF('CV Sun (agg)'!F:F,'CV Sun (cleaned)'!A5,'CV Sun (agg)'!L:L) -> 40 | C5: =_xlfn.XLOOKUP(A5,Master!B:B,Master!B:B,"Hehe") -> BOSCH Wiper Clear Advantage 14 inch BCA14
A6: BOSCH Wiper Clear Advantage 16 inch BCA16 | B6: =SUMIF('CV Sun (agg)'!F:F,'CV Sun (cleaned)'!A6,'CV Sun (agg)'!L:L) -> 40 | C6: =_xlfn.XLOOKUP(A6,Master!B:B,Master!B:B,"Hehe") -> BOSCH Wiper Clear Advantage 16 inch BCA16
A7: BOSCH Wiper Clear Advantage 18 inch BCA18 | B7: =SUMIF('CV Sun (agg)'!F:F,'CV Sun (cleaned)'!A7,'CV Sun (agg)'!L:L) -> 40 | C7: =_xlfn.XLOOKUP(A7,Master!B:B,Master!B:B,"Hehe") -> BOSCH Wiper Clear Advantage 18 inch BCA18
A8: BOSCH Wiper Clear Advantage 19 inch BCA19 | B8: =SUMIF('CV Sun (agg)'!F:F,'CV Sun (cleaned)'!A8,'CV Sun (agg)'!L:L) -> 40 | C8: =_xlfn.XLOOKUP(A8,Master!B:B,Master!B:B,"Hehe") -> BOSCH Wiper Clear Advantage 19 inch BCA19
A9: BOSCH Wiper Clear Advantage 20 inch BCA20 | B9: =SUMIF('CV Sun (agg)'!F:F,'CV Sun (cleaned)'!A9,'CV Sun (agg)'!L:L) -> 40 | C9: =_xlfn.XLOOKUP(A9,Master!B:B,Master!B:B,"Hehe") -> BOSCH Wiper Clear Advantage 20 inch BCA20
A10: BOSCH Wiper Clear Advantage 21 inch BCA21 | B10: =SUMIF('CV Sun (agg)'!F:F,'CV Sun (cleaned)'!A10,'CV Sun (agg)'!L:L) -> 40 | C10: =_xlfn.XLOOKUP(A10,Master!B:B,Master!B:B,"Hehe") -> BOSCH Wiper Clear Advantage 21 inch BCA21
A11: BOSCH Wiper Clear Advantage 22 inch BCA22 | B11: =SUMIF('CV Sun (agg)'!F:F,'CV Sun (cleaned)'!A11,'CV Sun (agg)'!L:L) -> 40 | C11: =_xlfn.XLOOKUP(A11,Master!B:B,Master!B:B,"Hehe") -> BOSCH Wiper Clear Advantage 22 inch BCA22
A12: BOSCH Wiper Clear Advantage 24 inch BCA24 | B12: =SUMIF('CV Sun (agg)'!F:F,'CV Sun (cleaned)'!A12,'CV Sun (agg)'!L:L) -> 40 | C12: =_xlfn.XLOOKUP(A12,Master!B:B,Master!B:B,"Hehe") -> BOSCH Wiper Clear Advantage 24 inch BCA24
A13: BOSCH Wiper Clear Advantage 26 inch BCA26 | B13: =SUMIF('CV Sun (agg)'!F:F,'CV Sun (cleaned)'!A13,'CV Sun (agg)'!L:L) -> 20 | C13: =_xlfn.XLOOKUP(A13,Master!B:B,Master!B:B,"Hehe") -> BOSCH Wiper Clear Advantage 26 inch BCA26
C14: =_xlfn.XLOOKUP(A14,Master!B:B,Master!B:B,"Hehe") -> 0

Sheet Sumber Timur (clean)
B1: Kode Barang | F1: Nama Barang | L1: Kts. | P1: @Harga | T1: Diskon | AA1: Total Harga
A2: DEC | F2: BOSCH Wiper Advantage 16 inch BA16 | L2: 20 | P2: 50901 | T2: =L2*P2*35% -> 356307 | AA2: =L2*P2-T2 -> 661713
A3: DEC | F3: BOSCH Wiper Advantage 18 inch BA18 | L3: 20 | P3: 54505 | T3: =L3*P3*35% -> 381535 | AA3: =L3*P3-T3 -> 708565
A4: DEC | F4: BOSCH Wiper Advantage 20 inch BA20 | L4: 20 | P4: 57207 | T4: =L4*P4*35% -> 400449 | AA4: =L4*P4-T4 -> 743691
A5: DEC | F5: BOSCH Wiper Advantage 22 inch BA22 | L5: 20 | P5: 72973 | T5: =L5*P5*35% -> 510811 | AA5: =L5*P5-T5 -> 948649
A12: JAN | B12: 101737 | F12: BOSCH Oil Filter O 1041 | L12: 30 | P12: 43000 | T12: =L12*P12*35% -> 451500 | AA12: =L12*P12-T12 -> 838500
A13: JAN | B13: 101735 | F13: BOSCH Oil Filter O 0220 | L13: 20 | P13: 40800 | T13: =L13*P13*35% -> 285600 | AA13: =L13*P13-T13 -> 530400
A14: JAN | B14: 101750 | F14: BOSCH Oil Filter O 1001 | L14: 20 | P14: 56000 | T14: =L14*P14*35% -> 392000 | AA14: =L14*P14-T14 -> 728000
A15: JAN | B15: 101764 | F15: BOSCH Oil Filter O 1106 | L15: 20 | P15: 78500 | T15: =L15*P15*35% -> 549500 | AA15: =L15*P15-T15 -> 1020500
B17: Nama Barang | C17: Exist in Master
B18: BOSCH Oil Filter O 1041 | C18: =_xlfn.XLOOKUP(B18,Master!B:B,Master!B:B,"Hehe") -> BOSCH Oil Filter O 1041
B19: BOSCH Oil Filter O 0220 | C19: =_xlfn.XLOOKUP(B19,Master!B:B,Master!B:B,"Hehe") -> BOSCH Oil Filter O 0220
B20: BOSCH Oil Filter O 1001 | C20: =_xlfn.XLOOKUP(B20,Master!B:B,Master!B:B,"Hehe") -> BOSCH Oil Filter O 1001
B21: BOSCH Oil Filter O 1106 | C21: =_xlfn.XLOOKUP(B21,Master!B:B,Master!B:B,"Hehe") -> BOSCH Oil Filter O 1106

Sheet Honda Duren (clean)
B1: Kode Barang | F1: Nama Barang | L1: Kts. | P1: @Harga | T1: Diskon | AA1: Total Harga
A2: DEC | B2: 102134 | F2: BOSCH Battery MF Blue NS40ZL 40B19L 12V | L2: 4 | P2: 1029200 | T2: =L2*P2*35% -> 1440880 | AA2: =L2*P2-T2 -> 2675920
B4: Nama Barang | C4: Exist in Master
B5: BOSCH Battery MF Blue NS40ZL 40B19L 12V | C5: =_xlfn.XLOOKUP(B5,Master!B:B,Master!B:B,"Hehe") -> BOSCH Battery MF Blue NS40ZL 40B19L 12V
B8: Kode Barang | F8: Nama Barang | L8: Kts. | P8: @Harga | T8: Diskon | AA8: Total Harga
A9: FEB | B9: 109885 | F9: BOSCH Battery MF Blue NX100-S6L 55B24L 12V-45Ah | L9: 3 | P9: 1175100 | T9: =L9*P9*35% -> 1233855 | AA9: =L9*P9-T9 -> 2291445
B13: Kode Barang | F13: Nama Barang | L13: Kts. | P13: @Harga | T13: Diskon | AA13: Total Harga
A14: FEB | B14: 101761 | F14: BOSCH Wiper Clear Advantage 14 inch BCA14 | L14: 30 | P14: 77928 | T14: =L14*P14*35% -> 818244 | AA14: =L14*P14-T14 -> 1519596
A15: FEB | B15: 101762 | F15: BOSCH Wiper Clear Advantage 16 inch BCA16 | L15: 30 | P15: 77928 | T15: =L15*P15*35% -> 818244 | AA15: =L15*P15-T15 -> 1519596
A16: FEB | B16: 101779 | F16: BOSCH Wiper Clear Advantage 20 inch BCA20 | L16: 30 | P16: 96396 | T16: =L16*P16*35% -> 1012158 | AA16: =L16*P16-T16 -> 1879722
A17: FEB | B17: 101787 | F17: BOSCH Wiper Clear Advantage 22 inch BCA22 | L17: 30 | P17: 104955 | T17: =L17*P17*35% -> 1102027.5 | AA17: =L17*P17-T17 -> 2046622.5

Sheet Lavender（Agg）
B3: Kode Barang | F3: Nama Barang | L3: Kts. | P3: @Harga | T3: Diskon | AA3: Total Harga
A4: DEC | B4: 101742 | F4: BOSCH Oil Filter O 1014 | L4: 5 | P4: 49700 | T4: =L4*P4*0.35 -> 86975 | AA4: =L4*P4-T4 -> 161525
A5: DEC | B5: 101737 | F5: BOSCH Oil Filter O 1041 | L5: 5 | P5: 43000 | T5: =L5*P5*0.35 -> 75250 | AA5: =L5*P5-T5 -> 139750
A6: DEC | B6: 101743 | F6: BOSCH Oil Filter O 1042 | L6: 5 | P6: 50000 | T6: =L6*P6*0.35 -> 87500 | AA6: =L6*P6-T6 -> 162500
A7: DEC | B7: 101750 | F7: BOSCH Oil Filter O 1001 | L7: 5 | P7: 56000 | T7: =L7*P7*0.35 -> 98000 | AA7: =L7*P7-T7 -> 182000
A8: DEC | B8: 101807 | F8: BOSCH Spark Plug VR8SII30X - Iridium | L8: 10 | P8: 165400 | T8: =L8*P8*0.35 -> 578900 | AA8: =L8*P8-T8 -> 1075100
A9: DEC | B9: 101859 | F9: BOSCH Cabin Filter AP-N02 | L9: 2 | P9: 244600 | T9: =L9*P9*0.35 -> 171220 | AA9: =L9*P9-T9 -> 317980
A10: DEC | B10: 101853 | F10: BOSCH Cabin Filter AP-T02 | L10: 2 | P10: 228800 | T10: =L10*P10*0.35 -> 160160 | AA10: =L10*P10-T10 -> 297440
A11: DEC | B11: 101843 | F11: BOSCH Cabin Filter AP-T07 | L11: 2 | P11: 199000 | T11: =L11*P11*0.35 -> 139300 | AA11: =L11*P11-T11 -> 258700
A12: DEC | B12: 101854 | F12: BOSCH Cabin Filter AP-T10 | L12: 2 | P12: 228800 | T12: =L12*P12*0.35 -> 160160 | AA12: =L12*P12-T12 -> 297440
A13: DEC | B13: 101762 | F13: BOSCH Wiper Clear Advantage 16 inch BCA16 | L13: 10 | P13: 77928 | T13: =L13*P13*0.35 -> 272748 | AA13: =L13*P13-T13 -> 506532
A14: DEC | B14: 101788 | F14: BOSCH Wiper Clear Advantage 24 inch BCA24 | L14: 10 | P14: 104955 | T14: =L14*P14*0.35 -> 367342.5 | AA14: =L14*P14-T14 -> 682207.5
A19: JAN | B19: 101740 | F19: BOSCH Wiper Advantage 14 inch BA14 | L19: 10 | P19: 50901 | T19: =L19*P19*0.35 -> 178153.5 | AA19: =L19*P19-T19 -> 330856.5
... A40: JAN | B40: 101727 | F40: BOSCH Spark Plug K6TC0R(FR8DCX+) - Standard | L40: 20 | P40: 28500 | T40: =L40*P40*0.35 -> 199500 | AA40: =L40*P40-T40 -> 370500

Sheet Lavender（clean）
A1: {=_xlfn.UNIQUE('CV Sun (agg)'!F1:F34)} -> Nama Barang | B1: Total QTY | C1: Exist in Master
A2: BOSCH Oil Filter O 1014 | B2: =SUMIF('[1] Lavender(Agg)'!F:F,'CV Sun (cleaned)'!A2,'CV Sun (agg)'!L:L) -> #VALUE!
A3: BOSCH Oil Filter O 1041
A4: BOSCH Oil Filter O 1042
A5: BOSCH Oil Filter O 1001
A6: BOSCH Spark Plug VR8SII30X - Iridium
